Workbook
Name Fluxo: OFFSET([1]Cad_Natureza!$G$4,0,0,COUNTA([1]Cad_Natureza!$G$4:$G$102))
Name Fluxo: OFFSET(Cad_Natureza!$G$4,0,0,COUNTA(Cad_Natureza!$G$4:$G$102))
Name Lista_CRs: OFFSET([1]Cad_Natureza!$C$4,0,0,COUNTA([1]Cad_Natureza!$C$5:$C$52)+3)
Name Lista_CRs: OFFSET(Cad_Natureza!$C$4,0,0,COUNTA(Cad_Natureza!$C$5:$C$52)+3)
Name Lista_Socios: OFFSET([1]Cad_Natureza!$E$4,0,0,COUNTA([1]Cad_Natureza!$E$4:$E$102))
Name Lista_Socios: OFFSET(Cad_Natureza!$E$4,0,0,COUNTA(Cad_Natureza!$E$4:$E$102))

Sheet Cad_Natureza
B3: Natureza | C3: Descrição CR | E3: Entidade | G3: Fluxo
B4: - | C4: TODOS CRs | E4: MCS | F4: =OFFSET(Cad_Natureza!$E$4,0,0,COUNTA(Cad_Natureza!$E$4:$E$102)) -> MCS | G4: REAL | H4: =OFFSET(Cad_Natureza!$G$4,0,0,COUNTA(Cad_Natureza!$G$4:$G$102)) -> REAL
B5: REC1 | C5: CPF - Remun. Salário / Pró-Labore | G5: PREVISTO | H5: =OFFSET(Cad_Natureza!$G$4,0,0,COUNTA(Cad_Natureza!$G$4:$G$102)) -> PREVISTO
B6: REC2 | C6: CPF - Ajuda de custo - Combustível
B7: REC3 | C7: CPF - Ajuda de custo - Refeição
B8: REC4 | C8: CPF - Transf. Da conta PJ para a conta PF
B9: REC5 | C9: CPF - Outras receitas
B10: REC6 | C10: CPF - Pensão - Outras receitas
B11: REC7 | C11: CPF - Rec. Financeiras - Empréstimos
B13: OPF1 | C13: CPF - Desp. Alimentação / Refeição
B14: OPF2 | C14: CPF - Desp. Transporte / Combustível
B15: DESP1 | C15: CPF - Desp. Cartão de crédito
B16: DESP2 | C16: CPF - Desp. Telefone / Internet
B17: DESP3 | C17: CPF - Desp. com veículo - Manut. / Gastos
B18: DESP4 | C18: CPF - Desp. Moradia
... B53: X | C53: X

Sheet 2025
K1: =SUBTOTAL(9,K3:K940) -> 6120.48 | L1: -1
B2: EMPRESA | C2: x | D2: Natureza | E2: Descrição | F2: Centro de Resultado | G2: Entidade | H2: Data real | I2: Data prevista | J2: Observações | K2: Total | L2: Saldo banco | M2: x | N2: Empresa & CR | O2: Concat 2 | P2: Concat 3 | Q2: Concat 3 | R2: Empresa & Natureza | S2: x | T2: DATA REAL | U2: DATA PREVISTA | V2: X
B3: MCS | D3: =INDEX(Cad_Natureza!$B$3:$C$52,MATCH('2025'!F3,Cad_Natureza!$C$3:$C$52,0),MATCH('2025'!D$2,Cad_Natureza!$B$3:$C$3,0)) -> FIN2 | E3: JUROS EXCESSO LIM CONTA | F3: CPF - Desp. Financeiras - Juros / Tarifas | G3: MCS | H3: 45659 | J3: Juros / Tarifas bancárias | K3: -24.15 | L3: -5921.44 | N3: =B3&D3&F3 -> MCSFIN2CPF - Desp. Financeiras - Juros / Tarifas | O3: =D3&F3 -> FIN2CPF - Desp. Financeiras - Juros / Tarifas | P3: ="MCS"&D3&F3 -> MCSFIN2CPF - Desp. Financeiras - Juros / Tarifas | Q3: ="MCS"&D3 -> MCSFIN2 | R3: =B3&D3 -> MCSFIN2 | T3: =(1&"/"&MONTH(H3)&"/"&YEAR(H3))*1 -> 45658 | U3: =IF(I3="","",(1&"/"&MONTH(I3)&"/"&YEAR(I3))*1) | V3: Z
B4: MCS | D4: =INDEX(Cad_Natureza!$B$3:$C$52,MATCH('2025'!F4,Cad_Natureza!$C$3:$C$52,0),MATCH('2025'!D$2,Cad_Natureza!$B$3:$C$3,0)) -> FIN2 | E4: JUROS EXCESSO LIM CONTA | F4: CPF - Desp. Financeiras - Juros / Tarifas | G4: MCS | H4: 45659 | J4: Juros / Tarifas bancárias | K4: -17.09 | L4: -5938.53 | N4: =B4&D4&F4 -> MCSFIN2CPF - Desp. Financeiras - Juros / Tarifas | O4: =D4&F4 -> FIN2CPF - Desp. Financeiras - Juros / Tarifas | P4: ="MCS"&D4&F4 -> MCSFIN2CPF - Desp. Financeiras - Juros / Tarifas | Q4: ="MCS"&D4 -> MCSFIN2 | R4: =B4&D4 -> MCSFIN2 | T4: =(1&"/"&MONTH(H4)&"/"&YEAR(H4))*1 -> 45658 | U4: =IF(I4="","",(1&"/"&MONTH(I4)&"/"&YEAR(I4))*1) | V4: Z
B5: MCS | D5: =INDEX(Cad_Natureza!$B$3:$C$52,MATCH('2025'!F5,Cad_Natureza!$C$3:$C$52,0),MATCH('2025'!D$2,Cad_Natureza!$B$3:$C$3,0)) -> FIN2 | E5: IOF | F5: CPF - Desp. Financeiras - Juros / Tarifas | G5: MCS | H5: 45660 | J5: Impostos | K5: -17.02 | L5: -5955.55 | N5: =B5&D5&F5 -> MCSFIN2CPF - Desp. Financeiras - Juros / Tarifas | O5: =D5&F5 -> FIN2CPF - Desp. Financeiras - Juros / Tarifas | P5: ="MCS"&D5&F5 -> MCSFIN2CPF - Desp. Financeiras - Juros / Tarifas | Q5: ="MCS"&D5 -> MCSFIN2 | R5: =B5&D5 -> MCSFIN2 | T5: =(1&"/"&MONTH(H5)&"/"&YEAR(H5))*1 -> 45658 | U5: =IF(I5="","",(1&"/"&MONTH(I5)&"/"&YEAR(I5))*1) | V5: Z
B6: MCS | D6: =INDEX(Cad_Natureza!$B$3:$C$52,MATCH('2025'!F6,Cad_Natureza!$C$3:$C$52,0),MATCH('2025'!D$2,Cad_Natureza!$B$3:$C$3,0)) -> FIN1 | E6: CREDIARIO AUTOM 01/07 | F6: CPF - Desp. Financeiras - Empréstimos | G6: MCS | H6: 45665 | J6: Empréstimo cheque especial | K6: -127.18 | L6: -6082.73 | N6: =B6&D6&F6 -> MCSFIN1CPF - Desp. Financeiras - Empréstimos | O6: =D6&F6 -> FIN1CPF - Desp. Financeiras - Empréstimos | P6: ="MCS"&D6&F6 -> MCSFIN1CPF - Desp. Financeiras - Empréstimos | Q6: ="MCS"&D6 -> MCSFIN1 | R6: =B6&D6 -> MCSFIN1 | T6: =(1&"/"&MONTH(H6)&"/"&YEAR(H6))*1 -> 45658 | U6: =IF(I6="","",(1&"/"&MONTH(I6)&"/"&YEAR(I6))*1) | V6: Z
B7: MCS | D7: =INDEX(Cad_Natureza!$B$3:$C$52,MATCH('2025'!F7,Cad_Natureza!$C$3:$C$52,0),MATCH('2025'!D$2,Cad_Natureza!$B$3:$C$3,0)) -> DESP1 | E7: INT PAG TIT BANCO 237 | F7: CPF - Desp. Cartão de crédito | G7: MCS | H7: 45665 | J7: Pagamento de valor mínimo - Riachuelo | K7: -5.9 | L7: -6088.63 | N7: =B7&D7&F7 -> MCSDESP1CPF - Desp. Cartão de crédito | O7: =D7&F7 -> DESP1CPF - Desp. Cartão de crédito | P7: ="MCS"&D7&F7 -> MCSDESP1CPF - Desp. Cartão de crédito | Q7: ="MCS"&D7 -> MCSDESP1 | R7: =B7&D7 -> MCSDESP1 | T7: =(1&"/"&MONTH(H7)&"/"&YEAR(H7))*1 -> 45658 | U7: =IF(I7="","",(1&"/"&MONTH(I7)&"/"&YEAR(I7))*1) | V7: Z
B8: MCS | D8: =INDEX(Cad_Natureza!$B$3:$C$52,MATCH('2025'!F8,Cad_Natureza!$C$3:$C$52,0),MATCH('2025'!D$2,Cad_Natureza!$B$3:$C$3,0)) -> REC4 | E8: PIX TRANSF MCS SER08/01 | F8: CPF - Transf. Da conta PJ para a conta PF | G8: MCS | H8: 45665 | J8: Transferência entre contas | K8: 1000 | L8: -5088.63 | N8: =B8&D8&F8 -> MCSREC4CPF - Transf. Da conta PJ para a conta PF | O8: =D8&F8 -> REC4CPF - Transf. Da conta PJ para a conta PF | P8: ="MCS"&D8&F8 -> MCSREC4CPF - Transf. Da conta PJ para a conta PF | Q8: ="MCS"&D8 -> MCSREC4 | R8: =B8&D8 -> MCSREC4 | T8: =(1&"/"&MONTH(H8)&"/"&YEAR(H8))*1 -> 45658 | U8: =IF(I8="","",(1&"/"&MONTH(I8)&"/"&YEAR(I8))*1) | V8: Z
B9: MCS | D9: =INDEX(Cad_Natureza!$B$3:$C$52,MATCH('2025'!F9,Cad_Natureza!$C$3:$C$52,0),MATCH('2025'!D$2,Cad_Natureza!$B$3:$C$3,0)) -> PENS5 | E9: INT /BRK GOIA 4077325407 | F9: CPF - Pensão - Água | G9: MCS | H9: 45665 | J9: Pensão - fatura de água | K9: -205.22 | L9: -5293.85 | N9: =B9&D9&F9 -> MCSPENS5CPF - Pensão - Água | O9: =D9&F9 -> PENS5CPF - Pensão - Água | P9: ="MCS"&D9&F9 -> MCSPENS5CPF - Pensão - Água | Q9: ="MCS"&D9 -> MCSPENS5 | R9: =B9&D9 -> MCSPENS5 | T9: =(1&"/"&MONTH(H9)&"/"&YEAR(H9))*1 -> 45658 | U9: =IF(I9="","",(1&"/"&MONTH(I9)&"/"&YEAR(I9))*1) | V9: X
B10: MCS | D10: =INDEX(Cad_Natureza!$B$3:$C$52,MATCH('2025'!F10,Cad_Natureza!$C$3:$C$52,0),MATCH('2025'!D$2,Cad_Natureza!$B$3:$C$3,0)) -> PENS2 | E10: INT PAG TIT 338563315000 | F10: CPF - Pensão - Energia | G10: MCS | H10: 45665 | J10: Pensão - Conta de energia ref. 11/2024 | K10: -277.69 | L10: -5571.54 | N10: =B10&D10&F10 -> MCSPENS2CPF - Pensão - Energia | O10: =D10&F10 -> PENS2CPF - Pensão - Energia | P10: ="MCS"&D10&F10 -> MCSPENS2CPF - Pensão - Energia | Q10: ="MCS"&D10 -> MCSPENS2 | R10: =B10&D10 -> MCSPENS2 | T10: =(1&"/"&MONTH(H10)&"/"&YEAR(H10))*1 -> 45658 | U10: =IF(I10="","",(1&"/"&MONTH(I10)&"/"&YEAR(I10))*1) | V10: X
B11: MCS | D11: =INDEX(Cad_Natureza!$B$3:$C$52,MATCH('2025'!F11,Cad_Natureza!$C$3:$C$52,0),MATCH('2025'!D$2,Cad_Natureza!$B$3:$C$3,0)) -> FIN3 | E11: RENEGOCIACAO ITAU | F11: CPF - Desp. Financeiras - Empréstimos bancários | G11: MCS | H11: 45665 | J11: Renegociação cheque especial | K11: 6270.89 | L11: 699.35 | N11: =B11&D11&F11 -> MCSFIN3CPF - Desp. Financeiras - Empréstimos bancários | O11: =D11&F11 -> FIN3CPF - Desp. Financeiras - Empréstimos bancários | P11: ="MCS"&D11&F11 -> MCSFIN3CPF - Desp. Financeiras - Empréstimos bancários | Q11: ="MCS"&D11 -> MCSFIN3 | R11: =B11&D11 -> MCSFIN3 | T11: =(1&"/"&MONTH(H11)&"/"&YEAR(H11))*1 -> 45658 | U11: =IF(I11="","",(1&"/"&MONTH(I11)&"/"&YEAR(I11))*1) | V11: Z
B12: MCS | D12: =INDEX(Cad_Natureza!$B$3:$C$52,MATCH('2025'!F12,Cad_Natureza!$C$3:$C$52,0),MATCH('2025'!D$2,Cad_Natureza!$B$3:$C$3,0)) -> TRI1 | E12: TAR PACOTE ITAU DEZ/24 | F12: CPF - Desp. Impostos e Obrigações | G12: MCS | H12: 45665 | J12: Tarifas bancárias | K12: -28 | L12: 671.35 | N12: =B12&D12&F12 -> MCSTRI1CPF - Desp. Impostos e Obrigações | O12: =D12&F12 -> TRI1CPF - Desp. Impostos e Obrigações | P12: ="MCS"&D12&F12 -> MCSTRI1CPF - Desp. Impostos e Obrigações | Q12: ="MCS"&D12 -> MCSTRI1 | R12: =B12&D12 -> MCSTRI1 | T12: =(1&"/"&MONTH(H12)&"/"&YEAR(H12))*1 -> 45658 | U12: =IF(I12="","",(1&"/"&MONTH(I12)&"/"&YEAR(I12))*1) | V12: Z
B13: MCS | D13: =INDEX(Cad_Natureza!$B$3:$C$52,MATCH('2025'!F13,Cad_Natureza!$C$3:$C$52,0),MATCH('2025'!D$2,Cad_Natureza!$B$3:$C$3,0)) -> OPF2 | E13: RSCSS POSTO TALISM0901 POSTO TALISMA | F13: CPF - Desp. Transporte / Combustível | G13: MCS | H13: 45666 | J13: Combustível | K13: -50 | L13: 621.35 | N13: =B13&D13&F13 -> MCSOPF2CPF - Desp. Transporte / Combustível | O13: =D13&F13 -> OPF2CPF - Desp. Transporte / Combustível | P13: ="MCS"&D13&F13 -> MCSOPF2CPF - Desp. Transporte / Combustível | Q13: ="MCS"&D13 -> MCSOPF2 | R13: =B13&D13 -> MCSOPF2 | T13: =(1&"/"&MONTH(H13)&"/"&YEAR(H13))*1 -> 45658 | U13: =IF(I13="","",(1&"/"&MONTH(I13)&"/"&YEAR(I13))*1) | V13: Z
B14: MCS | D14: =INDEX(Cad_Natureza!$B$3:$C$52,MATCH('2025'!F14,Cad_Natureza!$C$3:$C$52,0),MATCH('2025'!D$2,Cad_Natureza!$B$3:$C$3,0)) -> PENS9 | E14: PIX TRANSF Dieyla 09/01 | F14: CPF - Pensão - Outros Gastos | G14: MCS | H14: 45666 | J14: Pensão - Gastos diversos | K14: -10 | L14: 611.35 | N14: =B14&D14&F14 -> MCSPENS9CPF - Pensão - Outros Gastos | O14: =D14&F14 -> PENS9CPF - Pensão - Outros Gastos | P14: ="MCS"&D14&F14 -> MCSPENS9CPF - Pensão - Outros Gastos | Q14: ="MCS"&D14 -> MCSPENS9 | R14: =B14&D14 -> MCSPENS9 | T14: =(1&"/"&MONTH(H14)&"/"&YEAR(H14))*1 -> 45658 | U14: =IF(I14="","",(1&"/"&MONTH(I14)&"/"&YEAR(I14))*1) | V14: X
... B442: MCS | D442: =INDEX(Cad_Natureza!$B$3:$C$52,MATCH('2025'!F442,Cad_Natureza!$C$3:$C$52,0),MATCH('2025'!D$2,Cad_Natureza!$B$3:$C$3,0)) -> PENS1 | E442: PIX TRANSF JOAO DE10/06 | F442: CPF - Pensão - Aluguel | G442: MCS | H442: 45818 | J442: Pensão - Aluguel ref. 06/2025 | K442: -700 | L442: 741.72 | N442: =B442&D442&F442 -> MCSPENS1CPF - Pensão - Aluguel | O442: =D442&F442 -> PENS1CPF - Pensão - Aluguel | P442: ="MCS"&D442&F442 -> MCSPENS1CPF - Pensão - Aluguel | Q442: ="MCS"&D442 -> MCSPENS1 | R442: =B442&D442 -> MCSPENS1 | T442: =(1&"/"&MONTH(H442)&"/"&YEAR(H442))*1 -> 45809 | U442: =IF(I442="","",(1&"/"&MONTH(I442)&"/"&YEAR(I442))*1) | V442: X
B443: MCS | D443: =INDEX(Cad_Natureza!$B$3:$C$52,MATCH('2025'!F443,Cad_Natureza!$C$3:$C$52,0),MATCH('2025'!D$2,Cad_Natureza!$B$3:$C$3,0)) -> DESP1 | E443: Cartão Riachuelo - seguro ref. 03/2025 | F443: CPF - Desp. Cartão de crédito | G443: MCS | H443: 45818 | J443: seguro ref. 03/2025 | K443: -5.9 | L443: =L442+K443 -> 735.82 | N443: =B443&D443&F443 -> MCSDESP1CPF - Desp. Cartão de crédito | O443: =D443&F443 -> DESP1CPF - Desp. Cartão de crédito | P443: ="MCS"&D443&F443 -> MCSDESP1CPF - Desp. Cartão de crédito | Q443: ="MCS"&D443 -> MCSDESP1 | R443: =B443&D443 -> MCSDESP1 | T443: =(1&"/"&MONTH(H443)&"/"&YEAR(H443))*1 -> 45809 | U443: =IF(I443="","",(1&"/"&MONTH(I443)&"/"&YEAR(I443))*1) | V443: Z
B444: MCS | D444: =INDEX(Cad_Natureza!$B$3:$C$52,MATCH('2025'!F444,Cad_Natureza!$C$3:$C$52,0),MATCH('2025'!D$2,Cad_Natureza!$B$3:$C$3,0)) -> GAST2 | E444: RSCSS ALTAS HORAS 1106 | F444: CPF - Desp. Lazer e Entretenimento - Cigarro | G444: MCS | H444: 45819 | J444: Palheiro | K444: -32 | L444: =L443+K444 -> 703.82 | N444: =B444&D444&F444 -> MCSGAST2CPF - Desp. Lazer e Entretenimento - Cigarro | O444: =D444&F444 -> GAST2CPF - Desp. Lazer e Entretenimento - Cigarro | P444: ="MCS"&D444&F444 -> MCSGAST2CPF - Desp. Lazer e Entretenimento - Cigarro | Q444: ="MCS"&D444 -> MCSGAST2 | R444: =B444&D444 -> MCSGAST2 | T444: =(1&"/"&MONTH(H444)&"/"&YEAR(H444))*1 -> 45809 | U444: =IF(I444="","",(1&"/"&MONTH(I444)&"/"&YEAR(I444))*1) | V444: Z
B445: MCS | D445: =INDEX(Cad_Natureza!$B$3:$C$52,MATCH('2025'!F445,Cad_Natureza!$C$3:$C$52,0),MATCH('2025'!D$2,Cad_Natureza!$B$3:$C$3,0)) -> GAST1 | E445: RSCSS DISTRIBUIDOR1206 - BAR DO CEARÁ | F445: CPF - Desp. Lazer e Entretenimento - Bares | G445: MCS | H445: 45820 | J445: Bares - Com a Débora | K445: -78.5 | L445: =L444+K445 -> 625.32 | N445: =B445&D445&F445 -> MCSGAST1CPF - Desp. Lazer e Entretenimento - Bares | O445: =D445&F445 -> GAST1CPF - Desp. Lazer e Entretenimento - Bares | P445: ="MCS"&D445&F445 -> MCSGAST1CPF - Desp. Lazer e Entretenimento - Bares | Q445: ="MCS"&D445 -> MCSGAST1 | R445: =B445&D445 -> MCSGAST1 | T445: =(1&"/"&MONTH(H445)&"/"&YEAR(H445))*1 -> 45809 | U445: =IF(I445="","",(1&"/"&MONTH(I445)&"/"&YEAR(I445))*1) | V445: Z
B446: MCS | D446: =INDEX(Cad_Natureza!$B$3:$C$52,MATCH('2025'!F446,Cad_Natureza!$C$3:$C$52,0),MATCH('2025'!D$2,Cad_Natureza!$B$3:$C$3,0)) -> OPF2 | E446: RSCSS AUTO POSTO D1206 | F446: CPF - Desp. Transporte / Combustível | G446: MCS | H446: 45820 | J446: Combustível | K446: -50 | L446: =L445+K446 -> 575.32 | N446: =B446&D446&F446 -> MCSOPF2CPF - Desp. Transporte / Combustível | O446: =D446&F446 -> OPF2CPF - Desp. Transporte / Combustível | P446: ="MCS"&D446&F446 -> MCSOPF2CPF - Desp. Transporte / Combustível | Q446: ="MCS"&D446 -> MCSOPF2 | R446: =B446&D446 -> MCSOPF2 | T446: =(1&"/"&MONTH(H446)&"/"&YEAR(H446))*1 -> 45809 | U446: =IF(I446="","",(1&"/"&MONTH(I446)&"/"&YEAR(I446))*1) | V446: Z
B447: MCS | D447: =INDEX(Cad_Natureza!$B$3:$C$52,MATCH('2025'!F447,Cad_Natureza!$C$3:$C$52,0),MATCH('2025'!D$2,Cad_Natureza!$B$3:$C$3,0)) -> GAST1 | E447: RSCSS ORIENTE BEBI1206 | F447: CPF - Desp. Lazer e Entretenimento - Bares | G447: MCS | H447: 45820 | J447: Bares (antes da meia noite) - Com a Débora | K447: -13 | L447: =L446+K447 -> 562.32 | N447: =B447&D447&F447 -> MCSGAST1CPF - Desp. Lazer e Entretenimento - Bares | O447: =D447&F447 -> GAST1CPF - Desp. Lazer e Entretenimento - Bares | P447: ="MCS"&D447&F447 -> MCSGAST1CPF - Desp. Lazer e Entretenimento - Bares | Q447: ="MCS"&D447 -> MCSGAST1 | R447: =B447&D447 -> MCSGAST1 | T447: =(1&"/"&MONTH(H447)&"/"&YEAR(H447))*1 -> 45809 | U447: =IF(I447="","",(1&"/"&MONTH(I447)&"/"&YEAR(I447))*1) | V447: Z
B448: MCS | D448: =INDEX(Cad_Natureza!$B$3:$C$52,MATCH('2025'!F448,Cad_Natureza!$C$3:$C$52,0),MATCH('2025'!D$2,Cad_Natureza!$B$3:$C$3,0)) -> GAST1 | E448: RSCSS ORIENTE BEBI1206 | F448: CPF - Desp. Lazer e Entretenimento - Bares | G448: MCS | H448: 45820 | J448: Bares (antes da meia noite) - Com a Débora | K448: -12 | L448: =L447+K448 -> 550.32 | N448: =B448&D448&F448 -> MCSGAST1CPF - Desp. Lazer e Entretenimento - Bares | O448: =D448&F448 -> GAST1CPF - Desp. Lazer e Entretenimento - Bares | P448: ="MCS"&D448&F448 -> MCSGAST1CPF - Desp. Lazer e Entretenimento - Bares | Q448: ="MCS"&D448 -> MCSGAST1 | R448: =B448&D448 -> MCSGAST1 | T448: =(1&"/"&MONTH(H448)&"/"&YEAR(H448))*1 -> 45809 | U448: =IF(I448="","",(1&"/"&MONTH(I448)&"/"&YEAR(I448))*1) | V448: Z
B449: MCS | D449: =INDEX(Cad_Natureza!$B$3:$C$52,MATCH('2025'!F449,Cad_Natureza!$C$3:$C$52,0),MATCH('2025'!D$2,Cad_Natureza!$B$3:$C$3,0)) -> GAST1 | E449: RSCSS ORIENTE BEBI1206 | F449: CPF - Desp. Lazer e Entretenimento - Bares | G449: MCS | H449: 45820 | J449: Bares (antes da meia noite) - Com a Débora | K449: -19 | L449: =L448+K449 -> 531.32 | N449: =B449&D449&F449 -> MCSGAST1CPF - Desp. Lazer e Entretenimento - Bares | O449: =D449&F449 -> GAST1CPF - Desp. Lazer e Entretenimento - Bares | P449: ="MCS"&D449&F449 -> MCSGAST1CPF - Desp. Lazer e Entretenimento - Bares | Q449: ="MCS"&D449 -> MCSGAST1 | R449: =B449&D449 -> MCSGAST1 | T449: =(1&"/"&MONTH(H449)&"/"&YEAR(H449))*1 -> 45809 | U449: =IF(I449="","",(1&"/"&MONTH(I449)&"/"&YEAR(I449))*1) | V449: Z
B450: MCS | D450: =INDEX(Cad_Natureza!$B$3:$C$52,MATCH('2025'!F450,Cad_Natureza!$C$3:$C$52,0),MATCH('2025'!D$2,Cad_Natureza!$B$3:$C$3,0)) -> GAST1 | E450: RSCSS ORIENTE BEBI1306 | F450: CPF - Desp. Lazer e Entretenimento - Bares | G450: MCS | H450: 45821 | J450: Bares (depois da meia noite) - Com a Débora | K450: -14 | L450: =L449+K450 -> 517.32 | N450: =B450&D450&F450 -> MCSGAST1CPF - Desp. Lazer e Entretenimento - Bares | O450: =D450&F450 -> GAST1CPF - Desp. Lazer e Entretenimento - Bares | P450: ="MCS"&D450&F450 -> MCSGAST1CPF - Desp. Lazer e Entretenimento - Bares | Q450: ="MCS"&D450 -> MCSGAST1 | R450: =B450&D450 -> MCSGAST1 | T450: =(1&"/"&MONTH(H450)&"/"&YEAR(H450))*1 -> 45809 | U450: =IF(I450="","",(1&"/"&MONTH(I450)&"/"&YEAR(I450))*1) | V450: Z
B451: MCS | D451: =INDEX(Cad_Natureza!$B$3:$C$52,MATCH('2025'!F451,Cad_Natureza!$C$3:$C$52,0),MATCH('2025'!D$2,Cad_Natureza!$B$3:$C$3,0)) -> FIN3 | E451: RENEGOCIACAO ITAU 06/18 | F451: CPF - Desp. Financeiras - Empréstimos bancários | G451: MCS | H451: 45821 | J451: Renegociação cheque especial | K451: -538.03 | L451: =L450+K451 -> -20.71 | N451: =B451&D451&F451 -> MCSFIN3CPF - Desp. Financeiras - Empréstimos bancários | O451: =D451&F451 -> FIN3CPF - Desp. Financeiras - Empréstimos bancários | P451: ="MCS"&D451&F451 -> MCSFIN3CPF - Desp. Financeiras - Empréstimos bancários | Q451: ="MCS"&D451 -> MCSFIN3 | R451: =B451&D451 -> MCSFIN3 | T451: =(1&"/"&MONTH(H451)&"/"&YEAR(H451))*1 -> 45809 | U451: =IF(I451="","",(1&"/"&MONTH(I451)&"/"&YEAR(I451))*1) | V451: Z
B452: MCS | D452: =INDEX(Cad_Natureza!$B$3:$C$52,MATCH('2025'!F452,Cad_Natureza!$C$3:$C$52,0),MATCH('2025'!D$2,Cad_Natureza!$B$3:$C$3,0)) -> REC5 | E452: PIX TRANSF DEBORAH13/06 | F452: CPF - Outras receitas | G452: MCS | H452: 45821 | J452: Reembolso gasolina | K452: 30 | L452: =L451+K452 -> 9.29 | N452: =B452&D452&F452 -> MCSREC5CPF - Outras receitas | O452: =D452&F452 -> REC5CPF - Outras receitas | P452: ="MCS"&D452&F452 -> MCSREC5CPF - Outras receitas | Q452: ="MCS"&D452 -> MCSREC5 | R452: =B452&D452 -> MCSREC5 | T452: =(1&"/"&MONTH(H452)&"/"&YEAR(H452))*1 -> 45809 | U452: =IF(I452="","",(1&"/"&MONTH(I452)&"/"&YEAR(I452))*1) | V452: Z
B453: MCS | D453: =INDEX(Cad_Natureza!$B$3:$C$52,MATCH('2025'!F453,Cad_Natureza!$C$3:$C$52,0),MATCH('2025'!D$2,Cad_Natureza!$B$3:$C$3,0)) -> OPF2 | E453: RSCSS AUTO POSTO R1306 | F453: CPF - Desp. Transporte / Combustível | G453: MCS | H453: 45821 | J453: Combustível - perto da rodoviária de Ap. Gyn buscar a Débora | K453: -30 | L453: =L452+K453 -> -20.71 | N453: =B453&D453&F453 -> MCSOPF2CPF - Desp. Transporte / Combustível | O453: =D453&F453 -> OPF2CPF - Desp. Transporte / Combustível | P453: ="MCS"&D453&F453 -> MCSOPF2CPF - Desp. Transporte / Combustível | Q453: ="MCS"&D453 -> MCSOPF2 | R453: =B453&D453 -> MCSOPF2 | T453: =(1&"/"&MONTH(H453)&"/"&YEAR(H453))*1 -> 45809 | U453: =IF(I453="","",(1&"/"&MONTH(I453)&"/"&YEAR(I453))*1) | V453: Z
B454: MCS | D454: =INDEX(Cad_Natureza!$B$3:$C$52,MATCH('2025'!F454,Cad_Natureza!$C$3:$C$52,0),MATCH('2025'!D$2,Cad_Natureza!$B$3:$C$3,0)) -> REC3 | E454: PIX TRANSF FABRICI13/06 | F454: CPF - Ajuda de custo - Refeição | G454: MCS | H454: 45821 | J454: Ajuda de custo - Alimentação | K454: 300 | L454: =L453+K454 -> 279.29 | N454: =B454&D454&F454 -> MCSREC3CPF - Ajuda de custo - Refeição | O454: =D454&F454 -> REC3CPF - Ajuda de custo - Refeição | P454: ="MCS"&D454&F454 -> MCSREC3CPF - Ajuda de custo - Refeição | Q454: ="MCS"&D454 -> MCSREC3 | R454: =B454&D454 -> MCSREC3 | T454: =(1&"/"&MONTH(H454)&"/"&YEAR(H454))*1 -> 45809 | U454: =IF(I454="","",(1&"/"&MONTH(I454)&"/"&YEAR(I454))*1) | V454: Z
... B560: MCS | D560: =INDEX(Cad_Natureza!$B$3:$C$52,MATCH('2025'!F560,Cad_Natureza!$C$3:$C$52,0),MATCH('2025'!D$2,Cad_Natureza!$B$3:$C$3,0)) -> PENS1 | E560: PIX TRANSF Dieyla 08/07 | F560: CPF - Pensão - Aluguel | G560: MCS | H560: 45846 | J560: Pensão - aluguel 07 2025 | K560: -600 | L560: =L559+K560 -> 1392.81 | N560: =B560&D560&F560 -> MCSPENS1CPF - Pensão - Aluguel | O560: =D560&F560 -> PENS1CPF - Pensão - Aluguel | P560: ="MCS"&D560&F560 -> MCSPENS1CPF - Pensão - Aluguel | Q560: ="MCS"&D560 -> MCSPENS1 | R560: =B560&D560 -> MCSPENS1 | T560: =(1&"/"&MONTH(H560)&"/"&YEAR(H560))*1 -> 45839 | U560: =IF(I560="","",(1&"/"&MONTH(I560)&"/"&YEAR(I560))*1) | V560: X
B561: MCS | D561: =INDEX(Cad_Natureza!$B$3:$C$52,MATCH('2025'!F561,Cad_Natureza!$C$3:$C$52,0),MATCH('2025'!D$2,Cad_Natureza!$B$3:$C$3,0)) -> REC6 | E561: PIX TRANSF Maria D09/07 | F561: CPF - Pensão - Outras receitas | G561: MCS | H561: 45847 | J561: Pensão - Rcbto para comprar Antibiótico para Alice | K561: 105 | L561: 1497.81 | N561: =B561&D561&F561 -> MCSREC6CPF - Pensão - Outras receitas | O561: =D561&F561 -> REC6CPF - Pensão - Outras receitas | P561: ="MCS"&D561&F561 -> MCSREC6CPF - Pensão - Outras receitas | Q561: ="MCS"&D561 -> MCSREC6 | R561: =B561&D561 -> MCSREC6 | T561: =(1&"/"&MONTH(H561)&"/"&YEAR(H561))*1 -> 45839 | U561: =IF(I561="","",(1&"/"&MONTH(I561)&"/"&YEAR(I561))*1) | V561: X
B562: MCS | D562: =INDEX(Cad_Natureza!$B$3:$C$52,MATCH('2025'!F562,Cad_Natureza!$C$3:$C$52,0),MATCH('2025'!D$2,Cad_Natureza!$B$3:$C$3,0)) -> PENS6 | E562: RSCSS GIFARMA DROG0907 | F562: CPF - Pensão - Farmácia e Saúde | G562: MCS | H562: 45847 | J562: Pensão - Farmácia | K562: -95 | L562: 1402.81 | N562: =B562&D562&F562 -> MCSPENS6CPF - Pensão - Farmácia e Saúde | O562: =D562&F562 -> PENS6CPF - Pensão - Farmácia e Saúde | P562: ="MCS"&D562&F562 -> MCSPENS6CPF - Pensão - Farmácia e Saúde | Q562: ="MCS"&D562 -> MCSPENS6 | R562: =B562&D562 -> MCSPENS6 | T562: =(1&"/"&MONTH(H562)&"/"&YEAR(H562))*1 -> 45839 | U562: =IF(I562="","",(1&"/"&MONTH(I562)&"/"&YEAR(I562))*1) | V562: X
B563: MCS | D563: =INDEX(Cad_Natureza!$B$3:$C$52,MATCH('2025'!F563,Cad_Natureza!$C$3:$C$52,0),MATCH('2025'!D$2,Cad_Natureza!$B$3:$C$3,0)) -> OPF2 | E563: PIX QRS AUTO POSTO 10/07 | F563: CPF - Desp. Transporte / Combustível | G563: MCS | H563: 45848 | J563: Combustível | K563: -50 | L563: 1352.81 | N563: =B563&D563&F563 -> MCSOPF2CPF - Desp. Transporte / Combustível | O563: =D563&F563 -> OPF2CPF - Desp. Transporte / Combustível | P563: ="MCS"&D563&F563 -> MCSOPF2CPF - Desp. Transporte / Combustível | Q563: ="MCS"&D563 -> MCSOPF2 | R563: =B563&D563 -> MCSOPF2 | T563: =(1&"/"&MONTH(H563)&"/"&YEAR(H563))*1 -> 45839 | U563: =IF(I563="","",(1&"/"&MONTH(I563)&"/"&YEAR(I563))*1) | V563: Z
B564: MCS | D564: =INDEX(Cad_Natureza!$B$3:$C$52,MATCH('2025'!F564,Cad_Natureza!$C$3:$C$52,0),MATCH('2025'!D$2,Cad_Natureza!$B$3:$C$3,0)) -> GAST1 | E564: RSCSS VanderleiDaS1007 | F564: CPF - Desp. Lazer e Entretenimento - Bares | G564: MCS | H564: 45848 | J564: Bares | K564: -26.5 | L564: 1326.31 | N564: =B564&D564&F564 -> MCSGAST1CPF - Desp. Lazer e Entretenimento - Bares | O564: =D564&F564 -> GAST1CPF - Desp. Lazer e Entretenimento - Bares | P564: ="MCS"&D564&F564 -> MCSGAST1CPF - Desp. Lazer e Entretenimento - Bares | Q564: ="MCS"&D564 -> MCSGAST1 | R564: =B564&D564 -> MCSGAST1 | T564: =(1&"/"&MONTH(H564)&"/"&YEAR(H564))*1 -> 45839 | U564: =IF(I564="","",(1&"/"&MONTH(I564)&"/"&YEAR(I564))*1) | V564: Z
B565: MCS | D565: =INDEX(Cad_Natureza!$B$3:$C$52,MATCH('2025'!F565,Cad_Natureza!$C$3:$C$52,0),MATCH('2025'!D$2,Cad_Natureza!$B$3:$C$3,0)) -> GAST1 | E565: RSCSS VanderleiDaS1107 | F565: CPF - Desp. Lazer e Entretenimento - Bares | G565: MCS | H565: 45849 | J565: Bares | K565: -10 | L565: 1316.31 | N565: =B565&D565&F565 -> MCSGAST1CPF - Desp. Lazer e Entretenimento - Bares | O565: =D565&F565 -> GAST1CPF - Desp. Lazer e Entretenimento - Bares | P565: ="MCS"&D565&F565 -> MCSGAST1CPF - Desp. Lazer e Entretenimento - Bares | Q565: ="MCS"&D565 -> MCSGAST1 | R565: =B565&D565 -> MCSGAST1 | T565: =(1&"/"&MONTH(H565)&"/"&YEAR(H565))*1 -> 45839 | U565: =IF(I565="","",(1&"/"&MONTH(I565)&"/"&YEAR(I565))*1) | V565: Z
B566: MCS | D566: =INDEX(Cad_Natureza!$B$3:$C$52,MATCH('2025'!F566,Cad_Natureza!$C$3:$C$52,0),MATCH('2025'!D$2,Cad_Natureza!$B$3:$C$3,0)) -> GAST2 | E566: RSCSS RenatoLoiola1207 | F566: CPF - Desp. Lazer e Entretenimento - Cigarro | G566: MCS | H566: 45852 | J566: Palheiro | K566: -35 | L566: 1281.31 | N566: =B566&D566&F566 -> MCSGAST2CPF - Desp. Lazer e Entretenimento - Cigarro | O566: =D566&F566 -> GAST2CPF - Desp. Lazer e Entretenimento - Cigarro | P566: ="MCS"&D566&F566 -> MCSGAST2CPF - Desp. Lazer e Entretenimento - Cigarro | Q566: ="MCS"&D566 -> MCSGAST2 | R566: =B566&D566 -> MCSGAST2 | T566: =(1&"/"&MONTH(H566)&"/"&YEAR(H566))*1 -> 45839 | U566: =IF(I566="","",(1&"/"&MONTH(I566)&"/"&YEAR(I566))*1) | V566: Z
B567: MCS | D567: =INDEX(Cad_Natureza!$B$3:$C$52,MATCH('2025'!F567,Cad_Natureza!$C$3:$C$52,0),MATCH('2025'!D$2,Cad_Natureza!$B$3:$C$3,0)) -> GAST1 | E567: RSCSS ORIENTE BEBI1207 | F567: CPF - Desp. Lazer e Entretenimento - Bares | G567: MCS | H567: 45852 | J567: Bares - Com a Danilla | K567: -5 | L567: 1276.31 | N567: =B567&D567&F567 -> MCSGAST1CPF - Desp. Lazer e Entretenimento - Bares | O567: =D567&F567 -> GAST1CPF - Desp. Lazer e Entretenimento - Bares | P567: ="MCS"&D567&F567 -> MCSGAST1CPF - Desp. Lazer e Entretenimento - Bares | Q567: ="MCS"&D567 -> MCSGAST1 | R567: =B567&D567 -> MCSGAST1 | T567: =(1&"/"&MONTH(H567)&"/"&YEAR(H567))*1 -> 45839 | U567: =IF(I567="","",(1&"/"&MONTH(I567)&"/"&YEAR(I567))*1) | V567: Z
B568: MCS | D568: =INDEX(Cad_Natureza!$B$3:$C$52,MATCH('2025'!F568,Cad_Natureza!$C$3:$C$52,0),MATCH('2025'!D$2,Cad_Natureza!$B$3:$C$3,0)) -> GAST1 | E568: RSCSS ORIENTE BEBI1307 | F568: CPF - Desp. Lazer e Entretenimento - Bares | G568: MCS | H568: 45852 | J568: Bares - Com a Danilla | K568: -10 | L568: 1266.31 | N568: =B568&D568&F568 -> MCSGAST1CPF - Desp. Lazer e Entretenimento - Bares | O568: =D568&F568 -> GAST1CPF - Desp. Lazer e Entretenimento - Bares | P568: ="MCS"&D568&F568 -> MCSGAST1CPF - Desp. Lazer e Entretenimento - Bares | Q568: ="MCS"&D568 -> MCSGAST1 | R568: =B568&D568 -> MCSGAST1 | T568: =(1&"/"&MONTH(H568)&"/"&YEAR(H568))*1 -> 45839 | U568: =IF(I568="","",(1&"/"&MONTH(I568)&"/"&YEAR(I568))*1) | V568: Z
B569: MCS | D569: =INDEX(Cad_Natureza!$B$3:$C$52,MATCH('2025'!F569,Cad_Natureza!$C$3:$C$52,0),MATCH('2025'!D$2,Cad_Natureza!$B$3:$C$3,0)) -> GAST1 | E569: RSCSS ORIENTE BEBI1307 | F569: CPF - Desp. Lazer e Entretenimento - Bares | G569: MCS | H569: 45852 | J569: Bares - Com a Danilla | K569: -5 | L569: 1261.31 | N569: =B569&D569&F569 -> MCSGAST1CPF - Desp. Lazer e Entretenimento - Bares | O569: =D569&F569 -> GAST1CPF - Desp. Lazer e Entretenimento - Bares | P569: ="MCS"&D569&F569 -> MCSGAST1CPF - Desp. Lazer e Entretenimento - Bares | Q569: ="MCS"&D569 -> MCSGAST1 | R569: =B569&D569 -> MCSGAST1 | T569: =(1&"/"&MONTH(H569)&"/"&YEAR(H569))*1 -> 45839 | U569: =IF(I569="","",(1&"/"&MONTH(I569)&"/"&YEAR(I569))*1) | V569: Z
B570: MCS | D570: =INDEX(Cad_Natureza!$B$3:$C$52,MATCH('2025'!F570,Cad_Natureza!$C$3:$C$52,0),MATCH('2025'!D$2,Cad_Natureza!$B$3:$C$3,0)) -> GAST1 | E570: RSCSS ORIENTE BEBI1307 | F570: CPF - Desp. Lazer e Entretenimento - Bares | G570: MCS | H570: 45852 | J570: Bares - Com a Danilla | K570: -4 | L570: 1257.31 | N570: =B570&D570&F570 -> MCSGAST1CPF - Desp. Lazer e Entretenimento - Bares | O570: =D570&F570 -> GAST1CPF - Desp. Lazer e Entretenimento - Bares | P570: ="MCS"&D570&F570 -> MCSGAST1CPF - Desp. Lazer e Entretenimento - Bares | Q570: ="MCS"&D570 -> MCSGAST1 | R570: =B570&D570 -> MCSGAST1 | T570: =(1&"/"&MONTH(H570)&"/"&YEAR(H570))*1 -> 45839 | U570: =IF(I570="","",(1&"/"&MONTH(I570)&"/"&YEAR(I570))*1) | V570: Z
B571: MCS | D571: =INDEX(Cad_Natureza!$B$3:$C$52,MATCH('2025'!F571,Cad_Natureza!$C$3:$C$52,0),MATCH('2025'!D$2,Cad_Natureza!$B$3:$C$3,0)) -> GAST1 | E571: RSCSS ORIENTE BEBI1307 | F571: CPF - Desp. Lazer e Entretenimento - Bares | G571: MCS | H571: 45852 | J571: Bares - Com a Danilla | K571: -5 | L571: 1252.31 | N571: =B571&D571&F571 -> MCSGAST1CPF - Desp. Lazer e Entretenimento - Bares | O571: =D571&F571 -> GAST1CPF - Desp. Lazer e Entretenimento - Bares | P571: ="MCS"&D571&F571 -> MCSGAST1CPF - Desp. Lazer e Entretenimento - Bares | Q571: ="MCS"&D571 -> MCSGAST1 | R571: =B571&D571 -> MCSGAST1 | T571: =(1&"/"&MONTH(H571)&"/"&YEAR(H571))*1 -> 45839 | U571: =IF(I571="","",(1&"/"&MONTH(I571)&"/"&YEAR(I571))*1) | V571: Z
B572: MCS | D572: =INDEX(Cad_Natureza!$B$3:$C$52,MATCH('2025'!F572,Cad_Natureza!$C$3:$C$52,0),MATCH('2025'!D$2,Cad_Natureza!$B$3:$C$3,0)) -> GAST1 | E572: RSCSS ORIENTE BEBI1307 | F572: CPF - Desp. Lazer e Entretenimento - Bares | G572: MCS | H572: 45852 | J572: Bares - Com a Danilla | K572: -8 | L572: 1244.31 | N572: =B572&D572&F572 -> MCSGAST1CPF - Desp. Lazer e Entretenimento - Bares | O572: =D572&F572 -> GAST1CPF - Desp. Lazer e Entretenimento - Bares | P572: ="MCS"&D572&F572 -> MCSGAST1CPF - Desp. Lazer e Entretenimento - Bares | Q572: ="MCS"&D572 -> MCSGAST1 | R572: =B572&D572 -> MCSGAST1 | T572: =(1&"/"&MONTH(H572)&"/"&YEAR(H572))*1 -> 45839 | U572: =IF(I572="","",(1&"/"&MONTH(I572)&"/"&YEAR(I572))*1) | V572: Z
... B637: MCS | D637: =INDEX(Cad_Natureza!$B$3:$C$52,MATCH('2025'!F637,Cad_Natureza!$C$3:$C$52,0),MATCH('2025'!D$2,Cad_Natureza!$B$3:$C$3,0)) -> PENS5 | E637: PIX QRS BRK AMBIENT29/07 | F637: CPF - Pensão - Água | G637: MCS | H637: 45867 | J637: Pensão - Conta de água atrasada ref. 06/2025 | K637: -104.65 | L637: 29.4 | N637: =B637&D637&F637 -> MCSPENS5CPF - Pensão - Água | O637: =D637&F637 -> PENS5CPF - Pensão - Água | P637: ="MCS"&D637&F637 -> MCSPENS5CPF - Pensão - Água | Q637: ="MCS"&D637 -> MCSPENS5 | R637: =B637&D637 -> MCSPENS5 | T637: =(1&"/"&MONTH(H637)&"/"&YEAR(H637))*1 -> 45839 | U637: =IF(I637="","",(1&"/"&MONTH(I637)&"/"&YEAR(I637))*1) | V637: X
B638: MCS | D638: =INDEX(Cad_Natureza!$B$3:$C$52,MATCH('2025'!F638,Cad_Natureza!$C$3:$C$52,0),MATCH('2025'!D$2,Cad_Natureza!$B$3:$C$3,0)) -> REC7 | E638: PIX TRANSF Fabrici30/07 | F638: CPF - Rec. Financeiras - Empréstimos | G638: MCS | H638: 45868 | J638: Adiantamento salarial | K638: 1000 | L638: 1029.4 | N638: =B638&D638&F638 -> MCSREC7CPF - Rec. Financeiras - Empréstimos | O638: =D638&F638 -> REC7CPF - Rec. Financeiras - Empréstimos | P638: ="MCS"&D638&F638 -> MCSREC7CPF - Rec. Financeiras - Empréstimos | Q638: ="MCS"&D638 -> MCSREC7 | R638: =B638&D638 -> MCSREC7 | T638: =(1&"/"&MONTH(H638)&"/"&YEAR(H638))*1 -> 45839 | U638: =IF(I638="","",(1&"/"&MONTH(I638)&"/"&YEAR(I638))*1)
B639: MCS | D639: =INDEX(Cad_Natureza!$B$3:$C$52,MATCH('2025'!F639,Cad_Natureza!$C$3:$C$52,0),MATCH('2025'!D$2,Cad_Natureza!$B$3:$C$3,0)) -> PENS2 | E639: PAG BOLETO EQUATORIAL GOIAS DISTR ENER | F639: CPF - Pensão - Energia | G639: MCS | H639: 45868 | J639: Pensão - Conta de energia ref. 05/2025 | K639: -678.47 | L639: 350.93 | N639: =B639&D639&F639 -> MCSPENS2CPF - Pensão - Energia | O639: =D639&F639 -> PENS2CPF - Pensão - Energia | P639: ="MCS"&D639&F639 -> MCSPENS2CPF - Pensão - Energia | Q639: ="MCS"&D639 -> MCSPENS2 | R639: =B639&D639 -> MCSPENS2 | T639: =(1&"/"&MONTH(H639)&"/"&YEAR(H639))*1 -> 45839 | U639: =IF(I639="","",(1&"/"&MONTH(I639)&"/"&YEAR(I639))*1) | V639: X
B640: MCS | D640: =INDEX(Cad_Natureza!$B$3:$C$52,MATCH('2025'!F640,Cad_Natureza!$C$3:$C$52,0),MATCH('2025'!D$2,Cad_Natureza!$B$3:$C$3,0)) -> PENS5 | E640: INT /BRK GOIA 4084237190 | F640: CPF - Pensão - Água | G640: MCS | H640: 45868 | J640: Pensão - Conta de água atrasada ref. 07/2025 | K640: -115.65 | L640: 235.28 | N640: =B640&D640&F640 -> MCSPENS5CPF - Pensão - Água | O640: =D640&F640 -> PENS5CPF - Pensão - Água | P640: ="MCS"&D640&F640 -> MCSPENS5CPF - Pensão - Água | Q640: ="MCS"&D640 -> MCSPENS5 | R640: =B640&D640 -> MCSPENS5 | T640: =(1&"/"&MONTH(H640)&"/"&YEAR(H640))*1 -> 45839 | U640: =IF(I640="","",(1&"/"&MONTH(I640)&"/"&YEAR(I640))*1) | V640: X
B641: MCS | D641: =INDEX(Cad_Natureza!$B$3:$C$52,MATCH('2025'!F641,Cad_Natureza!$C$3:$C$52,0),MATCH('2025'!D$2,Cad_Natureza!$B$3:$C$3,0)) -> REC7 | E641: PIX TRANSF Josimar31/07 | F641: CPF - Rec. Financeiras - Empréstimos | G641: MCS | H641: 45869 | J641: Empréstimo de Maurão paga pagar a contas atrasadas | K641: 105 | L641: =L640+K641 -> 340.28 | N641: =B641&D641&F641 -> MCSREC7CPF - Rec. Financeiras - Empréstimos | O641: =D641&F641 -> REC7CPF - Rec. Financeiras - Empréstimos | P641: ="MCS"&D641&F641 -> MCSREC7CPF - Rec. Financeiras - Empréstimos | Q641: ="MCS"&D641 -> MCSREC7 | R641: =B641&D641 -> MCSREC7 | T641: =(1&"/"&MONTH(H641)&"/"&YEAR(H641))*1 -> 45839 | U641: =IF(I641="","",(1&"/"&MONTH(I641)&"/"&YEAR(I641))*1)
B642: MCS | D642: =INDEX(Cad_Natureza!$B$3:$C$52,MATCH('2025'!F642,Cad_Natureza!$C$3:$C$52,0),MATCH('2025'!D$2,Cad_Natureza!$B$3:$C$3,0)) -> OPF2 | E642: RSCSS POSTO RIO NE3107 | F642: CPF - Desp. Transporte / Combustível | G642: MCS | H642: 45869 | J642: combustível | K642: -50 | L642: =L641+K642 -> 290.28 | N642: =B642&D642&F642 -> MCSOPF2CPF - Desp. Transporte / Combustível | O642: =D642&F642 -> OPF2CPF - Desp. Transporte / Combustível | P642: ="MCS"&D642&F642 -> MCSOPF2CPF - Desp. Transporte / Combustível | Q642: ="MCS"&D642 -> MCSOPF2 | R642: =B642&D642 -> MCSOPF2 | T642: =(1&"/"&MONTH(H642)&"/"&YEAR(H642))*1 -> 45839 | U642: =IF(I642="","",(1&"/"&MONTH(I642)&"/"&YEAR(I642))*1)
B643: MCS | D643: =INDEX(Cad_Natureza!$B$3:$C$52,MATCH('2025'!F643,Cad_Natureza!$C$3:$C$52,0),MATCH('2025'!D$2,Cad_Natureza!$B$3:$C$3,0)) -> GAST2 | E643: RSCSS 54760370 MAI0108 | F643: CPF - Desp. Lazer e Entretenimento - Cigarro | G643: MCS | H643: 45870 | J643: Palheiro | K643: -35 | L643: =L642+K643 -> 255.28 | N643: =B643&D643&F643 -> MCSGAST2CPF - Desp. Lazer e Entretenimento - Cigarro | O643: =D643&F643 -> GAST2CPF - Desp. Lazer e Entretenimento - Cigarro | P643: ="MCS"&D643&F643 -> MCSGAST2CPF - Desp. Lazer e Entretenimento - Cigarro | Q643: ="MCS"&D643 -> MCSGAST2 | R643: =B643&D643 -> MCSGAST2 | T643: =(1&"/"&MONTH(H643)&"/"&YEAR(H643))*1 -> 45870 | U643: =IF(I643="","",(1&"/"&MONTH(I643)&"/"&YEAR(I643))*1)
B644: MCS | D644: =INDEX(Cad_Natureza!$B$3:$C$52,MATCH('2025'!F644,Cad_Natureza!$C$3:$C$52,0),MATCH('2025'!D$2,Cad_Natureza!$B$3:$C$3,0)) -> OUG1 | E644: RSCSS DROGAZELO 0108 | F644: CPF - Outros gastos | G644: MCS | H644: 45870 | J644: Antitranspirante na farmácia do Pq. Amazônia | K644: -14.9 | L644: =L643+K644 -> 240.38 | N644: =B644&D644&F644 -> MCSOUG1CPF - Outros gastos | O644: =D644&F644 -> OUG1CPF - Outros gastos | P644: ="MCS"&D644&F644 -> MCSOUG1CPF - Outros gastos | Q644: ="MCS"&D644 -> MCSOUG1 | R644: =B644&D644 -> MCSOUG1 | T644: =(1&"/"&MONTH(H644)&"/"&YEAR(H644))*1 -> 45870 | U644: =IF(I644="","",(1&"/"&MONTH(I644)&"/"&YEAR(I644))*1)
B645: MCS | D645: =INDEX(Cad_Natureza!$B$3:$C$52,MATCH('2025'!F645,Cad_Natureza!$C$3:$C$52,0),MATCH('2025'!D$2,Cad_Natureza!$B$3:$C$3,0)) -> GAST1 | E645: RSCSS DANILLA CRIS0208 | F645: CPF - Desp. Lazer e Entretenimento - Bares | G645: MCS | H645: 45873 | K645: -25 | L645: =L644+K645 -> 215.38 | N645: =B645&D645&F645 -> MCSGAST1CPF - Desp. Lazer e Entretenimento - Bares | O645: =D645&F645 -> GAST1CPF - Desp. Lazer e Entretenimento - Bares | P645: ="MCS"&D645&F645 -> MCSGAST1CPF - Desp. Lazer e Entretenimento - Bares | Q645: ="MCS"&D645 -> MCSGAST1 | R645: =B645&D645 -> MCSGAST1 | T645: =(1&"/"&MONTH(H645)&"/"&YEAR(H645))*1 -> 45870 | U645: =IF(I645="","",(1&"/"&MONTH(I645)&"/"&YEAR(I645))*1)
B646: MCS | D646: =INDEX(Cad_Natureza!$B$3:$C$52,MATCH('2025'!F646,Cad_Natureza!$C$3:$C$52,0),MATCH('2025'!D$2,Cad_Natureza!$B$3:$C$3,0)) -> GAST1 | E646: RSCSS OXENTE BAR E0208 | F646: CPF - Desp. Lazer e Entretenimento - Bares | G646: MCS | H646: 45873 | J646: Bares | K646: -10 | L646: =L645+K646 -> 205.38 | N646: =B646&D646&F646 -> MCSGAST1CPF - Desp. Lazer e Entretenimento - Bares | O646: =D646&F646 -> GAST1CPF - Desp. Lazer e Entretenimento - Bares | P646: ="MCS"&D646&F646 -> MCSGAST1CPF - Desp. Lazer e Entretenimento - Bares | Q646: ="MCS"&D646 -> MCSGAST1 | R646: =B646&D646 -> MCSGAST1 | T646: =(1&"/"&MONTH(H646)&"/"&YEAR(H646))*1 -> 45870 | U646: =IF(I646="","",(1&"/"&MONTH(I646)&"/"&YEAR(I646))*1)
B647: MCS | D647: =INDEX(Cad_Natureza!$B$3:$C$52,MATCH('2025'!F647,Cad_Natureza!$C$3:$C$52,0),MATCH('2025'!D$2,Cad_Natureza!$B$3:$C$3,0)) -> OPF1 | E647: RSCSS MONDALE PANI0208 | F647: CPF - Desp. Alimentação / Refeição | G647: MCS | H647: 45873 | J647: Refeição | K647: -3.75 | L647: =L646+K647 -> 201.63 | N647: =B647&D647&F647 -> MCSOPF1CPF - Desp. Alimentação / Refeição | O647: =D647&F647 -> OPF1CPF - Desp. Alimentação / Refeição | P647: ="MCS"&D647&F647 -> MCSOPF1CPF - Desp. Alimentação / Refeição | Q647: ="MCS"&D647 -> MCSOPF1 | R647: =B647&D647 -> MCSOPF1 | T647: =(1&"/"&MONTH(H647)&"/"&YEAR(H647))*1 -> 45870 | U647: =IF(I647="","",(1&"/"&MONTH(I647)&"/"&YEAR(I647))*1)
B648: MCS | D648: =INDEX(Cad_Natureza!$B$3:$C$52,MATCH('2025'!F648,Cad_Natureza!$C$3:$C$52,0),MATCH('2025'!D$2,Cad_Natureza!$B$3:$C$3,0)) -> OPF2 | E648: RSCSS POSTO TALISM0208 | F648: CPF - Desp. Transporte / Combustível | G648: MCS | H648: 45873 | J648: combustível | K648: -50 | L648: =L647+K648 -> 151.63 | N648: =B648&D648&F648 -> MCSOPF2CPF - Desp. Transporte / Combustível | O648: =D648&F648 -> OPF2CPF - Desp. Transporte / Combustível | P648: ="MCS"&D648&F648 -> MCSOPF2CPF - Desp. Transporte / Combustível | Q648: ="MCS"&D648 -> MCSOPF2 | R648: =B648&D648 -> MCSOPF2 | T648: =(1&"/"&MONTH(H648)&"/"&YEAR(H648))*1 -> 45870 | U648: =IF(I648="","",(1&"/"&MONTH(I648)&"/"&YEAR(I648))*1)
B649: MCS | D649: =INDEX(Cad_Natureza!$B$3:$C$52,MATCH('2025'!F649,Cad_Natureza!$C$3:$C$52,0),MATCH('2025'!D$2,Cad_Natureza!$B$3:$C$3,0)) -> GAST2 | E649: RSCSS Gabriela 0208 | F649: CPF - Desp. Lazer e Entretenimento - Cigarro | G649: MCS | H649: 45873 | J649: Palheiro | K649: -4 | L649: =L648+K649 -> 147.63 | N649: =B649&D649&F649 -> MCSGAST2CPF - Desp. Lazer e Entretenimento - Cigarro | O649: =D649&F649 -> GAST2CPF - Desp. Lazer e Entretenimento - Cigarro | P649: ="MCS"&D649&F649 -> MCSGAST2CPF - Desp. Lazer e Entretenimento - Cigarro | Q649: ="MCS"&D649 -> MCSGAST2 | R649: =B649&D649 -> MCSGAST2 | T649: =(1&"/"&MONTH(H649)&"/"&YEAR(H649))*1 -> 45870 | U649: =IF(I649="","",(1&"/"&MONTH(I649)&"/"&YEAR(I649))*1)
B650: MCS | D650: =INDEX(Cad_Natureza!$B$3:$C$52,MATCH('2025'!F650,Cad_Natureza!$C$3:$C$52,0),MATCH('2025'!D$2,Cad_Natureza!$B$3:$C$3,0)) -> GAST1 | E650: RSCSS ANTONIO 0308 | F650: CPF - Desp. Lazer e Entretenimento - Bares | G650: MCS | H650: 45873 | J650: Bares - Som da Terra - Com a Meire | K650: -5 | L650: =L649+K650 -> 142.63 | N650: =B650&D650&F650 -> MCSGAST1CPF - Desp. Lazer e Entretenimento - Bares | O650: =D650&F650 -> GAST1CPF - Desp. Lazer e Entretenimento - Bares | P650: ="MCS"&D650&F650 -> MCSGAST1CPF - Desp. Lazer e Entretenimento - Bares | Q650: ="MCS"&D650 -> MCSGAST1 | R650: =B650&D650 -> MCSGAST1 | T650: =(1&"/"&MONTH(H650)&"/"&YEAR(H650))*1 -> 45870 | U650: =IF(I650="","",(1&"/"&MONTH(I650)&"/"&YEAR(I650))*1)
B651: MCS | D651: =INDEX(Cad_Natureza!$B$3:$C$52,MATCH('2025'!F651,Cad_Natureza!$C$3:$C$52,0),MATCH('2025'!D$2,Cad_Natureza!$B$3:$C$3,0)) -> GAST1 | E651: RSCSS ANTONIO 0308 | F651: CPF - Desp. Lazer e Entretenimento - Bares | G651: MCS | H651: 45873 | J651: Bares - Som da Terra - Com a Meire | K651: -5 | L651: =L650+K651 -> 137.63 | N651: =B651&D651&F651 -> MCSGAST1CPF - Desp. Lazer e Entretenimento - Bares | O651: =D651&F651 -> GAST1CPF - Desp. Lazer e Entretenimento - Bares | P651: ="MCS"&D651&F651 -> MCSGAST1CPF - Desp. Lazer e Entretenimento - Bares | Q651: ="MCS"&D651 -> MCSGAST1 | R651: =B651&D651 -> MCSGAST1 | T651: =(1&"/"&MONTH(H651)&"/"&YEAR(H651))*1 -> 45870 | U651: =IF(I651="","",(1&"/"&MONTH(I651)&"/"&YEAR(I651))*1)
B652: MCS | D652: =INDEX(Cad_Natureza!$B$3:$C$52,MATCH('2025'!F652,Cad_Natureza!$C$3:$C$52,0),MATCH('2025'!D$2,Cad_Natureza!$B$3:$C$3,0)) -> GAST1 | E652: RSCSS ANTONIO 0308 | F652: CPF - Desp. Lazer e Entretenimento - Bares | G652: MCS | H652: 45873 | J652: Bares - Som da Terra - Com a Meire | K652: -5 | L652: =L651+K652 -> 132.63 | N652: =B652&D652&F652 -> MCSGAST1CPF - Desp. Lazer e Entretenimento - Bares | O652: =D652&F652 -> GAST1CPF - Desp. Lazer e Entretenimento - Bares | P652: ="MCS"&D652&F652 -> MCSGAST1CPF - Desp. Lazer e Entretenimento - Bares | Q652: ="MCS"&D652 -> MCSGAST1 | R652: =B652&D652 -> MCSGAST1 | T652: =(1&"/"&MONTH(H652)&"/"&YEAR(H652))*1 -> 45870 | U652: =IF(I652="","",(1&"/"&MONTH(I652)&"/"&YEAR(I652))*1)
B653: MCS | D653: =INDEX(Cad_Natureza!$B$3:$C$52,MATCH('2025'!F653,Cad_Natureza!$C$3:$C$52,0),MATCH('2025'!D$2,Cad_Natureza!$B$3:$C$3,0)) -> GAST1 | E653: RSCSS ANTONIO 0308 | F653: CPF - Desp. Lazer e Entretenimento - Bares | G653: MCS | H653: 45873 | J653: Bares - Som da Terra - Com a Meire | K653: -5 | L653: =L652+K653 -> 127.63 | N653: =B653&D653&F653 -> MCSGAST1CPF - Desp. Lazer e Entretenimento - Bares | O653: =D653&F653 -> GAST1CPF - Desp. Lazer e Entretenimento - Bares | P653: ="MCS"&D653&F653 -> MCSGAST1CPF - Desp. Lazer e Entretenimento - Bares | Q653: ="MCS"&D653 -> MCSGAST1 | R653: =B653&D653 -> MCSGAST1 | T653: =(1&"/"&MONTH(H653)&"/"&YEAR(H653))*1 -> 45870 | U653: =IF(I653="","",(1&"/"&MONTH(I653)&"/"&YEAR(I653))*1)
B654: MCS | D654: =INDEX(Cad_Natureza!$B$3:$C$52,MATCH('2025'!F654,Cad_Natureza!$C$3:$C$52,0),MATCH('2025'!D$2,Cad_Natureza!$B$3:$C$3,0)) -> GAST1 | E654: RSCSS MP BARBOSAD0308 | F654: CPF - Desp. Lazer e Entretenimento - Bares | G654: MCS | H654: 45873 | J654: Bares - Bar da rua da feira do Serra Dourada | K654: -10 | L654: =L653+K654 -> 117.63 | N654: =B654&D654&F654 -> MCSGAST1CPF - Desp. Lazer e Entretenimento - Bares | O654: =D654&F654 -> GAST1CPF - Desp. Lazer e Entretenimento - Bares | P654: ="MCS"&D654&F654 -> MCSGAST1CPF - Desp. Lazer e Entretenimento - Bares | Q654: ="MCS"&D654 -> MCSGAST1 | R654: =B654&D654 -> MCSGAST1 | T654: =(1&"/"&MONTH(H654)&"/"&YEAR(H654))*1 -> 45870 | U654: =IF(I654="","",(1&"/"&MONTH(I654)&"/"&YEAR(I654))*1)
B655: MCS | D655: =INDEX(Cad_Natureza!$B$3:$C$52,MATCH('2025'!F655,Cad_Natureza!$C$3:$C$52,0),MATCH('2025'!D$2,Cad_Natureza!$B$3:$C$3,0)) -> GAST1 | E655: RSCSS BAIUCA DISTR0308 | F655: CPF - Desp. Lazer e Entretenimento - Bares | G655: MCS | H655: 45873 | J655: bares | K655: -6 | L655: =L654+K655 -> 111.63 | N655: =B655&D655&F655 -> MCSGAST1CPF - Desp. Lazer e Entretenimento - Bares | O655: =D655&F655 -> GAST1CPF - Desp. Lazer e Entretenimento - Bares | P655: ="MCS"&D655&F655 -> MCSGAST1CPF - Desp. Lazer e Entretenimento - Bares | Q655: ="MCS"&D655 -> MCSGAST1 | R655: =B655&D655 -> MCSGAST1 | T655: =(1&"/"&MONTH(H655)&"/"&YEAR(H655))*1 -> 45870 | U655: =IF(I655="","",(1&"/"&MONTH(I655)&"/"&YEAR(I655))*1)
B656: MCS | D656: =INDEX(Cad_Natureza!$B$3:$C$52,MATCH('2025'!F656,Cad_Natureza!$C$3:$C$52,0),MATCH('2025'!D$2,Cad_Natureza!$B$3:$C$3,0)) -> FIN2 | E656: TAR PACOTE ITAU JUL/25 | F656: CPF - Desp. Financeiras - Juros / Tarifas | G656: MCS | H656: 45873 | J656: Tarifas bancárias | K656: -28 | L656: =L655+K656 -> 83.63 | N656: =B656&D656&F656 -> MCSFIN2CPF - Desp. Financeiras - Juros / Tarifas | O656: =D656&F656 -> FIN2CPF - Desp. Financeiras - Juros / Tarifas | P656: ="MCS"&D656&F656 -> MCSFIN2CPF - Desp. Financeiras - Juros / Tarifas | Q656: ="MCS"&D656 -> MCSFIN2 | R656: =B656&D656 -> MCSFIN2 | T656: =(1&"/"&MONTH(H656)&"/"&YEAR(H656))*1 -> 45870 | U656: =IF(I656="","",(1&"/"&MONTH(I656)&"/"&YEAR(I656))*1)
B657: MCS | D657: =INDEX(Cad_Natureza!$B$3:$C$52,MATCH('2025'!F657,Cad_Natureza!$C$3:$C$52,0),MATCH('2025'!D$2,Cad_Natureza!$B$3:$C$3,0)) -> GAST2 | E657: RSCSS AgnaldoCosta0608 | F657: CPF - Desp. Lazer e Entretenimento - Cigarro | G657: MCS | H657: 45875 | J657: Palheiro | K657: -6 | L657: =L656+K657 -> 77.63 | N657: =B657&D657&F657 -> MCSGAST2CPF - Desp. Lazer e Entretenimento - Cigarro | O657: =D657&F657 -> GAST2CPF - Desp. Lazer e Entretenimento - Cigarro | P657: ="MCS"&D657&F657 -> MCSGAST2CPF - Desp. Lazer e Entretenimento - Cigarro | Q657: ="MCS"&D657 -> MCSGAST2 | R657: =B657&D657 -> MCSGAST2 | T657: =(1&"/"&MONTH(H657)&"/"&YEAR(H657))*1 -> 45870 | U657: =IF(I657="","",(1&"/"&MONTH(I657)&"/"&YEAR(I657))*1)
B658: MCS | D658: =INDEX(Cad_Natureza!$B$3:$C$52,MATCH('2025'!F658,Cad_Natureza!$C$3:$C$52,0),MATCH('2025'!D$2,Cad_Natureza!$B$3:$C$3,0)) -> REC1 | E658: PIX TRANSF FABRICI06/08 | F658: CPF - Remun. Salário / Pró-Labore | G658: MCS | H658: 45875 | J658: Remuneração | K658: 2500 | L658: =L657+K658 -> 2577.63 | N658: =B658&D658&F658 -> MCSREC1CPF - Remun. Salário / Pró-Labore | O658: =D658&F658 -> REC1CPF - Remun. Salário / Pró-Labore | P658: ="MCS"&D658&F658 -> MCSREC1CPF - Remun. Salário / Pró-Labore | Q658: ="MCS"&D658 -> MCSREC1 | R658: =B658&D658 -> MCSREC1 | T658: =(1&"/"&MONTH(H658)&"/"&YEAR(H658))*1 -> 45870 | U658: =IF(I658="","",(1&"/"&MONTH(I658)&"/"&YEAR(I658))*1)
B659: MCS | D659: =INDEX(Cad_Natureza!$B$3:$C$52,MATCH('2025'!F659,Cad_Natureza!$C$3:$C$52,0),MATCH('2025'!D$2,Cad_Natureza!$B$3:$C$3,0)) -> PENS3 | E659: Pensão - Plano de saúde de Alice e Davi ref. 08/2025 | F659: CPF - Pensão - Plano de saúde | G659: MCS | H659: 45874 | J659: Pensão - Plano de saúde de Alice e Davi ref. 08/2025 | K659: -638.57 | L659: =L658+K659 -> 1939.06 | N659: =B659&D659&F659 -> MCSPENS3CPF - Pensão - Plano de saúde | O659: =D659&F659 -> PENS3CPF - Pensão - Plano de saúde | P659: ="MCS"&D659&F659 -> MCSPENS3CPF - Pensão - Plano de saúde | Q659: ="MCS"&D659 -> MCSPENS3 | R659: =B659&D659 -> MCSPENS3 | T659: =(1&"/"&MONTH(H659)&"/"&YEAR(H659))*1 -> 45870 | U659: =IF(I659="","",(1&"/"&MONTH(I659)&"/"&YEAR(I659))*1) | V659: X
B660: MCS | D660: =INDEX(Cad_Natureza!$B$3:$C$52,MATCH('2025'!F660,Cad_Natureza!$C$3:$C$52,0),MATCH('2025'!D$2,Cad_Natureza!$B$3:$C$3,0)) -> PENS3 | E660: Pensão - Plano de saúde de Alice e Davi ref. 09/2025 | F660: CPF - Pensão - Plano de saúde | G660: MCS | H660: 46280 | J660: Pensão - Plano de saúde de Alice e Davi ref. 09/2025 | K660: 0 | L660: =L659+K660 -> 1939.06 | N660: =B660&D660&F660 -> MCSPENS3CPF - Pensão - Plano de saúde | O660: =D660&F660 -> PENS3CPF - Pensão - Plano de saúde | P660: ="MCS"&D660&F660 -> MCSPENS3CPF - Pensão - Plano de saúde | Q660: ="MCS"&D660 -> MCSPENS3 | R660: =B660&D660 -> MCSPENS3 | T660: =(1&"/"&MONTH(H660)&"/"&YEAR(H660))*1 -> 46266 | U660: =IF(I660="","",(1&"/"&MONTH(I660)&"/"&YEAR(I660))*1) | V660: X
B661: MCS | D661: =INDEX(Cad_Natureza!$B$3:$C$52,MATCH('2025'!F661,Cad_Natureza!$C$3:$C$52,0),MATCH('2025'!D$2,Cad_Natureza!$B$3:$C$3,0)) -> PENS3 | E661: Pensão - Plano de saúde de Alice e Davi ref. 09/2025 | F661: CPF - Pensão - Plano de saúde | G661: MCS | H661: 46280 | J661: Pensão - Plano de saúde de Alice e Davi ref. 10/2025 | K661: 0 | L661: =L660+K661 -> 1939.06 | N661: =B661&D661&F661 -> MCSPENS3CPF - Pensão - Plano de saúde | O661: =D661&F661 -> PENS3CPF - Pensão - Plano de saúde | P661: ="MCS"&D661&F661 -> MCSPENS3CPF - Pensão - Plano de saúde | Q661: ="MCS"&D661 -> MCSPENS3 | R661: =B661&D661 -> MCSPENS3 | T661: =(1&"/"&MONTH(H661)&"/"&YEAR(H661))*1 -> 46266 | U661: =IF(I661="","",(1&"/"&MONTH(I661)&"/"&YEAR(I661))*1) | V661: X
B662: MCS | D662: =INDEX(Cad_Natureza!$B$3:$C$52,MATCH('2025'!F662,Cad_Natureza!$C$3:$C$52,0),MATCH('2025'!D$2,Cad_Natureza!$B$3:$C$3,0)) -> PENS2 | E662: Pensão - Conta de energia ref. 06/2025, vcto 02/07 | F662: CPF - Pensão - Energia | G662: MCS | H662: 45874 | J662: Pensão - Conta de energia ref. 06/2025 | K662: -677.92 | L662: =L661+K662 -> 1261.14 | N662: =B662&D662&F662 -> MCSPENS2CPF - Pensão - Energia | O662: =D662&F662 -> PENS2CPF - Pensão - Energia | P662: ="MCS"&D662&F662 -> MCSPENS2CPF - Pensão - Energia | Q662: ="MCS"&D662 -> MCSPENS2 | R662: =B662&D662 -> MCSPENS2 | T662: =(1&"/"&MONTH(H662)&"/"&YEAR(H662))*1 -> 45870 | U662: =IF(I662="","",(1&"/"&MONTH(I662)&"/"&YEAR(I662))*1) | V662: X
B663: MCS | D663: =INDEX(Cad_Natureza!$B$3:$C$52,MATCH('2025'!F663,Cad_Natureza!$C$3:$C$52,0),MATCH('2025'!D$2,Cad_Natureza!$B$3:$C$3,0)) -> PENS1 | E663: Pensão - Aluguel ref. 08/2025 | F663: CPF - Pensão - Aluguel | G663: MCS | H663: 45874 | J663: Pensão - aluguel 08 2025 | K663: -600 | L663: =L662+K663 -> 661.14 | N663: =B663&D663&F663 -> MCSPENS1CPF - Pensão - Aluguel | O663: =D663&F663 -> PENS1CPF - Pensão - Aluguel | P663: ="MCS"&D663&F663 -> MCSPENS1CPF - Pensão - Aluguel | Q663: ="MCS"&D663 -> MCSPENS1 | R663: =B663&D663 -> MCSPENS1 | T663: =(1&"/"&MONTH(H663)&"/"&YEAR(H663))*1 -> 45870 | U663: =IF(I663="","",(1&"/"&MONTH(I663)&"/"&YEAR(I663))*1) | V663: X
B664: MCS | D664: =INDEX(Cad_Natureza!$B$3:$C$52,MATCH('2025'!F664,Cad_Natureza!$C$3:$C$52,0),MATCH('2025'!D$2,Cad_Natureza!$B$3:$C$3,0)) -> OPF1 | E664: RSCSS MP BEMBOLAD0708 | F664: CPF - Desp. Alimentação / Refeição | G664: MCS | H664: 45876 | J664: Refeição dos dias que estavam em aberto | K664: -184 | L664: =L663+K664 -> 477.14 | N664: =B664&D664&F664 -> MCSOPF1CPF - Desp. Alimentação / Refeição | O664: =D664&F664 -> OPF1CPF - Desp. Alimentação / Refeição | P664: ="MCS"&D664&F664 -> MCSOPF1CPF - Desp. Alimentação / Refeição | Q664: ="MCS"&D664 -> MCSOPF1 | R664: =B664&D664 -> MCSOPF1 | T664: =(1&"/"&MONTH(H664)&"/"&YEAR(H664))*1 -> 45870 | U664: =IF(I664="","",(1&"/"&MONTH(I664)&"/"&YEAR(I664))*1)
B665: MCS | D665: =INDEX(Cad_Natureza!$B$3:$C$52,MATCH('2025'!F665,Cad_Natureza!$C$3:$C$52,0),MATCH('2025'!D$2,Cad_Natureza!$B$3:$C$3,0)) -> GAST2 | E665: RSCSS MP EMPRIOMA0708 | F665: CPF - Desp. Lazer e Entretenimento - Cigarro | G665: MCS | H665: 45876 | J665: Palheiro | K665: -2.5 | L665: =L664+K665 -> 474.64 | N665: =B665&D665&F665 -> MCSGAST2CPF - Desp. Lazer e Entretenimento - Cigarro | O665: =D665&F665 -> GAST2CPF - Desp. Lazer e Entretenimento - Cigarro | P665: ="MCS"&D665&F665 -> MCSGAST2CPF - Desp. Lazer e Entretenimento - Cigarro | Q665: ="MCS"&D665 -> MCSGAST2 | R665: =B665&D665 -> MCSGAST2 | T665: =(1&"/"&MONTH(H665)&"/"&YEAR(H665))*1 -> 45870 | U665: =IF(I665="","",(1&"/"&MONTH(I665)&"/"&YEAR(I665))*1)
B666: MCS | D666: =INDEX(Cad_Natureza!$B$3:$C$52,MATCH('2025'!F666,Cad_Natureza!$C$3:$C$52,0),MATCH('2025'!D$2,Cad_Natureza!$B$3:$C$3,0)) -> REC5 | E666: PIX TRANSF ANA COS07/08 | F666: CPF - Outras receitas | G666: MCS | H666: 45876 | J666: Rcbto para pagar a internet. Não consegui pagar | K666: 120 | L666: =L665+K666 -> 594.64 | N666: =B666&D666&F666 -> MCSREC5CPF - Outras receitas | O666: =D666&F666 -> REC5CPF - Outras receitas | P666: ="MCS"&D666&F666 -> MCSREC5CPF - Outras receitas | Q666: ="MCS"&D666 -> MCSREC5 | R666: =B666&D666 -> MCSREC5 | T666: =(1&"/"&MONTH(H666)&"/"&YEAR(H666))*1 -> 45870 | U666: =IF(I666="","",(1&"/"&MONTH(I666)&"/"&YEAR(I666))*1)
B667: MCS | D667: =INDEX(Cad_Natureza!$B$3:$C$52,MATCH('2025'!F667,Cad_Natureza!$C$3:$C$52,0),MATCH('2025'!D$2,Cad_Natureza!$B$3:$C$3,0)) -> GAST2 | E667: RSCSS ALTAS HORAS 0708 | F667: CPF - Desp. Lazer e Entretenimento - Cigarro | G667: MCS | H667: 45876 | J667: Palheiro | K667: -35 | L667: =L666+K667 -> 559.64 | N667: =B667&D667&F667 -> MCSGAST2CPF - Desp. Lazer e Entretenimento - Cigarro | O667: =D667&F667 -> GAST2CPF - Desp. Lazer e Entretenimento - Cigarro | P667: ="MCS"&D667&F667 -> MCSGAST2CPF - Desp. Lazer e Entretenimento - Cigarro | Q667: ="MCS"&D667 -> MCSGAST2 | R667: =B667&D667 -> MCSGAST2 | T667: =(1&"/"&MONTH(H667)&"/"&YEAR(H667))*1 -> 45870 | U667: =IF(I667="","",(1&"/"&MONTH(I667)&"/"&YEAR(I667))*1)
B668: MCS | D668: =INDEX(Cad_Natureza!$B$3:$C$52,MATCH('2025'!F668,Cad_Natureza!$C$3:$C$52,0),MATCH('2025'!D$2,Cad_Natureza!$B$3:$C$3,0)) -> GAST1 | E668: RSCSS VanderleiDaS0708 | F668: CPF - Desp. Lazer e Entretenimento - Bares | G668: MCS | H668: 45876 | J668: Bares | K668: -13 | L668: =L667+K668 -> 546.64 | N668: =B668&D668&F668 -> MCSGAST1CPF - Desp. Lazer e Entretenimento - Bares | O668: =D668&F668 -> GAST1CPF - Desp. Lazer e Entretenimento - Bares | P668: ="MCS"&D668&F668 -> MCSGAST1CPF - Desp. Lazer e Entretenimento - Bares | Q668: ="MCS"&D668 -> MCSGAST1 | R668: =B668&D668 -> MCSGAST1 | T668: =(1&"/"&MONTH(H668)&"/"&YEAR(H668))*1 -> 45870 | U668: =IF(I668="","",(1&"/"&MONTH(I668)&"/"&YEAR(I668))*1)
B669: MCS | D669: =INDEX(Cad_Natureza!$B$3:$C$52,MATCH('2025'!F669,Cad_Natureza!$C$3:$C$52,0),MATCH('2025'!D$2,Cad_Natureza!$B$3:$C$3,0)) -> GAST2 | E669: RSCSS FIORELLA PAN0808 | F669: CPF - Desp. Lazer e Entretenimento - Cigarro | G669: MCS | H669: 45877 | J669: Palheiro | K669: -2.5 | L669: =L668+K669 -> 544.14 | N669: =B669&D669&F669 -> MCSGAST2CPF - Desp. Lazer e Entretenimento - Cigarro | O669: =D669&F669 -> GAST2CPF - Desp. Lazer e Entretenimento - Cigarro | P669: ="MCS"&D669&F669 -> MCSGAST2CPF - Desp. Lazer e Entretenimento - Cigarro | Q669: ="MCS"&D669 -> MCSGAST2 | R669: =B669&D669 -> MCSGAST2 | T669: =(1&"/"&MONTH(H669)&"/"&YEAR(H669))*1 -> 45870 | U669: =IF(I669="","",(1&"/"&MONTH(I669)&"/"&YEAR(I669))*1)
B670: MCS | D670: =INDEX(Cad_Natureza!$B$3:$C$52,MATCH('2025'!F670,Cad_Natureza!$C$3:$C$52,0),MATCH('2025'!D$2,Cad_Natureza!$B$3:$C$3,0)) -> OPF2 | E670: RSCSS POSTO SAO SE0808 | F670: CPF - Desp. Transporte / Combustível | G670: MCS | H670: 45877 | J670: combustível | K670: -50 | L670: =L669+K670 -> 494.14 | N670: =B670&D670&F670 -> MCSOPF2CPF - Desp. Transporte / Combustível | O670: =D670&F670 -> OPF2CPF - Desp. Transporte / Combustível | P670: ="MCS"&D670&F670 -> MCSOPF2CPF - Desp. Transporte / Combustível | Q670: ="MCS"&D670 -> MCSOPF2 | R670: =B670&D670 -> MCSOPF2 | T670: =(1&"/"&MONTH(H670)&"/"&YEAR(H670))*1 -> 45870 | U670: =IF(I670="","",(1&"/"&MONTH(I670)&"/"&YEAR(I670))*1)
B671: MCS | D671: =INDEX(Cad_Natureza!$B$3:$C$52,MATCH('2025'!F671,Cad_Natureza!$C$3:$C$52,0),MATCH('2025'!D$2,Cad_Natureza!$B$3:$C$3,0)) -> GAST1 | E671: RSCSS MP BARJR 0808 | F671: CPF - Desp. Lazer e Entretenimento - Bares | G671: MCS | H671: 45877 | J671: Bares | K671: -5 | L671: =L670+K671 -> 489.14 | N671: =B671&D671&F671 -> MCSGAST1CPF - Desp. Lazer e Entretenimento - Bares | O671: =D671&F671 -> GAST1CPF - Desp. Lazer e Entretenimento - Bares | P671: ="MCS"&D671&F671 -> MCSGAST1CPF - Desp. Lazer e Entretenimento - Bares | Q671: ="MCS"&D671 -> MCSGAST1 | R671: =B671&D671 -> MCSGAST1 | T671: =(1&"/"&MONTH(H671)&"/"&YEAR(H671))*1 -> 45870 | U671: =IF(I671="","",(1&"/"&MONTH(I671)&"/"&YEAR(I671))*1)
B672: MCS | D672: =INDEX(Cad_Natureza!$B$3:$C$52,MATCH('2025'!F672,Cad_Natureza!$C$3:$C$52,0),MATCH('2025'!D$2,Cad_Natureza!$B$3:$C$3,0)) -> GAST1 | E672: RSCSS OXENTE BAR E0908 | F672: CPF - Desp. Lazer e Entretenimento - Bares | G672: MCS | H672: 45880 | J672: Oxente com a Kessia | K672: -25 | L672: =L671+K672 -> 464.14 | N672: =B672&D672&F672 -> MCSGAST1CPF - Desp. Lazer e Entretenimento - Bares | O672: =D672&F672 -> GAST1CPF - Desp. Lazer e Entretenimento - Bares | P672: ="MCS"&D672&F672 -> MCSGAST1CPF - Desp. Lazer e Entretenimento - Bares | Q672: ="MCS"&D672 -> MCSGAST1 | R672: =B672&D672 -> MCSGAST1 | T672: =(1&"/"&MONTH(H672)&"/"&YEAR(H672))*1 -> 45870 | U672: =IF(I672="","",(1&"/"&MONTH(I672)&"/"&YEAR(I672))*1)
B673: MCS | D673: =INDEX(Cad_Natureza!$B$3:$C$52,MATCH('2025'!F673,Cad_Natureza!$C$3:$C$52,0),MATCH('2025'!D$2,Cad_Natureza!$B$3:$C$3,0)) -> GAST1 | E673: RSCSS OXENTE BAR E0908 | F673: CPF - Desp. Lazer e Entretenimento - Bares | G673: MCS | H673: 45880 | J673: Oxente com a Kessia | K673: -18 | L673: =L672+K673 -> 446.14 | N673: =B673&D673&F673 -> MCSGAST1CPF - Desp. Lazer e Entretenimento - Bares | O673: =D673&F673 -> GAST1CPF - Desp. Lazer e Entretenimento - Bares | P673: ="MCS"&D673&F673 -> MCSGAST1CPF - Desp. Lazer e Entretenimento - Bares | Q673: ="MCS"&D673 -> MCSGAST1 | R673: =B673&D673 -> MCSGAST1 | T673: =(1&"/"&MONTH(H673)&"/"&YEAR(H673))*1 -> 45870 | U673: =IF(I673="","",(1&"/"&MONTH(I673)&"/"&YEAR(I673))*1)
B674: MCS | D674: =INDEX(Cad_Natureza!$B$3:$C$52,MATCH('2025'!F674,Cad_Natureza!$C$3:$C$52,0),MATCH('2025'!D$2,Cad_Natureza!$B$3:$C$3,0)) -> GAST1 | E674: PIX QRS Sandra Silv09/08 | F674: CPF - Desp. Lazer e Entretenimento - Bares | G674: MCS | H674: 45880 | K674: -18 | L674: =L673+K674 -> 428.14 | N674: =B674&D674&F674 -> MCSGAST1CPF - Desp. Lazer e Entretenimento - Bares | O674: =D674&F674 -> GAST1CPF - Desp. Lazer e Entretenimento - Bares | P674: ="MCS"&D674&F674 -> MCSGAST1CPF - Desp. Lazer e Entretenimento - Bares | Q674: ="MCS"&D674 -> MCSGAST1 | R674: =B674&D674 -> MCSGAST1 | T674: =(1&"/"&MONTH(H674)&"/"&YEAR(H674))*1 -> 45870 | U674: =IF(I674="","",(1&"/"&MONTH(I674)&"/"&YEAR(I674))*1)
B675: MCS | D675: =INDEX(Cad_Natureza!$B$3:$C$52,MATCH('2025'!F675,Cad_Natureza!$C$3:$C$52,0),MATCH('2025'!D$2,Cad_Natureza!$B$3:$C$3,0)) -> OPF2 | E675: RSCSS AUTO POSTO I0908 | F675: CPF - Desp. Transporte / Combustível | G675: MCS | H675: 45880 | J675: combustível | K675: -50 | L675: =L674+K675 -> 378.14 | N675: =B675&D675&F675 -> MCSOPF2CPF - Desp. Transporte / Combustível | O675: =D675&F675 -> OPF2CPF - Desp. Transporte / Combustível | P675: ="MCS"&D675&F675 -> MCSOPF2CPF - Desp. Transporte / Combustível | Q675: ="MCS"&D675 -> MCSOPF2 | R675: =B675&D675 -> MCSOPF2 | T675: =(1&"/"&MONTH(H675)&"/"&YEAR(H675))*1 -> 45870 | U675: =IF(I675="","",(1&"/"&MONTH(I675)&"/"&YEAR(I675))*1)
B676: MCS | D676: =INDEX(Cad_Natureza!$B$3:$C$52,MATCH('2025'!F676,Cad_Natureza!$C$3:$C$52,0),MATCH('2025'!D$2,Cad_Natureza!$B$3:$C$3,0)) -> GAST1 | E676: RSCSS DANCETERIA CHAVES1008 | F676: CPF - Desp. Lazer e Entretenimento - Bares | G676: MCS | H676: 45880 | J676: Danceteria Chaves | K676: -15 | L676: =L675+K676 -> 363.14 | N676: =B676&D676&F676 -> MCSGAST1CPF - Desp. Lazer e Entretenimento - Bares | O676: =D676&F676 -> GAST1CPF - Desp. Lazer e Entretenimento - Bares | P676: ="MCS"&D676&F676 -> MCSGAST1CPF - Desp. Lazer e Entretenimento - Bares | Q676: ="MCS"&D676 -> MCSGAST1 | R676: =B676&D676 -> MCSGAST1 | T676: =(1&"/"&MONTH(H676)&"/"&YEAR(H676))*1 -> 45870 | U676: =IF(I676="","",(1&"/"&MONTH(I676)&"/"&YEAR(I676))*1)
B677: MCS | D677: =INDEX(Cad_Natureza!$B$3:$C$52,MATCH('2025'!F677,Cad_Natureza!$C$3:$C$52,0),MATCH('2025'!D$2,Cad_Natureza!$B$3:$C$3,0)) -> GAST1 | E677: RSCSS NovoTomShow 1008 | F677: CPF - Desp. Lazer e Entretenimento - Bares | G677: MCS | H677: 45880 | J677: Bares - Tom Brasil com a Lidia | K677: -15 | L677: =L676+K677 -> 348.14 | N677: =B677&D677&F677 -> MCSGAST1CPF - Desp. Lazer e Entretenimento - Bares | O677: =D677&F677 -> GAST1CPF - Desp. Lazer e Entretenimento - Bares | P677: ="MCS"&D677&F677 -> MCSGAST1CPF - Desp. Lazer e Entretenimento - Bares | Q677: ="MCS"&D677 -> MCSGAST1 | R677: =B677&D677 -> MCSGAST1 | T677: =(1&"/"&MONTH(H677)&"/"&YEAR(H677))*1 -> 45870 | U677: =IF(I677="","",(1&"/"&MONTH(I677)&"/"&YEAR(I677))*1)
B678: MCS | D678: =INDEX(Cad_Natureza!$B$3:$C$52,MATCH('2025'!F678,Cad_Natureza!$C$3:$C$52,0),MATCH('2025'!D$2,Cad_Natureza!$B$3:$C$3,0)) -> OPF1 | E678: RSCSS AVAMTHE SUPE1008 | F678: CPF - Desp. Alimentação / Refeição | G678: MCS | H678: 45880 | J678: Carne para churrasco na casa da mãe do Deka | K678: -29.22 | L678: =L677+K678 -> 318.92 | N678: =B678&D678&F678 -> MCSOPF1CPF - Desp. Alimentação / Refeição | O678: =D678&F678 -> OPF1CPF - Desp. Alimentação / Refeição | P678: ="MCS"&D678&F678 -> MCSOPF1CPF - Desp. Alimentação / Refeição | Q678: ="MCS"&D678 -> MCSOPF1 | R678: =B678&D678 -> MCSOPF1 | T678: =(1&"/"&MONTH(H678)&"/"&YEAR(H678))*1 -> 45870 | U678: =IF(I678="","",(1&"/"&MONTH(I678)&"/"&YEAR(I678))*1)
B679: MCS | D679: =INDEX(Cad_Natureza!$B$3:$C$52,MATCH('2025'!F679,Cad_Natureza!$C$3:$C$52,0),MATCH('2025'!D$2,Cad_Natureza!$B$3:$C$3,0)) -> OPF2 | E679: RSCSS POSTO SAO SE1008 | F679: CPF - Desp. Transporte / Combustível | G679: MCS | H679: 45880 | J679: combustível | K679: -50 | L679: =L678+K679 -> 268.92 | N679: =B679&D679&F679 -> MCSOPF2CPF - Desp. Transporte / Combustível | O679: =D679&F679 -> OPF2CPF - Desp. Transporte / Combustível | P679: ="MCS"&D679&F679 -> MCSOPF2CPF - Desp. Transporte / Combustível | Q679: ="MCS"&D679 -> MCSOPF2 | R679: =B679&D679 -> MCSOPF2 | T679: =(1&"/"&MONTH(H679)&"/"&YEAR(H679))*1 -> 45870 | U679: =IF(I679="","",(1&"/"&MONTH(I679)&"/"&YEAR(I679))*1)
B680: MCS | D680: =INDEX(Cad_Natureza!$B$3:$C$52,MATCH('2025'!F680,Cad_Natureza!$C$3:$C$52,0),MATCH('2025'!D$2,Cad_Natureza!$B$3:$C$3,0)) -> DESP5 | E680: PIX TRANSF MCS SER11/08 | F680: CPF - Transf. Da conta PF para a conta PJ | G680: MCS | H680: 45880 | J680: Transferência entre contas | K680: -268 | L680: =L679+K680 -> 0.92 | N680: =B680&D680&F680 -> MCSDESP5CPF - Transf. Da conta PF para a conta PJ | O680: =D680&F680 -> DESP5CPF - Transf. Da conta PF para a conta PJ | P680: ="MCS"&D680&F680 -> MCSDESP5CPF - Transf. Da conta PF para a conta PJ | Q680: ="MCS"&D680 -> MCSDESP5 | R680: =B680&D680 -> MCSDESP5 | T680: =(1&"/"&MONTH(H680)&"/"&YEAR(H680))*1 -> 45870 | U680: =IF(I680="","",(1&"/"&MONTH(I680)&"/"&YEAR(I680))*1)
B681: MCS | D681: =INDEX(Cad_Natureza!$B$3:$C$52,MATCH('2025'!F681,Cad_Natureza!$C$3:$C$52,0),MATCH('2025'!D$2,Cad_Natureza!$B$3:$C$3,0)) -> GAST2 | E681: RSCSS ALTAS HORAS 1108 | F681: CPF - Desp. Lazer e Entretenimento - Cigarro | G681: MCS | H681: 45880 | J681: Palheiro | K681: -5 | L681: =L680+K681 -> -4.08 | N681: =B681&D681&F681 -> MCSGAST2CPF - Desp. Lazer e Entretenimento - Cigarro | O681: =D681&F681 -> GAST2CPF - Desp. Lazer e Entretenimento - Cigarro | P681: ="MCS"&D681&F681 -> MCSGAST2CPF - Desp. Lazer e Entretenimento - Cigarro | Q681: ="MCS"&D681 -> MCSGAST2 | R681: =B681&D681 -> MCSGAST2 | T681: =(1&"/"&MONTH(H681)&"/"&YEAR(H681))*1 -> 45870 | U681: =IF(I681="","",(1&"/"&MONTH(I681)&"/"&YEAR(I681))*1)
B682: MCS | D682: =INDEX(Cad_Natureza!$B$3:$C$52,MATCH('2025'!F682,Cad_Natureza!$C$3:$C$52,0),MATCH('2025'!D$2,Cad_Natureza!$B$3:$C$3,0)) -> GAST1 | E682: RSCSS VanderleiDaS1108 | F682: CPF - Desp. Lazer e Entretenimento - Bares | G682: MCS | H682: 45880 | J682: Bares | K682: -5 | L682: =L681+K682 -> -9.08 | N682: =B682&D682&F682 -> MCSGAST1CPF - Desp. Lazer e Entretenimento - Bares | O682: =D682&F682 -> GAST1CPF - Desp. Lazer e Entretenimento - Bares | P682: ="MCS"&D682&F682 -> MCSGAST1CPF - Desp. Lazer e Entretenimento - Bares | Q682: ="MCS"&D682 -> MCSGAST1 | R682: =B682&D682 -> MCSGAST1 | T682: =(1&"/"&MONTH(H682)&"/"&YEAR(H682))*1 -> 45870 | U682: =IF(I682="","",(1&"/"&MONTH(I682)&"/"&YEAR(I682))*1)
B683: MCS | D683: =INDEX(Cad_Natureza!$B$3:$C$52,MATCH('2025'!F683,Cad_Natureza!$C$3:$C$52,0),MATCH('2025'!D$2,Cad_Natureza!$B$3:$C$3,0)) -> GAST1 | E683: RSCSS VanderleiDaS1208 | F683: CPF - Desp. Lazer e Entretenimento - Bares | G683: MCS | H683: 45881 | J683: Bares | K683: -9 | L683: =L682+K683 -> -18.08 | N683: =B683&D683&F683 -> MCSGAST1CPF - Desp. Lazer e Entretenimento - Bares | O683: =D683&F683 -> GAST1CPF - Desp. Lazer e Entretenimento - Bares | P683: ="MCS"&D683&F683 -> MCSGAST1CPF - Desp. Lazer e Entretenimento - Bares | Q683: ="MCS"&D683 -> MCSGAST1 | R683: =B683&D683 -> MCSGAST1 | T683: =(1&"/"&MONTH(H683)&"/"&YEAR(H683))*1 -> 45870 | U683: =IF(I683="","",(1&"/"&MONTH(I683)&"/"&YEAR(I683))*1)
B684: MCS | D684: =INDEX(Cad_Natureza!$B$3:$C$52,MATCH('2025'!F684,Cad_Natureza!$C$3:$C$52,0),MATCH('2025'!D$2,Cad_Natureza!$B$3:$C$3,0)) -> FIN3 | E684: RENEGOCIACAO ITAU 08/18 | F684: CPF - Desp. Financeiras - Empréstimos bancários | G684: MCS | H684: 45882 | J684: Renegociação cheque especial (parte do saldo) | K684: -31.92 | L684: =L683+K684 -> -50 | N684: =B684&D684&F684 -> MCSFIN3CPF - Desp. Financeiras - Empréstimos bancários | O684: =D684&F684 -> FIN3CPF - Desp. Financeiras - Empréstimos bancários | P684: ="MCS"&D684&F684 -> MCSFIN3CPF - Desp. Financeiras - Empréstimos bancários | Q684: ="MCS"&D684 -> MCSFIN3 | R684: =B684&D684 -> MCSFIN3 | T684: =(1&"/"&MONTH(H684)&"/"&YEAR(H684))*1 -> 45870 | U684: =IF(I684="","",(1&"/"&MONTH(I684)&"/"&YEAR(I684))*1)
B685: MCS | D685: =INDEX(Cad_Natureza!$B$3:$C$52,MATCH('2025'!F685,Cad_Natureza!$C$3:$C$52,0),MATCH('2025'!D$2,Cad_Natureza!$B$3:$C$3,0)) -> FIN2 | E685: JUROS LIMITE DA CONTA | F685: CPF - Desp. Financeiras - Juros / Tarifas | G685: MCS | H685: 45889 | J685: Juros do cheque especial | K685: -1 | L685: =L684+K685 -> -51 | N685: =B685&D685&F685 -> MCSFIN2CPF - Desp. Financeiras - Juros / Tarifas | O685: =D685&F685 -> FIN2CPF - Desp. Financeiras - Juros / Tarifas | P685: ="MCS"&D685&F685 -> MCSFIN2CPF - Desp. Financeiras - Juros / Tarifas | Q685: ="MCS"&D685 -> MCSFIN2 | R685: =B685&D685 -> MCSFIN2 | T685: =(1&"/"&MONTH(H685)&"/"&YEAR(H685))*1 -> 45870 | U685: =IF(I685="","",(1&"/"&MONTH(I685)&"/"&YEAR(I685))*1)
B686: MCS | D686: =INDEX(Cad_Natureza!$B$3:$C$52,MATCH('2025'!F686,Cad_Natureza!$C$3:$C$52,0),MATCH('2025'!D$2,Cad_Natureza!$B$3:$C$3,0)) -> TRI1 | E686: IOF | F686: CPF - Desp. Impostos e Obrigações | G686: MCS | H686: 45902 | J686: Impostos | K686: -0.27 | L686: =L685+K686 -> -51.27 | N686: =B686&D686&F686 -> MCSTRI1CPF - Desp. Impostos e Obrigações | O686: =D686&F686 -> TRI1CPF - Desp. Impostos e Obrigações | P686: ="MCS"&D686&F686 -> MCSTRI1CPF - Desp. Impostos e Obrigações | Q686: ="MCS"&D686 -> MCSTRI1 | R686: =B686&D686 -> MCSTRI1 | T686: =(1&"/"&MONTH(H686)&"/"&YEAR(H686))*1 -> 45901 | U686: =IF(I686="","",(1&"/"&MONTH(I686)&"/"&YEAR(I686))*1)
... B721: MCS | D721: =INDEX(Cad_Natureza!$B$3:$C$52,MATCH('2025'!F721,Cad_Natureza!$C$3:$C$52,0),MATCH('2025'!D$2,Cad_Natureza!$B$3:$C$3,0)) -> GAST1 | E721: RSCSS VanderleiDaS0511 | F721: CPF - Desp. Lazer e Entretenimento - Bares | G721: MCS | H721: 45966 | J721: Bares | K721: -78 | L721: =L720+K721 -> 498.77 | N721: =B721&D721&F721 -> MCSGAST1CPF - Desp. Lazer e Entretenimento - Bares | O721: =D721&F721 -> GAST1CPF - Desp. Lazer e Entretenimento - Bares | P721: ="MCS"&D721&F721 -> MCSGAST1CPF - Desp. Lazer e Entretenimento - Bares | Q721: ="MCS"&D721 -> MCSGAST1 | R721: =B721&D721 -> MCSGAST1 | T721: =(1&"/"&MONTH(H721)&"/"&YEAR(H721))*1 -> 45962 | U721: =IF(I721="","",(1&"/"&MONTH(I721)&"/"&YEAR(I721))*1)
B722: MCS | D722: =INDEX(Cad_Natureza!$B$3:$C$52,MATCH('2025'!F722,Cad_Natureza!$C$3:$C$52,0),MATCH('2025'!D$2,Cad_Natureza!$B$3:$C$3,0)) -> PENS6 | E722: PIX QRS PAGBRASIL06/11 | F722: CPF - Pensão - Farmácia e Saúde | G722: MCS | H722: 45967 | J722: Pensão - Lenço umedecido | K722: -9.9 | L722: =L721+K722 -> 488.87 | N722: =B722&D722&F722 -> MCSPENS6CPF - Pensão - Farmácia e Saúde | O722: =D722&F722 -> PENS6CPF - Pensão - Farmácia e Saúde | P722: ="MCS"&D722&F722 -> MCSPENS6CPF - Pensão - Farmácia e Saúde | Q722: ="MCS"&D722 -> MCSPENS6 | R722: =B722&D722 -> MCSPENS6 | T722: =(1&"/"&MONTH(H722)&"/"&YEAR(H722))*1 -> 45962 | U722: =IF(I722="","",(1&"/"&MONTH(I722)&"/"&YEAR(I722))*1) | V722: X
B723: MCS | D723: =INDEX(Cad_Natureza!$B$3:$C$52,MATCH('2025'!F723,Cad_Natureza!$C$3:$C$52,0),MATCH('2025'!D$2,Cad_Natureza!$B$3:$C$3,0)) -> OPF1 | E723: RSCSS TOSCANO GRIL0611 | F723: CPF - Desp. Alimentação / Refeição | G723: MCS | H723: 45967 | J723: Refeição | K723: -20 | L723: =L722+K723 -> 468.87 | N723: =B723&D723&F723 -> MCSOPF1CPF - Desp. Alimentação / Refeição | O723: =D723&F723 -> OPF1CPF - Desp. Alimentação / Refeição | P723: ="MCS"&D723&F723 -> MCSOPF1CPF - Desp. Alimentação / Refeição | Q723: ="MCS"&D723 -> MCSOPF1 | R723: =B723&D723 -> MCSOPF1 | T723: =(1&"/"&MONTH(H723)&"/"&YEAR(H723))*1 -> 45962 | U723: =IF(I723="","",(1&"/"&MONTH(I723)&"/"&YEAR(I723))*1)
B724: MCS | D724: =INDEX(Cad_Natureza!$B$3:$C$52,MATCH('2025'!F724,Cad_Natureza!$C$3:$C$52,0),MATCH('2025'!D$2,Cad_Natureza!$B$3:$C$3,0)) -> FIN1 | E724: PIX TRANSF Josimar06/11 | F724: CPF - Desp. Financeiras - Empréstimos | G724: MCS | H724: 45967 | J724: Retorno de empréstimo ao Maurão | K724: -200 | L724: =L723+K724 -> 268.87 | N724: =B724&D724&F724 -> MCSFIN1CPF - Desp. Financeiras - Empréstimos | O724: =D724&F724 -> FIN1CPF - Desp. Financeiras - Empréstimos | P724: ="MCS"&D724&F724 -> MCSFIN1CPF - Desp. Financeiras - Empréstimos | Q724: ="MCS"&D724 -> MCSFIN1 | R724: =B724&D724 -> MCSFIN1 | T724: =(1&"/"&MONTH(H724)&"/"&YEAR(H724))*1 -> 45962 | U724: =IF(I724="","",(1&"/"&MONTH(I724)&"/"&YEAR(I724))*1)
B725: MCS | D725: =INDEX(Cad_Natureza!$B$3:$C$52,MATCH('2025'!F725,Cad_Natureza!$C$3:$C$52,0),MATCH('2025'!D$2,Cad_Natureza!$B$3:$C$3,0)) -> FIN1 | E725: PIX TRANSF UEMERSO06/11 | F725: CPF - Desp. Financeiras - Empréstimos | G725: MCS | H725: 45967 | J725: Retorno de empréstimo ao Parazinho | K725: -80 | L725: =L724+K725 -> 188.87 | N725: =B725&D725&F725 -> MCSFIN1CPF - Desp. Financeiras - Empréstimos | O725: =D725&F725 -> FIN1CPF - Desp. Financeiras - Empréstimos | P725: ="MCS"&D725&F725 -> MCSFIN1CPF - Desp. Financeiras - Empréstimos | Q725: ="MCS"&D725 -> MCSFIN1 | R725: =B725&D725 -> MCSFIN1 | T725: =(1&"/"&MONTH(H725)&"/"&YEAR(H725))*1 -> 45962 | U725: =IF(I725="","",(1&"/"&MONTH(I725)&"/"&YEAR(I725))*1)
B726: MCS | D726: =INDEX(Cad_Natureza!$B$3:$C$52,MATCH('2025'!F726,Cad_Natureza!$C$3:$C$52,0),MATCH('2025'!D$2,Cad_Natureza!$B$3:$C$3,0)) -> GAST1 | E726: PIX TRANSF UENDER 06/11 | F726: CPF - Desp. Lazer e Entretenimento - Bares | G726: MCS | H726: 45967 | J726: Bares - Partida de sinuca para o Parazinho | K726: -5 | L726: =L725+K726 -> 183.87 | N726: =B726&D726&F726 -> MCSGAST1CPF - Desp. Lazer e Entretenimento - Bares | O726: =D726&F726 -> GAST1CPF - Desp. Lazer e Entretenimento - Bares | P726: ="MCS"&D726&F726 -> MCSGAST1CPF - Desp. Lazer e Entretenimento - Bares | Q726: ="MCS"&D726 -> MCSGAST1 | R726: =B726&D726 -> MCSGAST1 | T726: =(1&"/"&MONTH(H726)&"/"&YEAR(H726))*1 -> 45962 | U726: =IF(I726="","",(1&"/"&MONTH(I726)&"/"&YEAR(I726))*1)
B727: MCS | D727: =INDEX(Cad_Natureza!$B$3:$C$52,MATCH('2025'!F727,Cad_Natureza!$C$3:$C$52,0),MATCH('2025'!D$2,Cad_Natureza!$B$3:$C$3,0)) -> GAST1 | E727: RSCSS VanderleiDaS0611 | F727: CPF - Desp. Lazer e Entretenimento - Bares | G727: MCS | H727: 45967 | J727: Bares | K727: -20 | L727: =L726+K727 -> 163.87 | N727: =B727&D727&F727 -> MCSGAST1CPF - Desp. Lazer e Entretenimento - Bares | O727: =D727&F727 -> GAST1CPF - Desp. Lazer e Entretenimento - Bares | P727: ="MCS"&D727&F727 -> MCSGAST1CPF - Desp. Lazer e Entretenimento - Bares | Q727: ="MCS"&D727 -> MCSGAST1 | R727: =B727&D727 -> MCSGAST1 | T727: =(1&"/"&MONTH(H727)&"/"&YEAR(H727))*1 -> 45962 | U727: =IF(I727="","",(1&"/"&MONTH(I727)&"/"&YEAR(I727))*1)
B728: MCS | D728: =INDEX(Cad_Natureza!$B$3:$C$52,MATCH('2025'!F728,Cad_Natureza!$C$3:$C$52,0),MATCH('2025'!D$2,Cad_Natureza!$B$3:$C$3,0)) -> PENS6 | E728: RSCSS PDV GRANDE M0611 | F728: CPF - Pensão - Farmácia e Saúde | G728: MCS | H728: 45967 | J728: Pensão - Farmácia | K728: -22.99 | L728: =L727+K728 -> 140.88 | N728: =B728&D728&F728 -> MCSPENS6CPF - Pensão - Farmácia e Saúde | O728: =D728&F728 -> PENS6CPF - Pensão - Farmácia e Saúde | P728: ="MCS"&D728&F728 -> MCSPENS6CPF - Pensão - Farmácia e Saúde | Q728: ="MCS"&D728 -> MCSPENS6 | R728: =B728&D728 -> MCSPENS6 | T728: =(1&"/"&MONTH(H728)&"/"&YEAR(H728))*1 -> 45962 | U728: =IF(I728="","",(1&"/"&MONTH(I728)&"/"&YEAR(I728))*1) | V728: X
B729: MCS | D729: =INDEX(Cad_Natureza!$B$3:$C$52,MATCH('2025'!F729,Cad_Natureza!$C$3:$C$52,0),MATCH('2025'!D$2,Cad_Natureza!$B$3:$C$3,0)) -> OPF1 | E729: RSCSS TOSCANO GRIL0711 | F729: CPF - Desp. Alimentação / Refeição | G729: MCS | H729: 45968 | J729: Refeição | K729: -20 | L729: =L728+K729 -> 120.88 | N729: =B729&D729&F729 -> MCSOPF1CPF - Desp. Alimentação / Refeição | O729: =D729&F729 -> OPF1CPF - Desp. Alimentação / Refeição | P729: ="MCS"&D729&F729 -> MCSOPF1CPF - Desp. Alimentação / Refeição | Q729: ="MCS"&D729 -> MCSOPF1 | R729: =B729&D729 -> MCSOPF1 | T729: =(1&"/"&MONTH(H729)&"/"&YEAR(H729))*1 -> 45962 | U729: =IF(I729="","",(1&"/"&MONTH(I729)&"/"&YEAR(I729))*1)
B730: MCS | D730: =INDEX(Cad_Natureza!$B$3:$C$52,MATCH('2025'!F730,Cad_Natureza!$C$3:$C$52,0),MATCH('2025'!D$2,Cad_Natureza!$B$3:$C$3,0)) -> REC4 | E730: PIX TRANSF MCS SER07/11 | F730: CPF - Transf. Da conta PJ para a conta PF | G730: MCS | H730: 45968 | J730: Transferência entre contas | K730: 3000 | L730: =L729+K730 -> 3120.88 | N730: =B730&D730&F730 -> MCSREC4CPF - Transf. Da conta PJ para a conta PF | O730: =D730&F730 -> REC4CPF - Transf. Da conta PJ para a conta PF | P730: ="MCS"&D730&F730 -> MCSREC4CPF - Transf. Da conta PJ para a conta PF | Q730: ="MCS"&D730 -> MCSREC4 | R730: =B730&D730 -> MCSREC4 | T730: =(1&"/"&MONTH(H730)&"/"&YEAR(H730))*1 -> 45962 | U730: =IF(I730="","",(1&"/"&MONTH(I730)&"/"&YEAR(I730))*1)
...

Sheet 2026
K1: =SUBTOTAL(9,K3:K687) -> -2945.87 | L1: -1
B2: EMPRESA | C2: x | D2: Natureza | E2: Descrição | F2: Centro de Resultado | G2: Entidade | H2: Data real | I2: Data prevista | J2: Observações | K2: Total | L2: Saldo banco | M2: x | N2: Empresa & CR | O2: Concat 2 | P2: Concat 3 | Q2: Concat 3 | R2: Empresa & Natureza | S2: x | T2: DATA REAL | U2: DATA PREVISTA | V2: X
B3: MCS | D3: =INDEX(Cad_Natureza!$B$3:$C$52,MATCH('2026'!F3,Cad_Natureza!$C$3:$C$52,0),MATCH('2026'!D$2,Cad_Natureza!$B$3:$C$3,0)) -> GAST2 | E3: RSCSS MP DISTIMPE0101 | F3: CPF - Desp. Lazer e Entretenimento - Cigarro | G3: MCS | H3: 46024 | J3: Palheiro | K3: -5 | L3: 347.96 | N3: =B3&D3&F3 -> MCSGAST2CPF - Desp. Lazer e Entretenimento - Cigarro | O3: =D3&F3 -> GAST2CPF - Desp. Lazer e Entretenimento - Cigarro | P3: ="MCS"&D3&F3 -> MCSGAST2CPF - Desp. Lazer e Entretenimento - Cigarro | Q3: ="MCS"&D3 -> MCSGAST2 | R3: =B3&D3 -> MCSGAST2 | T3: =(1&"/"&MONTH(H3)&"/"&YEAR(H3))*1 -> 46023 | U3: =IF(I3="","",(1&"/"&MONTH(I3)&"/"&YEAR(I3))*1) | V3: Z
B4: MCS | D4: =INDEX(Cad_Natureza!$B$3:$C$52,MATCH('2026'!F4,Cad_Natureza!$C$3:$C$52,0),MATCH('2026'!D$2,Cad_Natureza!$B$3:$C$3,0)) -> DESP2 | E4: PIX QRS Claro03/01 | F4: CPF - Desp. Telefone / Internet | G4: MCS | H4: 46027 | J4: Mensalidade do celular - em atraso | K4: -86.64 | L4: =L3+K4 -> 261.32 | N4: =B4&D4&F4 -> MCSDESP2CPF - Desp. Telefone / Internet | O4: =D4&F4 -> DESP2CPF - Desp. Telefone / Internet | P4: ="MCS"&D4&F4 -> MCSDESP2CPF - Desp. Telefone / Internet | Q4: ="MCS"&D4 -> MCSDESP2 | R4: =B4&D4 -> MCSDESP2 | T4: =(1&"/"&MONTH(H4)&"/"&YEAR(H4))*1 -> 46023 | U4: =IF(I4="","",(1&"/"&MONTH(I4)&"/"&YEAR(I4))*1) | V4: Z
B5: MCS | D5: =INDEX(Cad_Natureza!$B$3:$C$52,MATCH('2026'!F5,Cad_Natureza!$C$3:$C$52,0),MATCH('2026'!D$2,Cad_Natureza!$B$3:$C$3,0)) -> DESP2 | E5: INT /CLARO S.A 119210717 | F5: CPF - Desp. Telefone / Internet | G5: MCS | H5: 46027 | J5: Mensalidade do celular - em atraso - Parcela 1/5 | K5: -38.13 | L5: =L4+K5 -> 223.19 | N5: =B5&D5&F5 -> MCSDESP2CPF - Desp. Telefone / Internet | O5: =D5&F5 -> DESP2CPF - Desp. Telefone / Internet | P5: ="MCS"&D5&F5 -> MCSDESP2CPF - Desp. Telefone / Internet | Q5: ="MCS"&D5 -> MCSDESP2 | R5: =B5&D5 -> MCSDESP2 | T5: =(1&"/"&MONTH(H5)&"/"&YEAR(H5))*1 -> 46023 | U5: =IF(I5="","",(1&"/"&MONTH(I5)&"/"&YEAR(I5))*1) | V5: Z
B6: MCS | D6: =INDEX(Cad_Natureza!$B$3:$C$52,MATCH('2026'!F6,Cad_Natureza!$C$3:$C$52,0),MATCH('2026'!D$2,Cad_Natureza!$B$3:$C$3,0)) -> GAST2 | E6: RSCSS RosimilsonMa0301 | F6: CPF - Desp. Lazer e Entretenimento - Cigarro | G6: MCS | H6: 46027 | J6: Palheiro | K6: -10 | L6: =L5+K6 -> 213.19 | N6: =B6&D6&F6 -> MCSGAST2CPF - Desp. Lazer e Entretenimento - Cigarro | O6: =D6&F6 -> GAST2CPF - Desp. Lazer e Entretenimento - Cigarro | P6: ="MCS"&D6&F6 -> MCSGAST2CPF - Desp. Lazer e Entretenimento - Cigarro | Q6: ="MCS"&D6 -> MCSGAST2 | R6: =B6&D6 -> MCSGAST2 | T6: =(1&"/"&MONTH(H6)&"/"&YEAR(H6))*1 -> 46023 | U6: =IF(I6="","",(1&"/"&MONTH(I6)&"/"&YEAR(I6))*1) | V6: Z
B7: MCS | D7: =INDEX(Cad_Natureza!$B$3:$C$52,MATCH('2026'!F7,Cad_Natureza!$C$3:$C$52,0),MATCH('2026'!D$2,Cad_Natureza!$B$3:$C$3,0)) -> GAST2 | E7: RSCSS MARCOS PAULO0301 | F7: CPF - Desp. Lazer e Entretenimento - Cigarro | G7: MCS | H7: 46027 | J7: Palheiro | K7: -4 | L7: =L6+K7 -> 209.19 | N7: =B7&D7&F7 -> MCSGAST2CPF - Desp. Lazer e Entretenimento - Cigarro | O7: =D7&F7 -> GAST2CPF - Desp. Lazer e Entretenimento - Cigarro | P7: ="MCS"&D7&F7 -> MCSGAST2CPF - Desp. Lazer e Entretenimento - Cigarro | Q7: ="MCS"&D7 -> MCSGAST2 | R7: =B7&D7 -> MCSGAST2 | T7: =(1&"/"&MONTH(H7)&"/"&YEAR(H7))*1 -> 46023 | U7: =IF(I7="","",(1&"/"&MONTH(I7)&"/"&YEAR(I7))*1) | V7: Z
B8: MCS | D8: =INDEX(Cad_Natureza!$B$3:$C$52,MATCH('2026'!F8,Cad_Natureza!$C$3:$C$52,0),MATCH('2026'!D$2,Cad_Natureza!$B$3:$C$3,0)) -> OPF2 | E8: RSCSS POSTO SAO JO0501 | F8: CPF - Desp. Transporte / Combustível | G8: MCS | H8: 46027 | J8: Combustível | K8: -50 | L8: =L7+K8 -> 159.19 | N8: =B8&D8&F8 -> MCSOPF2CPF - Desp. Transporte / Combustível | O8: =D8&F8 -> OPF2CPF - Desp. Transporte / Combustível | P8: ="MCS"&D8&F8 -> MCSOPF2CPF - Desp. Transporte / Combustível | Q8: ="MCS"&D8 -> MCSOPF2 | R8: =B8&D8 -> MCSOPF2 | T8: =(1&"/"&MONTH(H8)&"/"&YEAR(H8))*1 -> 46023 | U8: =IF(I8="","",(1&"/"&MONTH(I8)&"/"&YEAR(I8))*1) | V8: Z
B9: MCS | D9: =INDEX(Cad_Natureza!$B$3:$C$52,MATCH('2026'!F9,Cad_Natureza!$C$3:$C$52,0),MATCH('2026'!D$2,Cad_Natureza!$B$3:$C$3,0)) -> OPF1 | E9: RSCSS TOSCANO GRIL0501 | F9: CPF - Desp. Alimentação / Refeição | G9: MCS | H9: 46027 | J9: Refeição | K9: -23.33 | L9: =L8+K9 -> 135.86 | N9: =B9&D9&F9 -> MCSOPF1CPF - Desp. Alimentação / Refeição | O9: =D9&F9 -> OPF1CPF - Desp. Alimentação / Refeição | P9: ="MCS"&D9&F9 -> MCSOPF1CPF - Desp. Alimentação / Refeição | Q9: ="MCS"&D9 -> MCSOPF1 | R9: =B9&D9 -> MCSOPF1 | T9: =(1&"/"&MONTH(H9)&"/"&YEAR(H9))*1 -> 46023 | U9: =IF(I9="","",(1&"/"&MONTH(I9)&"/"&YEAR(I9))*1) | V9: X
B10: MCS | D10: =INDEX(Cad_Natureza!$B$3:$C$52,MATCH('2026'!F10,Cad_Natureza!$C$3:$C$52,0),MATCH('2026'!D$2,Cad_Natureza!$B$3:$C$3,0)) -> GAST1 | E10: RSCSS MP 243303760501 | F10: CPF - Desp. Lazer e Entretenimento - Bares | G10: MCS | H10: 46027 | J10: Bares | K10: -16 | L10: =L9+K10 -> 119.86 | N10: =B10&D10&F10 -> MCSGAST1CPF - Desp. Lazer e Entretenimento - Bares | O10: =D10&F10 -> GAST1CPF - Desp. Lazer e Entretenimento - Bares | P10: ="MCS"&D10&F10 -> MCSGAST1CPF - Desp. Lazer e Entretenimento - Bares | Q10: ="MCS"&D10 -> MCSGAST1 | R10: =B10&D10 -> MCSGAST1 | T10: =(1&"/"&MONTH(H10)&"/"&YEAR(H10))*1 -> 46023 | U10: =IF(I10="","",(1&"/"&MONTH(I10)&"/"&YEAR(I10))*1) | V10: X
B11: MCS | D11: =INDEX(Cad_Natureza!$B$3:$C$52,MATCH('2026'!F11,Cad_Natureza!$C$3:$C$52,0),MATCH('2026'!D$2,Cad_Natureza!$B$3:$C$3,0)) -> PENS6 | E11: RSCSS DROGARIA MEN0501 | F11: CPF - Pensão - Farmácia e Saúde | G11: MCS | H11: 46027 | J11: Pensão - Farmácia | K11: -14.49 | L11: =L10+K11 -> 105.37 | N11: =B11&D11&F11 -> MCSPENS6CPF - Pensão - Farmácia e Saúde | O11: =D11&F11 -> PENS6CPF - Pensão - Farmácia e Saúde | P11: ="MCS"&D11&F11 -> MCSPENS6CPF - Pensão - Farmácia e Saúde | Q11: ="MCS"&D11 -> MCSPENS6 | R11: =B11&D11 -> MCSPENS6 | T11: =(1&"/"&MONTH(H11)&"/"&YEAR(H11))*1 -> 46023 | U11: =IF(I11="","",(1&"/"&MONTH(I11)&"/"&YEAR(I11))*1) | V11: Z
B12: MCS | D12: =INDEX(Cad_Natureza!$B$3:$C$52,MATCH('2026'!F12,Cad_Natureza!$C$3:$C$52,0),MATCH('2026'!D$2,Cad_Natureza!$B$3:$C$3,0)) -> GAST1 | E12: RSCSS LindomarBarb0501 | F12: CPF - Desp. Lazer e Entretenimento - Bares | G12: MCS | H12: 46027 | J12: Bares | K12: -10 | L12: =L11+K12 -> 95.37 | N12: =B12&D12&F12 -> MCSGAST1CPF - Desp. Lazer e Entretenimento - Bares | O12: =D12&F12 -> GAST1CPF - Desp. Lazer e Entretenimento - Bares | P12: ="MCS"&D12&F12 -> MCSGAST1CPF - Desp. Lazer e Entretenimento - Bares | Q12: ="MCS"&D12 -> MCSGAST1 | R12: =B12&D12 -> MCSGAST1 | T12: =(1&"/"&MONTH(H12)&"/"&YEAR(H12))*1 -> 46023 | U12: =IF(I12="","",(1&"/"&MONTH(I12)&"/"&YEAR(I12))*1) | V12: Z
B13: MCS | D13: =INDEX(Cad_Natureza!$B$3:$C$52,MATCH('2026'!F13,Cad_Natureza!$C$3:$C$52,0),MATCH('2026'!D$2,Cad_Natureza!$B$3:$C$3,0)) -> FIN2 | E13: TAR PACOTE ITAU DEZ/25 | F13: CPF - Desp. Financeiras - Juros / Tarifas | G13: MCS | H13: 46027 | J13: Tarifas bancárias | K13: -28 | L13: =L12+K13 -> 67.37 | N13: =B13&D13&F13 -> MCSFIN2CPF - Desp. Financeiras - Juros / Tarifas | O13: =D13&F13 -> FIN2CPF - Desp. Financeiras - Juros / Tarifas | P13: ="MCS"&D13&F13 -> MCSFIN2CPF - Desp. Financeiras - Juros / Tarifas | Q13: ="MCS"&D13 -> MCSFIN2 | R13: =B13&D13 -> MCSFIN2 | T13: =(1&"/"&MONTH(H13)&"/"&YEAR(H13))*1 -> 46023 | U13: =IF(I13="","",(1&"/"&MONTH(I13)&"/"&YEAR(I13))*1) | V13: Z
B14: MCS | D14: =INDEX(Cad_Natureza!$B$3:$C$52,MATCH('2026'!F14,Cad_Natureza!$C$3:$C$52,0),MATCH('2026'!D$2,Cad_Natureza!$B$3:$C$3,0)) -> OPF2 | E14: RSCSS POSTO SAO JO0601 | F14: CPF - Desp. Transporte / Combustível | G14: MCS | H14: 46028 | J14: Combustível | K14: -40 | L14: =L13+K14 -> 27.37 | N14: =B14&D14&F14 -> MCSOPF2CPF - Desp. Transporte / Combustível | O14: =D14&F14 -> OPF2CPF - Desp. Transporte / Combustível | P14: ="MCS"&D14&F14 -> MCSOPF2CPF - Desp. Transporte / Combustível | Q14: ="MCS"&D14 -> MCSOPF2 | R14: =B14&D14 -> MCSOPF2 | T14: =(1&"/"&MONTH(H14)&"/"&YEAR(H14))*1 -> 46023 | U14: =IF(I14="","",(1&"/"&MONTH(I14)&"/"&YEAR(I14))*1) | V14: Z
B15: MCS | D15: =INDEX(Cad_Natureza!$B$3:$C$52,MATCH('2026'!F15,Cad_Natureza!$C$3:$C$52,0),MATCH('2026'!D$2,Cad_Natureza!$B$3:$C$3,0)) -> GAST1 | E15: RSCSS MP 243303760601 | F15: CPF - Desp. Lazer e Entretenimento - Bares | G15: MCS | H15: 46028 | J15: Bares - Derley | K15: -10 | L15: =L14+K15 -> 17.37 | N15: =B15&D15&F15 -> MCSGAST1CPF - Desp. Lazer e Entretenimento - Bares | O15: =D15&F15 -> GAST1CPF - Desp. Lazer e Entretenimento - Bares | P15: ="MCS"&D15&F15 -> MCSGAST1CPF - Desp. Lazer e Entretenimento - Bares | Q15: ="MCS"&D15 -> MCSGAST1 | R15: =B15&D15 -> MCSGAST1 | T15: =(1&"/"&MONTH(H15)&"/"&YEAR(H15))*1 -> 46023 | U15: =IF(I15="","",(1&"/"&MONTH(I15)&"/"&YEAR(I15))*1) | V15: Z
... B650: MCS | D650: =INDEX(Cad_Natureza!$B$3:$C$52,MATCH('2026'!F650,Cad_Natureza!$C$3:$C$52,0),MATCH('2026'!D$2,Cad_Natureza!$B$3:$C$3,0)) -> PENS2 | E650: PIX QRS EQUATORIAL 15/06 | F650: CPF - Pensão - Energia | G650: MCS | H650: 46188 | J650: Pensão - Conta de energia ref. 04/2026 | K650: -490.89 | L650: =L649+K650 -> 596.13 | N650: =B650&D650&F650 -> MCSPENS2CPF - Pensão - Energia | O650: =D650&F650 -> PENS2CPF - Pensão - Energia | P650: ="MCS"&D650&F650 -> MCSPENS2CPF - Pensão - Energia | Q650: ="MCS"&D650 -> MCSPENS2 | R650: =B650&D650 -> MCSPENS2 | T650: =(1&"/"&MONTH(H650)&"/"&YEAR(H650))*1 -> 46174 | U650: =IF(I650="","",(1&"/"&MONTH(I650)&"/"&YEAR(I650))*1) | V650: X
B651: MCS | D651: =INDEX(Cad_Natureza!$B$3:$C$52,MATCH('2026'!F651,Cad_Natureza!$C$3:$C$52,0),MATCH('2026'!D$2,Cad_Natureza!$B$3:$C$3,0)) -> #N/A | G651: MCS | N651: =B651&D651&F651 -> #N/A | O651: =D651&F651 -> #N/A | P651: ="MCS"&D651&F651 -> #N/A | Q651: ="MCS"&D651 -> #N/A | R651: =B651&D651 -> #N/A | T651: =(1&"/"&MONTH(H651)&"/"&YEAR(H651))*1 -> 1 | U651: =IF(I651="","",(1&"/"&MONTH(I651)&"/"&YEAR(I651))*1) | V651: X
B652: MCS | D652: =INDEX(Cad_Natureza!$B$3:$C$52,MATCH('2026'!F652,Cad_Natureza!$C$3:$C$52,0),MATCH('2026'!D$2,Cad_Natureza!$B$3:$C$3,0)) -> #N/A | G652: MCS | N652: =B652&D652&F652 -> #N/A | O652: =D652&F652 -> #N/A | P652: ="MCS"&D652&F652 -> #N/A | Q652: ="MCS"&D652 -> #N/A | R652: =B652&D652 -> #N/A | T652: =(1&"/"&MONTH(H652)&"/"&YEAR(H652))*1 -> 1 | U652: =IF(I652="","",(1&"/"&MONTH(I652)&"/"&YEAR(I652))*1) | V652: Z
B653: MCS | D653: =INDEX(Cad_Natureza!$B$3:$C$52,MATCH('2026'!F653,Cad_Natureza!$C$3:$C$52,0),MATCH('2026'!D$2,Cad_Natureza!$B$3:$C$3,0)) -> #N/A | G653: MCS | N653: =B653&D653&F653 -> #N/A | O653: =D653&F653 -> #N/A | P653: ="MCS"&D653&F653 -> #N/A | Q653: ="MCS"&D653 -> #N/A | R653: =B653&D653 -> #N/A | T653: =(1&"/"&MONTH(H653)&"/"&YEAR(H653))*1 -> 1 | U653: =IF(I653="","",(1&"/"&MONTH(I653)&"/"&YEAR(I653))*1) | V653: Z
B654: MCS | D654: =INDEX(Cad_Natureza!$B$3:$C$52,MATCH('2026'!F654,Cad_Natureza!$C$3:$C$52,0),MATCH('2026'!D$2,Cad_Natureza!$B$3:$C$3,0)) -> #N/A | G654: MCS | N654: =B654&D654&F654 -> #N/A | O654: =D654&F654 -> #N/A | P654: ="MCS"&D654&F654 -> #N/A | Q654: ="MCS"&D654 -> #N/A | R654: =B654&D654 -> #N/A | T654: =(1&"/"&MONTH(H654)&"/"&YEAR(H654))*1 -> 1 | U654: =IF(I654="","",(1&"/"&MONTH(I654)&"/"&YEAR(I654))*1) | V654: Z
B655: MCS | D655: =INDEX(Cad_Natureza!$B$3:$C$52,MATCH('2026'!F655,Cad_Natureza!$C$3:$C$52,0),MATCH('2026'!D$2,Cad_Natureza!$B$3:$C$3,0)) -> #N/A | G655: MCS | N655: =B655&D655&F655 -> #N/A | O655: =D655&F655 -> #N/A | P655: ="MCS"&D655&F655 -> #N/A | Q655: ="MCS"&D655 -> #N/A | R655: =B655&D655 -> #N/A | T655: =(1&"/"&MONTH(H655)&"/"&YEAR(H655))*1 -> 1 | U655: =IF(I655="","",(1&"/"&MONTH(I655)&"/"&YEAR(I655))*1) | V655: Z
B656: MCS | D656: =INDEX(Cad_Natureza!$B$3:$C$52,MATCH('2026'!F656,Cad_Natureza!$C$3:$C$52,0),MATCH('2026'!D$2,Cad_Natureza!$B$3:$C$3,0)) -> #N/A | G656: MCS | N656: =B656&D656&F656 -> #N/A | O656: =D656&F656 -> #N/A | P656: ="MCS"&D656&F656 -> #N/A | Q656: ="MCS"&D656 -> #N/A | R656: =B656&D656 -> #N/A | T656: =(1&"/"&MONTH(H656)&"/"&YEAR(H656))*1 -> 1 | U656: =IF(I656="","",(1&"/"&MONTH(I656)&"/"&YEAR(I656))*1) | V656: Z
B657: MCS | D657: =INDEX(Cad_Natureza!$B$3:$C$52,MATCH('2026'!F657,Cad_Natureza!$C$3:$C$52,0),MATCH('2026'!D$2,Cad_Natureza!$B$3:$C$3,0)) -> #N/A | G657: MCS | J657: DAS - MCS Serviços ref. 09/2025 - Parcelar | K657: =-5000*6% -> -300 | N657: =B657&D657&F657 -> #N/A | O657: =D657&F657 -> #N/A | P657: ="MCS"&D657&F657 -> #N/A | Q657: ="MCS"&D657 -> #N/A | R657: =B657&D657 -> #N/A | T657: =(1&"/"&MONTH(H657)&"/"&YEAR(H657))*1 -> 1 | U657: =IF(I657="","",(1&"/"&MONTH(I657)&"/"&YEAR(I657))*1) | V657: X
B658: MCS | D658: =INDEX(Cad_Natureza!$B$3:$C$52,MATCH('2026'!F658,Cad_Natureza!$C$3:$C$52,0),MATCH('2026'!D$2,Cad_Natureza!$B$3:$C$3,0)) -> #N/A | G658: MCS | J658: DAS - MCS Serviços ref. 10/2025 - Parcelar | K658: =-5000*6% -> -300 | N658: =B658&D658&F658 -> #N/A | O658: =D658&F658 -> #N/A | P658: ="MCS"&D658&F658 -> #N/A | Q658: ="MCS"&D658 -> #N/A | R658: =B658&D658 -> #N/A | T658: =(1&"/"&MONTH(H658)&"/"&YEAR(H658))*1 -> 1 | U658: =IF(I658="","",(1&"/"&MONTH(I658)&"/"&YEAR(I658))*1) | V658: X
B659: MCS | D659: =INDEX(Cad_Natureza!$B$3:$C$52,MATCH('2026'!F659,Cad_Natureza!$C$3:$C$52,0),MATCH('2026'!D$2,Cad_Natureza!$B$3:$C$3,0)) -> #N/A | G659: MCS | J659: DAS - MCS Serviços ref. 11/2025 - Parcelar | K659: =-5000*6% -> -300 | N659: =B659&D659&F659 -> #N/A | O659: =D659&F659 -> #N/A | P659: ="MCS"&D659&F659 -> #N/A | Q659: ="MCS"&D659 -> #N/A | R659: =B659&D659 -> #N/A | T659: =(1&"/"&MONTH(H659)&"/"&YEAR(H659))*1 -> 1 | U659: =IF(I659="","",(1&"/"&MONTH(I659)&"/"&YEAR(I659))*1) | V659: Z
B660: MCS | D660: =INDEX(Cad_Natureza!$B$3:$C$52,MATCH('2026'!F660,Cad_Natureza!$C$3:$C$52,0),MATCH('2026'!D$2,Cad_Natureza!$B$3:$C$3,0)) -> #N/A | G660: MCS | J660: DAS - MCS Serviços ref. 12/2025 - Parcelar | K660: =-5000*6% -> -300 | N660: =B660&D660&F660 -> #N/A | O660: =D660&F660 -> #N/A | P660: ="MCS"&D660&F660 -> #N/A | Q660: ="MCS"&D660 -> #N/A | R660: =B660&D660 -> #N/A | T660: =(1&"/"&MONTH(H660)&"/"&YEAR(H660))*1 -> 1 | U660: =IF(I660="","",(1&"/"&MONTH(I660)&"/"&YEAR(I660))*1) | V660: Z
B661: MCS | D661: =INDEX(Cad_Natureza!$B$3:$C$52,MATCH('2026'!F661,Cad_Natureza!$C$3:$C$52,0),MATCH('2026'!D$2,Cad_Natureza!$B$3:$C$3,0)) -> #N/A | G661: MCS | J661: DAS - MCS Serviços ref. 01/2026 - Parcelar | K661: =-5000*6% -> -300 | N661: =B661&D661&F661 -> #N/A | O661: =D661&F661 -> #N/A | P661: ="MCS"&D661&F661 -> #N/A | Q661: ="MCS"&D661 -> #N/A | R661: =B661&D661 -> #N/A | T661: =(1&"/"&MONTH(H661)&"/"&YEAR(H661))*1 -> 1 | U661: =IF(I661="","",(1&"/"&MONTH(I661)&"/"&YEAR(I661))*1) | V661: Z
B662: MCS | D662: =INDEX(Cad_Natureza!$B$3:$C$52,MATCH('2026'!F662,Cad_Natureza!$C$3:$C$52,0),MATCH('2026'!D$2,Cad_Natureza!$B$3:$C$3,0)) -> #N/A | G662: MCS | J662: DAS - MCS Serviços ref. 02/2026 - Parcelar | K662: =-1500*6% -> -90 | N662: =B662&D662&F662 -> #N/A | O662: =D662&F662 -> #N/A | P662: ="MCS"&D662&F662 -> #N/A | Q662: ="MCS"&D662 -> #N/A | R662: =B662&D662 -> #N/A | T662: =(1&"/"&MONTH(H662)&"/"&YEAR(H662))*1 -> 1 | U662: =IF(I662="","",(1&"/"&MONTH(I662)&"/"&YEAR(I662))*1) | V662: Z
B663: MCS | G663: MCS | J663: DAS - MCS Serviços ref. 03/2026 - Parcelar | K663: =-5000*6% -> -300 | N663: =B663&D663&F663 -> MCS | O663: =D663&F663 | P663: ="MCS"&D663&F663 -> MCS | Q663: ="MCS"&D663 -> MCS | R663: =B663&D663 -> MCS | T663: =(1&"/"&MONTH(H663)&"/"&YEAR(H663))*1 -> 1 | U663: =IF(I663="","",(1&"/"&MONTH(I663)&"/"&YEAR(I663))*1)
B664: MCS | G664: MCS | J664: DAS - MCS Serviços ref. 04/2026 - Parcelar | K664: =-5000*6% -> -300 | N664: =B664&D664&F664 -> MCS | O664: =D664&F664 | P664: ="MCS"&D664&F664 -> MCS | Q664: ="MCS"&D664 -> MCS | R664: =B664&D664 -> MCS | T664: =(1&"/"&MONTH(H664)&"/"&YEAR(H664))*1 -> 1 | U664: =IF(I664="","",(1&"/"&MONTH(I664)&"/"&YEAR(I664))*1)
B665: MCS | G665: MCS | J665: DAS - MCS Serviços ref. 05/2026 - Parcelar | K665: =-5000*6% -> -300 | N665: =B665&D665&F665 -> MCS | O665: =D665&F665 | P665: ="MCS"&D665&F665 -> MCS | Q665: ="MCS"&D665 -> MCS | R665: =B665&D665 -> MCS | T665: =(1&"/"&MONTH(H665)&"/"&YEAR(H665))*1 -> 1 | U665: =IF(I665="","",(1&"/"&MONTH(I665)&"/"&YEAR(I665))*1)
B666: MCS | D666: =INDEX(Cad_Natureza!$B$3:$C$52,MATCH('2026'!F666,Cad_Natureza!$C$3:$C$52,0),MATCH('2026'!D$2,Cad_Natureza!$B$3:$C$3,0)) -> REC4 | E666: PIX TRANSF MCS SER10/11 | F666: CPF - Transf. Da conta PJ para a conta PF | G666: MCS | J666: Receita com prestação de serviços | K666: 5000 | L666: =L401+K666 -> 5477.15 | N666: =B666&D666&F666 -> MCSREC4CPF - Transf. Da conta PJ para a conta PF | O666: =D666&F666 -> REC4CPF - Transf. Da conta PJ para a conta PF | P666: ="MCS"&D666&F666 -> MCSREC4CPF - Transf. Da conta PJ para a conta PF | Q666: ="MCS"&D666 -> MCSREC4 | R666: =B666&D666 -> MCSREC4 | T666: =(1&"/"&MONTH(H666)&"/"&YEAR(H666))*1 -> 1 | U666: =IF(I666="","",(1&"/"&MONTH(I666)&"/"&YEAR(I666))*1)
B667: MCS | D667: =INDEX(Cad_Natureza!$B$3:$C$52,MATCH('2026'!F667,Cad_Natureza!$C$3:$C$52,0),MATCH('2026'!D$2,Cad_Natureza!$B$3:$C$3,0)) -> DESP1 | E667: Refeições para o mês | F667: CPF - Desp. Cartão de crédito | G667: MCS | K667: =Prev_Combust_Refei!K33 -> -440 | L667: =L666+K667 -> 5037.15 | N667: =B667&D667&F667 -> MCSDESP1CPF - Desp. Cartão de crédito | O667: =D667&F667 -> DESP1CPF - Desp. Cartão de crédito | P667: ="MCS"&D667&F667 -> MCSDESP1CPF - Desp. Cartão de crédito | Q667: ="MCS"&D667 -> MCSDESP1 | R667: =B667&D667 -> MCSDESP1 | T667: =(1&"/"&MONTH(H667)&"/"&YEAR(H667))*1 -> 1 | U667: =IF(I667="","",(1&"/"&MONTH(I667)&"/"&YEAR(I667))*1)
B668: MCS | D668: =INDEX(Cad_Natureza!$B$3:$C$52,MATCH('2026'!F668,Cad_Natureza!$C$3:$C$52,0),MATCH('2026'!D$2,Cad_Natureza!$B$3:$C$3,0)) -> FIN1 | E668: Combustível para o mês | F668: CPF - Desp. Financeiras - Empréstimos | G668: MCS | K668: =Prev_Combust_Refei!I33 -> -352 | L668: =L667+K668 -> 4685.15 | N668: =B668&D668&F668 -> MCSFIN1CPF - Desp. Financeiras - Empréstimos | O668: =D668&F668 -> FIN1CPF - Desp. Financeiras - Empréstimos | P668: ="MCS"&D668&F668 -> MCSFIN1CPF - Desp. Financeiras - Empréstimos | Q668: ="MCS"&D668 -> MCSFIN1 | R668: =B668&D668 -> MCSFIN1 | T668: =(1&"/"&MONTH(H668)&"/"&YEAR(H668))*1 -> 1 | U668: =IF(I668="","",(1&"/"&MONTH(I668)&"/"&YEAR(I668))*1)
B669: MCS | D669: =INDEX(Cad_Natureza!$B$3:$C$52,MATCH('2026'!F669,Cad_Natureza!$C$3:$C$52,0),MATCH('2026'!D$2,Cad_Natureza!$B$3:$C$3,0)) -> PENS2 | E669: Pensão - Conta de energia ref. 07/2025, vcto 02/08 | F669: CPF - Pensão - Energia | G669: MCS | J669: Pensão - Conta de energia ref. 04/2026 | K669: -816.87 | L669: =L668+K669 -> 3868.28 | N669: =B669&D669&F669 -> MCSPENS2CPF - Pensão - Energia | O669: =D669&F669 -> PENS2CPF - Pensão - Energia | P669: ="MCS"&D669&F669 -> MCSPENS2CPF - Pensão - Energia | Q669: ="MCS"&D669 -> MCSPENS2 | R669: =B669&D669 -> MCSPENS2 | T669: =(1&"/"&MONTH(H669)&"/"&YEAR(H669))*1 -> 1 | U669: =IF(I669="","",(1&"/"&MONTH(I669)&"/"&YEAR(I669))*1) | V669: X
B670: MCS | D670: =INDEX(Cad_Natureza!$B$3:$C$52,MATCH('2026'!F670,Cad_Natureza!$C$3:$C$52,0),MATCH('2026'!D$2,Cad_Natureza!$B$3:$C$3,0)) -> PENS5 | E670: Pensão - Conta de água atrasada ref. 07/2025 | F670: CPF - Pensão - Água | G670: MCS | J670: Pensão - Conta de água ref. 04/2025 | K670: =-135.47 -> -135.47 | L670: =L669+K670 -> 3732.81 | N670: =B670&D670&F670 -> MCSPENS5CPF - Pensão - Água | O670: =D670&F670 -> PENS5CPF - Pensão - Água | P670: ="MCS"&D670&F670 -> MCSPENS5CPF - Pensão - Água | Q670: ="MCS"&D670 -> MCSPENS5 | R670: =B670&D670 -> MCSPENS5 | T670: =(1&"/"&MONTH(H670)&"/"&YEAR(H670))*1 -> 1 | U670: =IF(I670="","",(1&"/"&MONTH(I670)&"/"&YEAR(I670))*1) | V670: X
A671: x | B671: MCS | D671: =INDEX(Cad_Natureza!$B$3:$C$52,MATCH('2026'!F671,Cad_Natureza!$C$3:$C$52,0),MATCH('2026'!D$2,Cad_Natureza!$B$3:$C$3,0)) -> PENS1 | E671: Pensão - Aluguel 09/2025 | F671: CPF - Pensão - Aluguel | G671: MCS | J671: Pensão - Aluguel 05/2025 | K671: -700 | L671: =L670+K671 -> 3032.81 | N671: =B671&D671&F671 -> MCSPENS1CPF - Pensão - Aluguel | O671: =D671&F671 -> PENS1CPF - Pensão - Aluguel | P671: ="MCS"&D671&F671 -> MCSPENS1CPF - Pensão - Aluguel | Q671: ="MCS"&D671 -> MCSPENS1 | R671: =B671&D671 -> MCSPENS1 | T671: =(1&"/"&MONTH(H671)&"/"&YEAR(H671))*1 -> 1 | U671: =IF(I671="","",(1&"/"&MONTH(I671)&"/"&YEAR(I671))*1) | V671: X
B672: MCS | D672: =INDEX(Cad_Natureza!$B$3:$C$52,MATCH('2026'!F672,Cad_Natureza!$C$3:$C$52,0),MATCH('2026'!D$2,Cad_Natureza!$B$3:$C$3,0)) -> PENS3 | E672: Pensão - Plano de saúde de Alice e Davi ref. 08/2025 | F672: CPF - Pensão - Plano de saúde | G672: MCS | J672: Pensão - Plano de saúde de Alice e Davi ref. 04/2025 | K672: -495.5 | L672: =L671+K672 -> 2537.31 | N672: =B672&D672&F672 -> MCSPENS3CPF - Pensão - Plano de saúde | O672: =D672&F672 -> PENS3CPF - Pensão - Plano de saúde | P672: ="MCS"&D672&F672 -> MCSPENS3CPF - Pensão - Plano de saúde | Q672: ="MCS"&D672 -> MCSPENS3 | R672: =B672&D672 -> MCSPENS3 | T672: =(1&"/"&MONTH(H672)&"/"&YEAR(H672))*1 -> 1 | U672: =IF(I672="","",(1&"/"&MONTH(I672)&"/"&YEAR(I672))*1) | V672: X
B673: MCS | D673: =INDEX(Cad_Natureza!$B$3:$C$52,MATCH('2026'!F673,Cad_Natureza!$C$3:$C$52,0),MATCH('2026'!D$2,Cad_Natureza!$B$3:$C$3,0)) -> PENS8 | E673: CPF - Pensão - Alimentação | F673: CPF - Pensão - Alimentação | G673: MCS | K673: 0 | L673: =L672+K673 -> 2537.31 | N673: =B673&D673&F673 -> MCSPENS8CPF - Pensão - Alimentação | O673: =D673&F673 -> PENS8CPF - Pensão - Alimentação | P673: ="MCS"&D673&F673 -> MCSPENS8CPF - Pensão - Alimentação | Q673: ="MCS"&D673 -> MCSPENS8 | R673: =B673&D673 -> MCSPENS8 | T673: =(1&"/"&MONTH(H673)&"/"&YEAR(H673))*1 -> 1 | U673: =IF(I673="","",(1&"/"&MONTH(I673)&"/"&YEAR(I673))*1)
B674: MCS | D674: =INDEX(Cad_Natureza!$B$3:$C$52,MATCH('2026'!F674,Cad_Natureza!$C$3:$C$52,0),MATCH('2026'!D$2,Cad_Natureza!$B$3:$C$3,0)) -> PENS9 | E674: CPF - Pensão - Outros Gastos | F674: CPF - Pensão - Outros Gastos | G674: MCS | K674: 0 | L674: =L673+K674 -> 2537.31 | N674: =B674&D674&F674 -> MCSPENS9CPF - Pensão - Outros Gastos | O674: =D674&F674 -> PENS9CPF - Pensão - Outros Gastos | P674: ="MCS"&D674&F674 -> MCSPENS9CPF - Pensão - Outros Gastos | Q674: ="MCS"&D674 -> MCSPENS9 | R674: =B674&D674 -> MCSPENS9 | T674: =(1&"/"&MONTH(H674)&"/"&YEAR(H674))*1 -> 1 | U674: =IF(I674="","",(1&"/"&MONTH(I674)&"/"&YEAR(I674))*1)
B675: MCS | D675: =INDEX(Cad_Natureza!$B$3:$C$52,MATCH('2026'!F675,Cad_Natureza!$C$3:$C$52,0),MATCH('2026'!D$2,Cad_Natureza!$B$3:$C$3,0)) -> FIN3 | E675: RENEGOCIACAO ITAU 07/18 | F675: CPF - Desp. Financeiras - Empréstimos bancários | G675: MCS | J675: Renegociação cheque especial parcela 10/18 | K675: -300 | L675: =L674+K675 -> 2237.31 | N675: =B675&D675&F675 -> MCSFIN3CPF - Desp. Financeiras - Empréstimos bancários | O675: =D675&F675 -> FIN3CPF - Desp. Financeiras - Empréstimos bancários | P675: ="MCS"&D675&F675 -> MCSFIN3CPF - Desp. Financeiras - Empréstimos bancários | Q675: ="MCS"&D675 -> MCSFIN3 | R675: =B675&D675 -> MCSFIN3 | T675: =(1&"/"&MONTH(H675)&"/"&YEAR(H675))*1 -> 1 | U675: =IF(I675="","",(1&"/"&MONTH(I675)&"/"&YEAR(I675))*1)
B676: MCS | D676: =INDEX(Cad_Natureza!$B$3:$C$52,MATCH('2026'!F676,Cad_Natureza!$C$3:$C$52,0),MATCH('2026'!D$2,Cad_Natureza!$B$3:$C$3,0)) -> DESP1 | E676: Cartão de crédito - ref. 07/2025 | F676: CPF - Desp. Cartão de crédito | G676: MCS | K676: 0 | L676: =L675+K676 -> 2237.31 | N676: =B676&D676&F676 -> MCSDESP1CPF - Desp. Cartão de crédito | O676: =D676&F676 -> DESP1CPF - Desp. Cartão de crédito | P676: ="MCS"&D676&F676 -> MCSDESP1CPF - Desp. Cartão de crédito | Q676: ="MCS"&D676 -> MCSDESP1 | R676: =B676&D676 -> MCSDESP1 | T676: =(1&"/"&MONTH(H676)&"/"&YEAR(H676))*1 -> 1 | U676: =IF(I676="","",(1&"/"&MONTH(I676)&"/"&YEAR(I676))*1)
B677: MCS | D677: =INDEX(Cad_Natureza!$B$3:$C$52,MATCH('2026'!F677,Cad_Natureza!$C$3:$C$52,0),MATCH('2026'!D$2,Cad_Natureza!$B$3:$C$3,0)) -> DESP1 | E677: Cartão Riachuelo - seguro ref. 07/2025 | F677: CPF - Desp. Cartão de crédito | G677: MCS | K677: -5.9 | L677: =L676+K677 -> 2231.41 | N677: =B677&D677&F677 -> MCSDESP1CPF - Desp. Cartão de crédito | O677: =D677&F677 -> DESP1CPF - Desp. Cartão de crédito | P677: ="MCS"&D677&F677 -> MCSDESP1CPF - Desp. Cartão de crédito | Q677: ="MCS"&D677 -> MCSDESP1 | R677: =B677&D677 -> MCSDESP1 | T677: =(1&"/"&MONTH(H677)&"/"&YEAR(H677))*1 -> 1 | U677: =IF(I677="","",(1&"/"&MONTH(I677)&"/"&YEAR(I677))*1)
B678: MCS | D678: =INDEX(Cad_Natureza!$B$3:$C$52,MATCH('2026'!F678,Cad_Natureza!$C$3:$C$52,0),MATCH('2026'!D$2,Cad_Natureza!$B$3:$C$3,0)) -> DESP2 | E678: DA CLARO CELULAR 92107 | F678: CPF - Desp. Telefone / Internet | G678: MCS | J678: Mensalidade do celular | K678: -95 | L678: =L677+K678 -> 2136.41 | N678: =B678&D678&F678 -> MCSDESP2CPF - Desp. Telefone / Internet | O678: =D678&F678 -> DESP2CPF - Desp. Telefone / Internet | P678: ="MCS"&D678&F678 -> MCSDESP2CPF - Desp. Telefone / Internet | Q678: ="MCS"&D678 -> MCSDESP2 | R678: =B678&D678 -> MCSDESP2 | T678: =(1&"/"&MONTH(H678)&"/"&YEAR(H678))*1 -> 1 | U678: =IF(I678="","",(1&"/"&MONTH(I678)&"/"&YEAR(I678))*1)
B679: MCS | D679: =INDEX(Cad_Natureza!$B$3:$C$52,MATCH('2026'!F679,Cad_Natureza!$C$3:$C$52,0),MATCH('2026'!D$2,Cad_Natureza!$B$3:$C$3,0)) -> DESP2 | E679: Internet casa dos pais | F679: CPF - Desp. Telefone / Internet | G679: MCS | J679: Internet casa dos pais | K679: =-125 -> -125 | L679: =L678+K679 -> 2011.41 | N679: =B679&D679&F679 -> MCSDESP2CPF - Desp. Telefone / Internet | O679: =D679&F679 -> DESP2CPF - Desp. Telefone / Internet | P679: ="MCS"&D679&F679 -> MCSDESP2CPF - Desp. Telefone / Internet | Q679: ="MCS"&D679 -> MCSDESP2 | R679: =B679&D679 -> MCSDESP2 | T679: =(1&"/"&MONTH(H679)&"/"&YEAR(H679))*1 -> 1 | U679: =IF(I679="","",(1&"/"&MONTH(I679)&"/"&YEAR(I679))*1)
B680: MCS | D680: =INDEX(Cad_Natureza!$B$3:$C$52,MATCH('2026'!F680,Cad_Natureza!$C$3:$C$52,0),MATCH('2026'!D$2,Cad_Natureza!$B$3:$C$3,0)) -> PENS1 | E680: Pensão - Aluguel 09/2025 | F680: CPF - Pensão - Aluguel | G680: MCS | K680: -700 | L680: =L679+K680 -> 1311.41 | N680: =B680&D680&F680 -> MCSPENS1CPF - Pensão - Aluguel | O680: =D680&F680 -> PENS1CPF - Pensão - Aluguel | P680: ="MCS"&D680&F680 -> MCSPENS1CPF - Pensão - Aluguel | Q680: ="MCS"&D680 -> MCSPENS1 | R680: =B680&D680 -> MCSPENS1 | T680: =(1&"/"&MONTH(H680)&"/"&YEAR(H680))*1 -> 1 | U680: =IF(I680="","",(1&"/"&MONTH(I680)&"/"&YEAR(I680))*1) | V680: X
B681: MCS | D681: =INDEX(Cad_Natureza!$B$3:$C$52,MATCH('2026'!F681,Cad_Natureza!$C$3:$C$52,0),MATCH('2026'!D$2,Cad_Natureza!$B$3:$C$3,0)) -> PENS1 | E681: Pensão - Aluguel 09/2025 | F681: CPF - Pensão - Aluguel | G681: MCS | K681: -700 | L681: =L680+K681 -> 611.41 | N681: =B681&D681&F681 -> MCSPENS1CPF - Pensão - Aluguel | O681: =D681&F681 -> PENS1CPF - Pensão - Aluguel | P681: ="MCS"&D681&F681 -> MCSPENS1CPF - Pensão - Aluguel | Q681: ="MCS"&D681 -> MCSPENS1 | R681: =B681&D681 -> MCSPENS1 | T681: =(1&"/"&MONTH(H681)&"/"&YEAR(H681))*1 -> 1 | U681: =IF(I681="","",(1&"/"&MONTH(I681)&"/"&YEAR(I681))*1) | V681: X
B682: MCS | G682: MCS | J682: Multa Detran | N682: =B682&D682&F682 -> MCS | O682: =D682&F682 | P682: ="MCS"&D682&F682 -> MCS | Q682: ="MCS"&D682 -> MCS | R682: =B682&D682 -> MCS | T682: =(1&"/"&MONTH(H682)&"/"&YEAR(H682))*1 -> 1 | U682: =IF(I682="","",(1&"/"&MONTH(I682)&"/"&YEAR(I682))*1)
B683: MCS | G683: MCS | J683: IPVA | N683: =B683&D683&F683 -> MCS | O683: =D683&F683 | P683: ="MCS"&D683&F683 -> MCS | Q683: ="MCS"&D683 -> MCS | R683: =B683&D683 -> MCS | T683: =(1&"/"&MONTH(H683)&"/"&YEAR(H683))*1 -> 1 | U683: =IF(I683="","",(1&"/"&MONTH(I683)&"/"&YEAR(I683))*1)
B684: MCS | D684: =INDEX(Cad_Natureza!$B$3:$C$52,MATCH('2026'!F684,Cad_Natureza!$C$3:$C$52,0),MATCH('2026'!D$2,Cad_Natureza!$B$3:$C$3,0)) -> PENS2 | E684: Pensão - Conta de energia ref. 07/2025, vcto 02/08 | F684: CPF - Pensão - Energia | G684: MCS | J684: Pensão - Conta de energia ref. 12/2025 | K684: -833.3 | L684: =L681+K684 -> -221.89 | N684: =B684&D684&F684 -> MCSPENS2CPF - Pensão - Energia | O684: =D684&F684 -> PENS2CPF - Pensão - Energia | P684: ="MCS"&D684&F684 -> MCSPENS2CPF - Pensão - Energia | Q684: ="MCS"&D684 -> MCSPENS2 | R684: =B684&D684 -> MCSPENS2 | T684: =(1&"/"&MONTH(H684)&"/"&YEAR(H684))*1 -> 1 | U684: =IF(I684="","",(1&"/"&MONTH(I684)&"/"&YEAR(I684))*1)
B685: MCS | G685: MCS | N685: =B685&D685&F685 -> MCS | O685: =D685&F685 | P685: ="MCS"&D685&F685 -> MCS | Q685: ="MCS"&D685 -> MCS | R685: =B685&D685 -> MCS | T685: =(1&"/"&MONTH(H685)&"/"&YEAR(H685))*1 -> 1 | U685: =IF(I685="","",(1&"/"&MONTH(I685)&"/"&YEAR(I685))*1)
B686: MCS | G686: MCS | N686: =B686&D686&F686 -> MCS | O686: =D686&F686 | P686: ="MCS"&D686&F686 -> MCS | Q686: ="MCS"&D686 -> MCS | R686: =B686&D686 -> MCS | T686: =(1&"/"&MONTH(H686)&"/"&YEAR(H686))*1 -> 1 | U686: =IF(I686="","",(1&"/"&MONTH(I686)&"/"&YEAR(I686))*1)
B687: MCS | G687: MCS | N687: =B687&D687&F687 -> MCS | O687: =D687&F687 | P687: ="MCS"&D687&F687 -> MCS | Q687: ="MCS"&D687 -> MCS | R687: =B687&D687 -> MCS | T687: =(1&"/"&MONTH(H687)&"/"&YEAR(H687))*1 -> 1 | U687: =IF(I687="","",(1&"/"&MONTH(I687)&"/"&YEAR(I687))*1)
B688: x | C688: x | D688: x | E688: x | F688: x | G688: x | H688: x | I688: x | J688: x | K688: x | M688: x | N688: x | O688: x | P688: x | Q688: x | R688: x | S688: x | T688: x | U688: x

Sheet CAIXA_REAL
A2: MCS | B2: FLUXO DE CAIXA ANO - MCS
A3: MCS | D3: SELECIONE A ENTIDADE QUE PAGOU OU RECEBEU => | E3: MCS | T3: RESUMO FLUXO CAIXA
A4: MCS | D4: SELECIONE O CENTRO DE RESULTADO => | E4: TODOS CRs | T4: GRUPO | U4: TOTAL | V4: A.V. %
A5: Sinko | T5: REC | U5: =SUMIFS($E$7:$E$40,$B$7:$B$40,T5) -> 33591.75 | V5: =IFERROR(ABS(U5/$U$5),0) -> 1
A6: TODAS | B6: Grupo | C6: Natureza | D6: ENTRADAS | E6: ACUM | F6: 46023 | G6: 46054 | H6: 46082 | I6: 46113 | J6: 46143 | K6: 46174 | L6: 46204 | M6: 46235 | N6: 46266 | O6: 46296 | P6: 46327 | Q6: 46357 | T6: PENS | U6: =SUMIFS($E$7:$E$40,$B$7:$B$40,T6) -> -11734.05 | V6: =IFERROR(ABS(U6/$U$5),0) -> 0.34931345
B7: REC | C7: REC1 | D7: CPF - Remun. Salário / Pró-Labore | E7: =SUM(F7:Q7) -> 0 | F7: =IF((AND($E$3="MCS",$E$4="TODOS CRs")), SUMIFS('2026'!$K:$K,'2026'!$R:$R,$E$3&$C7,'2026'!$T:$T,F$6), SUMIFS('2026'!$K:$K,'2026'!$N:$N,$E$3&$C7&$E$4,'2026'!$T:$T,F$6)) -> 0 | G7: =IF((AND($E$3="MCS",$E$4="TODOS CRs")), SUMIFS('2026'!$K:$K,'2026'!$R:$R,$E$3&$C7,'2026'!$T:$T,G$6), SUMIFS('2026'!$K:$K,'2026'!$N:$N,$E$3&$C7&$E$4,'2026'!$T:$T,G$6)) -> 0 | H7: =IF((AND($E$3="MCS",$E$4="TODOS CRs")), SUMIFS('2026'!$K:$K,'2026'!$R:$R,$E$3&$C7,'2026'!$T:$T,H$6), SUMIFS('2026'!$K:$K,'2026'!$N:$N,$E$3&$C7&$E$4,'2026'!$T:$T,H$6)) -> 0 | I7: =IF((AND($E$3="MCS",$E$4="TODOS CRs")), SUMIFS('2026'!$K:$K,'2026'!$R:$R,$E$3&$C7,'2026'!$T:$T,I$6), SUMIFS('2026'!$K:$K,'2026'!$N:$N,$E$3&$C7&$E$4,'2026'!$T:$T,I$6)) -> 0 | J7: =IF((AND($E$3="MCS",$E$4="TODOS CRs")), SUMIFS('2026'!$K:$K,'2026'!$R:$R,$E$3&$C7,'2026'!$T:$T,J$6), SUMIFS('2026'!$K:$K,'2026'!$N:$N,$E$3&$C7&$E$4,'2026'!$T:$T,J$6)) -> 0 | K7: =IF((AND($E$3="MCS",$E$4="TODOS CRs")), SUMIFS('2026'!$K:$K,'2026'!$R:$R,$E$3&$C7,'2026'!$T:$T,K$6), SUMIFS('2026'!$K:$K,'2026'!$N:$N,$E$3&$C7&$E$4,'2026'!$T:$T,K$6)) -> 0 | L7: =IF((AND($E$3="MCS",$E$4="TODOS CRs")), SUMIFS('2026'!$K:$K,'2026'!$R:$R,$E$3&$C7,'2026'!$T:$T,L$6), SUMIFS('2026'!$K:$K,'2026'!$N:$N,$E$3&$C7&$E$4,'2026'!$T:$T,L$6)) -> 0 | M7: =IF((AND($E$3="MCS",$E$4="TODOS CRs")), SUMIFS('2026'!$K:$K,'2026'!$R:$R,$E$3&$C7,'2026'!$T:$T,M$6), SUMIFS('2026'!$K:$K,'2026'!$N:$N,$E$3&$C7&$E$4,'2026'!$T:$T,M$6)) -> 0 | ... Q7: =IF((AND($E$3="MCS",$E$4="TODOS CRs")), SUMIFS('2026'!$K:$K,'2026'!$R:$R,$E$3&$C7,'2026'!$T:$T,Q$6), SUMIFS('2026'!$K:$K,'2026'!$N:$N,$E$3&$C7&$E$4,'2026'!$T:$T,Q$6)) -> 0 | T7: OPF | U7: =SUMIFS($E$7:$E$40,$B$7:$B$40,T7) -> -6840.46 | V7: =IFERROR(ABS(U7/$U$5),0) -> 0.20363512
B8: REC | C8: REC2 | D8: CPF - Ajuda de custo - Combustível | E8: =SUM(F8:Q8) -> 0 | F8: =IF((AND($E$3="MCS",$E$4="TODOS CRs")), SUMIFS('2026'!$K:$K,'2026'!$R:$R,$E$3&$C8,'2026'!$T:$T,F$6), SUMIFS('2026'!$K:$K,'2026'!$N:$N,$E$3&$C8&$E$4,'2026'!$T:$T,F$6)) -> 0 | G8: =IF((AND($E$3="MCS",$E$4="TODOS CRs")), SUMIFS('2026'!$K:$K,'2026'!$R:$R,$E$3&$C8,'2026'!$T:$T,G$6), SUMIFS('2026'!$K:$K,'2026'!$N:$N,$E$3&$C8&$E$4,'2026'!$T:$T,G$6)) -> 0 | H8: =IF((AND($E$3="MCS",$E$4="TODOS CRs")), SUMIFS('2026'!$K:$K,'2026'!$R:$R,$E$3&$C8,'2026'!$T:$T,H$6), SUMIFS('2026'!$K:$K,'2026'!$N:$N,$E$3&$C8&$E$4,'2026'!$T:$T,H$6)) -> 0 | I8: =IF((AND($E$3="MCS",$E$4="TODOS CRs")), SUMIFS('2026'!$K:$K,'2026'!$R:$R,$E$3&$C8,'2026'!$T:$T,I$6), SUMIFS('2026'!$K:$K,'2026'!$N:$N,$E$3&$C8&$E$4,'2026'!$T:$T,I$6)) -> 0 | J8: =IF((AND($E$3="MCS",$E$4="TODOS CRs")), SUMIFS('2026'!$K:$K,'2026'!$R:$R,$E$3&$C8,'2026'!$T:$T,J$6), SUMIFS('2026'!$K:$K,'2026'!$N:$N,$E$3&$C8&$E$4,'2026'!$T:$T,J$6)) -> 0 | K8: =IF((AND($E$3="MCS",$E$4="TODOS CRs")), SUMIFS('2026'!$K:$K,'2026'!$R:$R,$E$3&$C8,'2026'!$T:$T,K$6), SUMIFS('2026'!$K:$K,'2026'!$N:$N,$E$3&$C8&$E$4,'2026'!$T:$T,K$6)) -> 0 | L8: =IF((AND($E$3="MCS",$E$4="TODOS CRs")), SUMIFS('2026'!$K:$K,'2026'!$R:$R,$E$3&$C8,'2026'!$T:$T,L$6), SUMIFS('2026'!$K:$K,'2026'!$N:$N,$E$3&$C8&$E$4,'2026'!$T:$T,L$6)) -> 0 | M8: =IF((AND($E$3="MCS",$E$4="TODOS CRs")), SUMIFS('2026'!$K:$K,'2026'!$R:$R,$E$3&$C8,'2026'!$T:$T,M$6), SUMIFS('2026'!$K:$K,'2026'!$N:$N,$E$3&$C8&$E$4,'2026'!$T:$T,M$6)) -> 0 | ... Q8: =IF((AND($E$3="MCS",$E$4="TODOS CRs")), SUMIFS('2026'!$K:$K,'2026'!$R:$R,$E$3&$C8,'2026'!$T:$T,Q$6), SUMIFS('2026'!$K:$K,'2026'!$N:$N,$E$3&$C8&$E$4,'2026'!$T:$T,Q$6)) -> 0 | T8: GAST | U8: =SUMIFS($E$7:$E$40,$B$7:$B$40,T8) -> -6045.55 | V8: =IFERROR(ABS(U8/$U$5),0) -> 0.17997127
B9: REC | C9: REC3 | D9: CPF - Ajuda de custo - Refeição | E9: =SUM(F9:Q9) -> 0 | F9: =IF((AND($E$3="MCS",$E$4="TODOS CRs")), SUMIFS('2026'!$K:$K,'2026'!$R:$R,$E$3&$C9,'2026'!$T:$T,F$6), SUMIFS('2026'!$K:$K,'2026'!$N:$N,$E$3&$C9&$E$4,'2026'!$T:$T,F$6)) -> 0 | G9: =IF((AND($E$3="MCS",$E$4="TODOS CRs")), SUMIFS('2026'!$K:$K,'2026'!$R:$R,$E$3&$C9,'2026'!$T:$T,G$6), SUMIFS('2026'!$K:$K,'2026'!$N:$N,$E$3&$C9&$E$4,'2026'!$T:$T,G$6)) -> 0 | H9: =IF((AND($E$3="MCS",$E$4="TODOS CRs")), SUMIFS('2026'!$K:$K,'2026'!$R:$R,$E$3&$C9,'2026'!$T:$T,H$6), SUMIFS('2026'!$K:$K,'2026'!$N:$N,$E$3&$C9&$E$4,'2026'!$T:$T,H$6)) -> 0 | I9: =IF((AND($E$3="MCS",$E$4="TODOS CRs")), SUMIFS('2026'!$K:$K,'2026'!$R:$R,$E$3&$C9,'2026'!$T:$T,I$6), SUMIFS('2026'!$K:$K,'2026'!$N:$N,$E$3&$C9&$E$4,'2026'!$T:$T,I$6)) -> 0 | J9: =IF((AND($E$3="MCS",$E$4="TODOS CRs")), SUMIFS('2026'!$K:$K,'2026'!$R:$R,$E$3&$C9,'2026'!$T:$T,J$6), SUMIFS('2026'!$K:$K,'2026'!$N:$N,$E$3&$C9&$E$4,'2026'!$T:$T,J$6)) -> 0 | K9: =IF((AND($E$3="MCS",$E$4="TODOS CRs")), SUMIFS('2026'!$K:$K,'2026'!$R:$R,$E$3&$C9,'2026'!$T:$T,K$6), SUMIFS('2026'!$K:$K,'2026'!$N:$N,$E$3&$C9&$E$4,'2026'!$T:$T,K$6)) -> 0 | L9: =IF((AND($E$3="MCS",$E$4="TODOS CRs")), SUMIFS('2026'!$K:$K,'2026'!$R:$R,$E$3&$C9,'2026'!$T:$T,L$6), SUMIFS('2026'!$K:$K,'2026'!$N:$N,$E$3&$C9&$E$4,'2026'!$T:$T,L$6)) -> 0 | M9: =IF((AND($E$3="MCS",$E$4="TODOS CRs")), SUMIFS('2026'!$K:$K,'2026'!$R:$R,$E$3&$C9,'2026'!$T:$T,M$6), SUMIFS('2026'!$K:$K,'2026'!$N:$N,$E$3&$C9&$E$4,'2026'!$T:$T,M$6)) -> 0 | ... Q9: =IF((AND($E$3="MCS",$E$4="TODOS CRs")), SUMIFS('2026'!$K:$K,'2026'!$R:$R,$E$3&$C9,'2026'!$T:$T,Q$6), SUMIFS('2026'!$K:$K,'2026'!$N:$N,$E$3&$C9&$E$4,'2026'!$T:$T,Q$6)) -> 0 | T9: DESP | U9: =SUMIFS($E$7:$E$40,$B$7:$B$40,T9) -> -4028.63 | V9: =IFERROR(ABS(U9/$U$5),0) -> 0.11992915
B10: REC | C10: REC4 | D10: CPF - Transf. Da conta PJ para a conta PF | E10: =SUM(F10:Q10) -> 32740 | F10: =IF((AND($E$3="MCS",$E$4="TODOS CRs")), SUMIFS('2026'!$K:$K,'2026'!$R:$R,$E$3&$C10,'2026'!$T:$T,F$6), SUMIFS('2026'!$K:$K,'2026'!$N:$N,$E$3&$C10&$E$4,'2026'!$T:$T,F$6)) -> 4900 | G10: =IF((AND($E$3="MCS",$E$4="TODOS CRs")), SUMIFS('2026'!$K:$K,'2026'!$R:$R,$E$3&$C10,'2026'!$T:$T,G$6), SUMIFS('2026'!$K:$K,'2026'!$N:$N,$E$3&$C10&$E$4,'2026'!$T:$T,G$6)) -> 5500 | H10: =IF((AND($E$3="MCS",$E$4="TODOS CRs")), SUMIFS('2026'!$K:$K,'2026'!$R:$R,$E$3&$C10,'2026'!$T:$T,H$6), SUMIFS('2026'!$K:$K,'2026'!$N:$N,$E$3&$C10&$E$4,'2026'!$T:$T,H$6)) -> 5040 | I10: =IF((AND($E$3="MCS",$E$4="TODOS CRs")), SUMIFS('2026'!$K:$K,'2026'!$R:$R,$E$3&$C10,'2026'!$T:$T,I$6), SUMIFS('2026'!$K:$K,'2026'!$N:$N,$E$3&$C10&$E$4,'2026'!$T:$T,I$6)) -> 7000 | J10: =IF((AND($E$3="MCS",$E$4="TODOS CRs")), SUMIFS('2026'!$K:$K,'2026'!$R:$R,$E$3&$C10,'2026'!$T:$T,J$6), SUMIFS('2026'!$K:$K,'2026'!$N:$N,$E$3&$C10&$E$4,'2026'!$T:$T,J$6)) -> 6300 | K10: =IF((AND($E$3="MCS",$E$4="TODOS CRs")), SUMIFS('2026'!$K:$K,'2026'!$R:$R,$E$3&$C10,'2026'!$T:$T,K$6), SUMIFS('2026'!$K:$K,'2026'!$N:$N,$E$3&$C10&$E$4,'2026'!$T:$T,K$6)) -> 4000 | L10: =IF((AND($E$3="MCS",$E$4="TODOS CRs")), SUMIFS('2026'!$K:$K,'2026'!$R:$R,$E$3&$C10,'2026'!$T:$T,L$6), SUMIFS('2026'!$K:$K,'2026'!$N:$N,$E$3&$C10&$E$4,'2026'!$T:$T,L$6)) -> 0 | M10: =IF((AND($E$3="MCS",$E$4="TODOS CRs")), SUMIFS('2026'!$K:$K,'2026'!$R:$R,$E$3&$C10,'2026'!$T:$T,M$6), SUMIFS('2026'!$K:$K,'2026'!$N:$N,$E$3&$C10&$E$4,'2026'!$T:$T,M$6)) -> 0 | ... Q10: =IF((AND($E$3="MCS",$E$4="TODOS CRs")), SUMIFS('2026'!$K:$K,'2026'!$R:$R,$E$3&$C10,'2026'!$T:$T,Q$6), SUMIFS('2026'!$K:$K,'2026'!$N:$N,$E$3&$C10&$E$4,'2026'!$T:$T,Q$6)) -> 0 | T10: FIN | U10: =SUMIFS($E$7:$E$40,$B$7:$B$40,T10) -> -2350.3 | V10: =IFERROR(ABS(U10/$U$5),0) -> 0.069966584
B11: REC | C11: REC5 | D11: CPF - Outras receitas | E11: =SUM(F11:Q11) -> 681.75 | F11: =IF((AND($E$3="MCS",$E$4="TODOS CRs")), SUMIFS('2026'!$K:$K,'2026'!$R:$R,$E$3&$C11,'2026'!$T:$T,F$6), SUMIFS('2026'!$K:$K,'2026'!$N:$N,$E$3&$C11&$E$4,'2026'!$T:$T,F$6)) -> 0 | G11: =IF((AND($E$3="MCS",$E$4="TODOS CRs")), SUMIFS('2026'!$K:$K,'2026'!$R:$R,$E$3&$C11,'2026'!$T:$T,G$6), SUMIFS('2026'!$K:$K,'2026'!$N:$N,$E$3&$C11&$E$4,'2026'!$T:$T,G$6)) -> 17.62 | H11: =IF((AND($E$3="MCS",$E$4="TODOS CRs")), SUMIFS('2026'!$K:$K,'2026'!$R:$R,$E$3&$C11,'2026'!$T:$T,H$6), SUMIFS('2026'!$K:$K,'2026'!$N:$N,$E$3&$C11&$E$4,'2026'!$T:$T,H$6)) -> 56 | I11: =IF((AND($E$3="MCS",$E$4="TODOS CRs")), SUMIFS('2026'!$K:$K,'2026'!$R:$R,$E$3&$C11,'2026'!$T:$T,I$6), SUMIFS('2026'!$K:$K,'2026'!$N:$N,$E$3&$C11&$E$4,'2026'!$T:$T,I$6)) -> 25 | J11: =IF((AND($E$3="MCS",$E$4="TODOS CRs")), SUMIFS('2026'!$K:$K,'2026'!$R:$R,$E$3&$C11,'2026'!$T:$T,J$6), SUMIFS('2026'!$K:$K,'2026'!$N:$N,$E$3&$C11&$E$4,'2026'!$T:$T,J$6)) -> 189.99 | K11: =IF((AND($E$3="MCS",$E$4="TODOS CRs")), SUMIFS('2026'!$K:$K,'2026'!$R:$R,$E$3&$C11,'2026'!$T:$T,K$6), SUMIFS('2026'!$K:$K,'2026'!$N:$N,$E$3&$C11&$E$4,'2026'!$T:$T,K$6)) -> 393.14 | L11: =IF((AND($E$3="MCS",$E$4="TODOS CRs")), SUMIFS('2026'!$K:$K,'2026'!$R:$R,$E$3&$C11,'2026'!$T:$T,L$6), SUMIFS('2026'!$K:$K,'2026'!$N:$N,$E$3&$C11&$E$4,'2026'!$T:$T,L$6)) -> 0 | M11: =IF((AND($E$3="MCS",$E$4="TODOS CRs")), SUMIFS('2026'!$K:$K,'2026'!$R:$R,$E$3&$C11,'2026'!$T:$T,M$6), SUMIFS('2026'!$K:$K,'2026'!$N:$N,$E$3&$C11&$E$4,'2026'!$T:$T,M$6)) -> 0 | ... Q11: =IF((AND($E$3="MCS",$E$4="TODOS CRs")), SUMIFS('2026'!$K:$K,'2026'!$R:$R,$E$3&$C11,'2026'!$T:$T,Q$6), SUMIFS('2026'!$K:$K,'2026'!$N:$N,$E$3&$C11&$E$4,'2026'!$T:$T,Q$6)) -> 0 | T11: OUG | U11: =SUMIFS($E$7:$E$40,$B$7:$B$40,T11) -> -2053.59 | V11: =IFERROR(ABS(U11/$U$5),0) -> 0.061133761
B12: REC | C12: REC6 | D12: CPF - Pensão - Outras receitas | E12: =SUM(F12:Q12) -> 0 | F12: =IF((AND($E$3="MCS",$E$4="TODOS CRs")), SUMIFS('2026'!$K:$K,'2026'!$R:$R,$E$3&$C12,'2026'!$T:$T,F$6), SUMIFS('2026'!$K:$K,'2026'!$N:$N,$E$3&$C12&$E$4,'2026'!$T:$T,F$6)) -> 0 | G12: =IF((AND($E$3="MCS",$E$4="TODOS CRs")), SUMIFS('2026'!$K:$K,'2026'!$R:$R,$E$3&$C12,'2026'!$T:$T,G$6), SUMIFS('2026'!$K:$K,'2026'!$N:$N,$E$3&$C12&$E$4,'2026'!$T:$T,G$6)) -> 0 | H12: =IF((AND($E$3="MCS",$E$4="TODOS CRs")), SUMIFS('2026'!$K:$K,'2026'!$R:$R,$E$3&$C12,'2026'!$T:$T,H$6), SUMIFS('2026'!$K:$K,'2026'!$N:$N,$E$3&$C12&$E$4,'2026'!$T:$T,H$6)) -> 0 | I12: =IF((AND($E$3="MCS",$E$4="TODOS CRs")), SUMIFS('2026'!$K:$K,'2026'!$R:$R,$E$3&$C12,'2026'!$T:$T,I$6), SUMIFS('2026'!$K:$K,'2026'!$N:$N,$E$3&$C12&$E$4,'2026'!$T:$T,I$6)) -> 0 | J12: =IF((AND($E$3="MCS",$E$4="TODOS CRs")), SUMIFS('2026'!$K:$K,'2026'!$R:$R,$E$3&$C12,'2026'!$T:$T,J$6), SUMIFS('2026'!$K:$K,'2026'!$N:$N,$E$3&$C12&$E$4,'2026'!$T:$T,J$6)) -> 0 | K12: =IF((AND($E$3="MCS",$E$4="TODOS CRs")), SUMIFS('2026'!$K:$K,'2026'!$R:$R,$E$3&$C12,'2026'!$T:$T,K$6), SUMIFS('2026'!$K:$K,'2026'!$N:$N,$E$3&$C12&$E$4,'2026'!$T:$T,K$6)) -> 0 | L12: =IF((AND($E$3="MCS",$E$4="TODOS CRs")), SUMIFS('2026'!$K:$K,'2026'!$R:$R,$E$3&$C12,'2026'!$T:$T,L$6), SUMIFS('2026'!$K:$K,'2026'!$N:$N,$E$3&$C12&$E$4,'2026'!$T:$T,L$6)) -> 0 | M12: =IF((AND($E$3="MCS",$E$4="TODOS CRs")), SUMIFS('2026'!$K:$K,'2026'!$R:$R,$E$3&$C12,'2026'!$T:$T,M$6), SUMIFS('2026'!$K:$K,'2026'!$N:$N,$E$3&$C12&$E$4,'2026'!$T:$T,M$6)) -> 0 | ... Q12: =IF((AND($E$3="MCS",$E$4="TODOS CRs")), SUMIFS('2026'!$K:$K,'2026'!$R:$R,$E$3&$C12,'2026'!$T:$T,Q$6), SUMIFS('2026'!$K:$K,'2026'!$N:$N,$E$3&$C12&$E$4,'2026'!$T:$T,Q$6)) -> 0 | T12: TRI | U12: =SUMIFS($E$7:$E$40,$B$7:$B$40,T12) -> -296 | V12: =IFERROR(ABS(U12/$U$5),0) -> 0.0088116874
B13: REC | C13: REC7 | D13: CPF - Rec. Financeiras - Empréstimos | E13: =SUM(F13:Q13) -> 170 | F13: =IF((AND($E$3="MCS",$E$4="TODOS CRs")), SUMIFS('2026'!$K:$K,'2026'!$R:$R,$E$3&$C13,'2026'!$T:$T,F$6), SUMIFS('2026'!$K:$K,'2026'!$N:$N,$E$3&$C13&$E$4,'2026'!$T:$T,F$6)) -> 0 | G13: =IF((AND($E$3="MCS",$E$4="TODOS CRs")), SUMIFS('2026'!$K:$K,'2026'!$R:$R,$E$3&$C13,'2026'!$T:$T,G$6), SUMIFS('2026'!$K:$K,'2026'!$N:$N,$E$3&$C13&$E$4,'2026'!$T:$T,G$6)) -> 0 | H13: =IF((AND($E$3="MCS",$E$4="TODOS CRs")), SUMIFS('2026'!$K:$K,'2026'!$R:$R,$E$3&$C13,'2026'!$T:$T,H$6), SUMIFS('2026'!$K:$K,'2026'!$N:$N,$E$3&$C13&$E$4,'2026'!$T:$T,H$6)) -> 0 | I13: =IF((AND($E$3="MCS",$E$4="TODOS CRs")), SUMIFS('2026'!$K:$K,'2026'!$R:$R,$E$3&$C13,'2026'!$T:$T,I$6), SUMIFS('2026'!$K:$K,'2026'!$N:$N,$E$3&$C13&$E$4,'2026'!$T:$T,I$6)) -> 0 | J13: =IF((AND($E$3="MCS",$E$4="TODOS CRs")), SUMIFS('2026'!$K:$K,'2026'!$R:$R,$E$3&$C13,'2026'!$T:$T,J$6), SUMIFS('2026'!$K:$K,'2026'!$N:$N,$E$3&$C13&$E$4,'2026'!$T:$T,J$6)) -> 170 | K13: =IF((AND($E$3="MCS",$E$4="TODOS CRs")), SUMIFS('2026'!$K:$K,'2026'!$R:$R,$E$3&$C13,'2026'!$T:$T,K$6), SUMIFS('2026'!$K:$K,'2026'!$N:$N,$E$3&$C13&$E$4,'2026'!$T:$T,K$6)) -> 0 | L13: =IF((AND($E$3="MCS",$E$4="TODOS CRs")), SUMIFS('2026'!$K:$K,'2026'!$R:$R,$E$3&$C13,'2026'!$T:$T,L$6), SUMIFS('2026'!$K:$K,'2026'!$N:$N,$E$3&$C13&$E$4,'2026'!$T:$T,L$6)) -> 0 | M13: =IF((AND($E$3="MCS",$E$4="TODOS CRs")), SUMIFS('2026'!$K:$K,'2026'!$R:$R,$E$3&$C13,'2026'!$T:$T,M$6), SUMIFS('2026'!$K:$K,'2026'!$N:$N,$E$3&$C13&$E$4,'2026'!$T:$T,M$6)) -> 0 | ... Q13: =IF((AND($E$3="MCS",$E$4="TODOS CRs")), SUMIFS('2026'!$K:$K,'2026'!$R:$R,$E$3&$C13,'2026'!$T:$T,Q$6), SUMIFS('2026'!$K:$K,'2026'!$N:$N,$E$3&$C13&$E$4,'2026'!$T:$T,Q$6)) -> 0 | T13: TOTAL | U13: =SUMIFS($E$7:$E$40,$B$7:$B$40,T13) -> 0 | V13: =IFERROR(ABS(U13/$U$5),0) -> 0
D14: (=) TOTAL ENTRADAS | E14: =SUBTOTAL(9,E7:E13) -> 33591.75 | F14: =SUBTOTAL(9,F7:F13) -> 4900 | G14: =SUBTOTAL(9,G7:G13) -> 5517.62 | H14: =SUBTOTAL(9,H7:H13) -> 5096 | I14: =SUBTOTAL(9,I7:I13) -> 7025 | J14: =SUBTOTAL(9,J7:J13) -> 6659.99 | K14: =SUBTOTAL(9,K7:K13) -> 4393.14 | L14: =SUBTOTAL(9,L7:L13) -> 0 | ... Q14: =SUBTOTAL(9,Q7:Q13) -> 0 | T14: SUPERÁVIT | U14: =U5+U13 -> 33591.75 | V14: =ABS(U14/$U$5) -> 1
B16: Grupo | C16: Natureza | D16: SAÍDAS | E16: ACUM | F16: =F6 -> 46023 | G16: =G6 -> 46054 | H16: =H6 -> 46082 | I16: =I6 -> 46113 | J16: =J6 -> 46143 | K16: =K6 -> 46174 | L16: =L6 -> 46204 | M16: =M6 -> 46235 | ... Q16: =Q6 -> 46357
B17: OPF | C17: OPF1 | D17: CPF - Desp. Alimentação / Refeição | E17: =SUM(F17:Q17) -> -1928.08 | F17: =IF((AND($E$3="MCS",$E$4="TODOS CRs")), SUMIFS('2026'!$K:$K,'2026'!$R:$R,$E$3&$C17,'2026'!$T:$T,F$6), SUMIFS('2026'!$K:$K,'2026'!$N:$N,$E$3&$C17&$E$4,'2026'!$T:$T,F$6)) -> -416.33 | G17: =IF((AND($E$3="MCS",$E$4="TODOS CRs")), SUMIFS('2026'!$K:$K,'2026'!$R:$R,$E$3&$C17,'2026'!$T:$T,G$6), SUMIFS('2026'!$K:$K,'2026'!$N:$N,$E$3&$C17&$E$4,'2026'!$T:$T,G$6)) -> -293 | H17: =IF((AND($E$3="MCS",$E$4="TODOS CRs")), SUMIFS('2026'!$K:$K,'2026'!$R:$R,$E$3&$C17,'2026'!$T:$T,H$6), SUMIFS('2026'!$K:$K,'2026'!$N:$N,$E$3&$C17&$E$4,'2026'!$T:$T,H$6)) -> -24 | I17: =IF((AND($E$3="MCS",$E$4="TODOS CRs")), SUMIFS('2026'!$K:$K,'2026'!$R:$R,$E$3&$C17,'2026'!$T:$T,I$6), SUMIFS('2026'!$K:$K,'2026'!$N:$N,$E$3&$C17&$E$4,'2026'!$T:$T,I$6)) -> -250.16 | J17: =IF((AND($E$3="MCS",$E$4="TODOS CRs")), SUMIFS('2026'!$K:$K,'2026'!$R:$R,$E$3&$C17,'2026'!$T:$T,J$6), SUMIFS('2026'!$K:$K,'2026'!$N:$N,$E$3&$C17&$E$4,'2026'!$T:$T,J$6)) -> -497.16 | K17: =IF((AND($E$3="MCS",$E$4="TODOS CRs")), SUMIFS('2026'!$K:$K,'2026'!$R:$R,$E$3&$C17,'2026'!$T:$T,K$6), SUMIFS('2026'!$K:$K,'2026'!$N:$N,$E$3&$C17&$E$4,'2026'!$T:$T,K$6)) -> -447.43 | L17: =IF((AND($E$3="MCS",$E$4="TODOS CRs")), SUMIFS('2026'!$K:$K,'2026'!$R:$R,$E$3&$C17,'2026'!$T:$T,L$6), SUMIFS('2026'!$K:$K,'2026'!$N:$N,$E$3&$C17&$E$4,'2026'!$T:$T,L$6)) -> 0 | M17: =IF((AND($E$3="MCS",$E$4="TODOS CRs")), SUMIFS('2026'!$K:$K,'2026'!$R:$R,$E$3&$C17,'2026'!$T:$T,M$6), SUMIFS('2026'!$K:$K,'2026'!$N:$N,$E$3&$C17&$E$4,'2026'!$T:$T,M$6)) -> 0 | ... Q17: =IF((AND($E$3="MCS",$E$4="TODOS CRs")), SUMIFS('2026'!$K:$K,'2026'!$R:$R,$E$3&$C17,'2026'!$T:$T,Q$6), SUMIFS('2026'!$K:$K,'2026'!$N:$N,$E$3&$C17&$E$4,'2026'!$T:$T,Q$6)) -> 0
B18: OPF | C18: OPF2 | D18: CPF - Desp. Transporte / Combustível | E18: =SUM(F18:Q18) -> -4912.38 | F18: =IF((AND($E$3="MCS",$E$4="TODOS CRs")), SUMIFS('2026'!$K:$K,'2026'!$R:$R,$E$3&$C18,'2026'!$T:$T,F$6), SUMIFS('2026'!$K:$K,'2026'!$N:$N,$E$3&$C18&$E$4,'2026'!$T:$T,F$6)) -> -740 | G18: =IF((AND($E$3="MCS",$E$4="TODOS CRs")), SUMIFS('2026'!$K:$K,'2026'!$R:$R,$E$3&$C18,'2026'!$T:$T,G$6), SUMIFS('2026'!$K:$K,'2026'!$N:$N,$E$3&$C18&$E$4,'2026'!$T:$T,G$6)) -> -1096.67 | H18: =IF((AND($E$3="MCS",$E$4="TODOS CRs")), SUMIFS('2026'!$K:$K,'2026'!$R:$R,$E$3&$C18,'2026'!$T:$T,H$6), SUMIFS('2026'!$K:$K,'2026'!$N:$N,$E$3&$C18&$E$4,'2026'!$T:$T,H$6)) -> -675.2 | I18: =IF((AND($E$3="MCS",$E$4="TODOS CRs")), SUMIFS('2026'!$K:$K,'2026'!$R:$R,$E$3&$C18,'2026'!$T:$T,I$6), SUMIFS('2026'!$K:$K,'2026'!$N:$N,$E$3&$C18&$E$4,'2026'!$T:$T,I$6)) -> -887.68 | J18: =IF((AND($E$3="MCS",$E$4="TODOS CRs")), SUMIFS('2026'!$K:$K,'2026'!$R:$R,$E$3&$C18,'2026'!$T:$T,J$6), SUMIFS('2026'!$K:$K,'2026'!$N:$N,$E$3&$C18&$E$4,'2026'!$T:$T,J$6)) -> -1012.83 | K18: =IF((AND($E$3="MCS",$E$4="TODOS CRs")), SUMIFS('2026'!$K:$K,'2026'!$R:$R,$E$3&$C18,'2026'!$T:$T,K$6), SUMIFS('2026'!$K:$K,'2026'!$N:$N,$E$3&$C18&$E$4,'2026'!$T:$T,K$6)) -> -500 | L18: =IF((AND($E$3="MCS",$E$4="TODOS CRs")), SUMIFS('2026'!$K:$K,'2026'!$R:$R,$E$3&$C18,'2026'!$T:$T,L$6), SUMIFS('2026'!$K:$K,'2026'!$N:$N,$E$3&$C18&$E$4,'2026'!$T:$T,L$6)) -> 0 | M18: =IF((AND($E$3="MCS",$E$4="TODOS CRs")), SUMIFS('2026'!$K:$K,'2026'!$R:$R,$E$3&$C18,'2026'!$T:$T,M$6), SUMIFS('2026'!$K:$K,'2026'!$N:$N,$E$3&$C18&$E$4,'2026'!$T:$T,M$6)) -> 0 | ... Q18: =IF((AND($E$3="MCS",$E$4="TODOS CRs")), SUMIFS('2026'!$K:$K,'2026'!$R:$R,$E$3&$C18,'2026'!$T:$T,Q$6), SUMIFS('2026'!$K:$K,'2026'!$N:$N,$E$3&$C18&$E$4,'2026'!$T:$T,Q$6)) -> 0
B19: DESP | C19: DESP1 | D19: CPF - Desp. Cartão de crédito | E19: =SUM(F19:Q19) -> -215.52 | F19: =IF((AND($E$3="MCS",$E$4="TODOS CRs")), SUMIFS('2026'!$K:$K,'2026'!$R:$R,$E$3&$C19,'2026'!$T:$T,F$6), SUMIFS('2026'!$K:$K,'2026'!$N:$N,$E$3&$C19&$E$4,'2026'!$T:$T,F$6)) -> 0 | G19: =IF((AND($E$3="MCS",$E$4="TODOS CRs")), SUMIFS('2026'!$K:$K,'2026'!$R:$R,$E$3&$C19,'2026'!$T:$T,G$6), SUMIFS('2026'!$K:$K,'2026'!$N:$N,$E$3&$C19&$E$4,'2026'!$T:$T,G$6)) -> -203.49 | H19: =IF((AND($E$3="MCS",$E$4="TODOS CRs")), SUMIFS('2026'!$K:$K,'2026'!$R:$R,$E$3&$C19,'2026'!$T:$T,H$6), SUMIFS('2026'!$K:$K,'2026'!$N:$N,$E$3&$C19&$E$4,'2026'!$T:$T,H$6)) -> -5.9 | I19: =IF((AND($E$3="MCS",$E$4="TODOS CRs")), SUMIFS('2026'!$K:$K,'2026'!$R:$R,$E$3&$C19,'2026'!$T:$T,I$6), SUMIFS('2026'!$K:$K,'2026'!$N:$N,$E$3&$C19&$E$4,'2026'!$T:$T,I$6)) -> 0 | J19: =IF((AND($E$3="MCS",$E$4="TODOS CRs")), SUMIFS('2026'!$K:$K,'2026'!$R:$R,$E$3&$C19,'2026'!$T:$T,J$6), SUMIFS('2026'!$K:$K,'2026'!$N:$N,$E$3&$C19&$E$4,'2026'!$T:$T,J$6)) -> 0 | K19: =IF((AND($E$3="MCS",$E$4="TODOS CRs")), SUMIFS('2026'!$K:$K,'2026'!$R:$R,$E$3&$C19,'2026'!$T:$T,K$6), SUMIFS('2026'!$K:$K,'2026'!$N:$N,$E$3&$C19&$E$4,'2026'!$T:$T,K$6)) -> -6.13 | L19: =IF((AND($E$3="MCS",$E$4="TODOS CRs")), SUMIFS('2026'!$K:$K,'2026'!$R:$R,$E$3&$C19,'2026'!$T:$T,L$6), SUMIFS('2026'!$K:$K,'2026'!$N:$N,$E$3&$C19&$E$4,'2026'!$T:$T,L$6)) -> 0 | M19: =IF((AND($E$3="MCS",$E$4="TODOS CRs")), SUMIFS('2026'!$K:$K,'2026'!$R:$R,$E$3&$C19,'2026'!$T:$T,M$6), SUMIFS('2026'!$K:$K,'2026'!$N:$N,$E$3&$C19&$E$4,'2026'!$T:$T,M$6)) -> 0 | ... Q19: =IF((AND($E$3="MCS",$E$4="TODOS CRs")), SUMIFS('2026'!$K:$K,'2026'!$R:$R,$E$3&$C19,'2026'!$T:$T,Q$6), SUMIFS('2026'!$K:$K,'2026'!$N:$N,$E$3&$C19&$E$4,'2026'!$T:$T,Q$6)) -> 0
B20: DESP | C20: DESP2 | D20: CPF - Desp. Telefone / Internet | E20: =SUM(F20:Q20) -> -1380.41 | F20: =IF((AND($E$3="MCS",$E$4="TODOS CRs")), SUMIFS('2026'!$K:$K,'2026'!$R:$R,$E$3&$C20,'2026'!$T:$T,F$6), SUMIFS('2026'!$K:$K,'2026'!$N:$N,$E$3&$C20&$E$4,'2026'!$T:$T,F$6)) -> -248.12 | G20: =IF((AND($E$3="MCS",$E$4="TODOS CRs")), SUMIFS('2026'!$K:$K,'2026'!$R:$R,$E$3&$C20,'2026'!$T:$T,G$6), SUMIFS('2026'!$K:$K,'2026'!$N:$N,$E$3&$C20&$E$4,'2026'!$T:$T,G$6)) -> -124.97 | H20: =IF((AND($E$3="MCS",$E$4="TODOS CRs")), SUMIFS('2026'!$K:$K,'2026'!$R:$R,$E$3&$C20,'2026'!$T:$T,H$6), SUMIFS('2026'!$K:$K,'2026'!$N:$N,$E$3&$C20&$E$4,'2026'!$T:$T,H$6)) -> -447.99 | I20: =IF((AND($E$3="MCS",$E$4="TODOS CRs")), SUMIFS('2026'!$K:$K,'2026'!$R:$R,$E$3&$C20,'2026'!$T:$T,I$6), SUMIFS('2026'!$K:$K,'2026'!$N:$N,$E$3&$C20&$E$4,'2026'!$T:$T,I$6)) -> -125.21 | J20: =IF((AND($E$3="MCS",$E$4="TODOS CRs")), SUMIFS('2026'!$K:$K,'2026'!$R:$R,$E$3&$C20,'2026'!$T:$T,J$6), SUMIFS('2026'!$K:$K,'2026'!$N:$N,$E$3&$C20&$E$4,'2026'!$T:$T,J$6)) -> -309.02 | K20: =IF((AND($E$3="MCS",$E$4="TODOS CRs")), SUMIFS('2026'!$K:$K,'2026'!$R:$R,$E$3&$C20,'2026'!$T:$T,K$6), SUMIFS('2026'!$K:$K,'2026'!$N:$N,$E$3&$C20&$E$4,'2026'!$T:$T,K$6)) -> -125.1 | L20: =IF((AND($E$3="MCS",$E$4="TODOS CRs")), SUMIFS('2026'!$K:$K,'2026'!$R:$R,$E$3&$C20,'2026'!$T:$T,L$6), SUMIFS('2026'!$K:$K,'2026'!$N:$N,$E$3&$C20&$E$4,'2026'!$T:$T,L$6)) -> 0 | M20: =IF((AND($E$3="MCS",$E$4="TODOS CRs")), SUMIFS('2026'!$K:$K,'2026'!$R:$R,$E$3&$C20,'2026'!$T:$T,M$6), SUMIFS('2026'!$K:$K,'2026'!$N:$N,$E$3&$C20&$E$4,'2026'!$T:$T,M$6)) -> 0 | ... Q20: =IF((AND($E$3="MCS",$E$4="TODOS CRs")), SUMIFS('2026'!$K:$K,'2026'!$R:$R,$E$3&$C20,'2026'!$T:$T,Q$6), SUMIFS('2026'!$K:$K,'2026'!$N:$N,$E$3&$C20&$E$4,'2026'!$T:$T,Q$6)) -> 0
B21: DESP | C21: DESP3 | D21: CPF - Desp. com veículo - Manut. / Gastos | E21: =SUM(F21:Q21) -> -526.7 | F21: =IF((AND($E$3="MCS",$E$4="TODOS CRs")), SUMIFS('2026'!$K:$K,'2026'!$R:$R,$E$3&$C21,'2026'!$T:$T,F$6), SUMIFS('2026'!$K:$K,'2026'!$N:$N,$E$3&$C21&$E$4,'2026'!$T:$T,F$6)) -> 0 | G21: =IF((AND($E$3="MCS",$E$4="TODOS CRs")), SUMIFS('2026'!$K:$K,'2026'!$R:$R,$E$3&$C21,'2026'!$T:$T,G$6), SUMIFS('2026'!$K:$K,'2026'!$N:$N,$E$3&$C21&$E$4,'2026'!$T:$T,G$6)) -> -60 | H21: =IF((AND($E$3="MCS",$E$4="TODOS CRs")), SUMIFS('2026'!$K:$K,'2026'!$R:$R,$E$3&$C21,'2026'!$T:$T,H$6), SUMIFS('2026'!$K:$K,'2026'!$N:$N,$E$3&$C21&$E$4,'2026'!$T:$T,H$6)) -> 0 | I21: =IF((AND($E$3="MCS",$E$4="TODOS CRs")), SUMIFS('2026'!$K:$K,'2026'!$R:$R,$E$3&$C21,'2026'!$T:$T,I$6), SUMIFS('2026'!$K:$K,'2026'!$N:$N,$E$3&$C21&$E$4,'2026'!$T:$T,I$6)) -> 0 | J21: =IF((AND($E$3="MCS",$E$4="TODOS CRs")), SUMIFS('2026'!$K:$K,'2026'!$R:$R,$E$3&$C21,'2026'!$T:$T,J$6), SUMIFS('2026'!$K:$K,'2026'!$N:$N,$E$3&$C21&$E$4,'2026'!$T:$T,J$6)) -> -432.95 | K21: =IF((AND($E$3="MCS",$E$4="TODOS CRs")), SUMIFS('2026'!$K:$K,'2026'!$R:$R,$E$3&$C21,'2026'!$T:$T,K$6), SUMIFS('2026'!$K:$K,'2026'!$N:$N,$E$3&$C21&$E$4,'2026'!$T:$T,K$6)) -> -33.75 | L21: =IF((AND($E$3="MCS",$E$4="TODOS CRs")), SUMIFS('2026'!$K:$K,'2026'!$R:$R,$E$3&$C21,'2026'!$T:$T,L$6), SUMIFS('2026'!$K:$K,'2026'!$N:$N,$E$3&$C21&$E$4,'2026'!$T:$T,L$6)) -> 0 | M21: =IF((AND($E$3="MCS",$E$4="TODOS CRs")), SUMIFS('2026'!$K:$K,'2026'!$R:$R,$E$3&$C21,'2026'!$T:$T,M$6), SUMIFS('2026'!$K:$K,'2026'!$N:$N,$E$3&$C21&$E$4,'2026'!$T:$T,M$6)) -> 0 | ... Q21: =IF((AND($E$3="MCS",$E$4="TODOS CRs")), SUMIFS('2026'!$K:$K,'2026'!$R:$R,$E$3&$C21,'2026'!$T:$T,Q$6), SUMIFS('2026'!$K:$K,'2026'!$N:$N,$E$3&$C21&$E$4,'2026'!$T:$T,Q$6)) -> 0
B22: DESP | C22: DESP4 | D22: CPF - Desp. Moradia | E22: =SUM(F22:Q22) -> -1906 | F22: =IF((AND($E$3="MCS",$E$4="TODOS CRs")), SUMIFS('2026'!$K:$K,'2026'!$R:$R,$E$3&$C22,'2026'!$T:$T,F$6), SUMIFS('2026'!$K:$K,'2026'!$N:$N,$E$3&$C22&$E$4,'2026'!$T:$T,F$6)) -> 0 | G22: =IF((AND($E$3="MCS",$E$4="TODOS CRs")), SUMIFS('2026'!$K:$K,'2026'!$R:$R,$E$3&$C22,'2026'!$T:$T,G$6), SUMIFS('2026'!$K:$K,'2026'!$N:$N,$E$3&$C22&$E$4,'2026'!$T:$T,G$6)) -> -204.78 | H22: =IF((AND($E$3="MCS",$E$4="TODOS CRs")), SUMIFS('2026'!$K:$K,'2026'!$R:$R,$E$3&$C22,'2026'!$T:$T,H$6), SUMIFS('2026'!$K:$K,'2026'!$N:$N,$E$3&$C22&$E$4,'2026'!$T:$T,H$6)) -> -347.67 | I22: =IF((AND($E$3="MCS",$E$4="TODOS CRs")), SUMIFS('2026'!$K:$K,'2026'!$R:$R,$E$3&$C22,'2026'!$T:$T,I$6), SUMIFS('2026'!$K:$K,'2026'!$N:$N,$E$3&$C22&$E$4,'2026'!$T:$T,I$6)) -> -511.07 | J22: =IF((AND($E$3="MCS",$E$4="TODOS CRs")), SUMIFS('2026'!$K:$K,'2026'!$R:$R,$E$3&$C22,'2026'!$T:$T,J$6), SUMIFS('2026'!$K:$K,'2026'!$N:$N,$E$3&$C22&$E$4,'2026'!$T:$T,J$6)) -> -451.48 | K22: =IF((AND($E$3="MCS",$E$4="TODOS CRs")), SUMIFS('2026'!$K:$K,'2026'!$R:$R,$E$3&$C22,'2026'!$T:$T,K$6), SUMIFS('2026'!$K:$K,'2026'!$N:$N,$E$3&$C22&$E$4,'2026'!$T:$T,K$6)) -> -391 | L22: =IF((AND($E$3="MCS",$E$4="TODOS CRs")), SUMIFS('2026'!$K:$K,'2026'!$R:$R,$E$3&$C22,'2026'!$T:$T,L$6), SUMIFS('2026'!$K:$K,'2026'!$N:$N,$E$3&$C22&$E$4,'2026'!$T:$T,L$6)) -> 0 | M22: =IF((AND($E$3="MCS",$E$4="TODOS CRs")), SUMIFS('2026'!$K:$K,'2026'!$R:$R,$E$3&$C22,'2026'!$T:$T,M$6), SUMIFS('2026'!$K:$K,'2026'!$N:$N,$E$3&$C22&$E$4,'2026'!$T:$T,M$6)) -> 0 | ... Q22: =IF((AND($E$3="MCS",$E$4="TODOS CRs")), SUMIFS('2026'!$K:$K,'2026'!$R:$R,$E$3&$C22,'2026'!$T:$T,Q$6), SUMIFS('2026'!$K:$K,'2026'!$N:$N,$E$3&$C22&$E$4,'2026'!$T:$T,Q$6)) -> 0
B23: DESP | C23: DESP5 | D23: CPF - Transf. Da conta PF para a conta PJ | E23: =SUM(F23:Q23) -> 0 | F23: =IF((AND($E$3="MCS",$E$4="TODOS CRs")), SUMIFS('2026'!$K:$K,'2026'!$R:$R,$E$3&$C23,'2026'!$T:$T,F$6), SUMIFS('2026'!$K:$K,'2026'!$N:$N,$E$3&$C23&$E$4,'2026'!$T:$T,F$6)) -> 0 | G23: =IF((AND($E$3="MCS",$E$4="TODOS CRs")), SUMIFS('2026'!$K:$K,'2026'!$R:$R,$E$3&$C23,'2026'!$T:$T,G$6), SUMIFS('2026'!$K:$K,'2026'!$N:$N,$E$3&$C23&$E$4,'2026'!$T:$T,G$6)) -> 0 | H23: =IF((AND($E$3="MCS",$E$4="TODOS CRs")), SUMIFS('2026'!$K:$K,'2026'!$R:$R,$E$3&$C23,'2026'!$T:$T,H$6), SUMIFS('2026'!$K:$K,'2026'!$N:$N,$E$3&$C23&$E$4,'2026'!$T:$T,H$6)) -> 0 | I23: =IF((AND($E$3="MCS",$E$4="TODOS CRs")), SUMIFS('2026'!$K:$K,'2026'!$R:$R,$E$3&$C23,'2026'!$T:$T,I$6), SUMIFS('2026'!$K:$K,'2026'!$N:$N,$E$3&$C23&$E$4,'2026'!$T:$T,I$6)) -> 0 | J23: =IF((AND($E$3="MCS",$E$4="TODOS CRs")), SUMIFS('2026'!$K:$K,'2026'!$R:$R,$E$3&$C23,'2026'!$T:$T,J$6), SUMIFS('2026'!$K:$K,'2026'!$N:$N,$E$3&$C23&$E$4,'2026'!$T:$T,J$6)) -> 0 | K23: =IF((AND($E$3="MCS",$E$4="TODOS CRs")), SUMIFS('2026'!$K:$K,'2026'!$R:$R,$E$3&$C23,'2026'!$T:$T,K$6), SUMIFS('2026'!$K:$K,'2026'!$N:$N,$E$3&$C23&$E$4,'2026'!$T:$T,K$6)) -> 0 | L23: =IF((AND($E$3="MCS",$E$4="TODOS CRs")), SUMIFS('2026'!$K:$K,'2026'!$R:$R,$E$3&$C23,'2026'!$T:$T,L$6), SUMIFS('2026'!$K:$K,'2026'!$N:$N,$E$3&$C23&$E$4,'2026'!$T:$T,L$6)) -> 0 | M23: =IF((AND($E$3="MCS",$E$4="TODOS CRs")), SUMIFS('2026'!$K:$K,'2026'!$R:$R,$E$3&$C23,'2026'!$T:$T,M$6), SUMIFS('2026'!$K:$K,'2026'!$N:$N,$E$3&$C23&$E$4,'2026'!$T:$T,M$6)) -> 0 | ... Q23: =IF((AND($E$3="MCS",$E$4="TODOS CRs")), SUMIFS('2026'!$K:$K,'2026'!$R:$R,$E$3&$C23,'2026'!$T:$T,Q$6), SUMIFS('2026'!$K:$K,'2026'!$N:$N,$E$3&$C23&$E$4,'2026'!$T:$T,Q$6)) -> 0
B24: GAST | C24: GAST1 | D24: CPF - Desp. Lazer e Entretenimento - Bares | E24: =SUM(F24:Q24) -> -5237.55 | F24: =IF((AND($E$3="MCS",$E$4="TODOS CRs")), SUMIFS('2026'!$K:$K,'2026'!$R:$R,$E$3&$C24,'2026'!$T:$T,F$6), SUMIFS('2026'!$K:$K,'2026'!$N:$N,$E$3&$C24&$E$4,'2026'!$T:$T,F$6)) -> -849.87 | G24: =IF((AND($E$3="MCS",$E$4="TODOS CRs")), SUMIFS('2026'!$K:$K,'2026'!$R:$R,$E$3&$C24,'2026'!$T:$T,G$6), SUMIFS('2026'!$K:$K,'2026'!$N:$N,$E$3&$C24&$E$4,'2026'!$T:$T,G$6)) -> -662.01 | H24: =IF((AND($E$3="MCS",$E$4="TODOS CRs")), SUMIFS('2026'!$K:$K,'2026'!$R:$R,$E$3&$C24,'2026'!$T:$T,H$6), SUMIFS('2026'!$K:$K,'2026'!$N:$N,$E$3&$C24&$E$4,'2026'!$T:$T,H$6)) -> -332.84 | I24: =IF((AND($E$3="MCS",$E$4="TODOS CRs")), SUMIFS('2026'!$K:$K,'2026'!$R:$R,$E$3&$C24,'2026'!$T:$T,I$6), SUMIFS('2026'!$K:$K,'2026'!$N:$N,$E$3&$C24&$E$4,'2026'!$T:$T,I$6)) -> -1448.71 | J24: =IF((AND($E$3="MCS",$E$4="TODOS CRs")), SUMIFS('2026'!$K:$K,'2026'!$R:$R,$E$3&$C24,'2026'!$T:$T,J$6), SUMIFS('2026'!$K:$K,'2026'!$N:$N,$E$3&$C24&$E$4,'2026'!$T:$T,J$6)) -> -1099.45 | K24: =IF((AND($E$3="MCS",$E$4="TODOS CRs")), SUMIFS('2026'!$K:$K,'2026'!$R:$R,$E$3&$C24,'2026'!$T:$T,K$6), SUMIFS('2026'!$K:$K,'2026'!$N:$N,$E$3&$C24&$E$4,'2026'!$T:$T,K$6)) -> -844.67 | L24: =IF((AND($E$3="MCS",$E$4="TODOS CRs")), SUMIFS('2026'!$K:$K,'2026'!$R:$R,$E$3&$C24,'2026'!$T:$T,L$6), SUMIFS('2026'!$K:$K,'2026'!$N:$N,$E$3&$C24&$E$4,'2026'!$T:$T,L$6)) -> 0 | M24: =IF((AND($E$3="MCS",$E$4="TODOS CRs")), SUMIFS('2026'!$K:$K,'2026'!$R:$R,$E$3&$C24,'2026'!$T:$T,M$6), SUMIFS('2026'!$K:$K,'2026'!$N:$N,$E$3&$C24&$E$4,'2026'!$T:$T,M$6)) -> 0 | ... Q24: =IF((AND($E$3="MCS",$E$4="TODOS CRs")), SUMIFS('2026'!$K:$K,'2026'!$R:$R,$E$3&$C24,'2026'!$T:$T,Q$6), SUMIFS('2026'!$K:$K,'2026'!$N:$N,$E$3&$C24&$E$4,'2026'!$T:$T,Q$6)) -> 0
B25: GAST | C25: GAST2 | D25: CPF - Desp. Lazer e Entretenimento - Cigarro | E25: =SUM(F25:Q25) -> -808 | F25: =IF((AND($E$3="MCS",$E$4="TODOS CRs")), SUMIFS('2026'!$K:$K,'2026'!$R:$R,$E$3&$C25,'2026'!$T:$T,F$6), SUMIFS('2026'!$K:$K,'2026'!$N:$N,$E$3&$C25&$E$4,'2026'!$T:$T,F$6)) -> -134 | G25: =IF((AND($E$3="MCS",$E$4="TODOS CRs")), SUMIFS('2026'!$K:$K,'2026'!$R:$R,$E$3&$C25,'2026'!$T:$T,G$6), SUMIFS('2026'!$K:$K,'2026'!$N:$N,$E$3&$C25&$E$4,'2026'!$T:$T,G$6)) -> -196.5 | H25: =IF((AND($E$3="MCS",$E$4="TODOS CRs")), SUMIFS('2026'!$K:$K,'2026'!$R:$R,$E$3&$C25,'2026'!$T:$T,H$6), SUMIFS('2026'!$K:$K,'2026'!$N:$N,$E$3&$C25&$E$4,'2026'!$T:$T,H$6)) -> 0 | I25: =IF((AND($E$3="MCS",$E$4="TODOS CRs")), SUMIFS('2026'!$K:$K,'2026'!$R:$R,$E$3&$C25,'2026'!$T:$T,I$6), SUMIFS('2026'!$K:$K,'2026'!$N:$N,$E$3&$C25&$E$4,'2026'!$T:$T,I$6)) -> -174 | J25: =IF((AND($E$3="MCS",$E$4="TODOS CRs")), SUMIFS('2026'!$K:$K,'2026'!$R:$R,$E$3&$C25,'2026'!$T:$T,J$6), SUMIFS('2026'!$K:$K,'2026'!$N:$N,$E$3&$C25&$E$4,'2026'!$T:$T,J$6)) -> -176 | K25: =IF((AND($E$3="MCS",$E$4="TODOS CRs")), SUMIFS('2026'!$K:$K,'2026'!$R:$R,$E$3&$C25,'2026'!$T:$T,K$6), SUMIFS('2026'!$K:$K,'2026'!$N:$N,$E$3&$C25&$E$4,'2026'!$T:$T,K$6)) -> -127.5 | L25: =IF((AND($E$3="MCS",$E$4="TODOS CRs")), SUMIFS('2026'!$K:$K,'2026'!$R:$R,$E$3&$C25,'2026'!$T:$T,L$6), SUMIFS('2026'!$K:$K,'2026'!$N:$N,$E$3&$C25&$E$4,'2026'!$T:$T,L$6)) -> 0 | M25: =IF((AND($E$3="MCS",$E$4="TODOS CRs")), SUMIFS('2026'!$K:$K,'2026'!$R:$R,$E$3&$C25,'2026'!$T:$T,M$6), SUMIFS('2026'!$K:$K,'2026'!$N:$N,$E$3&$C25&$E$4,'2026'!$T:$T,M$6)) -> 0 | ... Q25: =IF((AND($E$3="MCS",$E$4="TODOS CRs")), SUMIFS('2026'!$K:$K,'2026'!$R:$R,$E$3&$C25,'2026'!$T:$T,Q$6), SUMIFS('2026'!$K:$K,'2026'!$N:$N,$E$3&$C25&$E$4,'2026'!$T:$T,Q$6)) -> 0
B26: FIN | C26: FIN1 | D26: CPF - Desp. Financeiras - Empréstimos | E26: =SUM(F26:Q26) -> -400 | F26: =IF((AND($E$3="MCS",$E$4="TODOS CRs")), SUMIFS('2026'!$K:$K,'2026'!$R:$R,$E$3&$C26,'2026'!$T:$T,F$6), SUMIFS('2026'!$K:$K,'2026'!$N:$N,$E$3&$C26&$E$4,'2026'!$T:$T,F$6)) -> -200 | G26: =IF((AND($E$3="MCS",$E$4="TODOS CRs")), SUMIFS('2026'!$K:$K,'2026'!$R:$R,$E$3&$C26,'2026'!$T:$T,G$6), SUMIFS('2026'!$K:$K,'2026'!$N:$N,$E$3&$C26&$E$4,'2026'!$T:$T,G$6)) -> 0 | H26: =IF((AND($E$3="MCS",$E$4="TODOS CRs")), SUMIFS('2026'!$K:$K,'2026'!$R:$R,$E$3&$C26,'2026'!$T:$T,H$6), SUMIFS('2026'!$K:$K,'2026'!$N:$N,$E$3&$C26&$E$4,'2026'!$T:$T,H$6)) -> -170 | I26: =IF((AND($E$3="MCS",$E$4="TODOS CRs")), SUMIFS('2026'!$K:$K,'2026'!$R:$R,$E$3&$C26,'2026'!$T:$T,I$6), SUMIFS('2026'!$K:$K,'2026'!$N:$N,$E$3&$C26&$E$4,'2026'!$T:$T,I$6)) -> -30 | J26: =IF((AND($E$3="MCS",$E$4="TODOS CRs")), SUMIFS('2026'!$K:$K,'2026'!$R:$R,$E$3&$C26,'2026'!$T:$T,J$6), SUMIFS('2026'!$K:$K,'2026'!$N:$N,$E$3&$C26&$E$4,'2026'!$T:$T,J$6)) -> 0 | K26: =IF((AND($E$3="MCS",$E$4="TODOS CRs")), SUMIFS('2026'!$K:$K,'2026'!$R:$R,$E$3&$C26,'2026'!$T:$T,K$6), SUMIFS('2026'!$K:$K,'2026'!$N:$N,$E$3&$C26&$E$4,'2026'!$T:$T,K$6)) -> 0 | L26: =IF((AND($E$3="MCS",$E$4="TODOS CRs")), SUMIFS('2026'!$K:$K,'2026'!$R:$R,$E$3&$C26,'2026'!$T:$T,L$6), SUMIFS('2026'!$K:$K,'2026'!$N:$N,$E$3&$C26&$E$4,'2026'!$T:$T,L$6)) -> 0 | M26: =IF((AND($E$3="MCS",$E$4="TODOS CRs")), SUMIFS('2026'!$K:$K,'2026'!$R:$R,$E$3&$C26,'2026'!$T:$T,M$6), SUMIFS('2026'!$K:$K,'2026'!$N:$N,$E$3&$C26&$E$4,'2026'!$T:$T,M$6)) -> 0 | ... Q26: =IF((AND($E$3="MCS",$E$4="TODOS CRs")), SUMIFS('2026'!$K:$K,'2026'!$R:$R,$E$3&$C26,'2026'!$T:$T,Q$6), SUMIFS('2026'!$K:$K,'2026'!$N:$N,$E$3&$C26&$E$4,'2026'!$T:$T,Q$6)) -> 0
B27: FIN | C27: FIN2 | D27: CPF - Desp. Financeiras - Juros / Tarifas | E27: =SUM(F27:Q27) -> -168 | F27: =IF((AND($E$3="MCS",$E$4="TODOS CRs")), SUMIFS('2026'!$K:$K,'2026'!$R:$R,$E$3&$C27,'2026'!$T:$T,F$6), SUMIFS('2026'!$K:$K,'2026'!$N:$N,$E$3&$C27&$E$4,'2026'!$T:$T,F$6)) -> -28 | G27: =IF((AND($E$3="MCS",$E$4="TODOS CRs")), SUMIFS('2026'!$K:$K,'2026'!$R:$R,$E$3&$C27,'2026'!$T:$T,G$6), SUMIFS('2026'!$K:$K,'2026'!$N:$N,$E$3&$C27&$E$4,'2026'!$T:$T,G$6)) -> -28 | H27: =IF((AND($E$3="MCS",$E$4="TODOS CRs")), SUMIFS('2026'!$K:$K,'2026'!$R:$R,$E$3&$C27,'2026'!$T:$T,H$6), SUMIFS('2026'!$K:$K,'2026'!$N:$N,$E$3&$C27&$E$4,'2026'!$T:$T,H$6)) -> -28 | I27: =IF((AND($E$3="MCS",$E$4="TODOS CRs")), SUMIFS('2026'!$K:$K,'2026'!$R:$R,$E$3&$C27,'2026'!$T:$T,I$6), SUMIFS('2026'!$K:$K,'2026'!$N:$N,$E$3&$C27&$E$4,'2026'!$T:$T,I$6)) -> -28 | J27: =IF((AND($E$3="MCS",$E$4="TODOS CRs")), SUMIFS('2026'!$K:$K,'2026'!$R:$R,$E$3&$C27,'2026'!$T:$T,J$6), SUMIFS('2026'!$K:$K,'2026'!$N:$N,$E$3&$C27&$E$4,'2026'!$T:$T,J$6)) -> -28 | K27: =IF((AND($E$3="MCS",$E$4="TODOS CRs")), SUMIFS('2026'!$K:$K,'2026'!$R:$R,$E$3&$C27,'2026'!$T:$T,K$6), SUMIFS('2026'!$K:$K,'2026'!$N:$N,$E$3&$C27&$E$4,'2026'!$T:$T,K$6)) -> -28 | L27: =IF((AND($E$3="MCS",$E$4="TODOS CRs")), SUMIFS('2026'!$K:$K,'2026'!$R:$R,$E$3&$C27,'2026'!$T:$T,L$6), SUMIFS('2026'!$K:$K,'2026'!$N:$N,$E$3&$C27&$E$4,'2026'!$T:$T,L$6)) -> 0 | M27: =IF((AND($E$3="MCS",$E$4="TODOS CRs")), SUMIFS('2026'!$K:$K,'2026'!$R:$R,$E$3&$C27,'2026'!$T:$T,M$6), SUMIFS('2026'!$K:$K,'2026'!$N:$N,$E$3&$C27&$E$4,'2026'!$T:$T,M$6)) -> 0 | ... Q27: =IF((AND($E$3="MCS",$E$4="TODOS CRs")), SUMIFS('2026'!$K:$K,'2026'!$R:$R,$E$3&$C27,'2026'!$T:$T,Q$6), SUMIFS('2026'!$K:$K,'2026'!$N:$N,$E$3&$C27&$E$4,'2026'!$T:$T,Q$6)) -> 0
B28: FIN | C28: FIN3 | D28: CPF - Desp. Financeiras - Juros / Tarifas | E28: =SUM(F28:Q28) -> -1782.3 | F28: =IF((AND($E$3="MCS",$E$4="TODOS CRs")), SUMIFS('2026'!$K:$K,'2026'!$R:$R,$E$3&$C28,'2026'!$T:$T,F$6), SUMIFS('2026'!$K:$K,'2026'!$N:$N,$E$3&$C28&$E$4,'2026'!$T:$T,F$6)) -> -297.05 | G28: =IF((AND($E$3="MCS",$E$4="TODOS CRs")), SUMIFS('2026'!$K:$K,'2026'!$R:$R,$E$3&$C28,'2026'!$T:$T,G$6), SUMIFS('2026'!$K:$K,'2026'!$N:$N,$E$3&$C28&$E$4,'2026'!$T:$T,G$6)) -> -297.05 | H28: =IF((AND($E$3="MCS",$E$4="TODOS CRs")), SUMIFS('2026'!$K:$K,'2026'!$R:$R,$E$3&$C28,'2026'!$T:$T,H$6), SUMIFS('2026'!$K:$K,'2026'!$N:$N,$E$3&$C28&$E$4,'2026'!$T:$T,H$6)) -> -297.05 | I28: =IF((AND($E$3="MCS",$E$4="TODOS CRs")), SUMIFS('2026'!$K:$K,'2026'!$R:$R,$E$3&$C28,'2026'!$T:$T,I$6), SUMIFS('2026'!$K:$K,'2026'!$N:$N,$E$3&$C28&$E$4,'2026'!$T:$T,I$6)) -> -297.05 | J28: =IF((AND($E$3="MCS",$E$4="TODOS CRs")), SUMIFS('2026'!$K:$K,'2026'!$R:$R,$E$3&$C28,'2026'!$T:$T,J$6), SUMIFS('2026'!$K:$K,'2026'!$N:$N,$E$3&$C28&$E$4,'2026'!$T:$T,J$6)) -> -297.05 | K28: =IF((AND($E$3="MCS",$E$4="TODOS CRs")), SUMIFS('2026'!$K:$K,'2026'!$R:$R,$E$3&$C28,'2026'!$T:$T,K$6), SUMIFS('2026'!$K:$K,'2026'!$N:$N,$E$3&$C28&$E$4,'2026'!$T:$T,K$6)) -> -297.05 | L28: =IF((AND($E$3="MCS",$E$4="TODOS CRs")), SUMIFS('2026'!$K:$K,'2026'!$R:$R,$E$3&$C28,'2026'!$T:$T,L$6), SUMIFS('2026'!$K:$K,'2026'!$N:$N,$E$3&$C28&$E$4,'2026'!$T:$T,L$6)) -> 0 | M28: =IF((AND($E$3="MCS",$E$4="TODOS CRs")), SUMIFS('2026'!$K:$K,'2026'!$R:$R,$E$3&$C28,'2026'!$T:$T,M$6), SUMIFS('2026'!$K:$K,'2026'!$N:$N,$E$3&$C28&$E$4,'2026'!$T:$T,M$6)) -> 0 | ... Q28: =IF((AND($E$3="MCS",$E$4="TODOS CRs")), SUMIFS('2026'!$K:$K,'2026'!$R:$R,$E$3&$C28,'2026'!$T:$T,Q$6), SUMIFS('2026'!$K:$K,'2026'!$N:$N,$E$3&$C28&$E$4,'2026'!$T:$T,Q$6)) -> 0
... B39: PENS | C39: PENS9 | D39: CPF - Pensão - Outros Gastos | E39: =SUM(F39:Q39) -> 0 | F39: =IF((AND($E$3="MCS",$E$4="TODOS CRs")), SUMIFS('2026'!$K:$K,'2026'!$R:$R,$E$3&$C39,'2026'!$T:$T,F$6), SUMIFS('2026'!$K:$K,'2026'!$N:$N,$E$3&$C39&$E$4,'2026'!$T:$T,F$6)) -> 0 | G39: =IF((AND($E$3="MCS",$E$4="TODOS CRs")), SUMIFS('2026'!$K:$K,'2026'!$R:$R,$E$3&$C39,'2026'!$T:$T,G$6), SUMIFS('2026'!$K:$K,'2026'!$N:$N,$E$3&$C39&$E$4,'2026'!$T:$T,G$6)) -> 0 | H39: =IF((AND($E$3="MCS",$E$4="TODOS CRs")), SUMIFS('2026'!$K:$K,'2026'!$R:$R,$E$3&$C39,'2026'!$T:$T,H$6), SUMIFS('2026'!$K:$K,'2026'!$N:$N,$E$3&$C39&$E$4,'2026'!$T:$T,H$6)) -> 0 | I39: =IF((AND($E$3="MCS",$E$4="TODOS CRs")), SUMIFS('2026'!$K:$K,'2026'!$R:$R,$E$3&$C39,'2026'!$T:$T,I$6), SUMIFS('2026'!$K:$K,'2026'!$N:$N,$E$3&$C39&$E$4,'2026'!$T:$T,I$6)) -> 0 | J39: =IF((AND($E$3="MCS",$E$4="TODOS CRs")), SUMIFS('2026'!$K:$K,'2026'!$R:$R,$E$3&$C39,'2026'!$T:$T,J$6), SUMIFS('2026'!$K:$K,'2026'!$N:$N,$E$3&$C39&$E$4,'2026'!$T:$T,J$6)) -> 0 | K39: =IF((AND($E$3="MCS",$E$4="TODOS CRs")), SUMIFS('2026'!$K:$K,'2026'!$R:$R,$E$3&$C39,'2026'!$T:$T,K$6), SUMIFS('2026'!$K:$K,'2026'!$N:$N,$E$3&$C39&$E$4,'2026'!$T:$T,K$6)) -> 0 | L39: =IF((AND($E$3="MCS",$E$4="TODOS CRs")), SUMIFS('2026'!$K:$K,'2026'!$R:$R,$E$3&$C39,'2026'!$T:$T,L$6), SUMIFS('2026'!$K:$K,'2026'!$N:$N,$E$3&$C39&$E$4,'2026'!$T:$T,L$6)) -> 0 | M39: =IF((AND($E$3="MCS",$E$4="TODOS CRs")), SUMIFS('2026'!$K:$K,'2026'!$R:$R,$E$3&$C39,'2026'!$T:$T,M$6), SUMIFS('2026'!$K:$K,'2026'!$N:$N,$E$3&$C39&$E$4,'2026'!$T:$T,M$6)) -> 0 | ... Q39: =IF((AND($E$3="MCS",$E$4="TODOS CRs")), SUMIFS('2026'!$K:$K,'2026'!$R:$R,$E$3&$C39,'2026'!$T:$T,Q$6), SUMIFS('2026'!$K:$K,'2026'!$N:$N,$E$3&$C39&$E$4,'2026'!$T:$T,Q$6)) -> 0
B40: - | C40: - | D40: (=) TOTAL SAÍDAS | E40: =SUBTOTAL(9,E17:E39) -> -33348.58 | F40: =SUBTOTAL(9,F17:F39) -> -5100.28 | G40: =SUBTOTAL(9,G17:G39) -> -5411.31 | H40: =SUBTOTAL(9,H17:H39) -> -4888.92 | I40: =SUBTOTAL(9,I17:I39) -> -7250.92 | J40: =SUBTOTAL(9,J17:J39) -> -5999.93 | K40: =SUBTOTAL(9,K17:K39) -> -4697.22 | L40: =SUBTOTAL(9,L17:L39) -> 0 | ... Q40: =SUBTOTAL(9,Q17:Q39) -> 0
D42: RESULTADO | E42: ACUM | F42: =F6 -> 46023 | G42: =G6 -> 46054 | H42: =H6 -> 46082 | I42: =I6 -> 46113 | J42: =J6 -> 46143 | K42: =K6 -> 46174 | L42: =L6 -> 46204 | M42: =M6 -> 46235 | ... Q42: =Q6 -> 46357
D43: SALDO ANTERIOR | E43: 0 | F43: 352.96 | G43: =IF(AND(G44=0,G45=0),0,F46) -> 152.68 | H43: =IF(AND(H44=0,H45=0),0,G46) -> 258.99 | I43: =IF(AND(I44=0,I45=0),0,H46) -> 466.07 | J43: =IF(AND(J44=0,J45=0),0,I46) -> 240.15 | K43: =IF(AND(K44=0,K45=0),0,J46) -> 900.21 | L43: =IF(AND(L44=0,L45=0),0,K46) -> 0 | M43: =IF(AND(M44=0,M45=0),0,L46) -> 0 | N43: =IF(AND(N44=0,N45=0),0,M46) -> 0 | ... Q43: =IF(AND(Q44=0,Q45=0),0,P46) -> 0
D44: (+) TOTAL DE ENTRADAS | E44: =SUM(F44:Q44) -> 33591.75 | F44: =F14 -> 4900 | G44: =G14 -> 5517.62 | H44: =H14 -> 5096 | I44: =I14 -> 7025 | J44: =J14 -> 6659.99 | K44: =K14 -> 4393.14 | L44: =L14 -> 0 | M44: =M14 -> 0 | ... Q44: =Q14 -> 0
D45: (-) TOTAL DE SAÍDAS | E45: =SUM(F45:Q45) -> -33348.58 | F45: =F40 -> -5100.28 | G45: =G40 -> -5411.31 | H45: =H40 -> -4888.92 | I45: =I40 -> -7250.92 | J45: =J40 -> -5999.93 | K45: =K40 -> -4697.22 | L45: =L40 -> 0 | M45: =M40 -> 0 | ... Q45: =Q40 -> 0
D46: (=) SALDO ATUAL | E46: =E44+E45 -> 243.17 | F46: =F43+F44+F45 -> 152.68 | G46: =G43+G44+G45 -> 258.99 | H46: =H43+H44+H45 -> 466.07 | I46: =I43+I44+I45 -> 240.15 | J46: =J43+J44+J45 -> 900.21 | K46: =K43+K44+K45 -> 596.13 | L46: =L43+L44+L45 -> 0 | M46: =M43+M44+M45 -> 0 | ... Q46: =Q43+Q44+Q45 -> 0
E48: CARGA % DA PENSÃO => | F48: =IFERROR(ABS(SUM(F31:F39))/F10,0) -> 0.42936939 | G48: =IFERROR(ABS(SUM(G31:G39))/G10,0) -> 0.38584545 | H48: =IFERROR(ABS(SUM(H31:H39))/H10,0) -> 0.46985913 | I48: =IFERROR(ABS(SUM(I31:I39))/I10,0) -> 0.32341571 | J48: =IFERROR(ABS(SUM(J31:J39))/J10,0) -> 0.25396667 | K48: =IFERROR(ABS(SUM(K31:K39))/K10,0) -> 0.319 | L48: =IFERROR(ABS(SUM(L31:L39))/L10,0) -> 0 | M48: =IFERROR(ABS(SUM(M31:M39))/M10,0) -> 0 | ... Q48: =IFERROR(ABS(SUM(Q31:Q39))/Q10,0) -> 0

Sheet CAIXA_PREVISTO
A2: MCS | B2: FLUXO DE CAIXA ANO - MCS
A3: MCS | D3: SELECIONE A ENTIDADE QUE PAGOU OU RECEBEU => | E3: MCS | T3: RESUMO FLUXO CAIXA
A4: MCS | D4: SELECIONE O CENTRO DE RESULTADO => | E4: TODOS CRs | T4: GRUPO | U4: TOTAL | V4: A.V. %
A5: Sinko | T5: REC | U5: =SUMIFS($E$6:$E$40,$B$6:$B$40,T5) -> 0 | V5: =IFERROR(ABS(U5/$U$5),0) -> 0
A6: TODAS | B6: Grupo | C6: Natureza | D6: ENTRADAS | E6: ACUM | F6: 46023 | G6: 46054 | H6: 46082 | I6: 46113 | J6: 46143 | K6: 46174 | L6: 46204 | M6: 46235 | N6: 46266 | O6: 46296 | P6: 46327 | Q6: 46357 | T6: PENS | U6: =SUMIFS($E$6:$E$40,$B$6:$B$40,T6) -> 0 | V6: =IFERROR(ABS(U6/$U$5),0) -> 0
B7: REC | C7: REC1 | D7: CPF - Remun. Salário / Pró-Labore | E7: =SUM(F7:Q7) -> 0 | F7: =IF((AND($E$3="MCS",$E$4="TODOS CRs")), SUMIFS('2026'!$K:$K,'2026'!$R:$R,$E$3&$C7,'2026'!$U:$U,F$6), SUMIFS('2026'!$K:$K,'2026'!$N:$N,$E$3&$C7&$E$4,'2026'!$U:$U,F$6)) -> 0 | G7: =IF((AND($E$3="MCS",$E$4="TODOS CRs")), SUMIFS('2026'!$K:$K,'2026'!$R:$R,$E$3&$C7,'2026'!$U:$U,G$6), SUMIFS('2026'!$K:$K,'2026'!$N:$N,$E$3&$C7&$E$4,'2026'!$U:$U,G$6)) -> 0 | H7: =IF((AND($E$3="MCS",$E$4="TODOS CRs")), SUMIFS('2026'!$K:$K,'2026'!$R:$R,$E$3&$C7,'2026'!$U:$U,H$6), SUMIFS('2026'!$K:$K,'2026'!$N:$N,$E$3&$C7&$E$4,'2026'!$U:$U,H$6)) -> 0 | I7: =IF((AND($E$3="MCS",$E$4="TODOS CRs")), SUMIFS('2026'!$K:$K,'2026'!$R:$R,$E$3&$C7,'2026'!$U:$U,I$6), SUMIFS('2026'!$K:$K,'2026'!$N:$N,$E$3&$C7&$E$4,'2026'!$U:$U,I$6)) -> 0 | J7: =IF((AND($E$3="MCS",$E$4="TODOS CRs")), SUMIFS('2026'!$K:$K,'2026'!$R:$R,$E$3&$C7,'2026'!$U:$U,J$6), SUMIFS('2026'!$K:$K,'2026'!$N:$N,$E$3&$C7&$E$4,'2026'!$U:$U,J$6)) -> 0 | K7: =IF((AND($E$3="MCS",$E$4="TODOS CRs")), SUMIFS('2026'!$K:$K,'2026'!$R:$R,$E$3&$C7,'2026'!$U:$U,K$6), SUMIFS('2026'!$K:$K,'2026'!$N:$N,$E$3&$C7&$E$4,'2026'!$U:$U,K$6)) -> 0 | L7: =IF((AND($E$3="MCS",$E$4="TODOS CRs")), SUMIFS('2026'!$K:$K,'2026'!$R:$R,$E$3&$C7,'2026'!$U:$U,L$6), SUMIFS('2026'!$K:$K,'2026'!$N:$N,$E$3&$C7&$E$4,'2026'!$U:$U,L$6)) -> 0 | M7: =IF((AND($E$3="MCS",$E$4="TODOS CRs")), SUMIFS('2026'!$K:$K,'2026'!$R:$R,$E$3&$C7,'2026'!$U:$U,M$6), SUMIFS('2026'!$K:$K,'2026'!$N:$N,$E$3&$C7&$E$4,'2026'!$U:$U,M$6)) -> 0 | ... Q7: =IF((AND($E$3="MCS",$E$4="TODOS CRs")), SUMIFS('2026'!$K:$K,'2026'!$R:$R,$E$3&$C7,'2026'!$U:$U,Q$6), SUMIFS('2026'!$K:$K,'2026'!$N:$N,$E$3&$C7&$E$4,'2026'!$U:$U,Q$6)) -> 0 | T7: DESP | U7: =SUMIFS($E$6:$E$40,$B$6:$B$40,T7) -> 0 | V7: =IFERROR(ABS(U7/$U$5),0) -> 0
B8: REC | C8: REC2 | D8: CPF - Ajuda de custo - Combustível | E8: =SUM(F8:Q8) -> 0 | F8: =IF((AND($E$3="MCS",$E$4="TODOS CRs")), SUMIFS('2026'!$K:$K,'2026'!$R:$R,$E$3&$C8,'2026'!$U:$U,F$6), SUMIFS('2026'!$K:$K,'2026'!$N:$N,$E$3&$C8&$E$4,'2026'!$U:$U,F$6)) -> 0 | G8: =IF((AND($E$3="MCS",$E$4="TODOS CRs")), SUMIFS('2026'!$K:$K,'2026'!$R:$R,$E$3&$C8,'2026'!$U:$U,G$6), SUMIFS('2026'!$K:$K,'2026'!$N:$N,$E$3&$C8&$E$4,'2026'!$U:$U,G$6)) -> 0 | H8: =IF((AND($E$3="MCS",$E$4="TODOS CRs")), SUMIFS('2026'!$K:$K,'2026'!$R:$R,$E$3&$C8,'2026'!$U:$U,H$6), SUMIFS('2026'!$K:$K,'2026'!$N:$N,$E$3&$C8&$E$4,'2026'!$U:$U,H$6)) -> 0 | I8: =IF((AND($E$3="MCS",$E$4="TODOS CRs")), SUMIFS('2026'!$K:$K,'2026'!$R:$R,$E$3&$C8,'2026'!$U:$U,I$6), SUMIFS('2026'!$K:$K,'2026'!$N:$N,$E$3&$C8&$E$4,'2026'!$U:$U,I$6)) -> 0 | J8: =IF((AND($E$3="MCS",$E$4="TODOS CRs")), SUMIFS('2026'!$K:$K,'2026'!$R:$R,$E$3&$C8,'2026'!$U:$U,J$6), SUMIFS('2026'!$K:$K,'2026'!$N:$N,$E$3&$C8&$E$4,'2026'!$U:$U,J$6)) -> 0 | K8: =IF((AND($E$3="MCS",$E$4="TODOS CRs")), SUMIFS('2026'!$K:$K,'2026'!$R:$R,$E$3&$C8,'2026'!$U:$U,K$6), SUMIFS('2026'!$K:$K,'2026'!$N:$N,$E$3&$C8&$E$4,'2026'!$U:$U,K$6)) -> 0 | L8: =IF((AND($E$3="MCS",$E$4="TODOS CRs")), SUMIFS('2026'!$K:$K,'2026'!$R:$R,$E$3&$C8,'2026'!$U:$U,L$6), SUMIFS('2026'!$K:$K,'2026'!$N:$N,$E$3&$C8&$E$4,'2026'!$U:$U,L$6)) -> 0 | M8: =IF((AND($E$3="MCS",$E$4="TODOS CRs")), SUMIFS('2026'!$K:$K,'2026'!$R:$R,$E$3&$C8,'2026'!$U:$U,M$6), SUMIFS('2026'!$K:$K,'2026'!$N:$N,$E$3&$C8&$E$4,'2026'!$U:$U,M$6)) -> 0 | ... Q8: =IF((AND($E$3="MCS",$E$4="TODOS CRs")), SUMIFS('2026'!$K:$K,'2026'!$R:$R,$E$3&$C8,'2026'!$U:$U,Q$6), SUMIFS('2026'!$K:$K,'2026'!$N:$N,$E$3&$C8&$E$4,'2026'!$U:$U,Q$6)) -> 0 | T8: OPF | U8: =SUMIFS($E$6:$E$40,$B$6:$B$40,T8) -> 0 | V8: =IFERROR(ABS(U8/$U$5),0) -> 0
B9: REC | C9: REC3 | D9: CPF - Ajuda de custo - Refeição | E9: =SUM(F9:Q9) -> 0 | F9: =IF((AND($E$3="MCS",$E$4="TODOS CRs")), SUMIFS('2026'!$K:$K,'2026'!$R:$R,$E$3&$C9,'2026'!$U:$U,F$6), SUMIFS('2026'!$K:$K,'2026'!$N:$N,$E$3&$C9&$E$4,'2026'!$U:$U,F$6)) -> 0 | G9: =IF((AND($E$3="MCS",$E$4="TODOS CRs")), SUMIFS('2026'!$K:$K,'2026'!$R:$R,$E$3&$C9,'2026'!$U:$U,G$6), SUMIFS('2026'!$K:$K,'2026'!$N:$N,$E$3&$C9&$E$4,'2026'!$U:$U,G$6)) -> 0 | H9: =IF((AND($E$3="MCS",$E$4="TODOS CRs")), SUMIFS('2026'!$K:$K,'2026'!$R:$R,$E$3&$C9,'2026'!$U:$U,H$6), SUMIFS('2026'!$K:$K,'2026'!$N:$N,$E$3&$C9&$E$4,'2026'!$U:$U,H$6)) -> 0 | I9: =IF((AND($E$3="MCS",$E$4="TODOS CRs")), SUMIFS('2026'!$K:$K,'2026'!$R:$R,$E$3&$C9,'2026'!$U:$U,I$6), SUMIFS('2026'!$K:$K,'2026'!$N:$N,$E$3&$C9&$E$4,'2026'!$U:$U,I$6)) -> 0 | J9: =IF((AND($E$3="MCS",$E$4="TODOS CRs")), SUMIFS('2026'!$K:$K,'2026'!$R:$R,$E$3&$C9,'2026'!$U:$U,J$6), SUMIFS('2026'!$K:$K,'2026'!$N:$N,$E$3&$C9&$E$4,'2026'!$U:$U,J$6)) -> 0 | K9: =IF((AND($E$3="MCS",$E$4="TODOS CRs")), SUMIFS('2026'!$K:$K,'2026'!$R:$R,$E$3&$C9,'2026'!$U:$U,K$6), SUMIFS('2026'!$K:$K,'2026'!$N:$N,$E$3&$C9&$E$4,'2026'!$U:$U,K$6)) -> 0 | L9: =IF((AND($E$3="MCS",$E$4="TODOS CRs")), SUMIFS('2026'!$K:$K,'2026'!$R:$R,$E$3&$C9,'2026'!$U:$U,L$6), SUMIFS('2026'!$K:$K,'2026'!$N:$N,$E$3&$C9&$E$4,'2026'!$U:$U,L$6)) -> 0 | M9: =IF((AND($E$3="MCS",$E$4="TODOS CRs")), SUMIFS('2026'!$K:$K,'2026'!$R:$R,$E$3&$C9,'2026'!$U:$U,M$6), SUMIFS('2026'!$K:$K,'2026'!$N:$N,$E$3&$C9&$E$4,'2026'!$U:$U,M$6)) -> 0 | ... Q9: =IF((AND($E$3="MCS",$E$4="TODOS CRs")), SUMIFS('2026'!$K:$K,'2026'!$R:$R,$E$3&$C9,'2026'!$U:$U,Q$6), SUMIFS('2026'!$K:$K,'2026'!$N:$N,$E$3&$C9&$E$4,'2026'!$U:$U,Q$6)) -> 0 | T9: FIN | U9: =SUMIFS($E$6:$E$40,$B$6:$B$40,T9) -> 0 | V9: =IFERROR(ABS(U9/$U$5),0) -> 0
B10: REC | C10: REC4 | D10: CPF - Transf. Da conta PJ para a conta PF | E10: =SUM(F10:Q10) -> 0 | F10: =IF((AND($E$3="MCS",$E$4="TODOS CRs")), SUMIFS('2026'!$K:$K,'2026'!$R:$R,$E$3&$C10,'2026'!$U:$U,F$6), SUMIFS('2026'!$K:$K,'2026'!$N:$N,$E$3&$C10&$E$4,'2026'!$U:$U,F$6)) -> 0 | G10: =IF((AND($E$3="MCS",$E$4="TODOS CRs")), SUMIFS('2026'!$K:$K,'2026'!$R:$R,$E$3&$C10,'2026'!$U:$U,G$6), SUMIFS('2026'!$K:$K,'2026'!$N:$N,$E$3&$C10&$E$4,'2026'!$U:$U,G$6)) -> 0 | H10: =IF((AND($E$3="MCS",$E$4="TODOS CRs")), SUMIFS('2026'!$K:$K,'2026'!$R:$R,$E$3&$C10,'2026'!$U:$U,H$6), SUMIFS('2026'!$K:$K,'2026'!$N:$N,$E$3&$C10&$E$4,'2026'!$U:$U,H$6)) -> 0 | I10: =IF((AND($E$3="MCS",$E$4="TODOS CRs")), SUMIFS('2026'!$K:$K,'2026'!$R:$R,$E$3&$C10,'2026'!$U:$U,I$6), SUMIFS('2026'!$K:$K,'2026'!$N:$N,$E$3&$C10&$E$4,'2026'!$U:$U,I$6)) -> 0 | J10: =IF((AND($E$3="MCS",$E$4="TODOS CRs")), SUMIFS('2026'!$K:$K,'2026'!$R:$R,$E$3&$C10,'2026'!$U:$U,J$6), SUMIFS('2026'!$K:$K,'2026'!$N:$N,$E$3&$C10&$E$4,'2026'!$U:$U,J$6)) -> 0 | K10: =IF((AND($E$3="MCS",$E$4="TODOS CRs")), SUMIFS('2026'!$K:$K,'2026'!$R:$R,$E$3&$C10,'2026'!$U:$U,K$6), SUMIFS('2026'!$K:$K,'2026'!$N:$N,$E$3&$C10&$E$4,'2026'!$U:$U,K$6)) -> 0 | L10: =IF((AND($E$3="MCS",$E$4="TODOS CRs")), SUMIFS('2026'!$K:$K,'2026'!$R:$R,$E$3&$C10,'2026'!$U:$U,L$6), SUMIFS('2026'!$K:$K,'2026'!$N:$N,$E$3&$C10&$E$4,'2026'!$U:$U,L$6)) -> 0 | M10: =IF((AND($E$3="MCS",$E$4="TODOS CRs")), SUMIFS('2026'!$K:$K,'2026'!$R:$R,$E$3&$C10,'2026'!$U:$U,M$6), SUMIFS('2026'!$K:$K,'2026'!$N:$N,$E$3&$C10&$E$4,'2026'!$U:$U,M$6)) -> 0 | ... Q10: =IF((AND($E$3="MCS",$E$4="TODOS CRs")), SUMIFS('2026'!$K:$K,'2026'!$R:$R,$E$3&$C10,'2026'!$U:$U,Q$6), SUMIFS('2026'!$K:$K,'2026'!$N:$N,$E$3&$C10&$E$4,'2026'!$U:$U,Q$6)) -> 0 | T10: GAST | U10: =SUMIFS($E$6:$E$40,$B$6:$B$40,T10) -> 0 | V10: =IFERROR(ABS(U10/$U$5),0) -> 0
B11: REC | C11: REC5 | D11: CPF - Outras receitas | E11: =SUM(F11:Q11) -> 0 | F11: =IF((AND($E$3="MCS",$E$4="TODOS CRs")), SUMIFS('2026'!$K:$K,'2026'!$R:$R,$E$3&$C11,'2026'!$U:$U,F$6), SUMIFS('2026'!$K:$K,'2026'!$N:$N,$E$3&$C11&$E$4,'2026'!$U:$U,F$6)) -> 0 | G11: =IF((AND($E$3="MCS",$E$4="TODOS CRs")), SUMIFS('2026'!$K:$K,'2026'!$R:$R,$E$3&$C11,'2026'!$U:$U,G$6), SUMIFS('2026'!$K:$K,'2026'!$N:$N,$E$3&$C11&$E$4,'2026'!$U:$U,G$6)) -> 0 | H11: =IF((AND($E$3="MCS",$E$4="TODOS CRs")), SUMIFS('2026'!$K:$K,'2026'!$R:$R,$E$3&$C11,'2026'!$U:$U,H$6), SUMIFS('2026'!$K:$K,'2026'!$N:$N,$E$3&$C11&$E$4,'2026'!$U:$U,H$6)) -> 0 | I11: =IF((AND($E$3="MCS",$E$4="TODOS CRs")), SUMIFS('2026'!$K:$K,'2026'!$R:$R,$E$3&$C11,'2026'!$U:$U,I$6), SUMIFS('2026'!$K:$K,'2026'!$N:$N,$E$3&$C11&$E$4,'2026'!$U:$U,I$6)) -> 0 | J11: =IF((AND($E$3="MCS",$E$4="TODOS CRs")), SUMIFS('2026'!$K:$K,'2026'!$R:$R,$E$3&$C11,'2026'!$U:$U,J$6), SUMIFS('2026'!$K:$K,'2026'!$N:$N,$E$3&$C11&$E$4,'2026'!$U:$U,J$6)) -> 0 | K11: =IF((AND($E$3="MCS",$E$4="TODOS CRs")), SUMIFS('2026'!$K:$K,'2026'!$R:$R,$E$3&$C11,'2026'!$U:$U,K$6), SUMIFS('2026'!$K:$K,'2026'!$N:$N,$E$3&$C11&$E$4,'2026'!$U:$U,K$6)) -> 0 | L11: =IF((AND($E$3="MCS",$E$4="TODOS CRs")), SUMIFS('2026'!$K:$K,'2026'!$R:$R,$E$3&$C11,'2026'!$U:$U,L$6), SUMIFS('2026'!$K:$K,'2026'!$N:$N,$E$3&$C11&$E$4,'2026'!$U:$U,L$6)) -> 0 | M11: =IF((AND($E$3="MCS",$E$4="TODOS CRs")), SUMIFS('2026'!$K:$K,'2026'!$R:$R,$E$3&$C11,'2026'!$U:$U,M$6), SUMIFS('2026'!$K:$K,'2026'!$N:$N,$E$3&$C11&$E$4,'2026'!$U:$U,M$6)) -> 0 | ... Q11: =IF((AND($E$3="MCS",$E$4="TODOS CRs")), SUMIFS('2026'!$K:$K,'2026'!$R:$R,$E$3&$C11,'2026'!$U:$U,Q$6), SUMIFS('2026'!$K:$K,'2026'!$N:$N,$E$3&$C11&$E$4,'2026'!$U:$U,Q$6)) -> 0 | T11: OUG | U11: =SUMIFS($E$6:$E$40,$B$6:$B$40,T11) -> 0 | V11: =IFERROR(ABS(U11/$U$5),0) -> 0
B12: REC | C12: REC6 | D12: CPF - Pensão - Outras receitas | E12: =SUM(F12:Q12) -> 0 | F12: =IF((AND($E$3="MCS",$E$4="TODOS CRs")), SUMIFS('2026'!$K:$K,'2026'!$R:$R,$E$3&$C12,'2026'!$U:$U,F$6), SUMIFS('2026'!$K:$K,'2026'!$N:$N,$E$3&$C12&$E$4,'2026'!$U:$U,F$6)) -> 0 | G12: =IF((AND($E$3="MCS",$E$4="TODOS CRs")), SUMIFS('2026'!$K:$K,'2026'!$R:$R,$E$3&$C12,'2026'!$U:$U,G$6), SUMIFS('2026'!$K:$K,'2026'!$N:$N,$E$3&$C12&$E$4,'2026'!$U:$U,G$6)) -> 0 | H12: =IF((AND($E$3="MCS",$E$4="TODOS CRs")), SUMIFS('2026'!$K:$K,'2026'!$R:$R,$E$3&$C12,'2026'!$U:$U,H$6), SUMIFS('2026'!$K:$K,'2026'!$N:$N,$E$3&$C12&$E$4,'2026'!$U:$U,H$6)) -> 0 | I12: =IF((AND($E$3="MCS",$E$4="TODOS CRs")), SUMIFS('2026'!$K:$K,'2026'!$R:$R,$E$3&$C12,'2026'!$U:$U,I$6), SUMIFS('2026'!$K:$K,'2026'!$N:$N,$E$3&$C12&$E$4,'2026'!$U:$U,I$6)) -> 0 | J12: =IF((AND($E$3="MCS",$E$4="TODOS CRs")), SUMIFS('2026'!$K:$K,'2026'!$R:$R,$E$3&$C12,'2026'!$U:$U,J$6), SUMIFS('2026'!$K:$K,'2026'!$N:$N,$E$3&$C12&$E$4,'2026'!$U:$U,J$6)) -> 0 | K12: =IF((AND($E$3="MCS",$E$4="TODOS CRs")), SUMIFS('2026'!$K:$K,'2026'!$R:$R,$E$3&$C12,'2026'!$U:$U,K$6), SUMIFS('2026'!$K:$K,'2026'!$N:$N,$E$3&$C12&$E$4,'2026'!$U:$U,K$6)) -> 0 | L12: =IF((AND($E$3="MCS",$E$4="TODOS CRs")), SUMIFS('2026'!$K:$K,'2026'!$R:$R,$E$3&$C12,'2026'!$U:$U,L$6), SUMIFS('2026'!$K:$K,'2026'!$N:$N,$E$3&$C12&$E$4,'2026'!$U:$U,L$6)) -> 0 | M12: =IF((AND($E$3="MCS",$E$4="TODOS CRs")), SUMIFS('2026'!$K:$K,'2026'!$R:$R,$E$3&$C12,'2026'!$U:$U,M$6), SUMIFS('2026'!$K:$K,'2026'!$N:$N,$E$3&$C12&$E$4,'2026'!$U:$U,M$6)) -> 0 | ... Q12: =IF((AND($E$3="MCS",$E$4="TODOS CRs")), SUMIFS('2026'!$K:$K,'2026'!$R:$R,$E$3&$C12,'2026'!$U:$U,Q$6), SUMIFS('2026'!$K:$K,'2026'!$N:$N,$E$3&$C12&$E$4,'2026'!$U:$U,Q$6)) -> 0 | T12: TRI | U12: =SUMIFS($E$6:$E$40,$B$6:$B$40,T12) -> 0 | V12: =IFERROR(ABS(U12/$U$5),0) -> 0
B13: REC | C13: REC7 | D13: CPF - Rec. Financeiras - Empréstimos | E13: =SUM(F13:Q13) -> 0 | F13: =IF((AND($E$3="MCS",$E$4="TODOS CRs")), SUMIFS('2026'!$K:$K,'2026'!$R:$R,$E$3&$C13,'2026'!$U:$U,F$6), SUMIFS('2026'!$K:$K,'2026'!$N:$N,$E$3&$C13&$E$4,'2026'!$U:$U,F$6)) -> 0 | G13: =IF((AND($E$3="MCS",$E$4="TODOS CRs")), SUMIFS('2026'!$K:$K,'2026'!$R:$R,$E$3&$C13,'2026'!$U:$U,G$6), SUMIFS('2026'!$K:$K,'2026'!$N:$N,$E$3&$C13&$E$4,'2026'!$U:$U,G$6)) -> 0 | H13: =IF((AND($E$3="MCS",$E$4="TODOS CRs")), SUMIFS('2026'!$K:$K,'2026'!$R:$R,$E$3&$C13,'2026'!$U:$U,H$6), SUMIFS('2026'!$K:$K,'2026'!$N:$N,$E$3&$C13&$E$4,'2026'!$U:$U,H$6)) -> 0 | I13: =IF((AND($E$3="MCS",$E$4="TODOS CRs")), SUMIFS('2026'!$K:$K,'2026'!$R:$R,$E$3&$C13,'2026'!$U:$U,I$6), SUMIFS('2026'!$K:$K,'2026'!$N:$N,$E$3&$C13&$E$4,'2026'!$U:$U,I$6)) -> 0 | J13: =IF((AND($E$3="MCS",$E$4="TODOS CRs")), SUMIFS('2026'!$K:$K,'2026'!$R:$R,$E$3&$C13,'2026'!$U:$U,J$6), SUMIFS('2026'!$K:$K,'2026'!$N:$N,$E$3&$C13&$E$4,'2026'!$U:$U,J$6)) -> 0 | K13: =IF((AND($E$3="MCS",$E$4="TODOS CRs")), SUMIFS('2026'!$K:$K,'2026'!$R:$R,$E$3&$C13,'2026'!$U:$U,K$6), SUMIFS('2026'!$K:$K,'2026'!$N:$N,$E$3&$C13&$E$4,'2026'!$U:$U,K$6)) -> 0 | L13: =IF((AND($E$3="MCS",$E$4="TODOS CRs")), SUMIFS('2026'!$K:$K,'2026'!$R:$R,$E$3&$C13,'2026'!$U:$U,L$6), SUMIFS('2026'!$K:$K,'2026'!$N:$N,$E$3&$C13&$E$4,'2026'!$U:$U,L$6)) -> 0 | M13: =IF((AND($E$3="MCS",$E$4="TODOS CRs")), SUMIFS('2026'!$K:$K,'2026'!$R:$R,$E$3&$C13,'2026'!$U:$U,M$6), SUMIFS('2026'!$K:$K,'2026'!$N:$N,$E$3&$C13&$E$4,'2026'!$U:$U,M$6)) -> 0 | ... Q13: =IF((AND($E$3="MCS",$E$4="TODOS CRs")), SUMIFS('2026'!$K:$K,'2026'!$R:$R,$E$3&$C13,'2026'!$U:$U,Q$6), SUMIFS('2026'!$K:$K,'2026'!$N:$N,$E$3&$C13&$E$4,'2026'!$U:$U,Q$6)) -> 0 | T13: TOTAL | U13: =SUMIFS($E$6:$E$40,$B$6:$B$40,T13) -> 0 | V13: =IFERROR(ABS(U13/$U$5),0) -> 0
D14: (=) TOTAL ENTRADAS | E14: =SUBTOTAL(9,E7:E13) -> 0 | F14: =SUBTOTAL(9,F7:F13) -> 0 | G14: =SUBTOTAL(9,G7:G13) -> 0 | H14: =SUBTOTAL(9,H7:H13) -> 0 | I14: =SUBTOTAL(9,I7:I13) -> 0 | J14: =SUBTOTAL(9,J7:J13) -> 0 | K14: =SUBTOTAL(9,K7:K13) -> 0 | L14: =SUBTOTAL(9,L7:L13) -> 0 | ... Q14: =SUBTOTAL(9,Q7:Q13) -> 0 | T14: SUPERÁVIT | U14: =U5+U13 -> 0 | V14: =ABS(U14/$U$5) -> #DIV/0!
B16: Grupo | C16: Natureza | D16: SAÍDAS | E16: ACUM | F16: =F6 -> 46023 | G16: =G6 -> 46054 | H16: =H6 -> 46082 | I16: =I6 -> 46113 | J16: =J6 -> 46143 | K16: =K6 -> 46174 | L16: =L6 -> 46204 | M16: =M6 -> 46235 | ... Q16: =Q6 -> 46357
B17: OPF | C17: OPF1 | D17: CPF - Desp. Alimentação / Refeição | E17: =SUM(F17:Q17) -> 0 | F17: =IF((AND($E$3="MCS",$E$4="TODOS CRs")), SUMIFS('2026'!$K:$K,'2026'!$R:$R,$E$3&$C17,'2026'!$U:$U,F$6), SUMIFS('2026'!$K:$K,'2026'!$N:$N,$E$3&$C17&$E$4,'2026'!$U:$U,F$6)) -> 0 | G17: =IF((AND($E$3="MCS",$E$4="TODOS CRs")), SUMIFS('2026'!$K:$K,'2026'!$R:$R,$E$3&$C17,'2026'!$U:$U,G$6), SUMIFS('2026'!$K:$K,'2026'!$N:$N,$E$3&$C17&$E$4,'2026'!$U:$U,G$6)) -> 0 | H17: =IF((AND($E$3="MCS",$E$4="TODOS CRs")), SUMIFS('2026'!$K:$K,'2026'!$R:$R,$E$3&$C17,'2026'!$U:$U,H$6), SUMIFS('2026'!$K:$K,'2026'!$N:$N,$E$3&$C17&$E$4,'2026'!$U:$U,H$6)) -> 0 | I17: =IF((AND($E$3="MCS",$E$4="TODOS CRs")), SUMIFS('2026'!$K:$K,'2026'!$R:$R,$E$3&$C17,'2026'!$U:$U,I$6), SUMIFS('2026'!$K:$K,'2026'!$N:$N,$E$3&$C17&$E$4,'2026'!$U:$U,I$6)) -> 0 | J17: =IF((AND($E$3="MCS",$E$4="TODOS CRs")), SUMIFS('2026'!$K:$K,'2026'!$R:$R,$E$3&$C17,'2026'!$U:$U,J$6), SUMIFS('2026'!$K:$K,'2026'!$N:$N,$E$3&$C17&$E$4,'2026'!$U:$U,J$6)) -> 0 | K17: =IF((AND($E$3="MCS",$E$4="TODOS CRs")), SUMIFS('2026'!$K:$K,'2026'!$R:$R,$E$3&$C17,'2026'!$U:$U,K$6), SUMIFS('2026'!$K:$K,'2026'!$N:$N,$E$3&$C17&$E$4,'2026'!$U:$U,K$6)) -> 0 | L17: =IF((AND($E$3="MCS",$E$4="TODOS CRs")), SUMIFS('2026'!$K:$K,'2026'!$R:$R,$E$3&$C17,'2026'!$U:$U,L$6), SUMIFS('2026'!$K:$K,'2026'!$N:$N,$E$3&$C17&$E$4,'2026'!$U:$U,L$6)) -> 0 | M17: =IF((AND($E$3="MCS",$E$4="TODOS CRs")), SUMIFS('2026'!$K:$K,'2026'!$R:$R,$E$3&$C17,'2026'!$U:$U,M$6), SUMIFS('2026'!$K:$K,'2026'!$N:$N,$E$3&$C17&$E$4,'2026'!$U:$U,M$6)) -> 0 | ... Q17: =IF((AND($E$3="MCS",$E$4="TODOS CRs")), SUMIFS('2026'!$K:$K,'2026'!$R:$R,$E$3&$C17,'2026'!$U:$U,Q$6), SUMIFS('2026'!$K:$K,'2026'!$N:$N,$E$3&$C17&$E$4,'2026'!$U:$U,Q$6)) -> 0
B18: OPF | C18: OPF2 | D18: CPF - Desp. Transporte / Combustível | E18: =SUM(F18:Q18) -> 0 | F18: =IF((AND($E$3="MCS",$E$4="TODOS CRs")), SUMIFS('2026'!$K:$K,'2026'!$R:$R,$E$3&$C18,'2026'!$U:$U,F$6), SUMIFS('2026'!$K:$K,'2026'!$N:$N,$E$3&$C18&$E$4,'2026'!$U:$U,F$6)) -> 0 | G18: =IF((AND($E$3="MCS",$E$4="TODOS CRs")), SUMIFS('2026'!$K:$K,'2026'!$R:$R,$E$3&$C18,'2026'!$U:$U,G$6), SUMIFS('2026'!$K:$K,'2026'!$N:$N,$E$3&$C18&$E$4,'2026'!$U:$U,G$6)) -> 0 | H18: =IF((AND($E$3="MCS",$E$4="TODOS CRs")), SUMIFS('2026'!$K:$K,'2026'!$R:$R,$E$3&$C18,'2026'!$U:$U,H$6), SUMIFS('2026'!$K:$K,'2026'!$N:$N,$E$3&$C18&$E$4,'2026'!$U:$U,H$6)) -> 0 | I18: =IF((AND($E$3="MCS",$E$4="TODOS CRs")), SUMIFS('2026'!$K:$K,'2026'!$R:$R,$E$3&$C18,'2026'!$U:$U,I$6), SUMIFS('2026'!$K:$K,'2026'!$N:$N,$E$3&$C18&$E$4,'2026'!$U:$U,I$6)) -> 0 | J18: =IF((AND($E$3="MCS",$E$4="TODOS CRs")), SUMIFS('2026'!$K:$K,'2026'!$R:$R,$E$3&$C18,'2026'!$U:$U,J$6), SUMIFS('2026'!$K:$K,'2026'!$N:$N,$E$3&$C18&$E$4,'2026'!$U:$U,J$6)) -> 0 | K18: =IF((AND($E$3="MCS",$E$4="TODOS CRs")), SUMIFS('2026'!$K:$K,'2026'!$R:$R,$E$3&$C18,'2026'!$U:$U,K$6), SUMIFS('2026'!$K:$K,'2026'!$N:$N,$E$3&$C18&$E$4,'2026'!$U:$U,K$6)) -> 0 | L18: =IF((AND($E$3="MCS",$E$4="TODOS CRs")), SUMIFS('2026'!$K:$K,'2026'!$R:$R,$E$3&$C18,'2026'!$U:$U,L$6), SUMIFS('2026'!$K:$K,'2026'!$N:$N,$E$3&$C18&$E$4,'2026'!$U:$U,L$6)) -> 0 | M18: =IF((AND($E$3="MCS",$E$4="TODOS CRs")), SUMIFS('2026'!$K:$K,'2026'!$R:$R,$E$3&$C18,'2026'!$U:$U,M$6), SUMIFS('2026'!$K:$K,'2026'!$N:$N,$E$3&$C18&$E$4,'2026'!$U:$U,M$6)) -> 0 | ... Q18: =IF((AND($E$3="MCS",$E$4="TODOS CRs")), SUMIFS('2026'!$K:$K,'2026'!$R:$R,$E$3&$C18,'2026'!$U:$U,Q$6), SUMIFS('2026'!$K:$K,'2026'!$N:$N,$E$3&$C18&$E$4,'2026'!$U:$U,Q$6)) -> 0
B19: DESP | C19: DESP1 | D19: CPF - Desp. Cartão de crédito | E19: =SUM(F19:Q19) -> 0 | F19: =IF((AND($E$3="MCS",$E$4="TODOS CRs")), SUMIFS('2026'!$K:$K,'2026'!$R:$R,$E$3&$C19,'2026'!$U:$U,F$6), SUMIFS('2026'!$K:$K,'2026'!$N:$N,$E$3&$C19&$E$4,'2026'!$U:$U,F$6)) -> 0 | G19: =IF((AND($E$3="MCS",$E$4="TODOS CRs")), SUMIFS('2026'!$K:$K,'2026'!$R:$R,$E$3&$C19,'2026'!$U:$U,G$6), SUMIFS('2026'!$K:$K,'2026'!$N:$N,$E$3&$C19&$E$4,'2026'!$U:$U,G$6)) -> 0 | H19: =IF((AND($E$3="MCS",$E$4="TODOS CRs")), SUMIFS('2026'!$K:$K,'2026'!$R:$R,$E$3&$C19,'2026'!$U:$U,H$6), SUMIFS('2026'!$K:$K,'2026'!$N:$N,$E$3&$C19&$E$4,'2026'!$U:$U,H$6)) -> 0 | I19: =IF((AND($E$3="MCS",$E$4="TODOS CRs")), SUMIFS('2026'!$K:$K,'2026'!$R:$R,$E$3&$C19,'2026'!$U:$U,I$6), SUMIFS('2026'!$K:$K,'2026'!$N:$N,$E$3&$C19&$E$4,'2026'!$U:$U,I$6)) -> 0 | J19: =IF((AND($E$3="MCS",$E$4="TODOS CRs")), SUMIFS('2026'!$K:$K,'2026'!$R:$R,$E$3&$C19,'2026'!$U:$U,J$6), SUMIFS('2026'!$K:$K,'2026'!$N:$N,$E$3&$C19&$E$4,'2026'!$U:$U,J$6)) -> 0 | K19: =IF((AND($E$3="MCS",$E$4="TODOS CRs")), SUMIFS('2026'!$K:$K,'2026'!$R:$R,$E$3&$C19,'2026'!$U:$U,K$6), SUMIFS('2026'!$K:$K,'2026'!$N:$N,$E$3&$C19&$E$4,'2026'!$U:$U,K$6)) -> 0 | L19: =IF((AND($E$3="MCS",$E$4="TODOS CRs")), SUMIFS('2026'!$K:$K,'2026'!$R:$R,$E$3&$C19,'2026'!$U:$U,L$6), SUMIFS('2026'!$K:$K,'2026'!$N:$N,$E$3&$C19&$E$4,'2026'!$U:$U,L$6)) -> 0 | M19: =IF((AND($E$3="MCS",$E$4="TODOS CRs")), SUMIFS('2026'!$K:$K,'2026'!$R:$R,$E$3&$C19,'2026'!$U:$U,M$6), SUMIFS('2026'!$K:$K,'2026'!$N:$N,$E$3&$C19&$E$4,'2026'!$U:$U,M$6)) -> 0 | ... Q19: =IF((AND($E$3="MCS",$E$4="TODOS CRs")), SUMIFS('2026'!$K:$K,'2026'!$R:$R,$E$3&$C19,'2026'!$U:$U,Q$6), SUMIFS('2026'!$K:$K,'2026'!$N:$N,$E$3&$C19&$E$4,'2026'!$U:$U,Q$6)) -> 0
B20: DESP | C20: DESP2 | D20: CPF - Desp. Telefone / Internet | E20: =SUM(F20:Q20) -> 0 | F20: =IF((AND($E$3="MCS",$E$4="TODOS CRs")), SUMIFS('2026'!$K:$K,'2026'!$R:$R,$E$3&$C20,'2026'!$U:$U,F$6), SUMIFS('2026'!$K:$K,'2026'!$N:$N,$E$3&$C20&$E$4,'2026'!$U:$U,F$6)) -> 0 | G20: =IF((AND($E$3="MCS",$E$4="TODOS CRs")), SUMIFS('2026'!$K:$K,'2026'!$R:$R,$E$3&$C20,'2026'!$U:$U,G$6), SUMIFS('2026'!$K:$K,'2026'!$N:$N,$E$3&$C20&$E$4,'2026'!$U:$U,G$6)) -> 0 | H20: =IF((AND($E$3="MCS",$E$4="TODOS CRs")), SUMIFS('2026'!$K:$K,'2026'!$R:$R,$E$3&$C20,'2026'!$U:$U,H$6), SUMIFS('2026'!$K:$K,'2026'!$N:$N,$E$3&$C20&$E$4,'2026'!$U:$U,H$6)) -> 0 | I20: =IF((AND($E$3="MCS",$E$4="TODOS CRs")), SUMIFS('2026'!$K:$K,'2026'!$R:$R,$E$3&$C20,'2026'!$U:$U,I$6), SUMIFS('2026'!$K:$K,'2026'!$N:$N,$E$3&$C20&$E$4,'2026'!$U:$U,I$6)) -> 0 | J20: =IF((AND($E$3="MCS",$E$4="TODOS CRs")), SUMIFS('2026'!$K:$K,'2026'!$R:$R,$E$3&$C20,'2026'!$U:$U,J$6), SUMIFS('2026'!$K:$K,'2026'!$N:$N,$E$3&$C20&$E$4,'2026'!$U:$U,J$6)) -> 0 | K20: =IF((AND($E$3="MCS",$E$4="TODOS CRs")), SUMIFS('2026'!$K:$K,'2026'!$R:$R,$E$3&$C20,'2026'!$U:$U,K$6), SUMIFS('2026'!$K:$K,'2026'!$N:$N,$E$3&$C20&$E$4,'2026'!$U:$U,K$6)) -> 0 | L20: =IF((AND($E$3="MCS",$E$4="TODOS CRs")), SUMIFS('2026'!$K:$K,'2026'!$R:$R,$E$3&$C20,'2026'!$U:$U,L$6), SUMIFS('2026'!$K:$K,'2026'!$N:$N,$E$3&$C20&$E$4,'2026'!$U:$U,L$6)) -> 0 | M20: =IF((AND($E$3="MCS",$E$4="TODOS CRs")), SUMIFS('2026'!$K:$K,'2026'!$R:$R,$E$3&$C20,'2026'!$U:$U,M$6), SUMIFS('2026'!$K:$K,'2026'!$N:$N,$E$3&$C20&$E$4,'2026'!$U:$U,M$6)) -> 0 | ... Q20: =IF((AND($E$3="MCS",$E$4="TODOS CRs")), SUMIFS('2026'!$K:$K,'2026'!$R:$R,$E$3&$C20,'2026'!$U:$U,Q$6), SUMIFS('2026'!$K:$K,'2026'!$N:$N,$E$3&$C20&$E$4,'2026'!$U:$U,Q$6)) -> 0
B21: DESP | C21: DESP3 | D21: CPF - Desp. com veículo - Manut. / Gastos | E21: =SUM(F21:Q21) -> 0 | F21: =IF((AND($E$3="MCS",$E$4="TODOS CRs")), SUMIFS('2026'!$K:$K,'2026'!$R:$R,$E$3&$C21,'2026'!$U:$U,F$6), SUMIFS('2026'!$K:$K,'2026'!$N:$N,$E$3&$C21&$E$4,'2026'!$U:$U,F$6)) -> 0 | G21: =IF((AND($E$3="MCS",$E$4="TODOS CRs")), SUMIFS('2026'!$K:$K,'2026'!$R:$R,$E$3&$C21,'2026'!$U:$U,G$6), SUMIFS('2026'!$K:$K,'2026'!$N:$N,$E$3&$C21&$E$4,'2026'!$U:$U,G$6)) -> 0 | H21: =IF((AND($E$3="MCS",$E$4="TODOS CRs")), SUMIFS('2026'!$K:$K,'2026'!$R:$R,$E$3&$C21,'2026'!$U:$U,H$6), SUMIFS('2026'!$K:$K,'2026'!$N:$N,$E$3&$C21&$E$4,'2026'!$U:$U,H$6)) -> 0 | I21: =IF((AND($E$3="MCS",$E$4="TODOS CRs")), SUMIFS('2026'!$K:$K,'2026'!$R:$R,$E$3&$C21,'2026'!$U:$U,I$6), SUMIFS('2026'!$K:$K,'2026'!$N:$N,$E$3&$C21&$E$4,'2026'!$U:$U,I$6)) -> 0 | J21: =IF((AND($E$3="MCS",$E$4="TODOS CRs")), SUMIFS('2026'!$K:$K,'2026'!$R:$R,$E$3&$C21,'2026'!$U:$U,J$6), SUMIFS('2026'!$K:$K,'2026'!$N:$N,$E$3&$C21&$E$4,'2026'!$U:$U,J$6)) -> 0 | K21: =IF((AND($E$3="MCS",$E$4="TODOS CRs")), SUMIFS('2026'!$K:$K,'2026'!$R:$R,$E$3&$C21,'2026'!$U:$U,K$6), SUMIFS('2026'!$K:$K,'2026'!$N:$N,$E$3&$C21&$E$4,'2026'!$U:$U,K$6)) -> 0 | L21: =IF((AND($E$3="MCS",$E$4="TODOS CRs")), SUMIFS('2026'!$K:$K,'2026'!$R:$R,$E$3&$C21,'2026'!$U:$U,L$6), SUMIFS('2026'!$K:$K,'2026'!$N:$N,$E$3&$C21&$E$4,'2026'!$U:$U,L$6)) -> 0 | M21: =IF((AND($E$3="MCS",$E$4="TODOS CRs")), SUMIFS('2026'!$K:$K,'2026'!$R:$R,$E$3&$C21,'2026'!$U:$U,M$6), SUMIFS('2026'!$K:$K,'2026'!$N:$N,$E$3&$C21&$E$4,'2026'!$U:$U,M$6)) -> 0 | ... Q21: =IF((AND($E$3="MCS",$E$4="TODOS CRs")), SUMIFS('2026'!$K:$K,'2026'!$R:$R,$E$3&$C21,'2026'!$U:$U,Q$6), SUMIFS('2026'!$K:$K,'2026'!$N:$N,$E$3&$C21&$E$4,'2026'!$U:$U,Q$6)) -> 0
B22: DESP | C22: DESP4 | D22: CPF - Desp. Moradia | E22: =SUM(F22:Q22) -> 0 | F22: =IF((AND($E$3="MCS",$E$4="TODOS CRs")), SUMIFS('2026'!$K:$K,'2026'!$R:$R,$E$3&$C22,'2026'!$U:$U,F$6), SUMIFS('2026'!$K:$K,'2026'!$N:$N,$E$3&$C22&$E$4,'2026'!$U:$U,F$6)) -> 0 | G22: =IF((AND($E$3="MCS",$E$4="TODOS CRs")), SUMIFS('2026'!$K:$K,'2026'!$R:$R,$E$3&$C22,'2026'!$U:$U,G$6), SUMIFS('2026'!$K:$K,'2026'!$N:$N,$E$3&$C22&$E$4,'2026'!$U:$U,G$6)) -> 0 | H22: =IF((AND($E$3="MCS",$E$4="TODOS CRs")), SUMIFS('2026'!$K:$K,'2026'!$R:$R,$E$3&$C22,'2026'!$U:$U,H$6), SUMIFS('2026'!$K:$K,'2026'!$N:$N,$E$3&$C22&$E$4,'2026'!$U:$U,H$6)) -> 0 | I22: =IF((AND($E$3="MCS",$E$4="TODOS CRs")), SUMIFS('2026'!$K:$K,'2026'!$R:$R,$E$3&$C22,'2026'!$U:$U,I$6), SUMIFS('2026'!$K:$K,'2026'!$N:$N,$E$3&$C22&$E$4,'2026'!$U:$U,I$6)) -> 0 | J22: =IF((AND($E$3="MCS",$E$4="TODOS CRs")), SUMIFS('2026'!$K:$K,'2026'!$R:$R,$E$3&$C22,'2026'!$U:$U,J$6), SUMIFS('2026'!$K:$K,'2026'!$N:$N,$E$3&$C22&$E$4,'2026'!$U:$U,J$6)) -> 0 | K22: =IF((AND($E$3="MCS",$E$4="TODOS CRs")), SUMIFS('2026'!$K:$K,'2026'!$R:$R,$E$3&$C22,'2026'!$U:$U,K$6), SUMIFS('2026'!$K:$K,'2026'!$N:$N,$E$3&$C22&$E$4,'2026'!$U:$U,K$6)) -> 0 | L22: =IF((AND($E$3="MCS",$E$4="TODOS CRs")), SUMIFS('2026'!$K:$K,'2026'!$R:$R,$E$3&$C22,'2026'!$U:$U,L$6), SUMIFS('2026'!$K:$K,'2026'!$N:$N,$E$3&$C22&$E$4,'2026'!$U:$U,L$6)) -> 0 | M22: =IF((AND($E$3="MCS",$E$4="TODOS CRs")), SUMIFS('2026'!$K:$K,'2026'!$R:$R,$E$3&$C22,'2026'!$U:$U,M$6), SUMIFS('2026'!$K:$K,'2026'!$N:$N,$E$3&$C22&$E$4,'2026'!$U:$U,M$6)) -> 0 | ... Q22: =IF((AND($E$3="MCS",$E$4="TODOS CRs")), SUMIFS('2026'!$K:$K,'2026'!$R:$R,$E$3&$C22,'2026'!$U:$U,Q$6), SUMIFS('2026'!$K:$K,'2026'!$N:$N,$E$3&$C22&$E$4,'2026'!$U:$U,Q$6)) -> 0
B23: DESP | C23: DESP5 | D23: CPF - Transf. Da conta PF para a conta PJ | E23: =SUM(F23:Q23) -> 0 | F23: =IF((AND($E$3="MCS",$E$4="TODOS CRs")), SUMIFS('2026'!$K:$K,'2026'!$R:$R,$E$3&$C23,'2026'!$U:$U,F$6), SUMIFS('2026'!$K:$K,'2026'!$N:$N,$E$3&$C23&$E$4,'2026'!$U:$U,F$6)) -> 0 | G23: =IF((AND($E$3="MCS",$E$4="TODOS CRs")), SUMIFS('2026'!$K:$K,'2026'!$R:$R,$E$3&$C23,'2026'!$U:$U,G$6), SUMIFS('2026'!$K:$K,'2026'!$N:$N,$E$3&$C23&$E$4,'2026'!$U:$U,G$6)) -> 0 | H23: =IF((AND($E$3="MCS",$E$4="TODOS CRs")), SUMIFS('2026'!$K:$K,'2026'!$R:$R,$E$3&$C23,'2026'!$U:$U,H$6), SUMIFS('2026'!$K:$K,'2026'!$N:$N,$E$3&$C23&$E$4,'2026'!$U:$U,H$6)) -> 0 | I23: =IF((AND($E$3="MCS",$E$4="TODOS CRs")), SUMIFS('2026'!$K:$K,'2026'!$R:$R,$E$3&$C23,'2026'!$U:$U,I$6), SUMIFS('2026'!$K:$K,'2026'!$N:$N,$E$3&$C23&$E$4,'2026'!$U:$U,I$6)) -> 0 | J23: =IF((AND($E$3="MCS",$E$4="TODOS CRs")), SUMIFS('2026'!$K:$K,'2026'!$R:$R,$E$3&$C23,'2026'!$U:$U,J$6), SUMIFS('2026'!$K:$K,'2026'!$N:$N,$E$3&$C23&$E$4,'2026'!$U:$U,J$6)) -> 0 | K23: =IF((AND($E$3="MCS",$E$4="TODOS CRs")), SUMIFS('2026'!$K:$K,'2026'!$R:$R,$E$3&$C23,'2026'!$U:$U,K$6), SUMIFS('2026'!$K:$K,'2026'!$N:$N,$E$3&$C23&$E$4,'2026'!$U:$U,K$6)) -> 0 | L23: =IF((AND($E$3="MCS",$E$4="TODOS CRs")), SUMIFS('2026'!$K:$K,'2026'!$R:$R,$E$3&$C23,'2026'!$U:$U,L$6), SUMIFS('2026'!$K:$K,'2026'!$N:$N,$E$3&$C23&$E$4,'2026'!$U:$U,L$6)) -> 0 | M23: =IF((AND($E$3="MCS",$E$4="TODOS CRs")), SUMIFS('2026'!$K:$K,'2026'!$R:$R,$E$3&$C23,'2026'!$U:$U,M$6), SUMIFS('2026'!$K:$K,'2026'!$N:$N,$E$3&$C23&$E$4,'2026'!$U:$U,M$6)) -> 0 | ... Q23: =IF((AND($E$3="MCS",$E$4="TODOS CRs")), SUMIFS('2026'!$K:$K,'2026'!$R:$R,$E$3&$C23,'2026'!$U:$U,Q$6), SUMIFS('2026'!$K:$K,'2026'!$N:$N,$E$3&$C23&$E$4,'2026'!$U:$U,Q$6)) -> 0
B24: GAST | C24: GAST1 | D24: CPF - Desp. Lazer e Entretenimento - Bares | E24: =SUM(F24:Q24) -> 0 | F24: =IF((AND($E$3="MCS",$E$4="TODOS CRs")), SUMIFS('2026'!$K:$K,'2026'!$R:$R,$E$3&$C24,'2026'!$U:$U,F$6), SUMIFS('2026'!$K:$K,'2026'!$N:$N,$E$3&$C24&$E$4,'2026'!$U:$U,F$6)) -> 0 | G24: =IF((AND($E$3="MCS",$E$4="TODOS CRs")), SUMIFS('2026'!$K:$K,'2026'!$R:$R,$E$3&$C24,'2026'!$U:$U,G$6), SUMIFS('2026'!$K:$K,'2026'!$N:$N,$E$3&$C24&$E$4,'2026'!$U:$U,G$6)) -> 0 | H24: =IF((AND($E$3="MCS",$E$4="TODOS CRs")), SUMIFS('2026'!$K:$K,'2026'!$R:$R,$E$3&$C24,'2026'!$U:$U,H$6), SUMIFS('2026'!$K:$K,'2026'!$N:$N,$E$3&$C24&$E$4,'2026'!$U:$U,H$6)) -> 0 | I24: =IF((AND($E$3="MCS",$E$4="TODOS CRs")), SUMIFS('2026'!$K:$K,'2026'!$R:$R,$E$3&$C24,'2026'!$U:$U,I$6), SUMIFS('2026'!$K:$K,'2026'!$N:$N,$E$3&$C24&$E$4,'2026'!$U:$U,I$6)) -> 0 | J24: =IF((AND($E$3="MCS",$E$4="TODOS CRs")), SUMIFS('2026'!$K:$K,'2026'!$R:$R,$E$3&$C24,'2026'!$U:$U,J$6), SUMIFS('2026'!$K:$K,'2026'!$N:$N,$E$3&$C24&$E$4,'2026'!$U:$U,J$6)) -> 0 | K24: =IF((AND($E$3="MCS",$E$4="TODOS CRs")), SUMIFS('2026'!$K:$K,'2026'!$R:$R,$E$3&$C24,'2026'!$U:$U,K$6), SUMIFS('2026'!$K:$K,'2026'!$N:$N,$E$3&$C24&$E$4,'2026'!$U:$U,K$6)) -> 0 | L24: =IF((AND($E$3="MCS",$E$4="TODOS CRs")), SUMIFS('2026'!$K:$K,'2026'!$R:$R,$E$3&$C24,'2026'!$U:$U,L$6), SUMIFS('2026'!$K:$K,'2026'!$N:$N,$E$3&$C24&$E$4,'2026'!$U:$U,L$6)) -> 0 | M24: =IF((AND($E$3="MCS",$E$4="TODOS CRs")), SUMIFS('2026'!$K:$K,'2026'!$R:$R,$E$3&$C24,'2026'!$U:$U,M$6), SUMIFS('2026'!$K:$K,'2026'!$N:$N,$E$3&$C24&$E$4,'2026'!$U:$U,M$6)) -> 0 | ... Q24: =IF((AND($E$3="MCS",$E$4="TODOS CRs")), SUMIFS('2026'!$K:$K,'2026'!$R:$R,$E$3&$C24,'2026'!$U:$U,Q$6), SUMIFS('2026'!$K:$K,'2026'!$N:$N,$E$3&$C24&$E$4,'2026'!$U:$U,Q$6)) -> 0
B25: GAST | C25: GAST2 | D25: CPF - Desp. Lazer e Entretenimento - Cigarro | E25: =SUM(F25:Q25) -> 0 | F25: =IF((AND($E$3="MCS",$E$4="TODOS CRs")), SUMIFS('2026'!$K:$K,'2026'!$R:$R,$E$3&$C25,'2026'!$U:$U,F$6), SUMIFS('2026'!$K:$K,'2026'!$N:$N,$E$3&$C25&$E$4,'2026'!$U:$U,F$6)) -> 0 | G25: =IF((AND($E$3="MCS",$E$4="TODOS CRs")), SUMIFS('2026'!$K:$K,'2026'!$R:$R,$E$3&$C25,'2026'!$U:$U,G$6), SUMIFS('2026'!$K:$K,'2026'!$N:$N,$E$3&$C25&$E$4,'2026'!$U:$U,G$6)) -> 0 | H25: =IF((AND($E$3="MCS",$E$4="TODOS CRs")), SUMIFS('2026'!$K:$K,'2026'!$R:$R,$E$3&$C25,'2026'!$U:$U,H$6), SUMIFS('2026'!$K:$K,'2026'!$N:$N,$E$3&$C25&$E$4,'2026'!$U:$U,H$6)) -> 0 | I25: =IF((AND($E$3="MCS",$E$4="TODOS CRs")), SUMIFS('2026'!$K:$K,'2026'!$R:$R,$E$3&$C25,'2026'!$U:$U,I$6), SUMIFS('2026'!$K:$K,'2026'!$N:$N,$E$3&$C25&$E$4,'2026'!$U:$U,I$6)) -> 0 | J25: =IF((AND($E$3="MCS",$E$4="TODOS CRs")), SUMIFS('2026'!$K:$K,'2026'!$R:$R,$E$3&$C25,'2026'!$U:$U,J$6), SUMIFS('2026'!$K:$K,'2026'!$N:$N,$E$3&$C25&$E$4,'2026'!$U:$U,J$6)) -> 0 | K25: =IF((AND($E$3="MCS",$E$4="TODOS CRs")), SUMIFS('2026'!$K:$K,'2026'!$R:$R,$E$3&$C25,'2026'!$U:$U,K$6), SUMIFS('2026'!$K:$K,'2026'!$N:$N,$E$3&$C25&$E$4,'2026'!$U:$U,K$6)) -> 0 | L25: =IF((AND($E$3="MCS",$E$4="TODOS CRs")), SUMIFS('2026'!$K:$K,'2026'!$R:$R,$E$3&$C25,'2026'!$U:$U,L$6), SUMIFS('2026'!$K:$K,'2026'!$N:$N,$E$3&$C25&$E$4,'2026'!$U:$U,L$6)) -> 0 | M25: =IF((AND($E$3="MCS",$E$4="TODOS CRs")), SUMIFS('2026'!$K:$K,'2026'!$R:$R,$E$3&$C25,'2026'!$U:$U,M$6), SUMIFS('2026'!$K:$K,'2026'!$N:$N,$E$3&$C25&$E$4,'2026'!$U:$U,M$6)) -> 0 | ... Q25: =IF((AND($E$3="MCS",$E$4="TODOS CRs")), SUMIFS('2026'!$K:$K,'2026'!$R:$R,$E$3&$C25,'2026'!$U:$U,Q$6), SUMIFS('2026'!$K:$K,'2026'!$N:$N,$E$3&$C25&$E$4,'2026'!$U:$U,Q$6)) -> 0
B26: FIN | C26: FIN1 | D26: CPF - Desp. Financeiras - Empréstimos | E26: =SUM(F26:Q26) -> 0 | F26: =IF((AND($E$3="MCS",$E$4="TODOS CRs")), SUMIFS('2026'!$K:$K,'2026'!$R:$R,$E$3&$C26,'2026'!$U:$U,F$6), SUMIFS('2026'!$K:$K,'2026'!$N:$N,$E$3&$C26&$E$4,'2026'!$U:$U,F$6)) -> 0 | G26: =IF((AND($E$3="MCS",$E$4="TODOS CRs")), SUMIFS('2026'!$K:$K,'2026'!$R:$R,$E$3&$C26,'2026'!$U:$U,G$6), SUMIFS('2026'!$K:$K,'2026'!$N:$N,$E$3&$C26&$E$4,'2026'!$U:$U,G$6)) -> 0 | H26: =IF((AND($E$3="MCS",$E$4="TODOS CRs")), SUMIFS('2026'!$K:$K,'2026'!$R:$R,$E$3&$C26,'2026'!$U:$U,H$6), SUMIFS('2026'!$K:$K,'2026'!$N:$N,$E$3&$C26&$E$4,'2026'!$U:$U,H$6)) -> 0 | I26: =IF((AND($E$3="MCS",$E$4="TODOS CRs")), SUMIFS('2026'!$K:$K,'2026'!$R:$R,$E$3&$C26,'2026'!$U:$U,I$6), SUMIFS('2026'!$K:$K,'2026'!$N:$N,$E$3&$C26&$E$4,'2026'!$U:$U,I$6)) -> 0 | J26: =IF((AND($E$3="MCS",$E$4="TODOS CRs")), SUMIFS('2026'!$K:$K,'2026'!$R:$R,$E$3&$C26,'2026'!$U:$U,J$6), SUMIFS('2026'!$K:$K,'2026'!$N:$N,$E$3&$C26&$E$4,'2026'!$U:$U,J$6)) -> 0 | K26: =IF((AND($E$3="MCS",$E$4="TODOS CRs")), SUMIFS('2026'!$K:$K,'2026'!$R:$R,$E$3&$C26,'2026'!$U:$U,K$6), SUMIFS('2026'!$K:$K,'2026'!$N:$N,$E$3&$C26&$E$4,'2026'!$U:$U,K$6)) -> 0 | L26: =IF((AND($E$3="MCS",$E$4="TODOS CRs")), SUMIFS('2026'!$K:$K,'2026'!$R:$R,$E$3&$C26,'2026'!$U:$U,L$6), SUMIFS('2026'!$K:$K,'2026'!$N:$N,$E$3&$C26&$E$4,'2026'!$U:$U,L$6)) -> 0 | M26: =IF((AND($E$3="MCS",$E$4="TODOS CRs")), SUMIFS('2026'!$K:$K,'2026'!$R:$R,$E$3&$C26,'2026'!$U:$U,M$6), SUMIFS('2026'!$K:$K,'2026'!$N:$N,$E$3&$C26&$E$4,'2026'!$U:$U,M$6)) -> 0 | ... Q26: =IF((AND($E$3="MCS",$E$4="TODOS CRs")), SUMIFS('2026'!$K:$K,'2026'!$R:$R,$E$3&$C26,'2026'!$U:$U,Q$6), SUMIFS('2026'!$K:$K,'2026'!$N:$N,$E$3&$C26&$E$4,'2026'!$U:$U,Q$6)) -> 0
B27: FIN | C27: FIN2 | D27: CPF - Desp. Financeiras - Juros / Tarifas | E27: =SUM(F27:Q27) -> 0 | F27: =IF((AND($E$3="MCS",$E$4="TODOS CRs")), SUMIFS('2026'!$K:$K,'2026'!$R:$R,$E$3&$C27,'2026'!$U:$U,F$6), SUMIFS('2026'!$K:$K,'2026'!$N:$N,$E$3&$C27&$E$4,'2026'!$U:$U,F$6)) -> 0 | G27: =IF((AND($E$3="MCS",$E$4="TODOS CRs")), SUMIFS('2026'!$K:$K,'2026'!$R:$R,$E$3&$C27,'2026'!$U:$U,G$6), SUMIFS('2026'!$K:$K,'2026'!$N:$N,$E$3&$C27&$E$4,'2026'!$U:$U,G$6)) -> 0 | H27: =IF((AND($E$3="MCS",$E$4="TODOS CRs")), SUMIFS('2026'!$K:$K,'2026'!$R:$R,$E$3&$C27,'2026'!$U:$U,H$6), SUMIFS('2026'!$K:$K,'2026'!$N:$N,$E$3&$C27&$E$4,'2026'!$U:$U,H$6)) -> 0 | I27: =IF((AND($E$3="MCS",$E$4="TODOS CRs")), SUMIFS('2026'!$K:$K,'2026'!$R:$R,$E$3&$C27,'2026'!$U:$U,I$6), SUMIFS('2026'!$K:$K,'2026'!$N:$N,$E$3&$C27&$E$4,'2026'!$U:$U,I$6)) -> 0 | J27: =IF((AND($E$3="MCS",$E$4="TODOS CRs")), SUMIFS('2026'!$K:$K,'2026'!$R:$R,$E$3&$C27,'2026'!$U:$U,J$6), SUMIFS('2026'!$K:$K,'2026'!$N:$N,$E$3&$C27&$E$4,'2026'!$U:$U,J$6)) -> 0 | K27: =IF((AND($E$3="MCS",$E$4="TODOS CRs")), SUMIFS('2026'!$K:$K,'2026'!$R:$R,$E$3&$C27,'2026'!$U:$U,K$6), SUMIFS('2026'!$K:$K,'2026'!$N:$N,$E$3&$C27&$E$4,'2026'!$U:$U,K$6)) -> 0 | L27: =IF((AND($E$3="MCS",$E$4="TODOS CRs")), SUMIFS('2026'!$K:$K,'2026'!$R:$R,$E$3&$C27,'2026'!$U:$U,L$6), SUMIFS('2026'!$K:$K,'2026'!$N:$N,$E$3&$C27&$E$4,'2026'!$U:$U,L$6)) -> 0 | M27: =IF((AND($E$3="MCS",$E$4="TODOS CRs")), SUMIFS('2026'!$K:$K,'2026'!$R:$R,$E$3&$C27,'2026'!$U:$U,M$6), SUMIFS('2026'!$K:$K,'2026'!$N:$N,$E$3&$C27&$E$4,'2026'!$U:$U,M$6)) -> 0 | ... Q27: =IF((AND($E$3="MCS",$E$4="TODOS CRs")), SUMIFS('2026'!$K:$K,'2026'!$R:$R,$E$3&$C27,'2026'!$U:$U,Q$6), SUMIFS('2026'!$K:$K,'2026'!$N:$N,$E$3&$C27&$E$4,'2026'!$U:$U,Q$6)) -> 0
B28: FIN | C28: FIN3 | D28: CPF - Desp. Financeiras - Juros / Tarifas | E28: =SUM(F28:Q28) -> 0 | F28: =IF((AND($E$3="MCS",$E$4="TODOS CRs")), SUMIFS('2026'!$K:$K,'2026'!$R:$R,$E$3&$C28,'2026'!$U:$U,F$6), SUMIFS('2026'!$K:$K,'2026'!$N:$N,$E$3&$C28&$E$4,'2026'!$U:$U,F$6)) -> 0 | G28: =IF((AND($E$3="MCS",$E$4="TODOS CRs")), SUMIFS('2026'!$K:$K,'2026'!$R:$R,$E$3&$C28,'2026'!$U:$U,G$6), SUMIFS('2026'!$K:$K,'2026'!$N:$N,$E$3&$C28&$E$4,'2026'!$U:$U,G$6)) -> 0 | H28: =IF((AND($E$3="MCS",$E$4="TODOS CRs")), SUMIFS('2026'!$K:$K,'2026'!$R:$R,$E$3&$C28,'2026'!$U:$U,H$6), SUMIFS('2026'!$K:$K,'2026'!$N:$N,$E$3&$C28&$E$4,'2026'!$U:$U,H$6)) -> 0 | I28: =IF((AND($E$3="MCS",$E$4="TODOS CRs")), SUMIFS('2026'!$K:$K,'2026'!$R:$R,$E$3&$C28,'2026'!$U:$U,I$6), SUMIFS('2026'!$K:$K,'2026'!$N:$N,$E$3&$C28&$E$4,'2026'!$U:$U,I$6)) -> 0 | J28: =IF((AND($E$3="MCS",$E$4="TODOS CRs")), SUMIFS('2026'!$K:$K,'2026'!$R:$R,$E$3&$C28,'2026'!$U:$U,J$6), SUMIFS('2026'!$K:$K,'2026'!$N:$N,$E$3&$C28&$E$4,'2026'!$U:$U,J$6)) -> 0 | K28: =IF((AND($E$3="MCS",$E$4="TODOS CRs")), SUMIFS('2026'!$K:$K,'2026'!$R:$R,$E$3&$C28,'2026'!$U:$U,K$6), SUMIFS('2026'!$K:$K,'2026'!$N:$N,$E$3&$C28&$E$4,'2026'!$U:$U,K$6)) -> 0 | L28: =IF((AND($E$3="MCS",$E$4="TODOS CRs")), SUMIFS('2026'!$K:$K,'2026'!$R:$R,$E$3&$C28,'2026'!$U:$U,L$6), SUMIFS('2026'!$K:$K,'2026'!$N:$N,$E$3&$C28&$E$4,'2026'!$U:$U,L$6)) -> 0 | M28: =IF((AND($E$3="MCS",$E$4="TODOS CRs")), SUMIFS('2026'!$K:$K,'2026'!$R:$R,$E$3&$C28,'2026'!$U:$U,M$6), SUMIFS('2026'!$K:$K,'2026'!$N:$N,$E$3&$C28&$E$4,'2026'!$U:$U,M$6)) -> 0 | ... Q28: =IF((AND($E$3="MCS",$E$4="TODOS CRs")), SUMIFS('2026'!$K:$K,'2026'!$R:$R,$E$3&$C28,'2026'!$U:$U,Q$6), SUMIFS('2026'!$K:$K,'2026'!$N:$N,$E$3&$C28&$E$4,'2026'!$U:$U,Q$6)) -> 0
... B39: PENS | C39: PENS9 | D39: CPF - Pensão - Outros Gastos | E39: =SUM(F39:Q39) -> 0 | F39: =IF((AND($E$3="MCS",$E$4="TODOS CRs")), SUMIFS('2026'!$K:$K,'2026'!$R:$R,$E$3&$C39,'2026'!$U:$U,F$6), SUMIFS('2026'!$K:$K,'2026'!$N:$N,$E$3&$C39&$E$4,'2026'!$U:$U,F$6)) -> 0 | G39: =IF((AND($E$3="MCS",$E$4="TODOS CRs")), SUMIFS('2026'!$K:$K,'2026'!$R:$R,$E$3&$C39,'2026'!$U:$U,G$6), SUMIFS('2026'!$K:$K,'2026'!$N:$N,$E$3&$C39&$E$4,'2026'!$U:$U,G$6)) -> 0 | H39: =IF((AND($E$3="MCS",$E$4="TODOS CRs")), SUMIFS('2026'!$K:$K,'2026'!$R:$R,$E$3&$C39,'2026'!$U:$U,H$6), SUMIFS('2026'!$K:$K,'2026'!$N:$N,$E$3&$C39&$E$4,'2026'!$U:$U,H$6)) -> 0 | I39: =IF((AND($E$3="MCS",$E$4="TODOS CRs")), SUMIFS('2026'!$K:$K,'2026'!$R:$R,$E$3&$C39,'2026'!$U:$U,I$6), SUMIFS('2026'!$K:$K,'2026'!$N:$N,$E$3&$C39&$E$4,'2026'!$U:$U,I$6)) -> 0 | J39: =IF((AND($E$3="MCS",$E$4="TODOS CRs")), SUMIFS('2026'!$K:$K,'2026'!$R:$R,$E$3&$C39,'2026'!$U:$U,J$6), SUMIFS('2026'!$K:$K,'2026'!$N:$N,$E$3&$C39&$E$4,'2026'!$U:$U,J$6)) -> 0 | K39: =IF((AND($E$3="MCS",$E$4="TODOS CRs")), SUMIFS('2026'!$K:$K,'2026'!$R:$R,$E$3&$C39,'2026'!$U:$U,K$6), SUMIFS('2026'!$K:$K,'2026'!$N:$N,$E$3&$C39&$E$4,'2026'!$U:$U,K$6)) -> 0 | L39: =IF((AND($E$3="MCS",$E$4="TODOS CRs")), SUMIFS('2026'!$K:$K,'2026'!$R:$R,$E$3&$C39,'2026'!$U:$U,L$6), SUMIFS('2026'!$K:$K,'2026'!$N:$N,$E$3&$C39&$E$4,'2026'!$U:$U,L$6)) -> 0 | M39: =IF((AND($E$3="MCS",$E$4="TODOS CRs")), SUMIFS('2026'!$K:$K,'2026'!$R:$R,$E$3&$C39,'2026'!$U:$U,M$6), SUMIFS('2026'!$K:$K,'2026'!$N:$N,$E$3&$C39&$E$4,'2026'!$U:$U,M$6)) -> 0 | ... Q39: =IF((AND($E$3="MCS",$E$4="TODOS CRs")), SUMIFS('2026'!$K:$K,'2026'!$R:$R,$E$3&$C39,'2026'!$U:$U,Q$6), SUMIFS('2026'!$K:$K,'2026'!$N:$N,$E$3&$C39&$E$4,'2026'!$U:$U,Q$6)) -> 0
B40: - | C40: - | D40: (=) TOTAL SAÍDAS | E40: =SUBTOTAL(9,E17:E39) -> 0 | F40: =SUBTOTAL(9,F17:F39) -> 0 | G40: =SUBTOTAL(9,G17:G39) -> 0 | H40: =SUBTOTAL(9,H17:H39) -> 0 | I40: =SUBTOTAL(9,I17:I39) -> 0 | J40: =SUBTOTAL(9,J17:J39) -> 0 | K40: =SUBTOTAL(9,K17:K39) -> 0 | L40: =SUBTOTAL(9,L17:L39) -> 0 | ... Q40: =SUBTOTAL(9,Q17:Q39) -> 0
D42: RESULTADO | E42: ACUM | F42: =F6 -> 46023 | G42: =G6 -> 46054 | H42: =H6 -> 46082 | I42: =I6 -> 46113 | J42: =J6 -> 46143 | K42: =K6 -> 46174 | L42: =L6 -> 46204 | M42: =M6 -> 46235 | ... Q42: =Q6 -> 46357
D43: SALDO ANTERIOR | E43: 0 | F43: =CAIXA_REAL!F46 -> 152.68 | G43: =IF(AND(G44=0,G45=0),0,#REF!) -> 0 | H43: =IF(AND(H44=0,H45=0),0,G46) -> 0 | I43: =IF(AND(I44=0,I45=0),0,H46) -> 0 | J43: =IF(AND(J44=0,J45=0),0,I46) -> 0 | K43: =IF(AND(K44=0,K45=0),0,J46) -> 0 | L43: =IF(AND(L44=0,L45=0),0,K46) -> 0 | M43: =IF(AND(M44=0,M45=0),0,L46) -> 0 | N43: =IF(AND(N44=0,N45=0),0,M46) -> 0 | O43: =IF(AND(O44=0,O45=0),0,N46) -> 0 | ... Q43: =IF(AND(Q44=0,Q45=0),0,P46) -> 0
D44: (+) TOTAL DE ENTRADAS | E44: =SUM(F44:Q44) -> 0 | F44: =F14 -> 0 | G44: =G14 -> 0 | H44: =H14 -> 0 | I44: =I14 -> 0 | J44: =J14 -> 0 | K44: =K14 -> 0 | L44: =L14 -> 0 | M44: =M14 -> 0 | ... Q44: =Q14 -> 0
D45: (-) TOTAL DE SAÍDAS | E45: =SUM(F45:Q45) -> 0 | F45: =F40 -> 0 | G45: =G40 -> 0 | H45: =H40 -> 0 | I45: =I40 -> 0 | J45: =J40 -> 0 | K45: =K40 -> 0 | L45: =L40 -> 0 | M45: =M40 -> 0 | ... Q45: =Q40 -> 0
D46: (=) SALDO ATUAL | E46: =E44+E45 -> 0 | F46: =F43+F44+F45 -> 152.68 | G46: =G43+G44+G45 -> 0 | H46: =H43+H44+H45 -> 0 | I46: =I43+I44+I45 -> 0 | J46: =J43+J44+J45 -> 0 | K46: =K43+K44+K45 -> 0 | L46: =L43+L44+L45 -> 0 | M46: =M43+M44+M45 -> 0 | ... Q46: =Q43+Q44+Q45 -> 0
E48: CARGA % DA PENSÃO => | F48: =IFERROR(ABS(SUM(F31:F39))/F10,0) -> 0 | G48: =IFERROR(ABS(SUM(G31:G39))/G10,0) -> 0 | H48: =IFERROR(ABS(SUM(H31:H39))/H10,0) -> 0 | I48: =IFERROR(ABS(SUM(I31:I39))/I10,0) -> 0 | J48: =IFERROR(ABS(SUM(J31:J39))/J10,0) -> 0 | K48: =IFERROR(ABS(SUM(K31:K39))/K10,0) -> 0 | L48: =IFERROR(ABS(SUM(L31:L39))/L10,0) -> 0 | M48: =IFERROR(ABS(SUM(M31:M39))/M10,0) -> 0 | ... Q48: =IFERROR(ABS(SUM(Q31:Q39))/Q10,0) -> 0

Sheet PARETO
J2: 45962
B3: ANO DE 2025 | H3: MÊS DE NOV/2025
C4: TOTAL | D4: =SUBTOTAL(9,D6:D27) -> #REF! | E4: =D4/$D$4 -> #REF! | F4: - | I4: TOTAL | J4: =SUBTOTAL(9,J6:J27) -> #REF! | K4: =J4/$D$4 -> #REF! | L4: -
B5: NATUREZA | C5: Centro de Resultado | D5: TOTAL | E5: % | F5: % PARETO | H5: NATUREZA | I5: Centro de Resultado | J5: TOTAL | K5: % | L5: % PARETO
B6: PENS1 | C6: =VLOOKUP(B6,CAIXA_REAL!C:D,2,0) -> CPF - Pensão - Aluguel | D6: =SUMIFS(CAIXA_REAL!#REF!,CAIXA_REAL!C:C,B6) -> #REF! | E6: =D6/$D$4 -> #REF! | F6: =E6 -> #REF! | H6: PENS2 | I6: =VLOOKUP(H6,CAIXA_REAL!C:D,2,0) -> CPF - Pensão - Energia | J6: =SUMIFS(CAIXA_REAL!#REF!,CAIXA_REAL!C:C,H6) -> #REF! | K6: =J6/$J$4 -> #REF! | L6: =K6 -> #REF!
B7: PENS3 | C7: =VLOOKUP(B7,CAIXA_REAL!C:D,2,0) -> CPF - Pensão - Plano de saúde | D7: =SUMIFS(CAIXA_REAL!#REF!,CAIXA_REAL!C:C,B7) -> #REF! | E7: =D7/$D$4 -> #REF! | F7: =F6+E7 -> #REF! | H7: PENS3 | I7: =VLOOKUP(H7,CAIXA_REAL!C:D,2,0) -> CPF - Pensão - Plano de saúde | J7: =SUMIFS(CAIXA_REAL!#REF!,CAIXA_REAL!C:C,H7) -> #REF! | K7: =J7/$J$4 -> #REF! | L7: =L6+K7 -> #REF!
B8: GAST1 | C8: =VLOOKUP(B8,CAIXA_REAL!C:D,2,0) -> CPF - Desp. Lazer e Entretenimento - Bares | D8: =SUMIFS(CAIXA_REAL!#REF!,CAIXA_REAL!C:C,B8) -> #REF! | E8: =D8/$D$4 -> #REF! | F8: =F7+E8 -> #REF! | H8: PENS1 | I8: =VLOOKUP(H8,CAIXA_REAL!C:D,2,0) -> CPF - Pensão - Aluguel | J8: =SUMIFS(CAIXA_REAL!#REF!,CAIXA_REAL!C:C,H8) -> #REF! | K8: =J8/$J$4 -> #REF! | L8: =L7+K8 -> #REF!
B9: PENS2 | C9: =VLOOKUP(B9,CAIXA_REAL!C:D,2,0) -> CPF - Pensão - Energia | D9: =SUMIFS(CAIXA_REAL!#REF!,CAIXA_REAL!C:C,B9) -> #REF! | E9: =D9/$D$4 -> #REF! | F9: =F8+E9 -> #REF! | H9: DESP5 | I9: =VLOOKUP(H9,CAIXA_REAL!C:D,2,0) -> CPF - Transf. Da conta PF para a conta PJ | J9: =SUMIFS(CAIXA_REAL!#REF!,CAIXA_REAL!C:C,H9) -> #REF! | K9: =J9/$J$4 -> #REF! | L9: =L8+K9 -> #REF!
B10: OPF1 | C10: =VLOOKUP(B10,CAIXA_REAL!C:D,2,0) -> CPF - Desp. Alimentação / Refeição | D10: =SUMIFS(CAIXA_REAL!#REF!,CAIXA_REAL!C:C,B10) -> #REF! | E10: =D10/$D$4 -> #REF! | F10: =F9+E10 -> #REF! | H10: OPF1 | I10: =VLOOKUP(H10,CAIXA_REAL!C:D,2,0) -> CPF - Desp. Alimentação / Refeição | J10: =SUMIFS(CAIXA_REAL!#REF!,CAIXA_REAL!C:C,H10) -> #REF! | K10: =J10/$J$4 -> #REF! | L10: =L9+K10 -> #REF!
B11: OPF2 | C11: =VLOOKUP(B11,CAIXA_REAL!C:D,2,0) -> CPF - Desp. Transporte / Combustível | D11: =SUMIFS(CAIXA_REAL!#REF!,CAIXA_REAL!C:C,B11) -> #REF! | E11: =D11/$D$4 -> #REF! | F11: =F10+E11 -> #REF! | H11: OPF2 | I11: =VLOOKUP(H11,CAIXA_REAL!C:D,2,0) -> CPF - Desp. Transporte / Combustível | J11: =SUMIFS(CAIXA_REAL!#REF!,CAIXA_REAL!C:C,H11) -> #REF! | K11: =J11/$J$4 -> #REF! | L11: =L10+K11 -> #REF!
B12: DESP1 | C12: =VLOOKUP(B12,CAIXA_REAL!C:D,2,0) -> CPF - Desp. Cartão de crédito | D12: =SUMIFS(CAIXA_REAL!#REF!,CAIXA_REAL!C:C,B12) -> #REF! | E12: =D12/$D$4 -> #REF! | F12: =F11+E12 -> #REF! | H12: GAST1 | I12: =VLOOKUP(H12,CAIXA_REAL!C:D,2,0) -> CPF - Desp. Lazer e Entretenimento - Bares | J12: =SUMIFS(CAIXA_REAL!#REF!,CAIXA_REAL!C:C,H12) -> #REF! | K12: =J12/$J$4 -> #REF! | L12: =L11+K12 -> #REF!
B13: DESP5 | C13: =VLOOKUP(B13,CAIXA_REAL!C:D,2,0) -> CPF - Transf. Da conta PF para a conta PJ | D13: =SUMIFS(CAIXA_REAL!#REF!,CAIXA_REAL!C:C,B13) -> #REF! | E13: =D13/$D$4 -> #REF! | F13: =F12+E13 -> #REF! | H13: GAST2 | I13: =VLOOKUP(H13,CAIXA_REAL!C:D,2,0) -> CPF - Desp. Lazer e Entretenimento - Cigarro | J13: =SUMIFS(CAIXA_REAL!#REF!,CAIXA_REAL!C:C,H13) -> #REF! | K13: =J13/$J$4 -> #REF! | L13: =L12+K13 -> #REF!
B14: PENS4 | C14: =VLOOKUP(B14,CAIXA_REAL!C:D,2,0) -> CPF - Pensão - Supermercado | D14: =SUMIFS(CAIXA_REAL!#REF!,CAIXA_REAL!C:C,B14) -> #REF! | E14: =D14/$D$4 -> #REF! | F14: =F13+E14 -> #REF! | H14: FIN2 | I14: =VLOOKUP(H14,CAIXA_REAL!C:D,2,0) -> CPF - Desp. Financeiras - Juros / Tarifas | J14: =SUMIFS(CAIXA_REAL!#REF!,CAIXA_REAL!C:C,H14) -> #REF! | K14: =J14/$J$4 -> #REF! | L14: =L13+K14 -> #REF!
B15: DESP2 | C15: =VLOOKUP(B15,CAIXA_REAL!C:D,2,0) -> CPF - Desp. Telefone / Internet | D15: =SUMIFS(CAIXA_REAL!#REF!,CAIXA_REAL!C:C,B15) -> #REF! | E15: =D15/$D$4 -> #REF! | F15: =F14+E15 -> #REF! | H15: OUG1 | I15: =VLOOKUP(H15,CAIXA_REAL!C:D,2,0) -> CPF - Outros gastos | J15: =SUMIFS(CAIXA_REAL!#REF!,CAIXA_REAL!C:C,H15) -> #REF! | K15: =J15/$J$4 -> #REF! | L15: =L14+K15 -> #REF!
B16: FIN1 | C16: =VLOOKUP(B16,CAIXA_REAL!C:D,2,0) -> CPF - Desp. Financeiras - Empréstimos | D16: =SUMIFS(CAIXA_REAL!#REF!,CAIXA_REAL!C:C,B16) -> #REF! | E16: =D16/$D$4 -> #REF! | F16: =F15+E16 -> #REF! | H16: FIN1 | I16: =VLOOKUP(H16,CAIXA_REAL!C:D,2,0) -> CPF - Desp. Financeiras - Empréstimos | J16: =SUMIFS(CAIXA_REAL!#REF!,CAIXA_REAL!C:C,H16) -> #REF! | K16: =J16/$J$4 -> #REF! | L16: =L15+K16 -> #REF!
B17: PENS5 | C17: =VLOOKUP(B17,CAIXA_REAL!C:D,2,0) -> CPF - Pensão - Água | D17: =SUMIFS(CAIXA_REAL!#REF!,CAIXA_REAL!C:C,B17) -> #REF! | E17: =D17/$D$4 -> #REF! | F17: =F16+E17 -> #REF! | H17: DESP1 | I17: =VLOOKUP(H17,CAIXA_REAL!C:D,2,0) -> CPF - Desp. Cartão de crédito | J17: =SUMIFS(CAIXA_REAL!#REF!,CAIXA_REAL!C:C,H17) -> #REF! | K17: =J17/$J$4 -> #REF! | L17: =L16+K17 -> #REF!
B18: GAST2 | C18: =VLOOKUP(B18,CAIXA_REAL!C:D,2,0) -> CPF - Desp. Lazer e Entretenimento - Cigarro | D18: =SUMIFS(CAIXA_REAL!#REF!,CAIXA_REAL!C:C,B18) -> #REF! | E18: =D18/$D$4 -> #REF! | F18: =F17+E18 -> #REF! | H18: DESP3 | I18: =VLOOKUP(H18,CAIXA_REAL!C:D,2,0) -> CPF - Desp. com veículo - Manut. / Gastos | J18: =SUMIFS(CAIXA_REAL!#REF!,CAIXA_REAL!C:C,H18) -> #REF! | K18: =J18/$J$4 -> #REF! | L18: =L17+K18 -> #REF!
... B27: PENS8 | C27: =VLOOKUP(B27,CAIXA_REAL!C:D,2,0) -> CPF - Pensão - Alimentação | D27: =SUMIFS(CAIXA_REAL!#REF!,CAIXA_REAL!C:C,B27) -> #REF! | E27: =D27/$D$4 -> #REF! | F27: =F26+E27 -> #REF! | H27: PENS8 | I27: =VLOOKUP(H27,CAIXA_REAL!C:D,2,0) -> CPF - Pensão - Alimentação | J27: =SUMIFS(CAIXA_REAL!#REF!,CAIXA_REAL!C:C,H27) -> #REF! | K27: =J27/$J$4 -> #REF! | L27: =L26+K27 -> #REF!

Sheet Resumo - Ação
B2: Despesa - Pensão | C2: Valor | D2: Qde pessoas | E2: Dependentes | F2: Vlr / pessoa
B3: Aluguel | C3: 700 | D3: 3 | E3: 2 | F3: =C3/D3*E3 -> 466.66667
B4: Energia | C4: 1000 | D4: 3 | E4: 2 | F4: =C4/D4*E4 -> 666.66667
B5: Plano de saúde | C5: 500 | D5: 3 | E5: 2 | F5: =C5/D5*E5 -> 333.33333 | N5: Negociação | O5: Valor
B6: Água | C6: 200 | D6: 3 | E6: 2 | F6: =C6/D6*E6 -> 133.33333 | N6: Parcela 1 | O6: 250
B7: Farmácia e Saúde | C7: 150 | D7: 3 | E7: 2 | F7: =C7/D7*E7 -> 100 | N7: Parcela 2 | O7: 250
B8: Supermercado | C8: 200 | D8: 3 | E8: 2 | F8: =C8/D8*E8 -> 133.33333 | N8: Parcela 3 | O8: 250
B9: Renegociação cheque especial (50%) | C9: =297.5/2 -> 148.75 | D9: 3 | E9: 2 | F9: =C9/D9*E9 -> 99.166667 | N9: Parcela 4 | O9: 250
B10: Total das despesas com pensão | C10: =SUM(C3:C9) -> 2898.75 | F10: =SUM(F3:F9) -> 1932.5 | H10: 1621 | I10: 0.8 | J10: =H10*I10 -> 1296.8 | N10: Parcela 5 | O10: 250
N11: Parcela 6 | O11: 250
N12: Parcela 7 | O12: 250
N13: Parcela 8 | O13: 250
B14: Despesas pessoais | C14: Valor | N14: Parcela 9 | O14: 250
B15: Desp. Alimentação / Refeição (26d) | C15: =26*20 -> 520 | N15: Parcela 10 | O15: 250
B16: Desp. Transporte / Combustível (26d) | C16: =16*2*26/12*6.6 -> 457.6 | N16: Parcela 11 | O16: 250
B17: Desp. Cartão de crédito - Dígio - renegociação | C17: 300 | N17: Parcela 12 | O17: 250
B18: Desp. Internet fixa - casa dos pais - mensal | C18: 120 | N18: Total | O18: =SUM(O6:O17) -> 3000
B19: Desp. Telefone móvel pessoal - mensal | C19: 91.81
B20: Desp. Moradia - mensal | C20: 300
B21: Renegociação cheque especial mensal | C21: 297 | D21: =36*290 -> 10440
B22: Manut. / Gastos do carro | C22: Pendente
B23: Guia do Simples Nacional ref. 10/2025 | C23: Inadimplente
B24: Guia do Simples Nacional ref. 11/2025 | C24: Inadimplente
B25: Guia do Simples Nacional do meu CNPJ ref. 12/2025 | C25: =5000*6% -> 300
B26: IPVA 2024 -inadimplente | C26: =700*0 -> 0
B27: Juros / Tarifas | C27: Variável
B28: Desp. Impostos e Obrigações | C28: Variável
B29: Outros gastos | C29: Variável
B30: Total das despesas pessoais | C30: =SUM(C15:C29) -> 2386.41 | F30: =C30 -> 2386.41 | J30: =C30 -> 2386.41
B33: Remuneração mensal | C33: 5000 | F33: 5000 | J33: 5000
B34: Total despesas (pensão + pessoal) | C34: =C10+C30 -> 5285.16 | F34: =F10+F30 -> 4318.91 | J34: =J10+J30 -> 3683.21
B35: Lucro / Prejuízo | C35: =C33-C34 -> -285.16 | F35: =F33-F34 -> 681.09 | J35: =J33-J34 -> 1316.79

Sheet 2025_Pensao_INDICE
F2: 45658 | G2: 45689 | H2: 45717 | I2: 45748 | J2: 45778 | K2: 45809 | L2: 45839 | M2: 45870
B3: Receitas
B4: Natureza | C4: Centro de resultado | D4: x | E4: TOTAL ANO | F4: JANEIRO | G4: FEVEREIRO | H4: MARÇO | I4: ABRIL | J4: MAIO | K4: JUNHO | L4: JULHO | M4: AGOSTO
B5: REC1 | C5: =VLOOKUP(B5,Cad_Natureza!B:C,2,0) -> CPF - Remun. Salário / Pró-Labore | E5: =SUM(F5:M5) -> 0 | F5: =SUMIFS('2026'!$K:$K,'2026'!$D:$D,$B5,'2026'!$T:$T,F$2) -> 0 | G5: =SUMIFS('2026'!$K:$K,'2026'!$D:$D,$B5,'2026'!$T:$T,G$2) -> 0 | H5: =SUMIFS('2026'!$K:$K,'2026'!$D:$D,$B5,'2026'!$T:$T,H$2) -> 0 | I5: =SUMIFS('2026'!$K:$K,'2026'!$D:$D,$B5,'2026'!$T:$T,I$2) -> 0 | J5: =SUMIFS('2026'!$K:$K,'2026'!$D:$D,$B5,'2026'!$T:$T,J$2) -> 0 | K5: =SUMIFS('2026'!$K:$K,'2026'!$D:$D,$B5,'2026'!$T:$T,K$2) -> 0 | L5: =SUMIFS('2026'!$K:$K,'2026'!$D:$D,$B5,'2026'!$T:$T,L$2) -> 0 | M5: =SUMIFS('2026'!$K:$K,'2026'!$D:$D,$B5,'2026'!$T:$T,M$2) -> 0
B7: Despesas com pensão | F7: Desempregado | G7: Desempregado | H7: 1º mês - Aquila | I7: 2º mês - Aquila | J7: 3º mês - Aquila | K7: 4º mês - Aquila | L7: 5º mês - Aquila | M7: 6º mês - Aquila
B8: Natureza | C8: Centro de resultado | E8: TOTAL ANO | F8: JANEIRO | G8: FEVEREIRO | H8: MARÇO | I8: ABRIL | J8: MAIO | K8: JUNHO | L8: JULHO | M8: AGOSTO
A9: x | B9: PENS1 | C9: CPF - Pensão - Aluguel | E9: =SUM(F9:M9) -> 0 | F9: =SUMIFS('2026'!$K:$K,'2026'!$D:$D,$B9,'2026'!$T:$T,F$2) -> 0 | G9: =SUMIFS('2026'!$K:$K,'2026'!$D:$D,$B9,'2026'!$T:$T,G$2) -> 0 | H9: =SUMIFS('2026'!$K:$K,'2026'!$D:$D,$B9,'2026'!$T:$T,H$2) -> 0 | I9: =SUMIFS('2026'!$K:$K,'2026'!$D:$D,$B9,'2026'!$T:$T,I$2) -> 0 | J9: =SUMIFS('2026'!$K:$K,'2026'!$D:$D,$B9,'2026'!$T:$T,J$2) -> 0 | K9: =SUMIFS('2026'!$K:$K,'2026'!$D:$D,$B9,'2026'!$T:$T,K$2) -> 0 | L9: =SUMIFS('2026'!$K:$K,'2026'!$D:$D,$B9,'2026'!$T:$T,L$2) -> 0 | M9: =SUMIFS('2026'!$K:$K,'2026'!$D:$D,$B9,'2026'!$T:$T,M$2) -> 0 | O9: 06/2025 | Q9: Pago
A10: x | B10: PENS2 | C10: CPF - Pensão - Energia | E10: =SUM(F10:M10) -> 0 | F10: =SUMIFS('2026'!$K:$K,'2026'!$D:$D,$B10,'2026'!$T:$T,F$2) -> 0 | G10: =SUMIFS('2026'!$K:$K,'2026'!$D:$D,$B10,'2026'!$T:$T,G$2) -> 0 | H10: =SUMIFS('2026'!$K:$K,'2026'!$D:$D,$B10,'2026'!$T:$T,H$2) -> 0 | I10: =SUMIFS('2026'!$K:$K,'2026'!$D:$D,$B10,'2026'!$T:$T,I$2) -> 0 | J10: =SUMIFS('2026'!$K:$K,'2026'!$D:$D,$B10,'2026'!$T:$T,J$2) -> 0 | K10: =SUMIFS('2026'!$K:$K,'2026'!$D:$D,$B10,'2026'!$T:$T,K$2) -> 0 | L10: =SUMIFS('2026'!$K:$K,'2026'!$D:$D,$B10,'2026'!$T:$T,L$2) -> 0 | M10: =SUMIFS('2026'!$K:$K,'2026'!$D:$D,$B10,'2026'!$T:$T,M$2) -> 0 | O10: -640.87 | Q10: Pago
A11: x | B11: PENS3 | C11: CPF - Pensão - Plano de saúde | E11: =SUM(F11:M11) -> 0 | F11: =SUMIFS('2026'!$K:$K,'2026'!$D:$D,$B11,'2026'!$T:$T,F$2) -> 0 | G11: =SUMIFS('2026'!$K:$K,'2026'!$D:$D,$B11,'2026'!$T:$T,G$2) -> 0 | H11: =SUMIFS('2026'!$K:$K,'2026'!$D:$D,$B11,'2026'!$T:$T,H$2) -> 0 | I11: =SUMIFS('2026'!$K:$K,'2026'!$D:$D,$B11,'2026'!$T:$T,I$2) -> 0 | J11: =SUMIFS('2026'!$K:$K,'2026'!$D:$D,$B11,'2026'!$T:$T,J$2) -> 0 | K11: =SUMIFS('2026'!$K:$K,'2026'!$D:$D,$B11,'2026'!$T:$T,K$2) -> 0 | L11: =SUMIFS('2026'!$K:$K,'2026'!$D:$D,$B11,'2026'!$T:$T,L$2) -> 0 | M11: =SUMIFS('2026'!$K:$K,'2026'!$D:$D,$B11,'2026'!$T:$T,M$2) -> 0 | Q11: Pago
B12: PENS4 | C12: CPF - Pensão - Supermercado | E12: =SUM(F12:M12) -> 0 | F12: =SUMIFS('2026'!$K:$K,'2026'!$D:$D,$B12,'2026'!$T:$T,F$2) -> 0 | G12: =SUMIFS('2026'!$K:$K,'2026'!$D:$D,$B12,'2026'!$T:$T,G$2) -> 0 | H12: =SUMIFS('2026'!$K:$K,'2026'!$D:$D,$B12,'2026'!$T:$T,H$2) -> 0 | I12: =SUMIFS('2026'!$K:$K,'2026'!$D:$D,$B12,'2026'!$T:$T,I$2) -> 0 | J12: =SUMIFS('2026'!$K:$K,'2026'!$D:$D,$B12,'2026'!$T:$T,J$2) -> 0 | K12: =SUMIFS('2026'!$K:$K,'2026'!$D:$D,$B12,'2026'!$T:$T,K$2) -> 0 | L12: =SUMIFS('2026'!$K:$K,'2026'!$D:$D,$B12,'2026'!$T:$T,L$2) -> 0 | M12: =SUMIFS('2026'!$K:$K,'2026'!$D:$D,$B12,'2026'!$T:$T,M$2) -> 0
A13: x | B13: PENS5 | C13: CPF - Pensão - Água | E13: =SUM(F13:M13) -> 0 | F13: =SUMIFS('2026'!$K:$K,'2026'!$D:$D,$B13,'2026'!$T:$T,F$2) -> 0 | G13: =SUMIFS('2026'!$K:$K,'2026'!$D:$D,$B13,'2026'!$T:$T,G$2) -> 0 | H13: =SUMIFS('2026'!$K:$K,'2026'!$D:$D,$B13,'2026'!$T:$T,H$2) -> 0 | I13: =SUMIFS('2026'!$K:$K,'2026'!$D:$D,$B13,'2026'!$T:$T,I$2) -> 0 | J13: =SUMIFS('2026'!$K:$K,'2026'!$D:$D,$B13,'2026'!$T:$T,J$2) -> 0 | K13: =SUMIFS('2026'!$K:$K,'2026'!$D:$D,$B13,'2026'!$T:$T,K$2) -> 0 | L13: =SUMIFS('2026'!$K:$K,'2026'!$D:$D,$B13,'2026'!$T:$T,L$2) -> 0 | M13: =SUMIFS('2026'!$K:$K,'2026'!$D:$D,$B13,'2026'!$T:$T,M$2) -> 0
B14: PENS6 | C14: CPF - Pensão - Farmácia e Saúde | E14: =SUM(F14:M14) -> 0 | F14: =SUMIFS('2026'!$K:$K,'2026'!$D:$D,$B14,'2026'!$T:$T,F$2) -> 0 | G14: =SUMIFS('2026'!$K:$K,'2026'!$D:$D,$B14,'2026'!$T:$T,G$2) -> 0 | H14: =SUMIFS('2026'!$K:$K,'2026'!$D:$D,$B14,'2026'!$T:$T,H$2) -> 0 | I14: =SUMIFS('2026'!$K:$K,'2026'!$D:$D,$B14,'2026'!$T:$T,I$2) -> 0 | J14: =SUMIFS('2026'!$K:$K,'2026'!$D:$D,$B14,'2026'!$T:$T,J$2) -> 0 | K14: =SUMIFS('2026'!$K:$K,'2026'!$D:$D,$B14,'2026'!$T:$T,K$2) -> 0 | L14: =SUMIFS('2026'!$K:$K,'2026'!$D:$D,$B14,'2026'!$T:$T,L$2) -> 0 | M14: =SUMIFS('2026'!$K:$K,'2026'!$D:$D,$B14,'2026'!$T:$T,M$2) -> 0
B15: PENS7 | C15: CPF - Pensão - Internet | E15: =SUM(F15:M15) -> 0 | F15: =SUMIFS('2026'!$K:$K,'2026'!$D:$D,$B15,'2026'!$T:$T,F$2) -> 0 | G15: =SUMIFS('2026'!$K:$K,'2026'!$D:$D,$B15,'2026'!$T:$T,G$2) -> 0 | H15: =SUMIFS('2026'!$K:$K,'2026'!$D:$D,$B15,'2026'!$T:$T,H$2) -> 0 | I15: =SUMIFS('2026'!$K:$K,'2026'!$D:$D,$B15,'2026'!$T:$T,I$2) -> 0 | J15: =SUMIFS('2026'!$K:$K,'2026'!$D:$D,$B15,'2026'!$T:$T,J$2) -> 0 | K15: =SUMIFS('2026'!$K:$K,'2026'!$D:$D,$B15,'2026'!$T:$T,K$2) -> 0 | L15: =SUMIFS('2026'!$K:$K,'2026'!$D:$D,$B15,'2026'!$T:$T,L$2) -> 0 | M15: =SUMIFS('2026'!$K:$K,'2026'!$D:$D,$B15,'2026'!$T:$T,M$2) -> 0
B16: PENS8 | C16: CPF - Pensão - Alimentação | E16: =SUM(F16:M16) -> 0 | F16: =SUMIFS('2026'!$K:$K,'2026'!$D:$D,$B16,'2026'!$T:$T,F$2) -> 0 | G16: =SUMIFS('2026'!$K:$K,'2026'!$D:$D,$B16,'2026'!$T:$T,G$2) -> 0 | H16: =SUMIFS('2026'!$K:$K,'2026'!$D:$D,$B16,'2026'!$T:$T,H$2) -> 0 | I16: =SUMIFS('2026'!$K:$K,'2026'!$D:$D,$B16,'2026'!$T:$T,I$2) -> 0 | J16: =SUMIFS('2026'!$K:$K,'2026'!$D:$D,$B16,'2026'!$T:$T,J$2) -> 0 | K16: =SUMIFS('2026'!$K:$K,'2026'!$D:$D,$B16,'2026'!$T:$T,K$2) -> 0 | L16: =SUMIFS('2026'!$K:$K,'2026'!$D:$D,$B16,'2026'!$T:$T,L$2) -> 0 | M16: =SUMIFS('2026'!$K:$K,'2026'!$D:$D,$B16,'2026'!$T:$T,M$2) -> 0
B17: PENS9 | C17: CPF - Pensão - Educação | E17: =SUM(F17:M17) -> 0 | F17: =SUMIFS('2026'!$K:$K,'2026'!$D:$D,$B17,'2026'!$T:$T,F$2) -> 0 | G17: =SUMIFS('2026'!$K:$K,'2026'!$D:$D,$B17,'2026'!$T:$T,G$2) -> 0 | H17: =SUMIFS('2026'!$K:$K,'2026'!$D:$D,$B17,'2026'!$T:$T,H$2) -> 0 | I17: =SUMIFS('2026'!$K:$K,'2026'!$D:$D,$B17,'2026'!$T:$T,I$2) -> 0 | J17: =SUMIFS('2026'!$K:$K,'2026'!$D:$D,$B17,'2026'!$T:$T,J$2) -> 0 | K17: =SUMIFS('2026'!$K:$K,'2026'!$D:$D,$B17,'2026'!$T:$T,K$2) -> 0 | L17: =SUMIFS('2026'!$K:$K,'2026'!$D:$D,$B17,'2026'!$T:$T,L$2) -> 0 | M17: =SUMIFS('2026'!$K:$K,'2026'!$D:$D,$B17,'2026'!$T:$T,M$2) -> 0
B18: PENS10 | C18: CPF - Pensão - Vestuário | E18: =SUM(F18:M18) -> 0 | F18: =SUMIFS('2026'!$K:$K,'2026'!$D:$D,$B18,'2026'!$T:$T,F$2) -> 0 | G18: =SUMIFS('2026'!$K:$K,'2026'!$D:$D,$B18,'2026'!$T:$T,G$2) -> 0 | H18: =SUMIFS('2026'!$K:$K,'2026'!$D:$D,$B18,'2026'!$T:$T,H$2) -> 0 | I18: =SUMIFS('2026'!$K:$K,'2026'!$D:$D,$B18,'2026'!$T:$T,I$2) -> 0 | J18: =SUMIFS('2026'!$K:$K,'2026'!$D:$D,$B18,'2026'!$T:$T,J$2) -> 0 | K18: =SUMIFS('2026'!$K:$K,'2026'!$D:$D,$B18,'2026'!$T:$T,K$2) -> 0 | L18: =SUMIFS('2026'!$K:$K,'2026'!$D:$D,$B18,'2026'!$T:$T,L$2) -> 0 | M18: =SUMIFS('2026'!$K:$K,'2026'!$D:$D,$B18,'2026'!$T:$T,M$2) -> 0
B19: PENS11 | C19: CPF - Pensão - Outros Gastos | E19: =SUM(F19:M19) -> 0 | F19: =SUMIFS('2026'!$K:$K,'2026'!$D:$D,$B19,'2026'!$T:$T,F$2) -> 0 | G19: =SUMIFS('2026'!$K:$K,'2026'!$D:$D,$B19,'2026'!$T:$T,G$2) -> 0 | H19: =SUMIFS('2026'!$K:$K,'2026'!$D:$D,$B19,'2026'!$T:$T,H$2) -> 0 | I19: =SUMIFS('2026'!$K:$K,'2026'!$D:$D,$B19,'2026'!$T:$T,I$2) -> 0 | J19: =SUMIFS('2026'!$K:$K,'2026'!$D:$D,$B19,'2026'!$T:$T,J$2) -> 0 | K19: =SUMIFS('2026'!$K:$K,'2026'!$D:$D,$B19,'2026'!$T:$T,K$2) -> 0 | L19: =SUMIFS('2026'!$K:$K,'2026'!$D:$D,$B19,'2026'!$T:$T,L$2) -> 0 | M19: =SUMIFS('2026'!$K:$K,'2026'!$D:$D,$B19,'2026'!$T:$T,M$2) -> 0
C20: TOTAL DE DESPESAS COM PENSÃO | E20: =SUM(E9:E19) -> 0 | F20: =SUM(F9:F19) -> 0 | G20: =SUM(G9:G19) -> 0 | H20: =SUM(H9:H19) -> 0 | I20: =SUM(I9:I19) -> 0 | J20: =SUM(J9:J19) -> 0 | K20: =SUM(K9:K19) -> 0 | L20: =SUM(L9:L19) -> 0 | M20: =SUM(M9:M19) -> 0
C22: PERCENTUAL DE PENSÃO % | E22: =ABS(E20)/E5 -> #DIV/0! | F22: =IFERROR(ABS(F20)/F5,0) -> 0 | G22: =IFERROR(ABS(G20)/G5,0) -> 0 | H22: =IFERROR(ABS(H20)/H5,0) -> 0 | I22: =IFERROR(ABS(I20)/I5,0) -> 0 | J22: =IFERROR(ABS(J20)/J5,0) -> 0 | K22: =IFERROR(ABS(K20)/K5,0) -> 0 | L22: =IFERROR(ABS(L20)/L5,0) -> 0 | M22: =IFERROR(ABS(M20)/M5,0) -> 0
B24: Despesas pessoais recorrentes

Sheet Saneago
B2: nascimento Dat 27/09/1945 | E2: CPF. 02164566149 | H2: Protocolo 2025062870331
E3: 2472693-1 | F3: 1065776-2 | R3: 1065776-2
B4: Referência | C4: Vencimento | D4: Pagamento | E4: Seu João Pagou | F4: Eu paguei errado | G4: Saldo | H4: Observação | O4: Referência | P4: Vencimento | Q4: Pagamento | R4: Valor Pago | S4: status | U4: Paguei | V4: Deveria pagar | W4: Saldo
B5: 45748 | C5: 45774 | D5: 45779 | E5: 82.65 | F5: 45.37 | G5: =F5-E5 -> -37.28 | H5: Paguei a menos neste mês | O5: 45748 | P5: 45763 | Q5: 45757 | R5: 45.37 | U5: =R5 -> 45.37 | V5: =E5 -> 82.65 | W5: =U5-V5 -> -37.28 | X5: Paguei a mais
B6: 45717 | C6: 45743 | D6: 45779 | E6: 89.9 | F6: 38.56 | G6: =F6-E6 -> -51.34 | H6: Paguei a menos neste mês | O6: 45717 | P6: 45732 | Q6: 45777 | R6: 38.56 | S6: Paguei | U6: =R6 -> 38.56 | V6: =E6 -> 89.9 | W6: =U6-V6 -> -51.34 | X6: Paguei a menos
B7: 45689 | C7: 45715 | D7: 45779 | E7: 79.34 | F7: 62.84 | G7: =F7-E7 -> -16.5 | H7: Paguei a menos neste mês | O7: 45689 | P7: 45704 | Q7: 45727 | R7: 62.84 | S7: Paguei | U7: =R7 -> 62.84 | V7: =E7 -> 79.34 | W7: =U7-V7 -> -16.5 | X7: Paguei a menos
B8: 45658 | C8: 45684 | D8: 45779 | E8: 75.04 | F8: 86 | G8: =E8-F8 -> -10.96 | H8: Paguei a mais neste mês | O8: 45658 | P8: 45673 | Q8: 45727 | R8: 86 | S8: Paguei | U8: =R8 -> 86 | V8: =E8 -> 75.04 | W8: =U8-V8 -> 10.96
E9: =SUM(E5:E8) -> 326.93 | F9: =SUM(F5:F8) -> 232.77 | G9: =SUM(G5:G8) -> -116.08 | H9: Valor a devolver | R9: =SUM(R5:R8) -> 232.77 | S9: Total pago | W9: =SUM(W5:W8) -> -94.16 | X9: Valor a devolver
C37: ZAP

Sheet Energia_Pgtos
B2: Nº Cliente | C2: Nome Cliente | D2: Nº Fatura | E2: Mês / Ano | F2: Vencimento | G2: Pagamento | H2: Valor Pago | I2: Tipo Fatura
B3: 259049 | C3: JOAO DE SOUZA LOBO SOBRINHO | D3: 2023004959988 | E3: 44927 | F3: 44959 | G3: 44960 | H3: 191.19 | I3: FATURA GRUPO B
B4: 259049 | C4: JOAO DE SOUZA LOBO SOBRINHO | D4: 2023014707796 | E4: 44958 | F4: 44987 | G4: 44991 | H4: 297.94 | I4: FATURA GRUPO B
B5: 259049 | C5: JOAO DE SOUZA LOBO SOBRINHO | D5: 2023024296910 | E5: 44986 | F5: 45018 | G5: 45026 | H5: 298.88 | I5: FATURA GRUPO B
B6: 259049 | C6: JOAO DE SOUZA LOBO SOBRINHO | D6: 2023033825407 | E6: 45017 | F6: 45048 | G6: 45062 | H6: 322.38 | I6: FATURA GRUPO B
B7: 259049 | C7: JOAO DE SOUZA LOBO SOBRINHO | D7: 2023043559318 | E7: 45047 | F7: 45079 | G7: 45111 | H7: 305.33 | I7: FATURA GRUPO B
B8: 259049 | C8: JOAO DE SOUZA LOBO SOBRINHO | D8: 2023053589419 | E8: 45078 | F8: 45109 | G8: 45111 | H8: 219.22 | I8: FATURA GRUPO B
B9: 259049 | C9: JOAO DE SOUZA LOBO SOBRINHO | D9: 2023063575130 | E9: 45108 | F9: 45140 | G9: 45148 | H9: 167.18 | I9: FATURA GRUPO B
B10: 259049 | C10: JOAO DE SOUZA LOBO SOBRINHO | D10: 2023073199330 | E10: 45139 | F10: 45171 | G10: 45181 | H10: 208.99 | I10: FATURA GRUPO B
B11: 259049 | C11: JOAO DE SOUZA LOBO SOBRINHO | D11: 2023083166750 | E11: 45170 | F11: 45201 | G11: 45208 | H11: 248.04 | I11: FATURA GRUPO B
B12: 259049 | C12: JOAO DE SOUZA LOBO SOBRINHO | D12: 2023092937893 | E12: 45200 | F12: 45232 | G12: 45259 | H12: 664.8 | I12: FATURA GRUPO B
B13: 259049 | C13: JOAO DE SOUZA LOBO SOBRINHO | D13: 2023104020631 | E13: 45231 | F13: 45262 | G13: 45280 | H13: 572.06 | I13: FATURA GRUPO B
B14: 259049 | C14: JOAO DE SOUZA LOBO SOBRINHO | D14: 2023114402076 | E14: 45261 | F14: 45293 | G14: 45299 | H14: 314.09 | I14: FATURA GRUPO B
... B32: 259049 | C32: JOAO DE SOUZA LOBO SOBRINHO | D32: 2025056839886 | E32: 45809 | F32: 45840 | G32: 45875 | H32: 677.92 | I32: FATURA GRUPO B
B33: 259049 | C33: JOAO DE SOUZA LOBO SOBRINHO | E33: 45839 | F33: 45871 | G33: 45915 | H33: 640.87 | I33: FATURA GRUPO B | J33: Seu João é que pagou
B34: 259049 | C34: JOAO DE SOUZA LOBO SOBRINHO | E34: 45870 | F34: 45902 | G34: 45943 | H34: 710.36 | I34: FATURA GRUPO B | J34: Comprovante na pasta
B35: 259049 | C35: JOAO DE SOUZA LOBO SOBRINHO | E35: 45901 | F35: 45932 | G35: 45971 | H35: 708.58 | I35: FATURA GRUPO B
B36: 259049 | C36: JOAO DE SOUZA LOBO SOBRINHO | E36: 45931 | F36: 45963 | G36: 46034 | H36: 816.87 | I36: FATURA GRUPO B | J36: Comprovante na pasta
B37: 259049 | C37: JOAO DE SOUZA LOBO SOBRINHO | E37: 45962 | F37: 45993 | G37: 45999 | H37: 1050.29 | I37: FATURA GRUPO B | J37: Comprovante na pasta
B38: 259049 | C38: JOAO DE SOUZA LOBO SOBRINHO | E38: 45992 | F38: 46024 | G38: 46062 | H38: 833.3 | I38: FATURA GRUPO B | J38: Comprovante na pasta

Sheet Composição
B2: Ref | C2: Energia | D2: Distribuição | E2: Transmissão | F2: Tributos | G2: Perdas | H2: ICMS | I2: PIS | J2: COFINS | K2: Demais Itens | L2: Total
