Workbook
Name Fluxo: OFFSET(Cad_Natureza!$G$4,0,0,COUNTA(Cad_Natureza!$G$4:$G$102))
Name Lista_CRs: OFFSET(Cad_Natureza!$C$4,0,0,COUNTA(Cad_Natureza!$C$5:$C$52)+3)
Name Lista_Socios: OFFSET(Cad_Natureza!$E$4,0,0,COUNTA(Cad_Natureza!$E$4:$E$102))

Sheet FLUXO DE CAIXA
A2: MCS | B2: FLUXO DE CAIXA ANO - MCS
A3: MCS | D3: SELECIONE A ENTIDADE QUE PAGOU OU RECEBEU => | E3: MCS | T3: RESUMO FLUXO CAIXA
A4: MCS | D4: SELECIONE O CENTRO DE RESULTADO => | E4: TODOS CRs | T4: GRUPO | U4: TOTAL | V4: A.V. %
A5: Sinko | T5: REC | U5: =SUMIFS($E$7:$E$40,$B$7:$B$40,T5) -> 33591.75 | V5: =IFERROR(ABS(U5/$U$5),0) -> 1
A6: TODAS | B6: Grupo | C6: Natureza | D6: ENTRADAS | E6: ACUM | F6: 46023 | G6: 46054 | H6: 46082 | I6: 46113 | J6: 46143 | K6: 46174 | L6: 46204 | M6: 46235 | N6: 46266 | O6: 46296 | P6: 46327 | Q6: 46357 | T6: PENS | U6: =SUMIFS($E$7:$E$40,$B$7:$B$40,T6) -> -11734.05 | V6: =IFERROR(ABS(U6/$U$5),0) -> 0.34931345
B7: REC | C7: REC1 | D7: CPF - Remun. Salário / Pró-Labore | E7: =SUM(F7:Q7) -> 0 | F7: =IF((AND($E$3="MCS",$E$4="TODOS CRs")), SUMIFS('2026'!$K:$K,'2026'!$R:$R,$E$3&$C7,'2026'!$T:$T,F$6), SUMIFS('2026'!$K:$K,'2026'!$N:$N,$E$3&$C7&$E$4,'2026'!$T:$T,F$6)) -> 0 | G7: =IF((AND($E$3="MCS",$E$4="TODOS CRs")), SUMIFS('2026'!$K:$K,'2026'!$R:$R,$E$3&$C7,'2026'!$T:$T,G$6), SUMIFS('2026'!$K:$K,'2026'!$N:$N,$E$3&$C7&$E$4,'2026'!$T:$T,G$6)) -> 0 | H7: =IF((AND($E$3="MCS",$E$4="TODOS CRs")), SUMIFS('2026'!$K:$K,'2026'!$R:$R,$E$3&$C7,'2026'!$T:$T,H$6), SUMIFS('2026'!$K:$K,'2026'!$N:$N,$E$3&$C7&$E$4,'2026'!$T:$T,H$6)) -> 0 | I7: =IF((AND($E$3="MCS",$E$4="TODOS CRs")), SUMIFS('2026'!$K:$K,'2026'!$R:$R,$E$3&$C7,'2026'!$T:$T,I$6), SUMIFS('2026'!$K:$K,'2026'!$N:$N,$E$3&$C7&$E$4,'2026'!$T:$T,I$6)) -> 0 | J7: =IF((AND($E$3="MCS",$E$4="TODOS CRs")), SUMIFS('2026'!$K:$K,'2026'!$R:$R,$E$3&$C7,'2026'!$T:$T,J$6), SUMIFS('2026'!$K:$K,'2026'!$N:$N,$E$3&$C7&$E$4,'2026'!$T:$T,J$6)) -> 0 | K7: =IF((AND($E$3="MCS",$E$4="TODOS CRs")), SUMIFS('2026'!$K:$K,'2026'!$R:$R,$E$3&$C7,'2026'!$T:$T,K$6), SUMIFS('2026'!$K:$K,'2026'!$N:$N,$E$3&$C7&$E$4,'2026'!$T:$T,K$6)) -> 0 | L7: =IF((AND($E$3="MCS",$E$4="TODOS CRs")), SUMIFS('2026'!$K:$K,'2026'!$R:$R,$E$3&$C7,'2026'!$T:$T,L$6), SUMIFS('2026'!$K:$K,'2026'!$N:$N,$E$3&$C7&$E$4,'2026'!$T:$T,L$6)) -> 0 | M7: =IF((AND($E$3="MCS",$E$4="TODOS CRs")), SUMIFS('2026'!$K:$K,'2026'!$R:$R,$E$3&$C7,'2026'!$T:$T,M$6), SUMIFS('2026'!$K:$K,'2026'!$N:$N,$E$3&$C7&$E$4,'2026'!$T:$T,M$6)) -> 0 | ... Q7: =IF((AND($E$3="MCS",$E$4="TODOS CRs")), SUMIFS('2026'!$K:$K,'2026'!$R:$R,$E$3&$C7,'2026'!$T:$T,Q$6), SUMIFS('2026'!$K:$K,'2026'!$N:$N,$E$3&$C7&$E$4,'2026'!$T:$T,Q$6)) -> 0 | T7: OPF | U7: =SUMIFS($E$7:$E$40,$B$7:$B$40,T7) -> -6840.46 | V7: =IFERROR(ABS(U7/$U$5),0) -> 0.20363512
B8: REC | C8: REC2 | D8: CPF - Ajuda de custo - Combustível | E8: =SUM(F8:Q8) -> 0 | F8: =IF((AND($E$3="MCS",$E$4="TODOS CRs")), SUMIFS('2026'!$K:$K,'2026'!$R:$R,$E$3&$C8,'2026'!$T:$T,F$6), SUMIFS('2026'!$K:$K,'2026'!$N:$N,$E$3&$C8&$E$4,'2026'!$T:$T,F$6)) -> 0 | G8: =IF((AND($E$3="MCS",$E$4="TODOS CRs")), SUMIFS('2026'!$K:$K,'2026'!$R:$R,$E$3&$C8,'2026'!$T:$T,G$6), SUMIFS('2026'!$K:$K,'2026'!$N:$N,$E$3&$C8&$E$4,'2026'!$T:$T,G$6)) -> 0 | H8: =IF((AND($E$3="MCS",$E$4="TODOS CRs")), SUMIFS('2026'!$K:$K,'2026'!$R:$R,$E$3&$C8,'2026'!$T:$T,H$6), SUMIFS('2026'!$K:$K,'2026'!$N:$N,$E$3&$C8&$E$4,'2026'!$T:$T,H$6)) -> 0 | I8: =IF((AND($E$3="MCS",$E$4="TODOS CRs")), SUMIFS('2026'!$K:$K,'2026'!$R:$R,$E$3&$C8,'2026'!$T:$T,I$6), SUMIFS('2026'!$K:$K,'2026'!$N:$N,$E$3&$C8&$E$4,'2026'!$T:$T,I$6)) -> 0 | J8: =IF((AND($E$3="MCS",$E$4="TODOS CRs")), SUMIFS('2026'!$K:$K,'2026'!$R:$R,$E$3&$C8,'2026'!$T:$T,J$6), SUMIFS('2026'!$K:$K,'2026'!$N:$N,$E$3&$C8&$E$4,'2026'!$T:$T,J$6)) -> 0 | K8: =IF((AND($E$3="MCS",$E$4="TODOS CRs")), SUMIFS('2026'!$K:$K,'2026'!$R:$R,$E$3&$C8,'2026'!$T:$T,K$6), SUMIFS('2026'!$K:$K,'2026'!$N:$N,$E$3&$C8&$E$4,'2026'!$T:$T,K$6)) -> 0 | L8: =IF((AND($E$3="MCS",$E$4="TODOS CRs")), SUMIFS('2026'!$K:$K,'2026'!$R:$R,$E$3&$C8,'2026'!$T:$T,L$6), SUMIFS('2026'!$K:$K,'2026'!$N:$N,$E$3&$C8&$E$4,'2026'!$T:$T,L$6)) -> 0 | M8: =IF((AND($E$3="MCS",$E$4="TODOS CRs")), SUMIFS('2026'!$K:$K,'2026'!$R:$R,$E$3&$C8,'2026'!$T:$T,M$6), SUMIFS('2026'!$K:$K,'2026'!$N:$N,$E$3&$C8&$E$4,'2026'!$T:$T,M$6)) -> 0 | ... Q8: =IF((AND($E$3="MCS",$E$4="TODOS CRs")), SUMIFS('2026'!$K:$K,'2026'!$R:$R,$E$3&$C8,'2026'!$T:$T,Q$6), SUMIFS('2026'!$K:$K,'2026'!$N:$N,$E$3&$C8&$E$4,'2026'!$T:$T,Q$6)) -> 0 | T8: GAST | U8: =SUMIFS($E$7:$E$40,$B$7:$B$40,T8) -> -6045.55 | V8: =IFERROR(ABS(U8/$U$5),0) -> 0.17997127
B9: REC | C9: REC3 | D9: CPF - Ajuda de custo - Refeição | E9: =SUM(F9:Q9) -> 0 | F9: =IF((AND($E$3="MCS",$E$4="TODOS CRs")), SUMIFS('2026'!$K:$K,'2026'!$R:$R,$E$3&$C9,'2026'!$T:$T,F$6), SUMIFS('2026'!$K:$K,'2026'!$N:$N,$E$3&$C9&$E$4,'2026'!$T:$T,F$6)) -> 0 | G9: =IF((AND($E$3="MCS",$E$4="TODOS CRs")), SUMIFS('2026'!$K:$K,'2026'!$R:$R,$E$3&$C9,'2026'!$T:$T,G$6), SUMIFS('2026'!$K:$K,'2026'!$N:$N,$E$3&$C9&$E$4,'2026'!$T:$T,G$6)) -> 0 | H9: =IF((AND($E$3="MCS",$E$4="TODOS CRs")), SUMIFS('2026'!$K:$K,'2026'!$R:$R,$E$3&$C9,'2026'!$T:$T,H$6), SUMIFS('2026'!$K:$K,'2026'!$N:$N,$E$3&$C9&$E$4,'2026'!$T:$T,H$6)) -> 0 | I9: =IF((AND($E$3="MCS",$E$4="TODOS CRs")), SUMIFS('2026'!$K:$K,'2026'!$R:$R,$E$3&$C9,'2026'!$T:$T,I$6), SUMIFS('2026'!$K:$K,'2026'!$N:$N,$E$3&$C9&$E$4,'2026'!$T:$T,I$6)) -> 0 | J9: =IF((AND($E$3="MCS",$E$4="TODOS CRs")), SUMIFS('2026'!$K:$K,'2026'!$R:$R,$E$3&$C9,'2026'!$T:$T,J$6), SUMIFS('2026'!$K:$K,'2026'!$N:$N,$E$3&$C9&$E$4,'2026'!$T:$T,J$6)) -> 0 | K9: =IF((AND($E$3="MCS",$E$4="TODOS CRs")), SUMIFS('2026'!$K:$K,'2026'!$R:$R,$E$3&$C9,'2026'!$T:$T,K$6), SUMIFS('2026'!$K:$K,'2026'!$N:$N,$E$3&$C9&$E$4,'2026'!$T:$T,K$6)) -> 0 | L9: =IF((AND($E$3="MCS",$E$4="TODOS CRs")), SUMIFS('2026'!$K:$K,'2026'!$R:$R,$E$3&$C9,'2026'!$T:$T,L$6), SUMIFS('2026'!$K:$K,'2026'!$N:$N,$E$3&$C9&$E$4,'2026'!$T:$T,L$6)) -> 0 | M9: =IF((AND($E$3="MCS",$E$4="TODOS CRs")), SUMIFS('2026'!$K:$K,'2026'!$R:$R,$E$3&$C9,'2026'!$T:$T,M$6), SUMIFS('2026'!$K:$K,'2026'!$N:$N,$E$3&$C9&$E$4,'2026'!$T:$T,M$6)) -> 0 | ... Q9: =IF((AND($E$3="MCS",$E$4="TODOS CRs")), SUMIFS('2026'!$K:$K,'2026'!$R:$R,$E$3&$C9,'2026'!$T:$T,Q$6), SUMIFS('2026'!$K:$K,'2026'!$N:$N,$E$3&$C9&$E$4,'2026'!$T:$T,Q$6)) -> 0 | T9: DESP | U9: =SUMIFS($E$7:$E$40,$B$7:$B$40,T9) -> -4028.63 | V9: =IFERROR(ABS(U9/$U$5),0) -> 0.11992915
B10: REC | C10: REC4 | D10: CPF - Transf. Da conta PJ para a conta PF | E10: =SUM(F10:Q10) -> 32740 | F10: =IF((AND($E$3="MCS",$E$4="TODOS CRs")), SUMIFS('2026'!$K:$K,'2026'!$R:$R,$E$3&$C10,'2026'!$T:$T,F$6), SUMIFS('2026'!$K:$K,'2026'!$N:$N,$E$3&$C10&$E$4,'2026'!$T:$T,F$6)) -> 4900 | G10: =IF((AND($E$3="MCS",$E$4="TODOS CRs")), SUMIFS('2026'!$K:$K,'2026'!$R:$R,$E$3&$C10,'2026'!$T:$T,G$6), SUMIFS('2026'!$K:$K,'2026'!$N:$N,$E$3&$C10&$E$4,'2026'!$T:$T,G$6)) -> 5500 | H10: =IF((AND($E$3="MCS",$E$4="TODOS CRs")), SUMIFS('2026'!$K:$K,'2026'!$R:$R,$E$3&$C10,'2026'!$T:$T,H$6), SUMIFS('2026'!$K:$K,'2026'!$N:$N,$E$3&$C10&$E$4,'2026'!$T:$T,H$6)) -> 5040 | I10: =IF((AND($E$3="MCS",$E$4="TODOS CRs")), SUMIFS('2026'!$K:$K,'2026'!$R:$R,$E$3&$C10,'2026'!$T:$T,I$6), SUMIFS('2026'!$K:$K,'2026'!$N:$N,$E$3&$C10&$E$4,'2026'!$T:$T,I$6)) -> 7000 | J10: =IF((AND($E$3="MCS",$E$4="TODOS CRs")), SUMIFS('2026'!$K:$K,'2026'!$R:$R,$E$3&$C10,'2026'!$T:$T,J$6), SUMIFS('2026'!$K:$K,'2026'!$N:$N,$E$3&$C10&$E$4,'2026'!$T:$T,J$6)) -> 6300 | K10: =IF((AND($E$3="MCS",$E$4="TODOS CRs")), SUMIFS('2026'!$K:$K,'2026'!$R:$R,$E$3&$C10,'2026'!$T:$T,K$6), SUMIFS('2026'!$K:$K,'2026'!$N:$N,$E$3&$C10&$E$4,'2026'!$T:$T,K$6)) -> 4000 | L10: =IF((AND($E$3="MCS",$E$4="TODOS CRs")), SUMIFS('2026'!$K:$K,'2026'!$R:$R,$E$3&$C10,'2026'!$T:$T,L$6), SUMIFS('2026'!$K:$K,'2026'!$N:$N,$E$3&$C10&$E$4,'2026'!$T:$T,L$6)) -> 0 | M10: =IF((AND($E$3="MCS",$E$4="TODOS CRs")), SUMIFS('2026'!$K:$K,'2026'!$R:$R,$E$3&$C10,'2026'!$T:$T,M$6), SUMIFS('2026'!$K:$K,'2026'!$N:$N,$E$3&$C10&$E$4,'2026'!$T:$T,M$6)) -> 0 | ... Q10: =IF((AND($E$3="MCS",$E$4="TODOS CRs")), SUMIFS('2026'!$K:$K,'2026'!$R:$R,$E$3&$C10,'2026'!$T:$T,Q$6), SUMIFS('2026'!$K:$K,'2026'!$N:$N,$E$3&$C10&$E$4,'2026'!$T:$T,Q$6)) -> 0 | T10: FIN | U10: =SUMIFS($E$7:$E$40,$B$7:$B$40,T10) -> -2350.3 | V10: =IFERROR(ABS(U10/$U$5),0) -> 0.069966584
B11: REC | C11: REC5 | D11: CPF - Outras receitas | E11: =SUM(F11:Q11) -> 681.75 | F11: =IF((AND($E$3="MCS",$E$4="TODOS CRs")), SUMIFS('2026'!$K:$K,'2026'!$R:$R,$E$3&$C11,'2026'!$T:$T,F$6), SUMIFS('2026'!$K:$K,'2026'!$N:$N,$E$3&$C11&$E$4,'2026'!$T:$T,F$6)) -> 0 | G11: =IF((AND($E$3="MCS",$E$4="TODOS CRs")), SUMIFS('2026'!$K:$K,'2026'!$R:$R,$E$3&$C11,'2026'!$T:$T,G$6), SUMIFS('2026'!$K:$K,'2026'!$N:$N,$E$3&$C11&$E$4,'2026'!$T:$T,G$6)) -> 17.62 | H11: =IF((AND($E$3="MCS",$E$4="TODOS CRs")), SUMIFS('2026'!$K:$K,'2026'!$R:$R,$E$3&$C11,'2026'!$T:$T,H$6), SUMIFS('2026'!$K:$K,'2026'!$N:$N,$E$3&$C11&$E$4,'2026'!$T:$T,H$6)) -> 56 | I11: =IF((AND($E$3="MCS",$E$4="TODOS CRs")), SUMIFS('2026'!$K:$K,'2026'!$R:$R,$E$3&$C11,'2026'!$T:$T,I$6), SUMIFS('2026'!$K:$K,'2026'!$N:$N,$E$3&$C11&$E$4,'2026'!$T:$T,I$6)) -> 25 | J11: =IF((AND($E$3="MCS",$E$4="TODOS CRs")), SUMIFS('2026'!$K:$K,'2026'!$R:$R,$E$3&$C11,'2026'!$T:$T,J$6), SUMIFS('2026'!$K:$K,'2026'!$N:$N,$E$3&$C11&$E$4,'2026'!$T:$T,J$6)) -> 189.99 | K11: =IF((AND($E$3="MCS",$E$4="TODOS CRs")), SUMIFS('2026'!$K:$K,'2026'!$R:$R,$E$3&$C11,'2026'!$T:$T,K$6), SUMIFS('2026'!$K:$K,'2026'!$N:$N,$E$3&$C11&$E$4,'2026'!$T:$T,K$6)) -> 393.14 | L11: =IF((AND($E$3="MCS",$E$4="TODOS CRs")), SUMIFS('2026'!$K:$K,'2026'!$R:$R,$E$3&$C11,'2026'!$T:$T,L$6), SUMIFS('2026'!$K:$K,'2026'!$N:$N,$E$3&$C11&$E$4,'2026'!$T:$T,L$6)) -> 0 | M11: =IF((AND($E$3="MCS",$E$4="TODOS CRs")), SUMIFS('2026'!$K:$K,'2026'!$R:$R,$E$3&$C11,'2026'!$T:$T,M$6), SUMIFS('2026'!$K:$K,'2026'!$N:$N,$E$3&$C11&$E$4,'2026'!$T:$T,M$6)) -> 0 | ... Q11: =IF((AND($E$3="MCS",$E$4="TODOS CRs")), SUMIFS('2026'!$K:$K,'2026'!$R:$R,$E$3&$C11,'2026'!$T:$T,Q$6), SUMIFS('2026'!$K:$K,'2026'!$N:$N,$E$3&$C11&$E$4,'2026'!$T:$T,Q$6)) -> 0 | T11: OUG | U11: =SUMIFS($E$7:$E$40,$B$7:$B$40,T11) -> -2053.59 | V11: =IFERROR(ABS(U11/$U$5),0) -> 0.061133761
B12: REC | C12: REC6 | D12: CPF - Pensão - Outras receitas | E12: =SUM(F12:Q12) -> 0 | F12: =IF((AND($E$3="MCS",$E$4="TODOS CRs")), SUMIFS('2026'!$K:$K,'2026'!$R:$R,$E$3&$C12,'2026'!$T:$T,F$6), SUMIFS('2026'!$K:$K,'2026'!$N:$N,$E$3&$C12&$E$4,'2026'!$T:$T,F$6)) -> 0 | G12: =IF((AND($E$3="MCS",$E$4="TODOS CRs")), SUMIFS('2026'!$K:$K,'2026'!$R:$R,$E$3&$C12,'2026'!$T:$T,G$6), SUMIFS('2026'!$K:$K,'2026'!$N:$N,$E$3&$C12&$E$4,'2026'!$T:$T,G$6)) -> 0 | H12: =IF((AND($E$3="MCS",$E$4="TODOS CRs")), SUMIFS('2026'!$K:$K,'2026'!$R:$R,$E$3&$C12,'2026'!$T:$T,H$6), SUMIFS('2026'!$K:$K,'2026'!$N:$N,$E$3&$C12&$E$4,'2026'!$T:$T,H$6)) -> 0 | I12: =IF((AND($E$3="MCS",$E$4="TODOS CRs")), SUMIFS('2026'!$K:$K,'2026'!$R:$R,$E$3&$C12,'2026'!$T:$T,I$6), SUMIFS('2026'!$K:$K,'2026'!$N:$N,$E$3&$C12&$E$4,'2026'!$T:$T,I$6)) -> 0 | J12: =IF((AND($E$3="MCS",$E$4="TODOS CRs")), SUMIFS('2026'!$K:$K,'2026'!$R:$R,$E$3&$C12,'2026'!$T:$T,J$6), SUMIFS('2026'!$K:$K,'2026'!$N:$N,$E$3&$C12&$E$4,'2026'!$T:$T,J$6)) -> 0 | K12: =IF((AND($E$3="MCS",$E$4="TODOS CRs")), SUMIFS('2026'!$K:$K,'2026'!$R:$R,$E$3&$C12,'2026'!$T:$T,K$6), SUMIFS('2026'!$K:$K,'2026'!$N:$N,$E$3&$C12&$E$4,'2026'!$T:$T,K$6)) -> 0 | L12: =IF((AND($E$3="MCS",$E$4="TODOS CRs")), SUMIFS('2026'!$K:$K,'2026'!$R:$R,$E$3&$C12,'2026'!$T:$T,L$6), SUMIFS('2026'!$K:$K,'2026'!$N:$N,$E$3&$C12&$E$4,'2026'!$T:$T,L$6)) -> 0 | M12: =IF((AND($E$3="MCS",$E$4="TODOS CRs")), SUMIFS('2026'!$K:$K,'2026'!$R:$R,$E$3&$C12,'2026'!$T:$T,M$6), SUMIFS('2026'!$K:$K,'2026'!$N:$N,$E$3&$C12&$E$4,'2026'!$T:$T,M$6)) -> 0 | ... Q12: =IF((AND($E$3="MCS",$E$4="TODOS CRs")), SUMIFS('2026'!$K:$K,'2026'!$R:$R,$E$3&$C12,'2026'!$T:$T,Q$6), SUMIFS('2026'!$K:$K,'2026'!$N:$N,$E$3&$C12&$E$4,'2026'!$T:$T,Q$6)) -> 0 | T12: TRI | U12: =SUMIFS($E$7:$E$40,$B$7:$B$40,T12) -> -296 | V12: =IFERROR(ABS(U12/$U$5),0) -> 0.0088116874
B13: REC | C13: REC7 | D13: CPF - Rec. Financeiras - Empréstimos | E13: =SUM(F13:Q13) -> 170 | F13: =IF((AND($E$3="MCS",$E$4="TODOS CRs")), SUMIFS('2026'!$K:$K,'2026'!$R:$R,$E$3&$C13,'2026'!$T:$T,F$6), SUMIFS('2026'!$K:$K,'2026'!$N:$N,$E$3&$C13&$E$4,'2026'!$T:$T,F$6)) -> 0 | G13: =IF((AND($E$3="MCS",$E$4="TODOS CRs")), SUMIFS('2026'!$K:$K,'2026'!$R:$R,$E$3&$C13,'2026'!$T:$T,G$6), SUMIFS('2026'!$K:$K,'2026'!$N:$N,$E$3&$C13&$E$4,'2026'!$T:$T,G$6)) -> 0 | H13: =IF((AND($E$3="MCS",$E$4="TODOS CRs")), SUMIFS('2026'!$K:$K,'2026'!$R:$R,$E$3&$C13,'2026'!$T:$T,H$6), SUMIFS('2026'!$K:$K,'2026'!$N:$N,$E$3&$C13&$E$4,'2026'!$T:$T,H$6)) -> 0 | I13: =IF((AND($E$3="MCS",$E$4="TODOS CRs")), SUMIFS('2026'!$K:$K,'2026'!$R:$R,$E$3&$C13,'2026'!$T:$T,I$6), SUMIFS('2026'!$K:$K,'2026'!$N:$N,$E$3&$C13&$E$4,'2026'!$T:$T,I$6)) -> 0 | J13: =IF((AND($E$3="MCS",$E$4="TODOS CRs")), SUMIFS('2026'!$K:$K,'2026'!$R:$R,$E$3&$C13,'2026'!$T:$T,J$6), SUMIFS('2026'!$K:$K,'2026'!$N:$N,$E$3&$C13&$E$4,'2026'!$T:$T,J$6)) -> 170 | K13: =IF((AND($E$3="MCS",$E$4="TODOS CRs")), SUMIFS('2026'!$K:$K,'2026'!$R:$R,$E$3&$C13,'2026'!$T:$T,K$6), SUMIFS('2026'!$K:$K,'2026'!$N:$N,$E$3&$C13&$E$4,'2026'!$T:$T,K$6)) -> 0 | L13: =IF((AND($E$3="MCS",$E$4="TODOS CRs")), SUMIFS('2026'!$K:$K,'2026'!$R:$R,$E$3&$C13,'2026'!$T:$T,L$6), SUMIFS('2026'!$K:$K,'2026'!$N:$N,$E$3&$C13&$E$4,'2026'!$T:$T,L$6)) -> 0 | M13: =IF((AND($E$3="MCS",$E$4="TODOS CRs")), SUMIFS('2026'!$K:$K,'2026'!$R:$R,$E$3&$C13,'2026'!$T:$T,M$6), SUMIFS('2026'!$K:$K,'2026'!$N:$N,$E$3&$C13&$E$4,'2026'!$T:$T,M$6)) -> 0 | ... Q13: =IF((AND($E$3="MCS",$E$4="TODOS CRs")), SUMIFS('2026'!$K:$K,'2026'!$R:$R,$E$3&$C13,'2026'!$T:$T,Q$6), SUMIFS('2026'!$K:$K,'2026'!$N:$N,$E$3&$C13&$E$4,'2026'!$T:$T,Q$6)) -> 0 | T13: TOTAL | U13: =SUMIFS($E$7:$E$40,$B$7:$B$40,T13) -> 0 | V13: =IFERROR(ABS(U13/$U$5),0) -> 0
D14: (=) TOTAL ENTRADAS | E14: =SUBTOTAL(9,E7:E13) -> 33591.75 | F14: =SUBTOTAL(9,F7:F13) -> 4900 | G14: =SUBTOTAL(9,G7:G13) -> 5517.62 | H14: =SUBTOTAL(9,H7:H13) -> 5096 | I14: =SUBTOTAL(9,I7:I13) -> 7025 | J14: =SUBTOTAL(9,J7:J13) -> 6659.99 | K14: =SUBTOTAL(9,K7:K13) -> 4393.14 | L14: =SUBTOTAL(9,L7:L13) -> 0 | ... Q14: =SUBTOTAL(9,Q7:Q13) -> 0 | T14: SUPERÁVIT | U14: =U5+U13 -> 33591.75 | V14: =ABS(U14/$U$5) -> 1
B16: Grupo | C16: Natureza | D16: SAÍDAS | E16: ACUM | F16: =F6 -> 46023 | G16: =G6 -> 46054 | H16: =H6 -> 46082 | I16: =I6 -> 46113 | J16: =J6 -> 46143 | K16: =K6 -> 46174 | L16: =L6 -> 46204 | M16: =M6 -> 46235 | ... Q16: =Q6 -> 46357
B17: OPF | C17: OPF1 | D17: CPF - Desp. Alimentação / Refeição | E17: =SUM(F17:Q17) -> -1928.08 | F17: =IF((AND($E$3="MCS",$E$4="TODOS CRs")), SUMIFS('2026'!$K:$K,'2026'!$R:$R,$E$3&$C17,'2026'!$T:$T,F$6), SUMIFS('2026'!$K:$K,'2026'!$N:$N,$E$3&$C17&$E$4,'2026'!$T:$T,F$6)) -> -416.33 | G17: =IF((AND($E$3="MCS",$E$4="TODOS CRs")), SUMIFS('2026'!$K:$K,'2026'!$R:$R,$E$3&$C17,'2026'!$T:$T,G$6), SUMIFS('2026'!$K:$K,'2026'!$N:$N,$E$3&$C17&$E$4,'2026'!$T:$T,G$6)) -> -293 | H17: =IF((AND($E$3="MCS",$E$4="TODOS CRs")), SUMIFS('2026'!$K:$K,'2026'!$R:$R,$E$3&$C17,'2026'!$T:$T,H$6), SUMIFS('2026'!$K:$K,'2026'!$N:$N,$E$3&$C17&$E$4,'2026'!$T:$T,H$6)) -> -24 | I17: =IF((AND($E$3="MCS",$E$4="TODOS CRs")), SUMIFS('2026'!$K:$K,'2026'!$R:$R,$E$3&$C17,'2026'!$T:$T,I$6), SUMIFS('2026'!$K:$K,'2026'!$N:$N,$E$3&$C17&$E$4,'2026'!$T:$T,I$6)) -> -250.16 | J17: =IF((AND($E$3="MCS",$E$4="TODOS CRs")), SUMIFS('2026'!$K:$K,'2026'!$R:$R,$E$3&$C17,'2026'!$T:$T,J$6), SUMIFS('2026'!$K:$K,'2026'!$N:$N,$E$3&$C17&$E$4,'2026'!$T:$T,J$6)) -> -497.16 | K17: =IF((AND($E$3="MCS",$E$4="TODOS CRs")), SUMIFS('2026'!$K:$K,'2026'!$R:$R,$E$3&$C17,'2026'!$T:$T,K$6), SUMIFS('2026'!$K:$K,'2026'!$N:$N,$E$3&$C17&$E$4,'2026'!$T:$T,K$6)) -> -447.43 | L17: =IF((AND($E$3="MCS",$E$4="TODOS CRs")), SUMIFS('2026'!$K:$K,'2026'!$R:$R,$E$3&$C17,'2026'!$T:$T,L$6), SUMIFS('2026'!$K:$K,'2026'!$N:$N,$E$3&$C17&$E$4,'2026'!$T:$T,L$6)) -> 0 | M17: =IF((AND($E$3="MCS",$E$4="TODOS CRs")), SUMIFS('2026'!$K:$K,'2026'!$R:$R,$E$3&$C17,'2026'!$T:$T,M$6), SUMIFS('2026'!$K:$K,'2026'!$N:$N,$E$3&$C17&$E$4,'2026'!$T:$T,M$6)) -> 0 | ... Q17: =IF((AND($E$3="MCS",$E$4="TODOS CRs")), SUMIFS('2026'!$K:$K,'2026'!$R:$R,$E$3&$C17,'2026'!$T:$T,Q$6), SUMIFS('2026'!$K:$K,'2026'!$N:$N,$E$3&$C17&$E$4,'2026'!$T:$T,Q$6)) -> 0
B18: OPF | C18: OPF2 | D18: CPF - Desp. Transporte / Combustível | E18: =SUM(F18:Q18) -> -4912.38 | F18: =IF((AND($E$3="MCS",$E$4="TODOS CRs")), SUMIFS('2026'!$K:$K,'2026'!$R:$R,$E$3&$C18,'2026'!$T:$T,F$6), SUMIFS('2026'!$K:$K,'2026'!$N:$N,$E$3&$C18&$E$4,'2026'!$T:$T,F$6)) -> -740 | G18: =IF((AND($E$3="MCS",$E$4="TODOS CRs")), SUMIFS('2026'!$K:$K,'2026'!$R:$R,$E$3&$C18,'2026'!$T:$T,G$6), SUMIFS('2026'!$K:$K,'2026'!$N:$N,$E$3&$C18&$E$4,'2026'!$T:$T,G$6)) -> -1096.67 | H18: =IF((AND($E$3="MCS",$E$4="TODOS CRs")), SUMIFS('2026'!$K:$K,'2026'!$R:$R,$E$3&$C18,'2026'!$T:$T,H$6), SUMIFS('2026'!$K:$K,'2026'!$N:$N,$E$3&$C18&$E$4,'2026'!$T:$T,H$6)) -> -675.2 | I18: =IF((AND($E$3="MCS",$E$4="TODOS CRs")), SUMIFS('2026'!$K:$K,'2026'!$R:$R,$E$3&$C18,'2026'!$T:$T,I$6), SUMIFS('2026'!$K:$K,'2026'!$N:$N,$E$3&$C18&$E$4,'2026'!$T:$T,I$6)) -> -887.68 | J18: =IF((AND($E$3="MCS",$E$4="TODOS CRs")), SUMIFS('2026'!$K:$K,'2026'!$R:$R,$E$3&$C18,'2026'!$T:$T,J$6), SUMIFS('2026'!$K:$K,'2026'!$N:$N,$E$3&$C18&$E$4,'2026'!$T:$T,J$6)) -> -1012.83 | K18: =IF((AND($E$3="MCS",$E$4="TODOS CRs")), SUMIFS('2026'!$K:$K,'2026'!$R:$R,$E$3&$C18,'2026'!$T:$T,K$6), SUMIFS('2026'!$K:$K,'2026'!$N:$N,$E$3&$C18&$E$4,'2026'!$T:$T,K$6)) -> -500 | L18: =IF((AND($E$3="MCS",$E$4="TODOS CRs")), SUMIFS('2026'!$K:$K,'2026'!$R:$R,$E$3&$C18,'2026'!$T:$T,L$6), SUMIFS('2026'!$K:$K,'2026'!$N:$N,$E$3&$C18&$E$4,'2026'!$T:$T,L$6)) -> 0 | M18: =IF((AND($E$3="MCS",$E$4="TODOS CRs")), SUMIFS('2026'!$K:$K,'2026'!$R:$R,$E$3&$C18,'2026'!$T:$T,M$6), SUMIFS('2026'!$K:$K,'2026'!$N:$N,$E$3&$C18&$E$4,'2026'!$T:$T,M$6)) -> 0 | ... Q18: =IF((AND($E$3="MCS",$E$4="TODOS CRs")), SUMIFS('2026'!$K:$K,'2026'!$R:$R,$E$3&$C18,'2026'!$T:$T,Q$6), SUMIFS('2026'!$K:$K,'2026'!$N:$N,$E$3&$C18&$E$4,'2026'!$T:$T,Q$6)) -> 0
B19: DESP | C19: DESP1 | D19: CPF - Desp. Cartão de crédito | E19: =SUM(F19:Q19) -> -215.52 | F19: =IF((AND($E$3="MCS",$E$4="TODOS CRs")), SUMIFS('2026'!$K:$K,'2026'!$R:$R,$E$3&$C19,'2026'!$T:$T,F$6), SUMIFS('2026'!$K:$K,'2026'!$N:$N,$E$3&$C19&$E$4,'2026'!$T:$T,F$6)) -> 0 | G19: =IF((AND($E$3="MCS",$E$4="TODOS CRs")), SUMIFS('2026'!$K:$K,'2026'!$R:$R,$E$3&$C19,'2026'!$T:$T,G$6), SUMIFS('2026'!$K:$K,'2026'!$N:$N,$E$3&$C19&$E$4,'2026'!$T:$T,G$6)) -> -203.49 | H19: =IF((AND($E$3="MCS",$E$4="TODOS CRs")), SUMIFS('2026'!$K:$K,'2026'!$R:$R,$E$3&$C19,'2026'!$T:$T,H$6), SUMIFS('2026'!$K:$K,'2026'!$N:$N,$E$3&$C19&$E$4,'2026'!$T:$T,H$6)) -> -5.9 | I19: =IF((AND($E$3="MCS",$E$4="TODOS CRs")), SUMIFS('2026'!$K:$K,'2026'!$R:$R,$E$3&$C19,'2026'!$T:$T,I$6), SUMIFS('2026'!$K:$K,'2026'!$N:$N,$E$3&$C19&$E$4,'2026'!$T:$T,I$6)) -> 0 | J19: =IF((AND($E$3="MCS",$E$4="TODOS CRs")), SUMIFS('2026'!$K:$K,'2026'!$R:$R,$E$3&$C19,'2026'!$T:$T,J$6), SUMIFS('2026'!$K:$K,'2026'!$N:$N,$E$3&$C19&$E$4,'2026'!$T:$T,J$6)) -> 0 | K19: =IF((AND($E$3="MCS",$E$4="TODOS CRs")), SUMIFS('2026'!$K:$K,'2026'!$R:$R,$E$3&$C19,'2026'!$T:$T,K$6), SUMIFS('2026'!$K:$K,'2026'!$N:$N,$E$3&$C19&$E$4,'2026'!$T:$T,K$6)) -> -6.13 | L19: =IF((AND($E$3="MCS",$E$4="TODOS CRs")), SUMIFS('2026'!$K:$K,'2026'!$R:$R,$E$3&$C19,'2026'!$T:$T,L$6), SUMIFS('2026'!$K:$K,'2026'!$N:$N,$E$3&$C19&$E$4,'2026'!$T:$T,L$6)) -> 0 | M19: =IF((AND($E$3="MCS",$E$4="TODOS CRs")), SUMIFS('2026'!$K:$K,'2026'!$R:$R,$E$3&$C19,'2026'!$T:$T,M$6), SUMIFS('2026'!$K:$K,'2026'!$N:$N,$E$3&$C19&$E$4,'2026'!$T:$T,M$6)) -> 0 | ... Q19: =IF((AND($E$3="MCS",$E$4="TODOS CRs")), SUMIFS('2026'!$K:$K,'2026'!$R:$R,$E$3&$C19,'2026'!$T:$T,Q$6), SUMIFS('2026'!$K:$K,'2026'!$N:$N,$E$3&$C19&$E$4,'2026'!$T:$T,Q$6)) -> 0
B20: DESP | C20: DESP2 | D20: CPF - Desp. Telefone / Internet | E20: =SUM(F20:Q20) -> -1380.41 | F20: =IF((AND($E$3="MCS",$E$4="TODOS CRs")), SUMIFS('2026'!$K:$K,'2026'!$R:$R,$E$3&$C20,'2026'!$T:$T,F$6), SUMIFS('2026'!$K:$K,'2026'!$N:$N,$E$3&$C20&$E$4,'2026'!$T:$T,F$6)) -> -248.12 | G20: =IF((AND($E$3="MCS",$E$4="TODOS CRs")), SUMIFS('2026'!$K:$K,'2026'!$R:$R,$E$3&$C20,'2026'!$T:$T,G$6), SUMIFS('2026'!$K:$K,'2026'!$N:$N,$E$3&$C20&$E$4,'2026'!$T:$T,G$6)) -> -124.97 | H20: =IF((AND($E$3="MCS",$E$4="TODOS CRs")), SUMIFS('2026'!$K:$K,'2026'!$R:$R,$E$3&$C20,'2026'!$T:$T,H$6), SUMIFS('2026'!$K:$K,'2026'!$N:$N,$E$3&$C20&$E$4,'2026'!$T:$T,H$6)) -> -447.99 | I20: =IF((AND($E$3="MCS",$E$4="TODOS CRs")), SUMIFS('2026'!$K:$K,'2026'!$R:$R,$E$3&$C20,'2026'!$T:$T,I$6), SUMIFS('2026'!$K:$K,'2026'!$N:$N,$E$3&$C20&$E$4,'2026'!$T:$T,I$6)) -> -125.21 | J20: =IF((AND($E$3="MCS",$E$4="TODOS CRs")), SUMIFS('2026'!$K:$K,'2026'!$R:$R,$E$3&$C20,'2026'!$T:$T,J$6), SUMIFS('2026'!$K:$K,'2026'!$N:$N,$E$3&$C20&$E$4,'2026'!$T:$T,J$6)) -> -309.02 | K20: =IF((AND($E$3="MCS",$E$4="TODOS CRs")), SUMIFS('2026'!$K:$K,'2026'!$R:$R,$E$3&$C20,'2026'!$T:$T,K$6), SUMIFS('2026'!$K:$K,'2026'!$N:$N,$E$3&$C20&$E$4,'2026'!$T:$T,K$6)) -> -125.1 | L20: =IF((AND($E$3="MCS",$E$4="TODOS CRs")), SUMIFS('2026'!$K:$K,'2026'!$R:$R,$E$3&$C20,'2026'!$T:$T,L$6), SUMIFS('2026'!$K:$K,'2026'!$N:$N,$E$3&$C20&$E$4,'2026'!$T:$T,L$6)) -> 0 | M20: =IF((AND($E$3="MCS",$E$4="TODOS CRs")), SUMIFS('2026'!$K:$K,'2026'!$R:$R,$E$3&$C20,'2026'!$T:$T,M$6), SUMIFS('2026'!$K:$K,'2026'!$N:$N,$E$3&$C20&$E$4,'2026'!$T:$T,M$6)) -> 0 | ... Q20: =IF((AND($E$3="MCS",$E$4="TODOS CRs")), SUMIFS('2026'!$K:$K,'2026'!$R:$R,$E$3&$C20,'2026'!$T:$T,Q$6), SUMIFS('2026'!$K:$K,'2026'!$N:$N,$E$3&$C20&$E$4,'2026'!$T:$T,Q$6)) -> 0
B21: DESP | C21: DESP3 | D21: CPF - Desp. com veículo - Manut. / Gastos | E21: =SUM(F21:Q21) -> -526.7 | F21: =IF((AND($E$3="MCS",$E$4="TODOS CRs")), SUMIFS('2026'!$K:$K,'2026'!$R:$R,$E$3&$C21,'2026'!$T:$T,F$6), SUMIFS('2026'!$K:$K,'2026'!$N:$N,$E$3&$C21&$E$4,'2026'!$T:$T,F$6)) -> 0 | G21: =IF((AND($E$3="MCS",$E$4="TODOS CRs")), SUMIFS('2026'!$K:$K,'2026'!$R:$R,$E$3&$C21,'2026'!$T:$T,G$6), SUMIFS('2026'!$K:$K,'2026'!$N:$N,$E$3&$C21&$E$4,'2026'!$T:$T,G$6)) -> -60 | H21: =IF((AND($E$3="MCS",$E$4="TODOS CRs")), SUMIFS('2026'!$K:$K,'2026'!$R:$R,$E$3&$C21,'2026'!$T:$T,H$6), SUMIFS('2026'!$K:$K,'2026'!$N:$N,$E$3&$C21&$E$4,'2026'!$T:$T,H$6)) -> 0 | I21: =IF((AND($E$3="MCS",$E$4="TODOS CRs")), SUMIFS('2026'!$K:$K,'2026'!$R:$R,$E$3&$C21,'2026'!$T:$T,I$6), SUMIFS('2026'!$K:$K,'2026'!$N:$N,$E$3&$C21&$E$4,'2026'!$T:$T,I$6)) -> 0 | J21: =IF((AND($E$3="MCS",$E$4="TODOS CRs")), SUMIFS('2026'!$K:$K,'2026'!$R:$R,$E$3&$C21,'2026'!$T:$T,J$6), SUMIFS('2026'!$K:$K,'2026'!$N:$N,$E$3&$C21&$E$4,'2026'!$T:$T,J$6)) -> -432.95 | K21: =IF((AND($E$3="MCS",$E$4="TODOS CRs")), SUMIFS('2026'!$K:$K,'2026'!$R:$R,$E$3&$C21,'2026'!$T:$T,K$6), SUMIFS('2026'!$K:$K,'2026'!$N:$N,$E$3&$C21&$E$4,'2026'!$T:$T,K$6)) -> -33.75 | L21: =IF((AND($E$3="MCS",$E$4="TODOS CRs")), SUMIFS('2026'!$K:$K,'2026'!$R:$R,$E$3&$C21,'2026'!$T:$T,L$6), SUMIFS('2026'!$K:$K,'2026'!$N:$N,$E$3&$C21&$E$4,'2026'!$T:$T,L$6)) -> 0 | M21: =IF((AND($E$3="MCS",$E$4="TODOS CRs")), SUMIFS('2026'!$K:$K,'2026'!$R:$R,$E$3&$C21,'2026'!$T:$T,M$6), SUMIFS('2026'!$K:$K,'2026'!$N:$N,$E$3&$C21&$E$4,'2026'!$T:$T,M$6)) -> 0 | ... Q21: =IF((AND($E$3="MCS",$E$4="TODOS CRs")), SUMIFS('2026'!$K:$K,'2026'!$R:$R,$E$3&$C21,'2026'!$T:$T,Q$6), SUMIFS('2026'!$K:$K,'2026'!$N:$N,$E$3&$C21&$E$4,'2026'!$T:$T,Q$6)) -> 0
B22: DESP | C22: DESP4 | D22: CPF - Desp. Moradia | E22: =SUM(F22:Q22) -> -1906 | F22: =IF((AND($E$3="MCS",$E$4="TODOS CRs")), SUMIFS('2026'!$K:$K,'2026'!$R:$R,$E$3&$C22,'2026'!$T:$T,F$6), SUMIFS('2026'!$K:$K,'2026'!$N:$N,$E$3&$C22&$E$4,'2026'!$T:$T,F$6)) -> 0 | G22: =IF((AND($E$3="MCS",$E$4="TODOS CRs")), SUMIFS('2026'!$K:$K,'2026'!$R:$R,$E$3&$C22,'2026'!$T:$T,G$6), SUMIFS('2026'!$K:$K,'2026'!$N:$N,$E$3&$C22&$E$4,'2026'!$T:$T,G$6)) -> -204.78 | H22: =IF((AND($E$3="MCS",$E$4="TODOS CRs")), SUMIFS('2026'!$K:$K,'2026'!$R:$R,$E$3&$C22,'2026'!$T:$T,H$6), SUMIFS('2026'!$K:$K,'2026'!$N:$N,$E$3&$C22&$E$4,'2026'!$T:$T,H$6)) -> -347.67 | I22: =IF((AND($E$3="MCS",$E$4="TODOS CRs")), SUMIFS('2026'!$K:$K,'2026'!$R:$R,$E$3&$C22,'2026'!$T:$T,I$6), SUMIFS('2026'!$K:$K,'2026'!$N:$N,$E$3&$C22&$E$4,'2026'!$T:$T,I$6)) -> -511.07 | J22: =IF((AND($E$3="MCS",$E$4="TODOS CRs")), SUMIFS('2026'!$K:$K,'2026'!$R:$R,$E$3&$C22,'2026'!$T:$T,J$6), SUMIFS('2026'!$K:$K,'2026'!$N:$N,$E$3&$C22&$E$4,'2026'!$T:$T,J$6)) -> -451.48 | K22: =IF((AND($E$3="MCS",$E$4="TODOS CRs")), SUMIFS('2026'!$K:$K,'2026'!$R:$R,$E$3&$C22,'2026'!$T:$T,K$6), SUMIFS('2026'!$K:$K,'2026'!$N:$N,$E$3&$C22&$E$4,'2026'!$T:$T,K$6)) -> -391 | L22: =IF((AND($E$3="MCS",$E$4="TODOS CRs")), SUMIFS('2026'!$K:$K,'2026'!$R:$R,$E$3&$C22,'2026'!$T:$T,L$6), SUMIFS('2026'!$K:$K,'2026'!$N:$N,$E$3&$C22&$E$4,'2026'!$T:$T,L$6)) -> 0 | M22: =IF((AND($E$3="MCS",$E$4="TODOS CRs")), SUMIFS('2026'!$K:$K,'2026'!$R:$R,$E$3&$C22,'2026'!$T:$T,M$6), SUMIFS('2026'!$K:$K,'2026'!$N:$N,$E$3&$C22&$E$4,'2026'!$T:$T,M$6)) -> 0 | ... Q22: =IF((AND($E$3="MCS",$E$4="TODOS CRs")), SUMIFS('2026'!$K:$K,'2026'!$R:$R,$E$3&$C22,'2026'!$T:$T,Q$6), SUMIFS('2026'!$K:$K,'2026'!$N:$N,$E$3&$C22&$E$4,'2026'!$T:$T,Q$6)) -> 0
B23: DESP | C23: DESP5 | D23: CPF - Transf. Da conta PF para a conta PJ | E23: =SUM(F23:Q23) -> 0 | F23: =IF((AND($E$3="MCS",$E$4="TODOS CRs")), SUMIFS('2026'!$K:$K,'2026'!$R:$R,$E$3&$C23,'2026'!$T:$T,F$6), SUMIFS('2026'!$K:$K,'2026'!$N:$N,$E$3&$C23&$E$4,'2026'!$T:$T,F$6)) -> 0 | G23: =IF((AND($E$3="MCS",$E$4="TODOS CRs")), SUMIFS('2026'!$K:$K,'2026'!$R:$R,$E$3&$C23,'2026'!$T:$T,G$6), SUMIFS('2026'!$K:$K,'2026'!$N:$N,$E$3&$C23&$E$4,'2026'!$T:$T,G$6)) -> 0 | H23: =IF((AND($E$3="MCS",$E$4="TODOS CRs")), SUMIFS('2026'!$K:$K,'2026'!$R:$R,$E$3&$C23,'2026'!$T:$T,H$6), SUMIFS('2026'!$K:$K,'2026'!$N:$N,$E$3&$C23&$E$4,'2026'!$T:$T,H$6)) -> 0 | I23: =IF((AND($E$3="MCS",$E$4="TODOS CRs")), SUMIFS('2026'!$K:$K,'2026'!$R:$R,$E$3&$C23,'2026'!$T:$T,I$6), SUMIFS('2026'!$K:$K,'2026'!$N:$N,$E$3&$C23&$E$4,'2026'!$T:$T,I$6)) -> 0 | J23: =IF((AND($E$3="MCS",$E$4="TODOS CRs")), SUMIFS('2026'!$K:$K,'2026'!$R:$R,$E$3&$C23,'2026'!$T:$T,J$6), SUMIFS('2026'!$K:$K,'2026'!$N:$N,$E$3&$C23&$E$4,'2026'!$T:$T,J$6)) -> 0 | K23: =IF((AND($E$3="MCS",$E$4="TODOS CRs")), SUMIFS('2026'!$K:$K,'2026'!$R:$R,$E$3&$C23,'2026'!$T:$T,K$6), SUMIFS('2026'!$K:$K,'2026'!$N:$N,$E$3&$C23&$E$4,'2026'!$T:$T,K$6)) -> 0 | L23: =IF((AND($E$3="MCS",$E$4="TODOS CRs")), SUMIFS('2026'!$K:$K,'2026'!$R:$R,$E$3&$C23,'2026'!$T:$T,L$6), SUMIFS('2026'!$K:$K,'2026'!$N:$N,$E$3&$C23&$E$4,'2026'!$T:$T,L$6)) -> 0 | M23: =IF((AND($E$3="MCS",$E$4="TODOS CRs")), SUMIFS('2026'!$K:$K,'2026'!$R:$R,$E$3&$C23,'2026'!$T:$T,M$6), SUMIFS('2026'!$K:$K,'2026'!$N:$N,$E$3&$C23&$E$4,'2026'!$T:$T,M$6)) -> 0 | ... Q23: =IF((AND($E$3="MCS",$E$4="TODOS CRs")), SUMIFS('2026'!$K:$K,'2026'!$R:$R,$E$3&$C23,'2026'!$T:$T,Q$6), SUMIFS('2026'!$K:$K,'2026'!$N:$N,$E$3&$C23&$E$4,'2026'!$T:$T,Q$6)) -> 0
B24: GAST | C24: GAST1 | D24: CPF - Desp. Lazer e Entretenimento - Bares | E24: =SUM(F24:Q24) -> -5237.55 | F24: =IF((AND($E$3="MCS",$E$4="TODOS CRs")), SUMIFS('2026'!$K:$K,'2026'!$R:$R,$E$3&$C24,'2026'!$T:$T,F$6), SUMIFS('2026'!$K:$K,'2026'!$N:$N,$E$3&$C24&$E$4,'2026'!$T:$T,F$6)) -> -849.87 | G24: =IF((AND($E$3="MCS",$E$4="TODOS CRs")), SUMIFS('2026'!$K:$K,'2026'!$R:$R,$E$3&$C24,'2026'!$T:$T,G$6), SUMIFS('2026'!$K:$K,'2026'!$N:$N,$E$3&$C24&$E$4,'2026'!$T:$T,G$6)) -> -662.01 | H24: =IF((AND($E$3="MCS",$E$4="TODOS CRs")), SUMIFS('2026'!$K:$K,'2026'!$R:$R,$E$3&$C24,'2026'!$T:$T,H$6), SUMIFS('2026'!$K:$K,'2026'!$N:$N,$E$3&$C24&$E$4,'2026'!$T:$T,H$6)) -> -332.84 | I24: =IF((AND($E$3="MCS",$E$4="TODOS CRs")), SUMIFS('2026'!$K:$K,'2026'!$R:$R,$E$3&$C24,'2026'!$T:$T,I$6), SUMIFS('2026'!$K:$K,'2026'!$N:$N,$E$3&$C24&$E$4,'2026'!$T:$T,I$6)) -> -1448.71 | J24: =IF((AND($E$3="MCS",$E$4="TODOS CRs")), SUMIFS('2026'!$K:$K,'2026'!$R:$R,$E$3&$C24,'2026'!$T:$T,J$6), SUMIFS('2026'!$K:$K,'2026'!$N:$N,$E$3&$C24&$E$4,'2026'!$T:$T,J$6)) -> -1099.45 | K24: =IF((AND($E$3="MCS",$E$4="TODOS CRs")), SUMIFS('2026'!$K:$K,'2026'!$R:$R,$E$3&$C24,'2026'!$T:$T,K$6), SUMIFS('2026'!$K:$K,'2026'!$N:$N,$E$3&$C24&$E$4,'2026'!$T:$T,K$6)) -> -844.67 | L24: =IF((AND($E$3="MCS",$E$4="TODOS CRs")), SUMIFS('2026'!$K:$K,'2026'!$R:$R,$E$3&$C24,'2026'!$T:$T,L$6), SUMIFS('2026'!$K:$K,'2026'!$N:$N,$E$3&$C24&$E$4,'2026'!$T:$T,L$6)) -> 0 | M24: =IF((AND($E$3="MCS",$E$4="TODOS CRs")), SUMIFS('2026'!$K:$K,'2026'!$R:$R,$E$3&$C24,'2026'!$T:$T,M$6), SUMIFS('2026'!$K:$K,'2026'!$N:$N,$E$3&$C24&$E$4,'2026'!$T:$T,M$6)) -> 0 | ... Q24: =IF((AND($E$3="MCS",$E$4="TODOS CRs")), SUMIFS('2026'!$K:$K,'2026'!$R:$R,$E$3&$C24,'2026'!$T:$T,Q$6), SUMIFS('2026'!$K:$K,'2026'!$N:$N,$E$3&$C24&$E$4,'2026'!$T:$T,Q$6)) -> 0
B25: GAST | C25: GAST2 | D25: CPF - Desp. Lazer e Entretenimento - Cigarro | E25: =SUM(F25:Q25) -> -808 | F25: =IF((AND($E$3="MCS",$E$4="TODOS CRs")), SUMIFS('2026'!$K:$K,'2026'!$R:$R,$E$3&$C25,'2026'!$T:$T,F$6), SUMIFS('2026'!$K:$K,'2026'!$N:$N,$E$3&$C25&$E$4,'2026'!$T:$T,F$6)) -> -134 | G25: =IF((AND($E$3="MCS",$E$4="TODOS CRs")), SUMIFS('2026'!$K:$K,'2026'!$R:$R,$E$3&$C25,'2026'!$T:$T,G$6), SUMIFS('2026'!$K:$K,'2026'!$N:$N,$E$3&$C25&$E$4,'2026'!$T:$T,G$6)) -> -196.5 | H25: =IF((AND($E$3="MCS",$E$4="TODOS CRs")), SUMIFS('2026'!$K:$K,'2026'!$R:$R,$E$3&$C25,'2026'!$T:$T,H$6), SUMIFS('2026'!$K:$K,'2026'!$N:$N,$E$3&$C25&$E$4,'2026'!$T:$T,H$6)) -> 0 | I25: =IF((AND($E$3="MCS",$E$4="TODOS CRs")), SUMIFS('2026'!$K:$K,'2026'!$R:$R,$E$3&$C25,'2026'!$T:$T,I$6), SUMIFS('2026'!$K:$K,'2026'!$N:$N,$E$3&$C25&$E$4,'2026'!$T:$T,I$6)) -> -174 | J25: =IF((AND($E$3="MCS",$E$4="TODOS CRs")), SUMIFS('2026'!$K:$K,'2026'!$R:$R,$E$3&$C25,'2026'!$T:$T,J$6), SUMIFS('2026'!$K:$K,'2026'!$N:$N,$E$3&$C25&$E$4,'2026'!$T:$T,J$6)) -> -176 | K25: =IF((AND($E$3="MCS",$E$4="TODOS CRs")), SUMIFS('2026'!$K:$K,'2026'!$R:$R,$E$3&$C25,'2026'!$T:$T,K$6), SUMIFS('2026'!$K:$K,'2026'!$N:$N,$E$3&$C25&$E$4,'2026'!$T:$T,K$6)) -> -127.5 | L25: =IF((AND($E$3="MCS",$E$4="TODOS CRs")), SUMIFS('2026'!$K:$K,'2026'!$R:$R,$E$3&$C25,'2026'!$T:$T,L$6), SUMIFS('2026'!$K:$K,'2026'!$N:$N,$E$3&$C25&$E$4,'2026'!$T:$T,L$6)) -> 0 | M25: =IF((AND($E$3="MCS",$E$4="TODOS CRs")), SUMIFS('2026'!$K:$K,'2026'!$R:$R,$E$3&$C25,'2026'!$T:$T,M$6), SUMIFS('2026'!$K:$K,'2026'!$N:$N,$E$3&$C25&$E$4,'2026'!$T:$T,M$6)) -> 0 | ... Q25: =IF((AND($E$3="MCS",$E$4="TODOS CRs")), SUMIFS('2026'!$K:$K,'2026'!$R:$R,$E$3&$C25,'2026'!$T:$T,Q$6), SUMIFS('2026'!$K:$K,'2026'!$N:$N,$E$3&$C25&$E$4,'2026'!$T:$T,Q$6)) -> 0
B26: FIN | C26: FIN1 | D26: CPF - Desp. Financeiras - Empréstimos | E26: =SUM(F26:Q26) -> -400 | F26: =IF((AND($E$3="MCS",$E$4="TODOS CRs")), SUMIFS('2026'!$K:$K,'2026'!$R:$R,$E$3&$C26,'2026'!$T:$T,F$6), SUMIFS('2026'!$K:$K,'2026'!$N:$N,$E$3&$C26&$E$4,'2026'!$T:$T,F$6)) -> -200 | G26: =IF((AND($E$3="MCS",$E$4="TODOS CRs")), SUMIFS('2026'!$K:$K,'2026'!$R:$R,$E$3&$C26,'2026'!$T:$T,G$6), SUMIFS('2026'!$K:$K,'2026'!$N:$N,$E$3&$C26&$E$4,'2026'!$T:$T,G$6)) -> 0 | H26: =IF((AND($E$3="MCS",$E$4="TODOS CRs")), SUMIFS('2026'!$K:$K,'2026'!$R:$R,$E$3&$C26,'2026'!$T:$T,H$6), SUMIFS('2026'!$K:$K,'2026'!$N:$N,$E$3&$C26&$E$4,'2026'!$T:$T,H$6)) -> -170 | I26: =IF((AND($E$3="MCS",$E$4="TODOS CRs")), SUMIFS('2026'!$K:$K,'2026'!$R:$R,$E$3&$C26,'2026'!$T:$T,I$6), SUMIFS('2026'!$K:$K,'2026'!$N:$N,$E$3&$C26&$E$4,'2026'!$T:$T,I$6)) -> -30 | J26: =IF((AND($E$3="MCS",$E$4="TODOS CRs")), SUMIFS('2026'!$K:$K,'2026'!$R:$R,$E$3&$C26,'2026'!$T:$T,J$6), SUMIFS('2026'!$K:$K,'2026'!$N:$N,$E$3&$C26&$E$4,'2026'!$T:$T,J$6)) -> 0 | K26: =IF((AND($E$3="MCS",$E$4="TODOS CRs")), SUMIFS('2026'!$K:$K,'2026'!$R:$R,$E$3&$C26,'2026'!$T:$T,K$6), SUMIFS('2026'!$K:$K,'2026'!$N:$N,$E$3&$C26&$E$4,'2026'!$T:$T,K$6)) -> 0 | L26: =IF((AND($E$3="MCS",$E$4="TODOS CRs")), SUMIFS('2026'!$K:$K,'2026'!$R:$R,$E$3&$C26,'2026'!$T:$T,L$6), SUMIFS('2026'!$K:$K,'2026'!$N:$N,$E$3&$C26&$E$4,'2026'!$T:$T,L$6)) -> 0 | M26: =IF((AND($E$3="MCS",$E$4="TODOS CRs")), SUMIFS('2026'!$K:$K,'2026'!$R:$R,$E$3&$C26,'2026'!$T:$T,M$6), SUMIFS('2026'!$K:$K,'2026'!$N:$N,$E$3&$C26&$E$4,'2026'!$T:$T,M$6)) -> 0 | ... Q26: =IF((AND($E$3="MCS",$E$4="TODOS CRs")), SUMIFS('2026'!$K:$K,'2026'!$R:$R,$E$3&$C26,'2026'!$T:$T,Q$6), SUMIFS('2026'!$K:$K,'2026'!$N:$N,$E$3&$C26&$E$4,'2026'!$T:$T,Q$6)) -> 0
B27: FIN | C27: FIN2 | D27: CPF - Desp. Financeiras - Juros / Tarifas | E27: =SUM(F27:Q27) -> -168 | F27: =IF((AND($E$3="MCS",$E$4="TODOS CRs")), SUMIFS('2026'!$K:$K,'2026'!$R:$R,$E$3&$C27,'2026'!$T:$T,F$6), SUMIFS('2026'!$K:$K,'2026'!$N:$N,$E$3&$C27&$E$4,'2026'!$T:$T,F$6)) -> -28 | G27: =IF((AND($E$3="MCS",$E$4="TODOS CRs")), SUMIFS('2026'!$K:$K,'2026'!$R:$R,$E$3&$C27,'2026'!$T:$T,G$6), SUMIFS('2026'!$K:$K,'2026'!$N:$N,$E$3&$C27&$E$4,'2026'!$T:$T,G$6)) -> -28 | H27: =IF((AND($E$3="MCS",$E$4="TODOS CRs")), SUMIFS('2026'!$K:$K,'2026'!$R:$R,$E$3&$C27,'2026'!$T:$T,H$6), SUMIFS('2026'!$K:$K,'2026'!$N:$N,$E$3&$C27&$E$4,'2026'!$T:$T,H$6)) -> -28 | I27: =IF((AND($E$3="MCS",$E$4="TODOS CRs")), SUMIFS('2026'!$K:$K,'2026'!$R:$R,$E$3&$C27,'2026'!$T:$T,I$6), SUMIFS('2026'!$K:$K,'2026'!$N:$N,$E$3&$C27&$E$4,'2026'!$T:$T,I$6)) -> -28 | J27: =IF((AND($E$3="MCS",$E$4="TODOS CRs")), SUMIFS('2026'!$K:$K,'2026'!$R:$R,$E$3&$C27,'2026'!$T:$T,J$6), SUMIFS('2026'!$K:$K,'2026'!$N:$N,$E$3&$C27&$E$4,'2026'!$T:$T,J$6)) -> -28 | K27: =IF((AND($E$3="MCS",$E$4="TODOS CRs")), SUMIFS('2026'!$K:$K,'2026'!$R:$R,$E$3&$C27,'2026'!$T:$T,K$6), SUMIFS('2026'!$K:$K,'2026'!$N:$N,$E$3&$C27&$E$4,'2026'!$T:$T,K$6)) -> -28 | L27: =IF((AND($E$3="MCS",$E$4="TODOS CRs")), SUMIFS('2026'!$K:$K,'2026'!$R:$R,$E$3&$C27,'2026'!$T:$T,L$6), SUMIFS('2026'!$K:$K,'2026'!$N:$N,$E$3&$C27&$E$4,'2026'!$T:$T,L$6)) -> 0 | M27: =IF((AND($E$3="MCS",$E$4="TODOS CRs")), SUMIFS('2026'!$K:$K,'2026'!$R:$R,$E$3&$C27,'2026'!$T:$T,M$6), SUMIFS('2026'!$K:$K,'2026'!$N:$N,$E$3&$C27&$E$4,'2026'!$T:$T,M$6)) -> 0 | ... Q27: =IF((AND($E$3="MCS",$E$4="TODOS CRs")), SUMIFS('2026'!$K:$K,'2026'!$R:$R,$E$3&$C27,'2026'!$T:$T,Q$6), SUMIFS('2026'!$K:$K,'2026'!$N:$N,$E$3&$C27&$E$4,'2026'!$T:$T,Q$6)) -> 0
B28: FIN | C28: FIN3 | D28: CPF - Desp. Financeiras - Juros / Tarifas | E28: =SUM(F28:Q28) -> -1782.3 | F28: =IF((AND($E$3="MCS",$E$4="TODOS CRs")), SUMIFS('2026'!$K:$K,'2026'!$R:$R,$E$3&$C28,'2026'!$T:$T,F$6), SUMIFS('2026'!$K:$K,'2026'!$N:$N,$E$3&$C28&$E$4,'2026'!$T:$T,F$6)) -> -297.05 | G28: =IF((AND($E$3="MCS",$E$4="TODOS CRs")), SUMIFS('2026'!$K:$K,'2026'!$R:$R,$E$3&$C28,'2026'!$T:$T,G$6), SUMIFS('2026'!$K:$K,'2026'!$N:$N,$E$3&$C28&$E$4,'2026'!$T:$T,G$6)) -> -297.05 | H28: =IF((AND($E$3="MCS",$E$4="TODOS CRs")), SUMIFS('2026'!$K:$K,'2026'!$R:$R,$E$3&$C28,'2026'!$T:$T,H$6), SUMIFS('2026'!$K:$K,'2026'!$N:$N,$E$3&$C28&$E$4,'2026'!$T:$T,H$6)) -> -297.05 | I28: =IF((AND($E$3="MCS",$E$4="TODOS CRs")), SUMIFS('2026'!$K:$K,'2026'!$R:$R,$E$3&$C28,'2026'!$T:$T,I$6), SUMIFS('2026'!$K:$K,'2026'!$N:$N,$E$3&$C28&$E$4,'2026'!$T:$T,I$6)) -> -297.05 | J28: =IF((AND($E$3="MCS",$E$4="TODOS CRs")), SUMIFS('2026'!$K:$K,'2026'!$R:$R,$E$3&$C28,'2026'!$T:$T,J$6), SUMIFS('2026'!$K:$K,'2026'!$N:$N,$E$3&$C28&$E$4,'2026'!$T:$T,J$6)) -> -297.05 | K28: =IF((AND($E$3="MCS",$E$4="TODOS CRs")), SUMIFS('2026'!$K:$K,'2026'!$R:$R,$E$3&$C28,'2026'!$T:$T,K$6), SUMIFS('2026'!$K:$K,'2026'!$N:$N,$E$3&$C28&$E$4,'2026'!$T:$T,K$6)) -> -297.05 | L28: =IF((AND($E$3="MCS",$E$4="TODOS CRs")), SUMIFS('2026'!$K:$K,'2026'!$R:$R,$E$3&$C28,'2026'!$T:$T,L$6), SUMIFS('2026'!$K:$K,'2026'!$N:$N,$E$3&$C28&$E$4,'2026'!$T:$T,L$6)) -> 0 | M28: =IF((AND($E$3="MCS",$E$4="TODOS CRs")), SUMIFS('2026'!$K:$K,'2026'!$R:$R,$E$3&$C28,'2026'!$T:$T,M$6), SUMIFS('2026'!$K:$K,'2026'!$N:$N,$E$3&$C28&$E$4,'2026'!$T:$T,M$6)) -> 0 | ... Q28: =IF((AND($E$3="MCS",$E$4="TODOS CRs")), SUMIFS('2026'!$K:$K,'2026'!$R:$R,$E$3&$C28,'2026'!$T:$T,Q$6), SUMIFS('2026'!$K:$K,'2026'!$N:$N,$E$3&$C28&$E$4,'2026'!$T:$T,Q$6)) -> 0
... B39: PENS | C39: PENS9 | D39: CPF - Pensão - Outros Gastos | E39: =SUM(F39:Q39) -> 0 | F39: =IF((AND($E$3="MCS",$E$4="TODOS CRs")), SUMIFS('2026'!$K:$K,'2026'!$R:$R,$E$3&$C39,'2026'!$T:$T,F$6), SUMIFS('2026'!$K:$K,'2026'!$N:$N,$E$3&$C39&$E$4,'2026'!$T:$T,F$6)) -> 0 | G39: =IF((AND($E$3="MCS",$E$4="TODOS CRs")), SUMIFS('2026'!$K:$K,'2026'!$R:$R,$E$3&$C39,'2026'!$T:$T,G$6), SUMIFS('2026'!$K:$K,'2026'!$N:$N,$E$3&$C39&$E$4,'2026'!$T:$T,G$6)) -> 0 | H39: =IF((AND($E$3="MCS",$E$4="TODOS CRs")), SUMIFS('2026'!$K:$K,'2026'!$R:$R,$E$3&$C39,'2026'!$T:$T,H$6), SUMIFS('2026'!$K:$K,'2026'!$N:$N,$E$3&$C39&$E$4,'2026'!$T:$T,H$6)) -> 0 | I39: =IF((AND($E$3="MCS",$E$4="TODOS CRs")), SUMIFS('2026'!$K:$K,'2026'!$R:$R,$E$3&$C39,'2026'!$T:$T,I$6), SUMIFS('2026'!$K:$K,'2026'!$N:$N,$E$3&$C39&$E$4,'2026'!$T:$T,I$6)) -> 0 | J39: =IF((AND($E$3="MCS",$E$4="TODOS CRs")), SUMIFS('2026'!$K:$K,'2026'!$R:$R,$E$3&$C39,'2026'!$T:$T,J$6), SUMIFS('2026'!$K:$K,'2026'!$N:$N,$E$3&$C39&$E$4,'2026'!$T:$T,J$6)) -> 0 | K39: =IF((AND($E$3="MCS",$E$4="TODOS CRs")), SUMIFS('2026'!$K:$K,'2026'!$R:$R,$E$3&$C39,'2026'!$T:$T,K$6), SUMIFS('2026'!$K:$K,'2026'!$N:$N,$E$3&$C39&$E$4,'2026'!$T:$T,K$6)) -> 0 | L39: =IF((AND($E$3="MCS",$E$4="TODOS CRs")), SUMIFS('2026'!$K:$K,'2026'!$R:$R,$E$3&$C39,'2026'!$T:$T,L$6), SUMIFS('2026'!$K:$K,'2026'!$N:$N,$E$3&$C39&$E$4,'2026'!$T:$T,L$6)) -> 0 | M39: =IF((AND($E$3="MCS",$E$4="TODOS CRs")), SUMIFS('2026'!$K:$K,'2026'!$R:$R,$E$3&$C39,'2026'!$T:$T,M$6), SUMIFS('2026'!$K:$K,'2026'!$N:$N,$E$3&$C39&$E$4,'2026'!$T:$T,M$6)) -> 0 | ... Q39: =IF((AND($E$3="MCS",$E$4="TODOS CRs")), SUMIFS('2026'!$K:$K,'2026'!$R:$R,$E$3&$C39,'2026'!$T:$T,Q$6), SUMIFS('2026'!$K:$K,'2026'!$N:$N,$E$3&$C39&$E$4,'2026'!$T:$T,Q$6)) -> 0
B40: - | C40: - | D40: (=) TOTAL SAÍDAS | E40: =SUBTOTAL(9,E17:E39) -> -33348.58 | F40: =SUBTOTAL(9,F17:F39) -> -5100.28 | G40: =SUBTOTAL(9,G17:G39) -> -5411.31 | H40: =SUBTOTAL(9,H17:H39) -> -4888.92 | I40: =SUBTOTAL(9,I17:I39) -> -7250.92 | J40: =SUBTOTAL(9,J17:J39) -> -5999.93 | K40: =SUBTOTAL(9,K17:K39) -> -4697.22 | L40: =SUBTOTAL(9,L17:L39) -> 0 | ... Q40: =SUBTOTAL(9,Q17:Q39) -> 0
D42: RESULTADO | E42: ACUM | F42: =F6 -> 46023 | G42: =G6 -> 46054 | H42: =H6 -> 46082 | I42: =I6 -> 46113 | J42: =J6 -> 46143 | K42: =K6 -> 46174 | L42: =L6 -> 46204 | M42: =M6 -> 46235 | ... Q42: =Q6 -> 46357
D43: SALDO ANTERIOR | E43: 0 | F43: 352.96 | G43: =IF(AND(G44=0,G45=0),0,F46) -> 152.68 | H43: =IF(AND(H44=0,H45=0),0,G46) -> 258.99 | I43: =IF(AND(I44=0,I45=0),0,H46) -> 466.07 | J43: =IF(AND(J44=0,J45=0),0,I46) -> 240.15 | K43: =IF(AND(K44=0,K45=0),0,J46) -> 900.21 | L43: =IF(AND(L44=0,L45=0),0,K46) -> 0 | M43: =IF(AND(M44=0,M45=0),0,L46) -> 0 | N43: =IF(AND(N44=0,N45=0),0,M46) -> 0 | ... Q43: =IF(AND(Q44=0,Q45=0),0,P46) -> 0
D44: (+) TOTAL DE ENTRADAS | E44: =SUM(F44:Q44) -> 33591.75 | F44: =F14 -> 4900 | G44: =G14 -> 5517.62 | H44: =H14 -> 5096 | I44: =I14 -> 7025 | J44: =J14 -> 6659.99 | K44: =K14 -> 4393.14 | L44: =L14 -> 0 | M44: =M14 -> 0 | ... Q44: =Q14 -> 0
D45: (-) TOTAL DE SAÍDAS | E45: =SUM(F45:Q45) -> -33348.58 | F45: =F40 -> -5100.28 | G45: =G40 -> -5411.31 | H45: =H40 -> -4888.92 | I45: =I40 -> -7250.92 | J45: =J40 -> -5999.93 | K45: =K40 -> -4697.22 | L45: =L40 -> 0 | M45: =M40 -> 0 | ... Q45: =Q40 -> 0
D46: (=) SALDO ATUAL | E46: =E44+E45 -> 243.17 | F46: =F43+F44+F45 -> 152.68 | G46: =G43+G44+G45 -> 258.99 | H46: =H43+H44+H45 -> 466.07 | I46: =I43+I44+I45 -> 240.15 | J46: =J43+J44+J45 -> 900.21 | K46: =K43+K44+K45 -> 596.13 | L46: =L43+L44+L45 -> 0 | M46: =M43+M44+M45 -> 0 | ... Q46: =Q43+Q44+Q45 -> 0
E48: CARGA % DA PENSÃO => | F48: =IFERROR(ABS(SUM(F31:F39))/F10,0) -> 0.42936939 | G48: =IFERROR(ABS(SUM(G31:G39))/G10,0) -> 0.38584545 | H48: =IFERROR(ABS(SUM(H31:H39))/H10,0) -> 0.46985913 | I48: =IFERROR(ABS(SUM(I31:I39))/I10,0) -> 0.32341571 | J48: =IFERROR(ABS(SUM(J31:J39))/J10,0) -> 0.25396667 | K48: =IFERROR(ABS(SUM(K31:K39))/K10,0) -> 0.319 | L48: =IFERROR(ABS(SUM(L31:L39))/L10,0) -> 0 | M48: =IFERROR(ABS(SUM(M31:M39))/M10,0) -> 0 | ... Q48: =IFERROR(ABS(SUM(Q31:Q39))/Q10,0) -> 0

Sheet 2026
K1: =SUBTOTAL(9,K3:K656) -> 243.17 | L1: -1
B2: EMPRESA | C2: x | D2: Natureza | E2: Descrição | F2: Centro de Resultado | G2: Entidade | H2: Data real | I2: Data prevista | J2: Observações | K2: Total | L2: Saldo banco | M2: x | N2: Empresa & CR | O2: Concat 2 | P2: Concat 3 | Q2: Concat 3 | R2: Empresa & Natureza | S2: x | T2: DATA REAL
B3: MCS | D3: =INDEX(Cad_Natureza!$B$3:$C$52,MATCH('2026'!F3,Cad_Natureza!$C$3:$C$52,0),MATCH('2026'!D$2,Cad_Natureza!$B$3:$C$3,0)) -> GAST2 | E3: =IF(K3<0,"Despesa "&U3,"Receita "&U3) -> Despesa 1 | F3: CPF - Desp. Lazer e Entretenimento - Cigarro | G3: MCS | H3: 46024 | J3: =IF(K3<0,"Observação da despesa "&U3,"Observação da receita "&U3) -> Observação da despesa 1 | K3: -5 | L3: 347.96 | N3: =B3&D3&F3 -> MCSGAST2CPF - Desp. Lazer e Entretenimento - Cigarro | O3: =D3&F3 -> GAST2CPF - Desp. Lazer e Entretenimento - Cigarro | P3: ="MCS"&D3&F3 -> MCSGAST2CPF - Desp. Lazer e Entretenimento - Cigarro | Q3: ="MCS"&D3 -> MCSGAST2 | R3: =B3&D3 -> MCSGAST2 | T3: =(1&"/"&MONTH(H3)&"/"&YEAR(H3))*1 -> 46023 | U3: 1
B4: MCS | D4: =INDEX(Cad_Natureza!$B$3:$C$52,MATCH('2026'!F4,Cad_Natureza!$C$3:$C$52,0),MATCH('2026'!D$2,Cad_Natureza!$B$3:$C$3,0)) -> DESP2 | E4: =IF(K4<0,"Despesa "&U4,"Receita "&U4) -> Despesa 2 | F4: CPF - Desp. Telefone / Internet | G4: MCS | H4: 46027 | J4: =IF(K4<0,"Observação da despesa "&U4,"Observação da receita "&U4) -> Observação da despesa 2 | K4: -86.64 | L4: =L3+K4 -> 261.32 | N4: =B4&D4&F4 -> MCSDESP2CPF - Desp. Telefone / Internet | O4: =D4&F4 -> DESP2CPF - Desp. Telefone / Internet | P4: ="MCS"&D4&F4 -> MCSDESP2CPF - Desp. Telefone / Internet | Q4: ="MCS"&D4 -> MCSDESP2 | R4: =B4&D4 -> MCSDESP2 | T4: =(1&"/"&MONTH(H4)&"/"&YEAR(H4))*1 -> 46023 | U4: 2
B5: MCS | D5: =INDEX(Cad_Natureza!$B$3:$C$52,MATCH('2026'!F5,Cad_Natureza!$C$3:$C$52,0),MATCH('2026'!D$2,Cad_Natureza!$B$3:$C$3,0)) -> DESP2 | E5: =IF(K5<0,"Despesa "&U5,"Receita "&U5) -> Despesa 3 | F5: CPF - Desp. Telefone / Internet | G5: MCS | H5: 46027 | J5: =IF(K5<0,"Observação da despesa "&U5,"Observação da receita "&U5) -> Observação da despesa 3 | K5: -38.13 | L5: =L4+K5 -> 223.19 | N5: =B5&D5&F5 -> MCSDESP2CPF - Desp. Telefone / Internet | O5: =D5&F5 -> DESP2CPF - Desp. Telefone / Internet | P5: ="MCS"&D5&F5 -> MCSDESP2CPF - Desp. Telefone / Internet | Q5: ="MCS"&D5 -> MCSDESP2 | R5: =B5&D5 -> MCSDESP2 | T5: =(1&"/"&MONTH(H5)&"/"&YEAR(H5))*1 -> 46023 | U5: 3
B6: MCS | D6: =INDEX(Cad_Natureza!$B$3:$C$52,MATCH('2026'!F6,Cad_Natureza!$C$3:$C$52,0),MATCH('2026'!D$2,Cad_Natureza!$B$3:$C$3,0)) -> GAST2 | E6: =IF(K6<0,"Despesa "&U6,"Receita "&U6) -> Despesa 4 | F6: CPF - Desp. Lazer e Entretenimento - Cigarro | G6: MCS | H6: 46027 | J6: =IF(K6<0,"Observação da despesa "&U6,"Observação da receita "&U6) -> Observação da despesa 4 | K6: -10 | L6: =L5+K6 -> 213.19 | N6: =B6&D6&F6 -> MCSGAST2CPF - Desp. Lazer e Entretenimento - Cigarro | O6: =D6&F6 -> GAST2CPF - Desp. Lazer e Entretenimento - Cigarro | P6: ="MCS"&D6&F6 -> MCSGAST2CPF - Desp. Lazer e Entretenimento - Cigarro | Q6: ="MCS"&D6 -> MCSGAST2 | R6: =B6&D6 -> MCSGAST2 | T6: =(1&"/"&MONTH(H6)&"/"&YEAR(H6))*1 -> 46023 | U6: 4
B7: MCS | D7: =INDEX(Cad_Natureza!$B$3:$C$52,MATCH('2026'!F7,Cad_Natureza!$C$3:$C$52,0),MATCH('2026'!D$2,Cad_Natureza!$B$3:$C$3,0)) -> GAST2 | E7: =IF(K7<0,"Despesa "&U7,"Receita "&U7) -> Despesa 5 | F7: CPF - Desp. Lazer e Entretenimento - Cigarro | G7: MCS | H7: 46027 | J7: =IF(K7<0,"Observação da despesa "&U7,"Observação da receita "&U7) -> Observação da despesa 5 | K7: -4 | L7: =L6+K7 -> 209.19 | N7: =B7&D7&F7 -> MCSGAST2CPF - Desp. Lazer e Entretenimento - Cigarro | O7: =D7&F7 -> GAST2CPF - Desp. Lazer e Entretenimento - Cigarro | P7: ="MCS"&D7&F7 -> MCSGAST2CPF - Desp. Lazer e Entretenimento - Cigarro | Q7: ="MCS"&D7 -> MCSGAST2 | R7: =B7&D7 -> MCSGAST2 | T7: =(1&"/"&MONTH(H7)&"/"&YEAR(H7))*1 -> 46023 | U7: 5
B8: MCS | D8: =INDEX(Cad_Natureza!$B$3:$C$52,MATCH('2026'!F8,Cad_Natureza!$C$3:$C$52,0),MATCH('2026'!D$2,Cad_Natureza!$B$3:$C$3,0)) -> OPF2 | E8: =IF(K8<0,"Despesa "&U8,"Receita "&U8) -> Despesa 6 | F8: CPF - Desp. Transporte / Combustível | G8: MCS | H8: 46027 | J8: =IF(K8<0,"Observação da despesa "&U8,"Observação da receita "&U8) -> Observação da despesa 6 | K8: -50 | L8: =L7+K8 -> 159.19 | N8: =B8&D8&F8 -> MCSOPF2CPF - Desp. Transporte / Combustível | O8: =D8&F8 -> OPF2CPF - Desp. Transporte / Combustível | P8: ="MCS"&D8&F8 -> MCSOPF2CPF - Desp. Transporte / Combustível | Q8: ="MCS"&D8 -> MCSOPF2 | R8: =B8&D8 -> MCSOPF2 | T8: =(1&"/"&MONTH(H8)&"/"&YEAR(H8))*1 -> 46023 | U8: 6
B9: MCS | D9: =INDEX(Cad_Natureza!$B$3:$C$52,MATCH('2026'!F9,Cad_Natureza!$C$3:$C$52,0),MATCH('2026'!D$2,Cad_Natureza!$B$3:$C$3,0)) -> OPF1 | E9: =IF(K9<0,"Despesa "&U9,"Receita "&U9) -> Despesa 7 | F9: CPF - Desp. Alimentação / Refeição | G9: MCS | H9: 46027 | J9: =IF(K9<0,"Observação da despesa "&U9,"Observação da receita "&U9) -> Observação da despesa 7 | K9: -23.33 | L9: =L8+K9 -> 135.86 | N9: =B9&D9&F9 -> MCSOPF1CPF - Desp. Alimentação / Refeição | O9: =D9&F9 -> OPF1CPF - Desp. Alimentação / Refeição | P9: ="MCS"&D9&F9 -> MCSOPF1CPF - Desp. Alimentação / Refeição | Q9: ="MCS"&D9 -> MCSOPF1 | R9: =B9&D9 -> MCSOPF1 | T9: =(1&"/"&MONTH(H9)&"/"&YEAR(H9))*1 -> 46023 | U9: 7
B10: MCS | D10: =INDEX(Cad_Natureza!$B$3:$C$52,MATCH('2026'!F10,Cad_Natureza!$C$3:$C$52,0),MATCH('2026'!D$2,Cad_Natureza!$B$3:$C$3,0)) -> GAST1 | E10: =IF(K10<0,"Despesa "&U10,"Receita "&U10) -> Despesa 8 | F10: CPF - Desp. Lazer e Entretenimento - Bares | G10: MCS | H10: 46027 | J10: =IF(K10<0,"Observação da despesa "&U10,"Observação da receita "&U10) -> Observação da despesa 8 | K10: -16 | L10: =L9+K10 -> 119.86 | N10: =B10&D10&F10 -> MCSGAST1CPF - Desp. Lazer e Entretenimento - Bares | O10: =D10&F10 -> GAST1CPF - Desp. Lazer e Entretenimento - Bares | P10: ="MCS"&D10&F10 -> MCSGAST1CPF - Desp. Lazer e Entretenimento - Bares | Q10: ="MCS"&D10 -> MCSGAST1 | R10: =B10&D10 -> MCSGAST1 | T10: =(1&"/"&MONTH(H10)&"/"&YEAR(H10))*1 -> 46023 | U10: 8
B11: MCS | D11: =INDEX(Cad_Natureza!$B$3:$C$52,MATCH('2026'!F11,Cad_Natureza!$C$3:$C$52,0),MATCH('2026'!D$2,Cad_Natureza!$B$3:$C$3,0)) -> PENS6 | E11: =IF(K11<0,"Despesa "&U11,"Receita "&U11) -> Despesa 9 | F11: CPF - Pensão - Farmácia e Saúde | G11: MCS | H11: 46027 | J11: =IF(K11<0,"Observação da despesa "&U11,"Observação da receita "&U11) -> Observação da despesa 9 | K11: -14.49 | L11: =L10+K11 -> 105.37 | N11: =B11&D11&F11 -> MCSPENS6CPF - Pensão - Farmácia e Saúde | O11: =D11&F11 -> PENS6CPF - Pensão - Farmácia e Saúde | P11: ="MCS"&D11&F11 -> MCSPENS6CPF - Pensão - Farmácia e Saúde | Q11: ="MCS"&D11 -> MCSPENS6 | R11: =B11&D11 -> MCSPENS6 | T11: =(1&"/"&MONTH(H11)&"/"&YEAR(H11))*1 -> 46023 | U11: 9
B12: MCS | D12: =INDEX(Cad_Natureza!$B$3:$C$52,MATCH('2026'!F12,Cad_Natureza!$C$3:$C$52,0),MATCH('2026'!D$2,Cad_Natureza!$B$3:$C$3,0)) -> GAST1 | E12: =IF(K12<0,"Despesa "&U12,"Receita "&U12) -> Despesa 10 | F12: CPF - Desp. Lazer e Entretenimento - Bares | G12: MCS | H12: 46027 | J12: =IF(K12<0,"Observação da despesa "&U12,"Observação da receita "&U12) -> Observação da despesa 10 | K12: -10 | L12: =L11+K12 -> 95.37 | N12: =B12&D12&F12 -> MCSGAST1CPF - Desp. Lazer e Entretenimento - Bares | O12: =D12&F12 -> GAST1CPF - Desp. Lazer e Entretenimento - Bares | P12: ="MCS"&D12&F12 -> MCSGAST1CPF - Desp. Lazer e Entretenimento - Bares | Q12: ="MCS"&D12 -> MCSGAST1 | R12: =B12&D12 -> MCSGAST1 | T12: =(1&"/"&MONTH(H12)&"/"&YEAR(H12))*1 -> 46023 | U12: 10
B13: MCS | D13: =INDEX(Cad_Natureza!$B$3:$C$52,MATCH('2026'!F13,Cad_Natureza!$C$3:$C$52,0),MATCH('2026'!D$2,Cad_Natureza!$B$3:$C$3,0)) -> FIN2 | E13: =IF(K13<0,"Despesa "&U13,"Receita "&U13) -> Despesa 11 | F13: CPF - Desp. Financeiras - Juros / Tarifas | G13: MCS | H13: 46027 | J13: =IF(K13<0,"Observação da despesa "&U13,"Observação da receita "&U13) -> Observação da despesa 11 | K13: -28 | L13: =L12+K13 -> 67.37 | N13: =B13&D13&F13 -> MCSFIN2CPF - Desp. Financeiras - Juros / Tarifas | O13: =D13&F13 -> FIN2CPF - Desp. Financeiras - Juros / Tarifas | P13: ="MCS"&D13&F13 -> MCSFIN2CPF - Desp. Financeiras - Juros / Tarifas | Q13: ="MCS"&D13 -> MCSFIN2 | R13: =B13&D13 -> MCSFIN2 | T13: =(1&"/"&MONTH(H13)&"/"&YEAR(H13))*1 -> 46023 | U13: 11
B14: MCS | D14: =INDEX(Cad_Natureza!$B$3:$C$52,MATCH('2026'!F14,Cad_Natureza!$C$3:$C$52,0),MATCH('2026'!D$2,Cad_Natureza!$B$3:$C$3,0)) -> OPF2 | E14: =IF(K14<0,"Despesa "&U14,"Receita "&U14) -> Despesa 12 | F14: CPF - Desp. Transporte / Combustível | G14: MCS | H14: 46028 | J14: =IF(K14<0,"Observação da despesa "&U14,"Observação da receita "&U14) -> Observação da despesa 12 | K14: -40 | L14: =L13+K14 -> 27.37 | N14: =B14&D14&F14 -> MCSOPF2CPF - Desp. Transporte / Combustível | O14: =D14&F14 -> OPF2CPF - Desp. Transporte / Combustível | P14: ="MCS"&D14&F14 -> MCSOPF2CPF - Desp. Transporte / Combustível | Q14: ="MCS"&D14 -> MCSOPF2 | R14: =B14&D14 -> MCSOPF2 | T14: =(1&"/"&MONTH(H14)&"/"&YEAR(H14))*1 -> 46023 | U14: 12
B15: MCS | D15: =INDEX(Cad_Natureza!$B$3:$C$52,MATCH('2026'!F15,Cad_Natureza!$C$3:$C$52,0),MATCH('2026'!D$2,Cad_Natureza!$B$3:$C$3,0)) -> GAST1 | E15: =IF(K15<0,"Despesa "&U15,"Receita "&U15) -> Despesa 13 | F15: CPF - Desp. Lazer e Entretenimento - Bares | G15: MCS | H15: 46028 | J15: =IF(K15<0,"Observação da despesa "&U15,"Observação da receita "&U15) -> Observação da despesa 13 | K15: -10 | L15: =L14+K15 -> 17.37 | N15: =B15&D15&F15 -> MCSGAST1CPF - Desp. Lazer e Entretenimento - Bares | O15: =D15&F15 -> GAST1CPF - Desp. Lazer e Entretenimento - Bares | P15: ="MCS"&D15&F15 -> MCSGAST1CPF - Desp. Lazer e Entretenimento - Bares | Q15: ="MCS"&D15 -> MCSGAST1 | R15: =B15&D15 -> MCSGAST1 | T15: =(1&"/"&MONTH(H15)&"/"&YEAR(H15))*1 -> 46023 | U15: 13
... B650: MCS | D650: =INDEX(Cad_Natureza!$B$3:$C$52,MATCH('2026'!F650,Cad_Natureza!$C$3:$C$52,0),MATCH('2026'!D$2,Cad_Natureza!$B$3:$C$3,0)) -> PENS2 | E650: =IF(K650<0,"Despesa "&U650,"Receita "&U650) -> Despesa 648 | F650: CPF - Pensão - Energia | G650: MCS | H650: 46188 | J650: =IF(K650<0,"Observação da despesa "&U650,"Observação da receita "&U650) -> Observação da despesa 648 | K650: -490.89 | L650: =L649+K650 -> 596.13 | N650: =B650&D650&F650 -> MCSPENS2CPF - Pensão - Energia | O650: =D650&F650 -> PENS2CPF - Pensão - Energia | P650: ="MCS"&D650&F650 -> MCSPENS2CPF - Pensão - Energia | Q650: ="MCS"&D650 -> MCSPENS2 | R650: =B650&D650 -> MCSPENS2 | T650: =(1&"/"&MONTH(H650)&"/"&YEAR(H650))*1 -> 46174 | U650: 648
B651: MCS | D651: =INDEX(Cad_Natureza!$B$3:$C$52,MATCH('2026'!F651,Cad_Natureza!$C$3:$C$52,0),MATCH('2026'!D$2,Cad_Natureza!$B$3:$C$3,0)) -> #N/A | G651: MCS | N651: =B651&D651&F651 -> #N/A | O651: =D651&F651 -> #N/A | P651: ="MCS"&D651&F651 -> #N/A | Q651: ="MCS"&D651 -> #N/A | R651: =B651&D651 -> #N/A | T651: =(1&"/"&MONTH(H651)&"/"&YEAR(H651))*1 -> 1 | U651: 649
B652: MCS | D652: =INDEX(Cad_Natureza!$B$3:$C$52,MATCH('2026'!F652,Cad_Natureza!$C$3:$C$52,0),MATCH('2026'!D$2,Cad_Natureza!$B$3:$C$3,0)) -> #N/A | G652: MCS | N652: =B652&D652&F652 -> #N/A | O652: =D652&F652 -> #N/A | P652: ="MCS"&D652&F652 -> #N/A | Q652: ="MCS"&D652 -> #N/A | R652: =B652&D652 -> #N/A | T652: =(1&"/"&MONTH(H652)&"/"&YEAR(H652))*1 -> 1 | U652: 650
B653: MCS | D653: =INDEX(Cad_Natureza!$B$3:$C$52,MATCH('2026'!F653,Cad_Natureza!$C$3:$C$52,0),MATCH('2026'!D$2,Cad_Natureza!$B$3:$C$3,0)) -> #N/A | G653: MCS | N653: =B653&D653&F653 -> #N/A | O653: =D653&F653 -> #N/A | P653: ="MCS"&D653&F653 -> #N/A | Q653: ="MCS"&D653 -> #N/A | R653: =B653&D653 -> #N/A | T653: =(1&"/"&MONTH(H653)&"/"&YEAR(H653))*1 -> 1 | U653: 651
B654: MCS | D654: =INDEX(Cad_Natureza!$B$3:$C$52,MATCH('2026'!F654,Cad_Natureza!$C$3:$C$52,0),MATCH('2026'!D$2,Cad_Natureza!$B$3:$C$3,0)) -> #N/A | G654: MCS | N654: =B654&D654&F654 -> #N/A | O654: =D654&F654 -> #N/A | P654: ="MCS"&D654&F654 -> #N/A | Q654: ="MCS"&D654 -> #N/A | R654: =B654&D654 -> #N/A | T654: =(1&"/"&MONTH(H654)&"/"&YEAR(H654))*1 -> 1 | U654: 652
B655: MCS | D655: =INDEX(Cad_Natureza!$B$3:$C$52,MATCH('2026'!F655,Cad_Natureza!$C$3:$C$52,0),MATCH('2026'!D$2,Cad_Natureza!$B$3:$C$3,0)) -> #N/A | G655: MCS | N655: =B655&D655&F655 -> #N/A | O655: =D655&F655 -> #N/A | P655: ="MCS"&D655&F655 -> #N/A | Q655: ="MCS"&D655 -> #N/A | R655: =B655&D655 -> #N/A | T655: =(1&"/"&MONTH(H655)&"/"&YEAR(H655))*1 -> 1 | U655: 653
B656: MCS | D656: =INDEX(Cad_Natureza!$B$3:$C$52,MATCH('2026'!F656,Cad_Natureza!$C$3:$C$52,0),MATCH('2026'!D$2,Cad_Natureza!$B$3:$C$3,0)) -> #N/A | G656: MCS | N656: =B656&D656&F656 -> #N/A | O656: =D656&F656 -> #N/A | P656: ="MCS"&D656&F656 -> #N/A | Q656: ="MCS"&D656 -> #N/A | R656: =B656&D656 -> #N/A | T656: =(1&"/"&MONTH(H656)&"/"&YEAR(H656))*1 -> 1 | U656: 654
B657: x | C657: x | D657: x | E657: x | F657: x | G657: x | H657: x | I657: x | J657: x | K657: x | M657: x | N657: x | O657: x | P657: x | Q657: x | R657: x | S657: x | T657: x | U657: 655

Sheet Cad_Natureza
B3: Natureza | C3: Descrição CR | E3: Entidade | G3: Fluxo
B4: - | C4: TODOS CRs | E4: MCS | F4: =OFFSET(Cad_Natureza!$E$4,0,0,COUNTA(Cad_Natureza!$E$4:$E$102)) -> MCS | G4: REAL | H4: =OFFSET(Cad_Natureza!$G$4,0,0,COUNTA(Cad_Natureza!$G$4:$G$102)) -> REAL
B5: REC1 | C5: CPF - Remun. Salário / Pró-Labore | G5: PREVISTO | H5: =OFFSET(Cad_Natureza!$G$4,0,0,COUNTA(Cad_Natureza!$G$4:$G$102)) -> PREVISTO
B6: REC2 | C6: CPF - Ajuda de custo - Combustível
B7: REC3 | C7: CPF - Ajuda de custo - Refeição
B8: REC4 | C8: CPF - Transf. Da conta PJ para a conta PF
B9: REC5 | C9: CPF - Outras receitas
B10: REC6 | C10: CPF - Pensão - Outras receitas
B11: REC7 | C11: CPF - Rec. Financeiras - Empréstimos
B13: OPF1 | C13: CPF - Desp. Alimentação / Refeição
B14: OPF2 | C14: CPF - Desp. Transporte / Combustível
B15: DESP1 | C15: CPF - Desp. Cartão de crédito
B16: DESP2 | C16: CPF - Desp. Telefone / Internet
B17: DESP3 | C17: CPF - Desp. com veículo - Manut. / Gastos
B18: DESP4 | C18: CPF - Desp. Moradia
... B53: X | C53: X
